Workbook
Name ADaM或衍生数据集个数: 项目参数!$C$84
Name ClinicalTrials翻译YN: 服务费明细!$D$32
Name CMP撰写YN: 服务费明细!$D$72
Name CRA和中心的医学支持YN: 服务费明细!$D$100
Name CRA人数: 项目参数!$C$51
Name CRF唯一页面数: 项目参数!$C$66
Name CRF重复页面数: 项目参数!$C$67
Name CRF总页数_每例: 项目时间计划!$D$61
Name CSR月: 项目时间计划!$G$17
Name CSR撰写YN: 服务费明细!$D$222
Name Dry_Run_YN: 服务费明细!$D$156
Name Dry_Run次数: 项目参数!$C$95
Name DSMB_DMC_IDMC次数: 项目参数!$C$98
Name DSMB_DMC_IDMC统计TFLs_Dry_Run: 服务费明细!$D$167
Name DSMB_DMC_IDMC项目管理: 服务费明细!$D$170
Name DSMB重复TLFs数: 项目参数!#REF!
Name DSUR_TLFs数: 项目参数!#REF!
Name DSUR递交YN: 服务费明细!$D$215
Name DSUR翻译YN: 服务费明细!$D$214
Name DSUR数: 项目参数!$C$103
Name DSUR医学审核YN: 服务费明细!$D$110
Name DSUR撰写_中文YN: 服务费明细!$D$213
Name EDC: 项目参数!$C$65
Name EDC上线前测试YN: 服务费明细!$D$28
Name EDC数据列表审核YN: 服务费明细!$D$105
Name IB更新YN: 服务费明细!$D$221
Name ICSR报告处理YN: 服务费明细!$D$211
Name ICSR报告流程培训YN: 服务费明细!$D$210
Name IPMP审核YN: 服务费明细!$D$74
Name IRC稽查YN: 服务费明细!$D$245
Name IRC日常沟通YN: 服务费明细!$D$82
Name MMP撰写YN: 服务费明细!$D$98
Name MMR_TLFs数: 项目参数!#REF!
Name PD分析: 服务费明细!$D$185
Name PK分析: 服务费明细!$D$184
Name PK列表: 项目参数!$C$94
Name PMP撰写YN: 服务费明细!$D$71
Name Pop报告撰写YN: 服务费明细!$D$194
Name Pop计划撰写YN: 服务费明细!$D$191
Name Pop建模与模拟YN: 服务费明细!$D$193
Name Print_Area_1: 'Rate Card'!$B$29:$O$30
Name Print_Area_2: 'Rate Card'!$A$31:$L$54
Name Print_Area_3: 'Rate Card'!$B$31:$M$54
Name PV报告处理语言: 项目参数!$C$100
Name SAE报告医学审核YN: 服务费明细!$D$109
Name SAE发生率: 项目参数!$C$34
Name SAE个案描述撰写YN: 服务费明细!$D$224
Name SAE交叉报告一致性比对YN: 服务费明细!#REF!
Name SAE例次数: 项目参数!$C$102
Name SAE例数: 项目参数!$C$35
Name SAP_YN: 服务费明细!$D$144
Name SDTM数据集个数: 项目参数!$C$83
Name SDV比例: 项目参数!$C$50
Name SMO日常沟通YN: 服务费明细!$D$78
Name SMP撰写YN: 服务费明细!$D$205
Name SRC_SMC会TLFs数: 项目参数!#REF!
Name SRC_SMC章程撰写YN: 服务费明细!$D$42
Name SRC会议次数: 项目参数!$C$49
Name SRC形式: 服务费明细!$AI$43
Name SUSAR报告递交YN: 服务费明细!#REF!

Sheet 工具维护记录
A1: 序号 | B1: 日期 | C1: 维修点 | D1: 版本号
A2: 1 | B2: 45222 | C2: 更换代码规则 | D2: v3.01
A3: 2 | B3: 45225 | C3: 根据近期HV审阅情况，底表增加HV标准工时 | D3: v3.01
A4: 3 | B4: 45233 | C4: 《T0467 安全性数据库用户体验测试》PVS和PVP默认改为不激活 | D4: v3.01_20231103
A5: 4 | B5: 45237 | C5: Sheet《其他费用》差旅费次数公式微调;Sheet《项目参数》关闭期公式微调;Sheet《注册申报底表》AB列公式修正 | D5: v3.01_20231107
A6: 5 | B6: 45237 | C6: Sheet《项目时间计划》随访期仅描述做调整:项目时间计划拆治疗随访1/2/3,相加等于客户展示页的治疗随访期 | D6: v3.01_20231107
A7: 6 | B7: 45238 | C7: 1.Gateway 测试服务：0次。XML递交测试服务：1次。（这个基本是每个项目都可以这样报价。对于客户指定采用国际双语数据库时，可以增加Gateway测试的费用）2.安全性信号检测：0次。若客户没有明确需要信号检测的服务，以后均可以默认为0。 | D7: v3.01_20231108
A8: 7 | B8: 45253 | C8: 匹配《其他费用》科目，更新ERP导入表 | D8: v3.02_20231123
A9: 8 | B9: 45253 | C9: 与ZJW确认 《保险日常沟通》改为按次 | D9: v3.02_20231123
A10: 9 | B10: 45257 | C10: 根据D365建议，将注册中方案撰写命名和编码稍作调整，并同步至IT | D10: v3.02_20231127
A11: 10 | B11: 45257 | C11: 根据GPP要求，更新1）A092的DTA起草和审核(外部供应商各1份)，2) A092客户展示数量*外部供应商数； | D11: v3.02_20231127
A12: 11 | B12: 45261 | C12: A151 SAE个案描述撰写仅保留一行MM | D12: v3.02_20231201
A13: 12 | B13: 45267 | C13: 《其他费用明细》中差旅次数公式更新 | D13: v3.02_20231207
... A20: 19 | B20: 45341 | C20: Rate Card: 1) 更新2024年Rate Card。 2) 删除三个场景Rate，增加一个Rate系数调整，但须总经理审批方可使用。 3) 删除Rate Card中Rate Cost信息和毛利计算。原则上，商务运营不再支持毛利计算。合同完签后，由财务统一计算初始合同毛利和跟进实际毛利。 | D20: v3.05_20240219
C21: 2. LSA 改为 SA，LST改为ST。 ERP上线测试阶段将同步至D365
A22: 20 | B22: 45343 | C22: 修订SA和ST误操作的问题 | D22: v3.05_20240221
A23: 21 | B23: 45359 | C23: 修订PV A137备注，其他研究 改为 本研究 | D23: v3.05_20240308
A24: 22 | B24: 45461 | C24: 邵健：与工时系统保持一致，“中文名称项目经理修改为临床项目经理, 项目管理副总监 需要修改成临床项目总监” | D24: v3.06_20240618
A25: 23 | B25: 45461 | C25: 尝试增加场景，但由于缺少工时依据，后续待持续优化 | D25: v3.06_20240618
A26: 24 | B26: 45461 | C26: 增加DVP，SAP，SMP的PM审核，各1小时；增加IIT/非注册试验的卫健委备案 | D26: v3.06_20240618
A27: 25 | B27: 45483 | C27: 【服务费明细】 A136、A138和A139 单位调整为"报告版本"，A136增加备注“本项目ICSR报告为中文处理，若产生中英双语录入的报告，按照两个版本/报告计费；若有境外SUSAR报告，可按照1版本/报告计费”；【服务费底表】Q666~O678相应更新；【二三级标注】中二级任务单位调整。 | D27: v3.07_20240712
A28: 26 | B28: 45512 | C28: 【封面】加了韩博和姜总的信息，更新了BD信息，更新了公司地址 【项目时间计划】调整了条目的名称--“访视、差旅及报告小时” 【费用摘要】调整了税前金额格式，保留两位小数。 【服务费底表】调整了 T0331-SAP审核，PM审核的逻辑 【其他费用明细】 调整了格式、细节 | D28: v3.08_20240808
A29: 27 | B29: 45516 | C29: 【服务费明细】更新【D128】dry run的逻辑；【D30】【E30】遗传办变更次数和参数页link 【其他费用明细】hide部分组合；添加CRO间接费用、会务费与供应商费用激活的逻辑；快递费单价保留小数两位，牵头费单价公式调整（iferror a/b）；机构管理费呈现调整（加“”）。 | D29: v3.09_20240812
A30: 28 | B30: 45524 | C30: 【封面】BD信息更新 【其他费用明细】TM随机系统名称更变为 ：TrialMaster 随机发药系统 (RTSM Master) | D30: v3.10_20240820
A31: 29 | B31: 45588 | C31: 【封面】BD信息更新 地址更新 【服务费明细】及【其他费用明细】更新逻辑错误的地方 | D31: v3.11_20241023
A32: 30 | B32: 45611 | C32: 【封面】BD信息更新 logo 地址 | D32: v3.12_20241115
A33: 31 | B33: 45741 | C33: 【封面】BD信息更新 | D33: v3.15_20250325
... A42: 40 | B42: 46037 | C42: PV服务 【服务费明细】A143 DSUR翻译变更成DSUR撰写(英文) 删除A138、A139、A141 【服务费底表】删除T0465、T0466、T0481、T0482、T0484a 临床运营 【服务费明细】增加A243、A244、A245、A246、A247、A277、A278、A279。 删除A020、A021、A022、A023、A024 【服务费底表】增加T0703、T0704、T0705、T0706、T0707、T0708、T0709、T0710、T0711、T0712、T0713、T0714、T0793、T0794、T0795、T0796、T0797、T0798、T0799 删除T0048、T0049、T0050、T0051、T0052、T0053、T0054、T0055、T0056、T0057、T0058、T0059、T0060 医学 【服务费明细】增加A267、A150a、A151a、A001a、A267a 【服务费底表】增加T0775、T0776、T0777、TT0778、TT0779、TT0780 MS角色的任务删除 药理 【服务费明细】增加A270、A268、A269 【服务费底表】增加T0785、T0781、T0782、T0783、T0784、T0785 | D42: v4.0_20260119
C43: 数统 【服务费明细】增加A249、A250、A251、A252、A253、A254、A255、A256、A257、A258、A259、A260、A264、A265、A266、A271、A272、A273、A274、A275、A280、A281、A261、A262、A263 删除A085、A091、A097、A093、A098、A112、A228、A229、A230、A113 【服务费底表】增加T0712、T0713、T0714、T0715、T0716、T0717、T0718、T0719、T0720、T0721、T0722、T0723、T0724、T0725、T0726、T0727、T0728、T0730、T0731、T0732、T0734、T0735、T0736、T0737、T0738、T0739、T0740、T0742、T0743、T0744、T0745、T0746、T0747、T0748、T0749、T0750、T0751、T0752、T0753、T0763、T0764、T0765、T0766、T0767、T0768、T0770、T0771、T0772、T0773、T0774、T0786、T0787、T0788、T0789、T0790、T0741、T0791、T0792、T0754、T0755、T0756、T0757、T0758、T0759、T0760、T0761、T0762 删除T0195、T0196、T0197、T0198、T0199、T0200、T0201、T0611、T0612、T0613、T0246、T0247、T0248、T0249、T0250、T0615、T0616、T0773、T0774、T0258、T0259、T0260、T0261、T0262、T0273、T0274、T0276、T0277、T0278、T0279、T0619、T0280、T0281、T0282、T0283、T0365、T0366、T0367、T0368、T0369、T0370、T0624、T0625、T0626、T0671、T0672、T0673、T0674、T0675、T0676、T0677、T0678、T0371、T0372、T0373、T0374、T0375、T0376、T0627、T0628、T0629
A44: 41 | B44: 46097 | C44: 【服务费明细】新增 A284 A285 A286 A287 A288 | D44: v4.1_20260316
A45: 42 | B45: 46113 | C45: 【服务费明细】新增二级 A289 A290 A291 A292 A293 A294 A295 A296 A297 A298 A299 A300 A301 A302 A303 A304 A305 A306 A307 A308 A309 A310 A311 A312 A313 A314 A315 A316 A317 A318 A319 A320 A321 A322 A323 A324 A325 A326 A327 A328 A329 A330 A331 A332 A333 A334 A335 A336 A337 新增一级 I028 I029 I030 I031 I032 I033 I034 | D45: v4.2_20260401
A46: 43 | B46: 46149 | C46: 【服务费明细】新增二级 A338 【服务费底表】增加T0899 | D46: v4.21_20260507

Sheet 模板注意事项
A1: 模板注意事项 | O1: 报价参考
Q2: 闭口合同酌情
A3: 一、除管理层审阅外，sheet标签颜色为黑的须隐藏+锁定 | O3: 2级编码 | P3: 2级任务 | Q3: 参考
O4: A001 | P4: 方案撰写
A5: 二、角色ID不能重复，增加角色，请联系许小燕 | O5: A002 | P5: 撰写CRF
O6: A003 | P6: 方案版本更新
A7: 三、不用的行，列，sheet表： 不要删除，可以隐藏+锁定 | O7: A004 | P7: 主知情同意撰写
O8: A005 | P8: 主知情同意版本更新
A9: 四、任务编码不能手工修改，增减请联系报价同事 | O9: A006 | P9: 受试者日记卡撰写 | Q9: 健康人无
O10: A007 | P10: 受试者招募广告撰写
A11: 五、<ERP报价导入模板>M2 ,如有尾差，导入ERP前需要手动调入数量为1的任务中，并且增加底色方便知道改了哪里。 | O11: A008 | P11: 召开客户启动会
A12: *尾差定义是几分钱差异 | O12: A009 | P12: 方案培训
A13: *如果差异大于1角，则要检查哪里错了 | O13: A010 | P13: 中心可行性调研 | Q13: 单中心主知情即可,中心知情可不报
O14: A011 | P14: 筛选访视
O15: A012 | P15: 机构立项
O16: A013 | P16: 首次伦理文件准备和递交
O17: A014 | P17: 中心知情同意书撰写 | Q17: 单中心主知情即可,中心知情可不报
O18: A015 | P18: EDC上线前测试
O19: A016 | P19: 研究中心启动文件准备和快递
O20: A017 | P20: 临床试验国家局备案
O21: A018 | P21: 临床试验省局备案 | Q21: 单中心不报
O22: A019 | P22: ClinicalTrials翻译
O23: A020 | P23: 遗传办首次国际合作审批申报 | Q23: A020和A021二选一，可能是走正式流程也可能走备案即可
O24: A021 | P24: 遗传办国际合作备案申报 | Q24: A020和A021二选一，可能是走正式流程也可能走备案即可
O25: A022 | P25: 遗传办数据备份备案申报 | Q25: 仅相关探索适用
O26: A023 | P26: 遗传办变更申报 | Q26: 默认不报
O27: A024 | P27: 遗传办国际合作总结报告撰写
O28: A025 | P28: 召开方案讨论会 | Q28: 涉及启动前的方案变更或方案讨论需要和PI沟通的报上
O29: A026 | P29: 召开首次研究者会 | Q29: 单中心默认不报
O30: A027 | P30: SRC/SMC章程撰写
O31: A028 | P31: 召开SRC/SMC会
O32: A029 | P32: 召开中期研究者会 | Q32: 默认不报
O33: A030 | P33: 召开研究总结会 | Q33: 默认不报
O34: A031 | P34: 准备或签署研究中心合同
O35: A032 | P35: 启动访视
O36: A033 | P36: 启动访视_启动会的医学远程支持
O37: A034 | P37: 常规监查访视
O38: A035 | P38: 计划外访视
O39: A036 | P39: 协同访视
O40: A037 | P40: 远程访视/电话访视
O41: A038 | P41: 质控访视
O42: A039 | P42: 稽查陪同
O43: A040 | P43: 中心安全性报告管理
O44: A041 | P44: 中心费用支付支持 | Q44: 健康人按每中心3次
O45: A042 | P45: 研究简报撰写 | Q45: 单中心默认不报
O46: A043 | P46: 研究药品申请管理
O47: A044 | P47: 研究物资申请和采购管理
O48: A045 | P48: 后续伦理文件准备和递交
O49: A046 | P49: 伦理年度报告准备和递交
O50: A047 | P50: 中心日常支持和管理
O51: A048 | P51: 机构自查访视 | Q51: 预算有限,可仅保留一定比例
O52: A049 | P52: 数据清理访视
O53: A050 | P53: 总结报告CSR中心签字和盖章
O54: A051 | P54: 关闭访视
O55: A052 | P55: 项目管理计划PMP撰写
O56: A053 | P56: 研究中心监查和管理计划CMP撰写
O57: A054 | P57: 中心实验室操作手册审核
O58: A055 | P58: 药物管理手册IPMP审核
O59: A056 | P59: 文件创建和维护
O60: A057 | P60: 供应商筛选和合同建立
O61: A058 | P61: SMO日常沟通
O62: A059 | P62: 招募日常沟通
O63: A060 | P63: 生物分析实验室日常沟通
... O133: A130 | P133: 安全管理计划SMP撰写
O134: A131 | P134: 药物警戒协议撰写 | Q134: 默认不报
O135: A132 | P135: 药物警戒委托协议撰写 | Q135: 默认不报
O136: A133 | P136: 安全性专有数据集建立
O137: A134 | P137: 安全性数据库配置和测试
O138: A135 | P138: ICSR报告流程培训
O139: A136 | P139: ICSR报告处理
O140: A137 | P140: SAE交叉报告一致性比对
O141: A138 | P141: SUSAR报告递交
O142: A139 | P142: SUSAR交叉报告
O143: A140 | P143: 定期汇总安全性报告
O144: A141 | P144: 安全性数据库维护
O145: A142 | P145: DSUR撰写(中文) | Q145: 非注册预算有限可不报
O146: A143 | P146: DSUR翻译
O147: A144 | P147: DSUR递交 | Q147: 默认不报
O148: A145 | P148: 安全性数据库变更 | Q148: 默认不报
O149: A146 | P149: 特殊事件的处理 | Q149: 默认不报
O150: A147 | P150: 安全信号检测
O151: A148 | P151: 安全警戒项目管理 | Q151: 已与韩博确认，月数按照模板设置
O152: A149 | P152: 研究者手册版本更新
O153: A150 | P153: 研究总结报告撰写
O154: A151 | P154: SAE个案描述撰写
O155: A152 | P155: 其他报告撰写
O156: A153 | P156: 召开非盲客户启动会
O157: A154 | P157: 非盲监查计划撰写
O158: A155 | P158: 非盲药物管理计划撰写
O159: A156 | P159: 非盲团队培训
O160: A157 | P160: 召开非盲监查员会
O161: A158 | P161: 召开非盲客户电话会
O162: A159 | P162: 非盲启动访视
O163: A160 | P163: 非盲常规监查访视
... O211: A208 | P211: 方案撰写/注册阶段

Sheet 签批页
B2: 客户名称 | C2: =封面!$C$20 -> 0 | F2: 方案名称或项目简称 | G2: =封面!$C$12 -> 0
B3: 商机编号 | F3: 商机主题
B4: 业务类型 | F4: 是否已完成业务审阅
B5: 是否申请折扣 | C5: =IF(费用摘要!$D$25>0,"是","否") -> 否 | F5: 预期折扣比例 | G5: ="服务费"&费用摘要!$G$25&费用摘要!C27&费用摘要!G27 -> 服务费0有临系统0
B6: 其他描述 | F6: 客户交付版本号 | G6: =费用摘要!C2 -> 0
B7: 中心数/个 | C7: =启动中心数 -> 4 | F7: 入组受试者/例 | G7: =入组受试者数 -> 30
B8: 服务期/月 | C8: =项目参数!$C$37 -> 22.5 | F8: 入组期/月 | G8: =筛选月+入组月 -> 6
B9: 治疗随访/月 | C9: =治疗月+随访月+长随访月 -> 7 | F9: 启动和关闭/月 | G9: =项目参数!$C$41+项目参数!$C$44+项目参数!$C$45 -> 9
B10: 服务范围 | F10: 间接范围 | J10: 供应商
B11: 参数变化描述 | F11: 服务范围变化描述
B12: 附件
B13: 折扣前/含税 | C13: 总费用 | D13: =费用摘要!$D$38 -> 3727153.9 | F13: 服务费 | G13: =费用摘要!$D$24 -> 3569865.6
C14: 单例总费用 | D14: =IFERROR(D13/入组受试者数,0) -> 124238.46 | F14: 单例服务费 | G14: =IFERROR(G13/入组受试者数,0) -> 118995.52
B15: 类别(折扣后/含税) | C15: 单例总费用 | D15: 单例服务费 | E15: 总费用 | F15: 服务费 | G15: 有临系统费 | H15: 代垫费 (内部供应商+CRO间接费+会议费) | I15: 过手费 (外部供应商+中心)
B16: 当前版本 | C16: =IFERROR($E$16/入组受试者数,0) -> 124238.46 | D16: =IFERROR($F$16/入组受试者数,0) -> 118995.52 | E16: =费用摘要!$F$38 -> 3727153.9 | F16: =费用摘要!$F$24 -> 3569865.6 | G16: =费用摘要!$F$27*(1+费用摘要!C33) -> 0 | H16: =(其他费用明细!$I$28+其他费用明细!$I$33+其他费用明细!$I$35+其他费用明细!$I$19+其他费用明细!$I$7+其他费用明细!I45)*(1+其他费用明细!D73) -> 157288.3 | I16: =(其他费用明细!$I$46+SUM(,其他费用明细!I29:$I$30,其他费用明细!$I$34,其他费用明细!$I$36:$I$44))*(1+其他费用明细!$D$73) -> 0
B17: 差异 (更新版vs上一版) | C17: =C16-C18 -> 124238.46 | D17: =D16-D18 -> 118995.52 | E17: =E16-E18 -> 3727153.9 | F17: =F16-F18 -> 3569865.6 | G17: =G16-G18 -> 0 | H17: =H16-H18 -> 157288.3 | I17: =I16-I18 -> 0
B18: 上一版 | J18: 更新版本时,先复制数值此行数据
B20: 不含税 | I20: 含税 | J20: =费用摘要!$C$23 -> 0.066
B21: 业务 | C21: 小计 | D21: 折扣后小计 | E21: 占比 | F21: 单例小计 | G21: 单例折扣后小计 | I21: 业务 | J21: 小计 | K21: 折扣后小计 | L21: 占比 | M21: 单例小计 | N21: 单例折扣后小计
B22: 临床药理 | C22: =SUMIF(服务费底表!$H:$H,$B22,服务费底表!$AD:$AD)+SUMIF(注册申报底表!$G:$G,$B22,注册申报底表!$AA:$AA) -> 136995 | D22: =SUMIF(服务费底表!$H:$H,$B22,服务费底表!$AG:$AG)+SUMIF(注册申报底表!$G:$G,$B22,注册申报底表!$AD:$AD) -> 136995 | E22: =IFERROR(D22/$D$36,0) -> 0.040908171 | F22: =IFERROR($C22/入组受试者数,0) -> 4566.5 | G22: =IFERROR($D22/入组受试者数,0) -> 4566.5 | I22: 临床药理 | J22: =C22*(1+$J$20) -> 146036.67 | K22: =D22*(1+$J$20) -> 146036.67 | L22: =IFERROR(K22/$K$36,0) -> 0.040908171 | M22: =IFERROR($J22/入组受试者数,0) -> 4867.889 | N22: =IFERROR($K22/入组受试者数,0) -> 4867.889
B23: 临床运营 | C23: =SUMIF(服务费底表!$H:$H,$B23,服务费底表!$AD:$AD)+SUMIF(注册申报底表!$G:$G,$B23,注册申报底表!$AA:$AA) -> 1926585 | D23: =SUMIF(服务费底表!$H:$H,$B23,服务费底表!$AG:$AG)+SUMIF(注册申报底表!$G:$G,$B23,注册申报底表!$AD:$AD) -> 1926585 | E23: =IFERROR(D23/$D$36,0) -> 0.57529886 | F23: =IFERROR($C23/入组受试者数,0) -> 64219.5 | G23: =IFERROR($D23/入组受试者数,0) -> 64219.5 | I23: 临床运营 | J23: =C23*(1+$J$20) -> 2053739.6 | K23: =D23*(1+$J$20) -> 2053739.6 | L23: =IFERROR(K23/$K$36,0) -> 0.57529886 | M23: =IFERROR($J23/入组受试者数,0) -> 68457.987 | N23: =IFERROR($K23/入组受试者数,0) -> 68457.987
B24: 项目管理 | C24: =SUMIF(服务费底表!$S:$S,$B24,服务费底表!$AD:$AD)+SUMIF(注册申报底表!$R:$R,$B24,注册申报底表!$AA:$AA) -> 875135 | D24: =SUMIF(服务费底表!$S:$S,$B24,服务费底表!$AG:$AG)+SUMIF(注册申报底表!$R:$R,$B24,注册申报底表!$AD:$AD) -> 875135 | E24: =IFERROR(D24/$D$36,0) -> 0.26132466 | F24: =IFERROR($C24/入组受试者数,0) -> 29171.167 | G24: =IFERROR($D24/入组受试者数,0) -> 29171.167 | I24: 项目管理 | J24: =C24*(1+$J$20) -> 932893.91 | K24: =D24*(1+$J$20) -> 932893.91 | L24: =IFERROR(K24/$K$36,0) -> 0.26132466 | M24: =IFERROR($J24/入组受试者数,0) -> 31096.464 | N24: =IFERROR($K24/入组受试者数,0) -> 31096.464
B25: 临床监查 | C25: =SUMIF(服务费底表!$S:$S,$B25,服务费底表!$AD:$AD)+SUMIF(注册申报底表!$R:$R,$B25,注册申报底表!$AA:$AA) -> 1051450 | D25: =SUMIF(服务费底表!$S:$S,$B25,服务费底表!$AG:$AG)+SUMIF(注册申报底表!$R:$R,$B25,注册申报底表!$AD:$AD) -> 1051450 | E25: =IFERROR(D25/$D$36,0) -> 0.3139742 | F25: =IFERROR($C25/入组受试者数,0) -> 35048.333 | G25: =IFERROR($D25/入组受试者数,0) -> 35048.333 | I25: 临床监查 | J25: =C25*(1+$J$20) -> 1120845.7 | K25: =D25*(1+$J$20) -> 1120845.7 | L25: =IFERROR(K25/$K$36,0) -> 0.3139742 | M25: =IFERROR($J25/入组受试者数,0) -> 37361.523 | N25: =IFERROR($K25/入组受试者数,0) -> 37361.523
B26: 数统 | C26: =SUM(C27:C29) -> 457861.5 | D26: =SUM(D27:D29) -> 457861.5 | E26: =IFERROR(D26/$D$36,0) -> 0.13672234 | F26: =IFERROR($C26/入组受试者数,0) -> 15262.05 | G26: =IFERROR($D26/入组受试者数,0) -> 15262.05 | I26: 数统 | J26: =C26*(1+$J$20) -> 488080.36 | K26: =D26*(1+$J$20) -> 488080.36 | L26: =IFERROR(K26/$K$36,0) -> 0.13672234 | M26: =IFERROR($J26/入组受试者数,0) -> 16269.345 | N26: =IFERROR($K26/入组受试者数,0) -> 16269.345
B27: 数据管理 | C27: =SUMIF(服务费底表!$S:$S,$B27,服务费底表!$AD:$AD)+SUMIF(注册申报底表!$R:$R,$B27,注册申报底表!$AA:$AA) -> 193399 | D27: =SUMIF(服务费底表!$S:$S,$B27,服务费底表!$AG:$AG)+SUMIF(注册申报底表!$R:$R,$B27,注册申报底表!$AD:$AD) -> 193399 | E27: =IFERROR(D27/$D$36,0) -> 0.057751008 | F27: =IFERROR($C27/入组受试者数,0) -> 6446.6333 | G27: =IFERROR($D27/入组受试者数,0) -> 6446.6333 | I27: 数据管理 | J27: =C27*(1+$J$20) -> 206163.33 | K27: =D27*(1+$J$20) -> 206163.33 | L27: =IFERROR(K27/$K$36,0) -> 0.057751008 | M27: =IFERROR($J27/入组受试者数,0) -> 6872.1111 | N27: =IFERROR($K27/入组受试者数,0) -> 6872.1111
B28: 生物统计 | C28: =SUMIF(服务费底表!$S:$S,$B28,服务费底表!$AD:$AD)+SUMIF(注册申报底表!$R:$R,$B28,注册申报底表!$AA:$AA) -> 82100 | D28: =SUMIF(服务费底表!$S:$S,$B28,服务费底表!$AG:$AG)+SUMIF(注册申报底表!$R:$R,$B28,注册申报底表!$AD:$AD) -> 82100 | E28: =IFERROR(D28/$D$36,0) -> 0.024515937 | F28: =IFERROR($C28/入组受试者数,0) -> 2736.6667 | G28: =IFERROR($D28/入组受试者数,0) -> 2736.6667 | I28: 生物统计 | J28: =C28*(1+$J$20) -> 87518.6 | K28: =D28*(1+$J$20) -> 87518.6 | L28: =IFERROR(K28/$K$36,0) -> 0.024515937 | M28: =IFERROR($J28/入组受试者数,0) -> 2917.2867 | N28: =IFERROR($K28/入组受试者数,0) -> 2917.2867
B29: 统计分析 | C29: =SUMIF(服务费底表!$S:$S,$B29,服务费底表!$AD:$AD)+SUMIF(注册申报底表!$R:$R,$B29,注册申报底表!$AA:$AA) -> 182362.5 | D29: =SUMIF(服务费底表!$S:$S,$B29,服务费底表!$AG:$AG)+SUMIF(注册申报底表!$R:$R,$B29,注册申报底表!$AD:$AD) -> 182362.5 | E29: =IFERROR(D29/$D$36,0) -> 0.054455391 | F29: =IFERROR($C29/入组受试者数,0) -> 6078.75 | G29: =IFERROR($D29/入组受试者数,0) -> 6078.75 | I29: 统计分析 | J29: =C29*(1+$J$20) -> 194398.42 | K29: =D29*(1+$J$20) -> 194398.42 | L29: =IFERROR(K29/$K$36,0) -> 0.054455391 | M29: =IFERROR($J29/入组受试者数,0) -> 6479.9475 | N29: =IFERROR($K29/入组受试者数,0) -> 6479.9475
B30: 药物警戒 | C30: =SUMIF(服务费底表!$H:$H,$B30,服务费底表!$AD:$AD)+SUMIF(注册申报底表!$G:$G,$B30,注册申报底表!$AA:$AA) -> 175875 | D30: =SUMIF(服务费底表!$H:$H,$B30,服务费底表!$AG:$AG)+SUMIF(注册申报底表!$G:$G,$B30,注册申报底表!$AD:$AD) -> 175875 | E30: =IFERROR(D30/$D$36,0) -> 0.052518154 | F30: =IFERROR($C30/入组受试者数,0) -> 5862.5 | G30: =IFERROR($D30/入组受试者数,0) -> 5862.5 | I30: 药物警戒 | J30: =C30*(1+$J$20) -> 187482.75 | K30: =D30*(1+$J$20) -> 187482.75 | L30: =IFERROR(K30/$K$36,0) -> 0.052518154 | M30: =IFERROR($J30/入组受试者数,0) -> 6249.425 | N30: =IFERROR($K30/入组受试者数,0) -> 6249.425
B31: 医学 | C31: =SUMIF(服务费底表!$H:$H,$B31,服务费底表!$AD:$AD)+SUMIF(注册申报底表!$G:$G,$B31,注册申报底表!$AA:$AA) -> 651525.5 | D31: =SUMIF(服务费底表!$H:$H,$B31,服务费底表!$AG:$AG)+SUMIF(注册申报底表!$G:$G,$B31,注册申报底表!$AD:$AD) -> 651525.5 | E31: =IFERROR(D31/$D$36,0) -> 0.19455248 | F31: =IFERROR($C31/入组受试者数,0) -> 21717.517 | G31: =IFERROR($D31/入组受试者数,0) -> 21717.517 | I31: 医学 | J31: =C31*(1+$J$20) -> 694526.18 | K31: =D31*(1+$J$20) -> 694526.18 | L31: =IFERROR(K31/$K$36,0) -> 0.19455248 | M31: =IFERROR($J31/入组受试者数,0) -> 23150.873 | N31: =IFERROR($K31/入组受试者数,0) -> 23150.873
B32: 医学撰写 | C32: =SUMIF(服务费底表!$S:$S,$B32,服务费底表!$AD:$AD)+SUMIF(注册申报底表!$R:$R,$B32,注册申报底表!$AA:$AA) -> 238275 | D32: =SUMIF(服务费底表!$S:$S,$B32,服务费底表!$AG:$AG)+SUMIF(注册申报底表!$R:$R,$B32,注册申报底表!$AD:$AD) -> 238275 | E32: =IFERROR(D32/$D$36,0) -> 0.071151461 | F32: =IFERROR($C32/入组受试者数,0) -> 7942.5 | G32: =IFERROR($D32/入组受试者数,0) -> 7942.5 | I32: 医学撰写 | J32: =C32*(1+$J$20) -> 254001.15 | K32: =D32*(1+$J$20) -> 254001.15 | L32: =IFERROR(K32/$K$36,0) -> 0.071151461 | M32: =IFERROR($J32/入组受试者数,0) -> 8466.705 | N32: =IFERROR($K32/入组受试者数,0) -> 8466.705
B33: 医学监查 | C33: =SUMIF(服务费底表!$S:$S,$B33,服务费底表!$AD:$AD)+SUMIF(注册申报底表!$R:$R,$B33,注册申报底表!$AA:$AA) -> 413250.5 | D33: =SUMIF(服务费底表!$S:$S,$B33,服务费底表!$AG:$AG)+SUMIF(注册申报底表!$R:$R,$B33,注册申报底表!$AD:$AD) -> 413250.5 | E33: =IFERROR(D33/$D$36,0) -> 0.12340101 | F33: =IFERROR($C33/入组受试者数,0) -> 13775.017 | G33: =IFERROR($D33/入组受试者数,0) -> 13775.017 | I33: 医学监查 | J33: =C33*(1+$J$20) -> 440525.03 | K33: =D33*(1+$J$20) -> 440525.03 | L33: =IFERROR(K33/$K$36,0) -> 0.12340101 | M33: =IFERROR($J33/入组受试者数,0) -> 14684.168 | N33: =IFERROR($K33/入组受试者数,0) -> 14684.168
B34: 质量保证 | C34: =SUMIF(服务费底表!$H:$H,$B34,服务费底表!$AD:$AD)+SUMIF(注册申报底表!$G:$G,$B34,注册申报底表!$AA:$AA) -> 0 | D34: =SUMIF(服务费底表!$H:$H,$B34,服务费底表!$AG:$AG)+SUMIF(注册申报底表!$G:$G,$B34,注册申报底表!$AD:$AD) -> 0 | E34: =IFERROR(D34/$D$36,0) -> 0 | F34: =IFERROR($C34/入组受试者数,0) -> 0 | G34: =IFERROR($D34/入组受试者数,0) -> 0 | I34: 质量保证 | J34: =C34*(1+$J$20) -> 0 | K34: =D34*(1+$J$20) -> 0 | L34: =IFERROR(K34/$K$36,0) -> 0 | M34: =IFERROR($J34/入组受试者数,0) -> 0 | N34: =IFERROR($K34/入组受试者数,0) -> 0
B35: 注册 | C35: =SUMIF(注册申报底表!$G:$G,$B35,注册申报底表!$AA:$AA) -> 0 | D35: =SUMIF(服务费底表!$H:$H,$B35,服务费底表!$AG:$AG)+SUMIF(注册申报底表!$G:$G,$B35,注册申报底表!$AD:$AD) -> 0 | E35: =IFERROR(D35/$D$36,0) -> 0 | F35: =IFERROR($C35/入组受试者数,0) -> 0 | G35: =IFERROR($D35/入组受试者数,0) -> 0 | I35: 注册 | J35: =C35*(1+$J$20) -> 0 | K35: =D35*(1+$J$20) -> 0 | L35: =IFERROR(K35/$K$36,0) -> 0 | M35: =IFERROR($J35/入组受试者数,0) -> 0 | N35: =IFERROR($K35/入组受试者数,0) -> 0
B36: 服务费 | C36: =SUM(C22:C23,C27:C31,C34:C35) -> 3348842 | D36: =SUM(D22:D23,D27:D31,D34:D35) -> 3348842 | E36: =SUM(E22:E23,E27:E31,E34:E35) -> 1 | F36: =SUM(F22:F23,F27:F31,F34:F35) -> 111628.07 | G36: =SUM(G22:G23,G27:G31,G34:G35) -> 111628.07 | I36: 服务费 | J36: =SUM(J22:J23,J27:J31,J34:J35) -> 3569865.6 | K36: =SUM(K22:K23,K27:K31,K34:K35) -> 3569865.6 | L36: =SUM(L22:L23,L27:L31,L34:L35) -> 1 | M36: =SUM(M22:M23,M27:M31,M34:M35) -> 118995.52 | N36: =SUM(N22:N23,N27:N31,N34:N35) -> 118995.52
B38: 服务费含税 | C38: =C36*(1+服务费明细!$C$252) -> 3569865.6 | D38: =D36*(1+服务费明细!$C$252) -> 3569865.6 | F38: =F36*(1+服务费明细!$C$252) -> 118995.52 | G38: =G36*(1+服务费明细!$C$252) -> 118995.52 | I38: 服务费含税Check | J38: =J36-C38 -> 0 | K38: =K36-D38 -> 0 | M38: =M36-F38 -> 0 | N38: =N36-G38 -> 0
B39: 其他费用含税 | C39: =费用摘要!D34 -> 157288.3 | D39: =费用摘要!F34 -> 157288.3 | F39: =IFERROR(C39/入组受试者数,0) -> 5242.9433 | G39: =IFERROR(D39/入组受试者数,0) -> 5242.9433
B40: 总计含税 | C40: =C38+C39 -> 3727153.9 | D40: =D38+D39 -> 3727153.9 | F40: =F38+F39 -> 124238.46 | G40: =G38+G39 -> 124238.46
B42: 服务费含税Check | C42: =C38-G13 -> 0.0020000003 | D42: =D38-F16 -> 0.0020000003 | F42: =F38-G14 -> 6.6666675e-05 | G42: =G38-D16 -> 6.6666675e-05
B43: 其他费用含税Check | C43: =C39-(D13-G13) -> 0 | D43: =D39-SUM(G16:I16) -> 0 | F43: =F39-(D14-G14) -> 1.8189894e-11 | G43: =G39-(C16-D16) -> 1.8189894e-11
B50: 名称-CN | C50: 部门名称-EN | D50: 业务属性 | E50: 报价岗位_通用名 | F50: 报价岗位_EN Abbr. | G50: 报价总工时
B51: 临床运营 | C51: CO | D51: 临床监查 | E51: 临床监查员 | F51: CRA | G51: =SUMIF(服务费底表!$T:$T,$F51,服务费底表!$AC:$AC)+SUMIF(注册申报底表!$S:$S,$F51,注册申报底表!$Z:$Z) -> 2739.5
B52: 临床运营 | C52: CO | D52: 临床监查 | E52: 临床试验助理 | F52: CTA | G52: =SUMIF(服务费底表!$T:$T,$F52,服务费底表!$AC:$AC)+SUMIF(注册申报底表!$S:$S,$F52,注册申报底表!$Z:$Z) -> 281
B53: 临床运营 | C53: CO | D53: 项目管理 | E53: 项目经理 | F53: PM | G53: =SUMIF(服务费底表!$T:$T,$F53,服务费底表!$AC:$AC)+SUMIF(注册申报底表!$S:$S,$F53,注册申报底表!$Z:$Z) -> 1291.9
B54: 临床运营 | C54: CO | D54: 项目管理 | E54: 项目管理副总监 | F54: PMD | G54: =SUMIF(服务费底表!$T:$T,$F54,服务费底表!$AC:$AC)+SUMIF(注册申报底表!$S:$S,$F54,注册申报底表!$Z:$Z) -> 44.25
B55: 临床运营 | C55: CO | D55: 临床监查 | E55: 临床质量控制经理 | F55: QCM | G55: =SUMIF(服务费底表!$T:$T,$F55,服务费底表!$AC:$AC)+SUMIF(注册申报底表!$S:$S,$F55,注册申报底表!$Z:$Z) -> 97
B56: 注册 | C56: RA | D56: 注册事务 | E56: 注册经理 | F56: RAM | G56: =SUMIF(服务费底表!$T:$T,$F56,服务费底表!$AC:$AC)+SUMIF(注册申报底表!$S:$S,$F56,注册申报底表!$Z:$Z) -> 0
B57: 注册 | C57: RA | D57: 注册事务 | E57: 注册总监 | F57: RAD | G57: =SUMIF(服务费底表!$T:$T,$F57,服务费底表!$AC:$AC)+SUMIF(注册申报底表!$S:$S,$F57,注册申报底表!$Z:$Z) -> 0
B58: 医学 | C58: MA | D58: 医学撰写/医学监查 | E58: 医学总监 | F58: MD | G58: =SUMIF(服务费底表!$T:$T,$F58,服务费底表!$AC:$AC)+SUMIF(注册申报底表!$S:$S,$F58,注册申报底表!$Z:$Z) -> 121.2
B59: 医学 | C59: MA | D59: 医学撰写/医学监查 | E59: 医学经理 | F59: MM | G59: =SUMIF(服务费底表!$T:$T,$F59,服务费底表!$AC:$AC)+SUMIF(注册申报底表!$S:$S,$F59,注册申报底表!$Z:$Z) -> 817.75
B60: 医学 | C60: MA | D60: 医学撰写/医学监查 | E60: 医学专员 | F60: MS | G60: =SUMIF(服务费底表!$T:$T,$F60,服务费底表!$AC:$AC)+SUMIF(注册申报底表!$S:$S,$F60,注册申报底表!$Z:$Z) -> 0
B61: 药物警戒 | C61: PV | D61: 药物警戒 | E61: 药物警戒经理 | F61: PVM | G61: =SUMIF(服务费底表!$T:$T,$F61,服务费底表!$AC:$AC)+SUMIF(注册申报底表!$S:$S,$F61,注册申报底表!$Z:$Z) -> 157.75
B62: 药物警戒 | C62: PV | D62: 药物警戒 | E62: 药物警戒医生 | F62: PVP | G62: =SUMIF(服务费底表!$T:$T,$F62,服务费底表!$AC:$AC)+SUMIF(注册申报底表!$S:$S,$F62,注册申报底表!$Z:$Z) -> 104.5
... B76: 临床药理 | C76: CP | D76: 临床药理 | E76: 临床药理高级专员 | F76: CPSS | G76: =SUMIF(服务费底表!$T:$T,$F76,服务费底表!$AC:$AC)+SUMIF(注册申报底表!$S:$S,$F76,注册申报底表!$Z:$Z) -> 86.75
G79: =SUM(G51:G76) -> 7698.85

Sheet Rebid记录
A2: 商机编号 | C2: 有临CRM系统形成的商机编号
G3: 含税
A4: 交付版本号 | B4: PM | C4: 报价人员 | D4: 交付日期 | E4: 参数变化 | F4: 服务范围变化 | G4: 合同额 | H4: 服务费 | I4: 其他费用 | J4: TrialMaster系统 | K4: CRO间接费用 | L4: 会议相关费用 | M4: 供应商费用 | N4: 研究中心费用 | O4: 辅助文件 (截图等)
A5: v1 | G5: =SUM(H5:N5) -> 0
A6: v2 | G6: =SUM(H6:N6) -> 0
A7: v3 | G7: =SUM(H7:N7) -> 0
A8: v4 | G8: =SUM(H8:N8) -> 0
A9: v5 | G9: =SUM(H9:N9) -> 0
A10: v6 | G10: =SUM(H10:N10) -> 0
A11: v7 | G11: =SUM(H11:N11) -> 0
A12: v8 | G12: =SUM(H12:N12) -> 0

Sheet 合同变更记录
A1: 项目编号 | C1: 有临项目立项和交接流程形成的项目编号
E2: 含税
A3: 合同类型 | B3: PM | C3: 报价人员 | D3: 签署日期 (年月日) | E3: 合同额 | F3: 服务费 | G3: 其他费用 | H3: 参数变更 | I3: 服务范围变更 | J3: 合同编号 | K3: 辅助文件 (截图等)
A4: 初始合同 | E4: =F4+G4 -> 0 | H4: NA | I4: NA
E5: =F5+G5 -> 0
E6: =F6+G6 -> 0
E7: =F7+G7 -> 0
E8: =F8+G8 -> 0
E9: =F9+G9 -> 0
E10: =F10+G10 -> 0
E11: =F11+G11 -> 0
E12: =F12+G12 -> 0
E13: =F13+G13 -> 0
D17: 截止当前本项目费用 | E17: =SUM(E4:E13) -> 0 | F17: =SUM(F4:F13) -> 0 | G17: =SUM(G4:G13) -> 0

Sheet 封面
B7: 临床试验服务预算计划书
B12: 方案或项目名称:
B18: 提供给
B20: 客户：
B25: 提供方： | C25: 上海有临医药科技有限公司(简称"有临")
B27: 地址： | C27: 上海市浦东新区育仁路188弄1号楼10楼（科学之门T2）
B29: 联系人: | F29: 姓名 | G29: 电话 | H29: 邮箱
F30: 谭玉怡 | G30: 15626128895 | H30: tanyy@unionclin.com
B31: 邮箱: | C31: =IF($C$29="","",INDEX($H:$H,MATCH($C$29,$F:$F,0))) | F31: 王伟彪 | G31: 15232100683 | H31: wangwb@unionclin.com
F32: 李乔 | G32: 18851700778 | H32: liq@unionclin.com
B33: 电话: | C33: =IF($C$29="","",INDEX($G:$G,MATCH($C$29,$F:$F,0))) | F33: 史永健 | G33: 15800945389 | H33: shiyj@unionclin.com
F34: 姜岚 | G34: 13611830883 | H34: jiangl@unionclin.com
F35: 韩海雄 | G35: 13601749801 | H35: haixiong.han@unionclin.com
F36: 魏晓巍 | G36: 18510789550 | H36: weixw@unionclin.com
F37: 董剑峰 | G37: 18701581821 | H37: dongjf@unionclin.com
F38: 刘冬雪 | G38: 15244624058 | H38: liudx@unionclin.com
F39: 顾盼盼 | G39: 13675191158 | H39: gupp@unionclin.com
F40: 刘婷婷 | G40: 13882274379 | H40: liutt@unionclin.com
F41: 周艳 | G41: 13818233228 | H41: zhouy@unionclin.com
B43: 备注条款：
B44: 1. | C44: 临床试验服务预算仅作为正式合作协议/合同的附件内容，在双方开展正式合作之前，应签署连同本临床试验服务预算的正式协议/合同；
B45: 2. | C45: 鉴于客户项目任务的时间要求，有临同意在签署正式的合作协议之前，如客户出具先行同意本临床试验服务预算，有临在获得书面同意后可以先行开展工作；先行同意后，如客户出于策略考虑，项目提前结束，客户应支付有临已发生的的费用，包括服务费和实报费。 如先行同意，客户应签署以下签字页，盖章后将正式书面文件提交给有临。
B47: 是否先行同意：
B49: 客户签字及盖章：
B51: 日期：

Sheet 项目参数
A1: 报价场景(必选) | C1: 人员场景(必选) | D1: 商机编号(必填) | E1: Hide
A2: 注册肿瘤I/II期 | C2: 标准 | E2: Hide
E3: Hide
A4: 序号 | B4: 业务属性 | C4: 是否执行 | D4: 优惠率 | E4: Hide | F4: 不对外展示，内部说明
A5: 1 | B5: 医学撰写 | C5: 1 | E5: Hide
A6: 2 | B6: 医学监查 | C6: 1 | E6: Hide
A7: 3 | B7: 项目管理 | C7: 1 | E7: Hide
A8: 4 | B8: 临床监查 | C8: 1 | E8: Hide
A9: 5 | B9: 数据管理 | C9: 1 | E9: Hide
A10: 6 | B10: 生物统计 | C10: 1 | E10: Hide
A11: 7 | B11: 统计分析 | C11: 1 | E11: Hide
A12: 8 | B12: 临床药理 | C12: 1 | E12: Hide
A13: 9 | B13: 药物警戒 | C13: 1 | E13: Hide
A14: 10 | B14: 质量保证 | C14: 0 | E14: Hide
A15: 11 | B15: 注册事务 | C15: 0 | E15: Hide
A17: 项目参数
A18: 类别 | B18: 参数 | C18: 参数值 | D18: 备注
A19: 项目概要 | B19: 项目类型 | E19: Hide
A20: 项目概要 | B20: 治疗领域 | E20: Hide
A21: 项目概要 | B21: 适应症
A22: 项目概要 | B22: 试验目的 | C22: 注册申报 | D22: ="试验分期:"&E22 -> 试验分期:Ia | E22: Ia
A23: 项目概要 | B23: 遗传办递交和跟进 | C23: 适用
A24: 项目概要 | B24: 数据收集的语言 | C24: 中文
A25: 项目概要 | B25: 试验地点 | C25: 国内试验
A26: 项目概要 | B26: 试验参与者类型 | C26: 肿瘤患者
A27: 项目信息 | B27: 调研中心数 | C27: =IF(启动中心数<=10,ROUNDUP(启动中心数*200%,0),ROUNDUP(启动中心数*150%,0)) -> 8 | D27: 默认电话调研 | F27: 默认10个中心以内，200%;10个以上,150%; 预算敏感,可合理下调。
A28: 项目信息 | B28: 筛选中心数 | C28: =ROUNDUP(启动中心数*130%,0) -> 6 | F28: 默认10个中心以内，130%;10个以上,120%; 预算敏感,可合理下调。
A29: 项目信息 | B29: 启动中心数 | C29: 4
A30: 项目信息 | B30: 筛选试验参与者数 | C30: {=ROUND(入组试验参与者数/(1-D30),0)} -> 38 | D30: 0.2 | F30: 健康人50%-70%, 其他20%,罕见靶点/入排难可提高
A31: 项目信息 | B31: 入组试验参与者数 | C31: 30 | K31: 服务周期大于24mths时,请勾选Y
A32: 项目信息 | B32: 完成试验参与者数 | C32: {=ROUND(入组试验参与者数*(1-D32),0)} -> 24 | D32: 0.2 | E32: Hide
A33: 项目信息 | B33: 平均入组率 | C33: {=IFERROR(ROUND(入组试验参与者数/启动中心数/入组月,2),0)} -> 1.25 | D33: 每月每中心 | E33: Hide | H33: 通胀系数 | J33: 添加通胀 | K33: N | L33: =IF(K33="Y",L48,1) -> 1
A34: 项目信息 | B34: SAE 发生率 | C34: 0.3 | F34: 肿瘤SAE发生率按30%发生率计算； 心血管15%-25%；其他非健康人：10%；健康人：1%-5%
A35: 项目信息 | B35: SAE 例数 | C35: {=ROUNDUP(入组试验参与者数*SAE发生率,0)} -> 9 | E35: 编程
A36: 项目信息 | B36: 招募试验参与者数 | C36: {=ROUNDUP(筛选试验参与者数*200%,0)} -> 76
A37: 项目信息 | B37: 试验周期(月) | C37: =IFERROR(ROUND(项目时间计划!G20,1),) -> 22.5 | D37: 时间计划包括客户的审批时间，如因客户审批回复不及时等原因，项目时间计划将相应调整。关键节点如遇春节，十一等法定节假日，项目时间计划将相应顺延。 | G37: 年 | H37: 月数 | I37: 月数占比 | J37: 通胀每年 | K37: 累计通胀 | L37: 平均通胀
A38: 项目信息 | B38: 项目开始时间 (年月日) | C38: =IFERROR(项目时间计划!$E$20,) -> 46082 | D38: 研究中心启动时间为预估，如因研究药品不能及时到位或其他非CRO直接原因导致的研究中心不能及时启动，项目时间计划将相应调整。 | F38: 注意开始时间是否合理 | G38: 45657 | H38: =IF(AND(YEAR($C$38)<=YEAR($G$38),YEAR($C$39)>=YEAR($G38)),DATEDIF($C$38,$G38,"M")+1,0) -> 0 | I38: =H38/$H$48 -> 0 | J38: 1 | K38: 1 | L38: =ROUND(I38*K38,4) -> 0
A39: 项目信息 | B39: 项目结束时间 (年月日) | C39: =IFERROR(项目时间计划!$F$20,) -> 46763.975 | G39: 46022 | H39: =IF(YEAR($C$39)=YEAR($G39),MONTH($C$39),IF(AND(YEAR($C$38)<=YEAR($G39),YEAR($C$39)>=YEAR($G39)),DATEDIF($C$38,$G39,"M")+1-$H$38,0)) -> 0 | I39: =H39/$H$48 -> 0 | J39: 1 | K39: =J38*J39 -> 1 | L39: =ROUND(I39*K39,4) -> 0
A40: 项目信息 | B40: 方案定稿(月) | C40: =方案定稿月 -> 0.5 | G40: 46387 | H40: =IF(YEAR($C$39)=YEAR($G40),MONTH($C$39),IF(AND(YEAR($C$38)<=YEAR($G40),YEAR($C$39)>=YEAR($G40)),DATEDIF($C$38,$G40,"M")+1-SUM($H$38:H39),0)) -> 10 | I40: =H40/$H$48 -> 0.43478261 | J40: 1.05 | K40: =K39*J40 -> 1.05 | L40: =ROUND(I40*K40,4) -> 0.4565
A41: 项目信息 | B41: 启动期(月) | C41: =首家伦理月+遗传办月+首家合同月+项目时间计划!$G$8 -> 3 | G41: 46752 | H41: =IF(YEAR($C$39)=YEAR($G41),MONTH($C$39),IF(AND(YEAR($C$38)<=YEAR($G41),YEAR($C$39)>=YEAR($G41)),DATEDIF($C$38,$G41,"M")+1-SUM($H$38:H40),0)) -> 12 | I41: =H41/$H$48 -> 0.52173913 | J41: 1.05 | K41: =K40*J41 -> 1.1025 | L41: =ROUND(I41*K41,4) -> 0.5752
A42: 项目信息 | B42: 入组期(月) | C42: =筛选月+入组月 -> 6 | D42: 首例入组至末例入组 | F42: 数据采集类研究，客户呈现时修改描述"数据采集期" | G42: 47118 | H42: =IF(YEAR($C$39)=YEAR($G42),MONTH($C$39),IF(AND(YEAR($C$38)<=YEAR($G42),YEAR($C$39)>=YEAR($G42)),DATEDIF($C$38,$G42,"M")+1-SUM($H$38:H41),0)) -> 1 | I42: =H42/$H$48 -> 0.043478261 | J42: 1.05 | K42: =K41*J42 -> 1.157625 | L42: =ROUND(I42*K42,4) -> 0.0503
A43: 项目信息 | B43: 治疗随访期(月) | C43: =治疗月+随访月+长随访月 -> 7 | D43: 末例入组至末例出组 | G43: 47483 | H43: =IF(YEAR($C$39)=YEAR($G43),MONTH($C$39),IF(AND(YEAR($C$38)<=YEAR($G43),YEAR($C$39)>=YEAR($G43)),DATEDIF($C$38,$G43,"M")+1-SUM($H$38:H42),0)) -> 0 | I43: =H43/$H$48 -> 0 | J43: 1.05 | K43: =K42*J43 -> 1.2155063 | L43: =ROUND(I43*K43,4) -> 0
A44: 项目信息 | B44: 锁库期(月) | C44: =锁库月 -> 1 | G44: 47848 | H44: =IF(YEAR($C$39)=YEAR($G44),MONTH($C$39),IF(AND(YEAR($C$38)<=YEAR($G44),YEAR($C$39)>=YEAR($G44)),DATEDIF($C$38,$G44,"M")+1-SUM($H$38:H43),0)) -> 0 | I44: =H44/$H$48 -> 0 | J44: 1.05 | K44: =K43*J44 -> 1.2762816 | L44: =ROUND(I44*K44,4) -> 0
A45: 项目信息 | B45: 关闭期(月) | C45: {=TFLs月+CSR月+项目时间计划!$G$18+项目时间计划!$G$19} -> 5 | D45: 包括关中心及文件移交 | G45: 48213 | H45: =IF(YEAR($C$39)=YEAR($G45),MONTH($C$39),IF(AND(YEAR($C$38)<=YEAR($G45),YEAR($C$39)>=YEAR($G45)),DATEDIF($C$38,$G45,"M")+1-SUM($H$38:H44),0)) -> 0 | I45: =H45/$H$48 -> 0 | J45: 1.05 | K45: =K44*J45 -> 1.3400956 | L45: =ROUND(I45*K45,4) -> 0
A46: 项目信息 | B46: 盲法 | C46: 否 | G46: 48579 | H46: =IF(YEAR($C$39)=YEAR($G46),MONTH($C$39),IF(AND(YEAR($C$38)<=YEAR($G46),YEAR($C$39)>=YEAR($G46)),DATEDIF($C$38,$G46,"M")+1-SUM($H$38:H45),0)) -> 0 | I46: =H46/$H$48 -> 0 | J46: 1.05 | K46: =K45*J46 -> 1.4071004 | L46: =ROUND(I46*K46,4) -> 0
A47: 项目信息 | B47: 随机化设计 | C47: 非随机化 | G47: 48944 | H47: =IF(YEAR($C$39)=YEAR($G47),MONTH($C$39),IF(AND(YEAR($C$38)<=YEAR($G47),YEAR($C$39)>=YEAR($G47)),DATEDIF($C$38,$G47,"M")+1-SUM($H$38:H46),0)) -> 0 | I47: =H47/$H$48 -> 0 | J47: 1.05 | K47: =K46*J47 -> 1.4774554 | L47: =ROUND(I47*K47,4) -> 0
A48: 项目信息 | B48: 期中分析次数 | C48: 0 | H48: =SUM(H38:H47) -> 23 | I48: =SUM(I38:I47) -> 1 | K48: 平均通胀 | L48: =SUM(L38:L47) -> 1.082
A49: 项目信息 | B49: SRC会议次数 | C49: 6
A50: 临床运营 | B50: SDV比例 | C50: =IF(试验目的="注册申报",100%,50%) -> 1 | F50: 考虑目前承接项目试验参与者数量都不多,非注册暂定50%,可酌情至20%
A51: 临床运营 | B51: CRA人数 | C51: =IF(试验目的="注册申报",ROUNDUP(启动中心数/3,0),ROUNDUP(启动中心数/4,0)) -> 2 | E51: Hide
A52: 临床运营 | B52: 访视平均差旅时间 | C52: =ROUND(异地差旅比例*异地往返平均差旅时间+(1-异地差旅比例)*本地往返差旅时间,0) -> 5 | E52: Hide
A53: 临床运营 | B53: 异地差旅比例 | C53: 0.5 | E53: Hide | F53: 默认50%，可酌情调整。
A54: 临床运营 | B54: 本地往返差旅时间 | C54: 3 | E54: Hide | F54: 默认3，可酌情调整。
A55: 临床运营 | B55: 异地往返平均差旅时间 | C55: 6 | E55: Hide | F55: 默认6，可酌情调整。
A56: 临床运营 | B56: 中心激活月 | C56: =ROUND((入组月+治疗月+随访月+长随访月+锁库月)*启动中心数,0) -> 56 | E56: Hide | F56: 如多阶段设计,且各阶段中心数不一致,合理扣减
A57: 临床运营 | B57: 遗传办变更申报次数 | C57: 0 | D57: ="默认"&$C$57&"次,若因为方案变更,新增中心等，根据更新的内容进行费用的增加。" -> 默认0次,若因为方案变更,新增中心等，根据更新的内容进行费用的增加。 | F57: 如RFP阶段报变更,三级任务新增中心按启动中心15%取整; 如已知新增中心数,按实际新增填写。
A58: 临床运营 | B58: 常规监查安排 | D58: <如展示,据实填写并去除提示和高亮;不展示，则隐藏.>
A59: 临床运营 | B59: 常规监查访视次数 | C59: =项目时间计划!$G$27+项目时间计划!$G$28+项目时间计划!$G$29+项目时间计划!$G$30 -> 13 | D59: 每中心平均次数
A60: 临床运营 | B60: 与客户电话会议频次 | D60: <如展示,据实填写并去除提示和高亮;不展示，则隐藏.>
A61: 临床运营 | B61: 项目会议频次 | D61: <如展示,据实填写并去除提示和高亮;不展示，则隐藏.>
A62: 临床运营 | B62: 监查员会议频次 | D62: <如展示,据实填写并去除提示和高亮;不展示，则隐藏.>
A63: 临床运营 | B63: 供应商管理数量 | C63: =COUNTIF(服务费明细!$D$78:$D$85,1) -> 5
A64: 非盲临床运营 | B64: CRA人数 | C64: {=_xlfn.IFS(AND(非盲临床运营YN=1,试验目的="注册申报"),ROUNDUP(启动中心数/4.5,0),AND(非盲临床运营YN=1,试验目的<>"注册申报"),ROUNDUP(启动中心数/6,0),非盲临床运营YN<>1,0)} -> 0 | E64: Hide
A65: 数据管理 | B65: EDC系统 | C65: TrialMaster | D65: <非TM,请注明: > | E65: Hide | G65: 参数 | H65: 注册肿瘤I/II期 | I65: 注册肿瘤III期 | J65: 非肿I期(健康人） | K65: 非肿II_III期 | L65: 非注册-IIT | M65: RWS等 | N65: buffer | O65: 非肿I期(非健康人）
A66: 数据管理 | B66: CRF唯一页面数 | C66: =HLOOKUP(报价场景,$H$65:$O$95,2,0) -> 50 | D66: 每入组试验参与者 | G66: CRF唯一页面数 | H66: 50 | I66: 50 | J66: 40 | K66: 50 | L66: 50 | M66: 30 | N66: =H66 -> 50 | O66: 40
A67: 数据管理 | B67: CRF重复页面数 | C67: =HLOOKUP(报价场景,$H$65:$O$95,3,0) -> 130 | D67: 每入组试验参与者 | G67: CRF重复页面数 | H67: 130 | I67: 150 | J67: 100 | K67: 150 | L67: 100 | M67: 90 | N67: =H67 -> 130 | O67: 100
A68: 数据管理 | B68: 数据核查计划条数 | C68: =逻辑核查总数+人工数据线下列表数 -> 670 | D68: 每项目 | F68: 默认:逻辑核查总数+人工数据线下列表数 | G68: 数据核查计划条数 | H68: =H69+H70 -> 670 | I68: =I69+I70 -> 700 | J68: =J69+J70 -> 530 | K68: =K69+K70 -> 690 | L68: =L69+L70 -> 630 | M68: =M69+M70 -> 420 | N68: =N69+N70 -> 670 | O68: =O69+O70 -> 530
A69: 数据管理 | B69: 逻辑核查总数 | C69: =CRF唯一页面数*10+CRF重复页面数 -> 630 | D69: 每项目 | F69: UP*10+RP | G69: 逻辑核查总数 | H69: =H66*10+H67 -> 630 | I69: =I66*10+I67 -> 650 | J69: =J66*10+J67 -> 500 | K69: =K66*10+K67 -> 650 | L69: =L66*10+L67 -> 600 | M69: =M66*10+M67 -> 390 | N69: =N66*10+N67 -> 630 | O69: =O66*10+O67 -> 500
A70: 数据管理 | B70: 人工数据线下列表数 | C70: =HLOOKUP(报价场景,$H$65:$O$95,6,0) -> 40 | F70: I期肿瘤,默认UP | G70: 人工数据线下列表数 | H70: 40 | I70: 50 | J70: 30 | K70: 40 | L70: 30 | M70: 30 | N70: =H70 -> 40 | O70: 30
A71: 数据管理 | B71: 人工数据线下列表运行频次 | C71: =HLOOKUP(报价场景,$H$65:$O$95,7,0) -> 1 | D71: 月/次 | F71: 默认每2月或每月 | G71: 人工数据线下列表运行频次 | H71: 1 | I71: 1 | J71: 2 | K71: 1 | L71: 3 | M71: 3 | N71: =H71 -> 1 | O71: 2
A72: 数据管理 | B72: 数据库变更次数 | C72: 0 | D72: ="默认"&数据库变更次数&"次,若因为方案变更或是客户需求数据库需要更新,根据更新的内容进行费用的增加。" -> 默认0次,若因为方案变更或是客户需求数据库需要更新,根据更新的内容进行费用的增加。 | F72: 打开明细A103 | G72: 数据库变更次数 | H72: 0 | I72: 0 | J72: 0 | K72: 0 | L72: 0 | M72: 0 | N72: =H72 -> 0 | O72: 0
A73: 数据管理 | B73: 系统质疑数 | C73: =HLOOKUP(报价场景,$H$65:$O$95,9,0) -> 30 | D73: 每入组试验参与者 | G73: 系统质疑数 | H73: 30 | I73: 40 | J73: 25 | K73: 30 | L73: 25 | M73: 15 | N73: =H73 -> 30 | O73: 25
A74: 数据管理 | B74: 人工质疑数 | C74: =HLOOKUP(报价场景,$H$65:$O$95,10,0) -> 25 | D74: 每入组试验参与者 | G74: 人工质疑数 | H74: 25 | I74: 30 | J74: 20 | K74: 25 | L74: 20 | M74: 10 | N74: =H74 -> 25 | O74: 20
A75: 数据管理 | B75: 外部数据供应商数 | C75: =HLOOKUP(报价场景,$H$65:$O$95,11,0) -> 2 | F75: 依据方案流程图同时结合外部供应商数量预计,PK,PD,ADA,Biomarker,IRC等 | G75: 外部数据供应商数 | H75: 2 | I75: 2 | J75: 2 | K75: 2 | L75: 2 | M75: 1 | N75: =H75 -> 2 | O75: 2
A76: 数据管理 | B76: 外部数据一致性核查频次 | C76: =HLOOKUP(报价场景,$H$65:$O$95,12,0) -> 3 | D76: 月/次 | F76: 默认每季度 | G76: 外部数据一致性核查频次 | H76: 3 | I76: 3 | J76: 4 | K76: 3 | L76: 8 | M76: 6 | N76: =H76 -> 3 | O76: 4
A77: 数据管理 | B77: SAE一致性核查频次 | C77: =HLOOKUP(报价场景,$H$65:$O$95,13,0) -> 3 | D77: 月/次 | G77: SAE一致性核查频次 | H77: 3 | I77: 3 | J77: 4 | K77: 3 | L77: 8 | M77: 6 | N77: =H77 -> 3 | O77: 4
A78: 数据管理 | B78: 医学编码MedDRA | C78: =HLOOKUP(报价场景,$H$65:$O$95,14,0) -> 8 | D78: 每入组试验参与者 | G78: 医学编码MedDRA | H78: 8 | I78: 20 | J78: 5 | K78: 18 | L78: 10 | M78: 5 | N78: =H78 -> 8 | O78: 5
A79: 数据管理 | B79: 医学编码WHODrug | C79: =HLOOKUP(报价场景,$H$65:$O$95,15,0) -> 10 | D79: 每入组试验参与者 | G79: 医学编码WHODrug | H79: 10 | I79: 30 | J79: 5 | K79: 25 | L79: 15 | M79: 5 | N79: =H79 -> 10 | O79: 5
A80: 数据管理 | B80: 医学编码报告频次 | C80: =HLOOKUP(报价场景,$H$65:$O$95,16,0) -> 3 | D80: 月/次 | F80: 默认每季度或每半年 | G80: 医学编码报告频次 | H80: 3 | I80: 1 | J80: 1 | K80: 1 | L80: 3 | M80: 6 | N80: =H80 -> 3 | O80: 1
A81: 数据管理 | B81: 数据状态报告频次 | C81: =HLOOKUP(报价场景,$H$65:$O$95,17,0) -> 1 | D81: 月/次 | F81: 默认每月 | G81: 数据状态报告频次 | H81: 1 | I81: 1 | J81: 1 | K81: 1 | L81: 3 | M81: 3 | N81: =H81 -> 1 | O81: 1
A82: 数据管理 | B82: 方案偏离审核频次 | C82: =HLOOKUP(报价场景,$H$65:$O$95,18,0) -> 3 | D82: 月/次 | G82: 方案偏离审核频次 | H82: 3 | I82: 2 | J82: 4 | K82: 3 | L82: 6 | M82: 4 | N82: =H82 -> 3 | O82: 4
A83: 生物统计及分析 | B83: SDTM数据集个数 | C83: =HLOOKUP(报价场景,$H$65:$O$95,19,0) -> 35 | G83: SDTM数据集个数 | H83: 35 | I83: 35 | J83: 25 | K83: 30 | L83: 0 | M83: 0 | N83: =H83 -> 35 | O83: 25
A84: 生物统计及分析 | B84: 分析数据集个数 | C84: =HLOOKUP(报价场景,$H$65:$O$95,20,0) -> 15 | G84: 分析数据集个数 | H84: 15 | I84: 15 | J84: 12 | K84: 14 | L84: 16 | M84: 12 | N84: =H84 -> 15 | O84: 12
A85: 生物统计及分析 | B85: 独立表格 | C85: =HLOOKUP(报价场景,$H$65:$O$95,21,0) -> 25 | G85: 独立表格 | H85: 25 | I85: 30 | J85: 20 | K85: 30 | L85: 20 | M85: 20 | N85: =H85 -> 25 | O85: 20
A86: 生物统计及分析 | B86: 独立图表 | C86: =HLOOKUP(报价场景,$H$65:$O$95,22,0) -> 5 | G86: 独立图表 | H86: 5 | I86: 5 | J86: 0 | K86: 0 | L86: 5 | M86: 0 | N86: =H86 -> 5 | O86: 0
A87: 生物统计及分析 | B87: 重复表格 | C87: =HLOOKUP(报价场景,$H$65:$O$95,23,0) -> 30 | G87: 重复表格 | H87: 30 | I87: 45 | J87: 30 | K87: 50 | L87: 15 | M87: 30 | N87: =H87 -> 30 | O87: 30
A88: 生物统计及分析 | B88: 重复图表 | C88: =HLOOKUP(报价场景,$H$65:$O$95,24,0) -> 5 | G88: 重复图表 | H88: 5 | I88: 10 | J88: 0 | K88: 0 | L88: 5 | M88: 0 | N88: =H88 -> 5 | O88: 0
A89: 生物统计及分析 | B89: 列表 | C89: =HLOOKUP(报价场景,$H$65:$O$95,25,0) -> 40 | G89: 列表 | H89: 40 | I89: 50 | J89: 30 | K89: 40 | L89: 15 | M89: 30 | N89: =H89 -> 40 | O89: 30
A90: 生物统计及分析 | B90: 独立PK表格 | C90: =HLOOKUP(报价场景,$H$65:$O$95,26,0) -> 6 | G90: 独立PK表格 | H90: 6 | I90: 0 | J90: 6 | K90: 0 | L90: 6 | M90: 0 | N90: =H90 -> 6 | O90: 6
A91: 生物统计及分析 | B91: 独立PK图表 | C91: =HLOOKUP(报价场景,$H$65:$O$95,27,0) -> 4 | G91: 独立PK图表 | H91: 4 | I91: 0 | J91: 4 | K91: 0 | L91: 4 | M91: 0 | N91: =H91 -> 4 | O91: 4
A92: 生物统计及分析 | B92: 重复PK表格 | C92: =HLOOKUP(报价场景,$H$65:$O$95,28,0) -> 2 | G92: 重复PK表格 | H92: 2 | I92: 0 | J92: 2 | K92: 0 | L92: 2 | M92: 0 | N92: =H92 -> 2 | O92: 2
A93: 生物统计及分析 | B93: 重复PK图表 | C93: =HLOOKUP(报价场景,$H$65:$O$95,29,0) -> 2 | G93: 重复PK图表 | H93: 2 | I93: 0 | J93: 2 | K93: 0 | L93: 2 | M93: 0 | N93: =H93 -> 2 | O93: 2
A94: 生物统计及分析 | B94: PK列表 | C94: =HLOOKUP(报价场景,$H$65:$O$95,30,0) -> 3 | G94: PK列表 | H94: 3 | I94: 0 | J94: 3 | K94: 0 | L94: 3 | M94: 0 | N94: =H94 -> 3 | O94: 3
A95: 生物统计及分析 | B95: Dry Run次数 | C95: =HLOOKUP(报价场景,$H$65:$O$95,31,0) -> 1 | G95: Dry Run次数 | H95: 1 | I95: 1 | J95: 0 | K95: 1 | L95: 0 | M95: 1 | N95: =H95 -> 1 | O95: 0
A96: 生物统计及分析 | B96: 方案偏离列表 | C96: 45 | E96: 编程
A97: 生物统计及分析 | B97: 方案偏离列表运行次数 | C97: =服务费明细!E134 -> 0 | E97: Hide
A98: 生物统计及分析 | B98: DSMB/DMC/IDMC会议次数 | C98: 1 | F98: 启动+1次IDMC(每次包含1次开门+1次闭门)，默认3次会议
A99: 生物统计及分析 | B99: DSMB/DMC/IDMC会议的Dry Run次数 | C99: 1
A100: 药物警戒 | B100: PV报告双语 | C100: 否 | E100: Hide
A101: 药物警戒 | B101: 版本数 | C101: 3 | E101: Hide
...

Sheet 费用摘要
B1: 报价摘要 | H1: 不对外展示，内部说明
B2: 报价版本号: | H2: 报价模板版本 | I2: v4.22
B3: 报价有效期: | C3: 90天 | E3: 不适用，则不展示 | F3: 不适用，则不展示 | H3: 报价模板版本日期 | I3: 46255
B4: 编码 | C4: 业务描述 | D4: 费用 (RMB) | E4: 优惠率 | F4: 折扣后费用 (RMB) | G4: 备注
B5: 注册申报 | C5: Pre-IND&IND&NDA | D5: =注册申报明细!H120 -> 0 | E5: =IF(F5<>D5,1-ROUND(IFERROR(F5/D5,0),2),"NA") -> NA | F5: =注册申报明细!J120 -> 0 | G5: 详情请见《注册申报费用明细》 | H5: 注册申报业务描述可根据实际情况调整
B6: 临床阶段 | D6: =SUM(D7:D21) -> 3348842 | E6: =IF(F6<>D6,1-ROUND(IFERROR(F6/D6,0),2),"NA") -> NA | F6: =SUM(F7:F21) -> 3348842 | H6: 如无注册申报相关服务，则不展示
B7: I001 | C7: =INDEX(服务费明细!$C:$C,MATCH(费用摘要!$B7,服务费明细!$B:$B,0)) -> 研究文件撰写和审核 | D7: =INDEX(服务费明细!$AF:$AF,MATCH(费用摘要!$B7,服务费明细!$B:$B,0)) -> 163695 | E7: =IF(F7<>D7,1-ROUND(IFERROR(F7/D7,0),2),"NA") -> NA | F7: =INDEX(服务费明细!$AH:$AH,MATCH(费用摘要!$B7,服务费明细!$B:$B,0)) -> 163695
B8: I002 | C8: =INDEX(服务费明细!$C:$C,MATCH(费用摘要!$B8,服务费明细!$B:$B,0)) -> 试验准备 | D8: =INDEX(服务费明细!$AF:$AF,MATCH(费用摘要!$B8,服务费明细!$B:$B,0)) -> 204560 | E8: =IF(F8<>D8,1-ROUND(IFERROR(F8/D8,0),2),"NA") -> NA | F8: =INDEX(服务费明细!$AH:$AH,MATCH(费用摘要!$B8,服务费明细!$B:$B,0)) -> 204560
B9: I003 | C9: =INDEX(服务费明细!$C:$C,MATCH(费用摘要!$B9,服务费明细!$B:$B,0)) -> 遗传办递交和跟进 | D9: =INDEX(服务费明细!$AF:$AF,MATCH(费用摘要!$B9,服务费明细!$B:$B,0)) -> 33020 | E9: =IF(F9<>D9,1-ROUND(IFERROR(F9/D9,0),2),"NA") -> NA | F9: =INDEX(服务费明细!$AH:$AH,MATCH(费用摘要!$B9,服务费明细!$B:$B,0)) -> 33020
B10: I004 | C10: =INDEX(服务费明细!$C:$C,MATCH(费用摘要!$B10,服务费明细!$B:$B,0)) -> 召开研究者会议 | D10: =INDEX(服务费明细!$AF:$AF,MATCH(费用摘要!$B10,服务费明细!$B:$B,0)) -> 73330 | E10: =IF(F10<>D10,1-ROUND(IFERROR(F10/D10,0),2),"NA") -> NA | F10: =INDEX(服务费明细!$AH:$AH,MATCH(费用摘要!$B10,服务费明细!$B:$B,0)) -> 73330
B11: I005 | C11: =INDEX(服务费明细!$C:$C,MATCH(费用摘要!$B11,服务费明细!$B:$B,0)) -> 临床监查和中心管理 | D11: =INDEX(服务费明细!$AF:$AF,MATCH(费用摘要!$B11,服务费明细!$B:$B,0)) -> 971055 | E11: =IF(F11<>D11,1-ROUND(IFERROR(F11/D11,0),2),"NA") -> NA | F11: =INDEX(服务费明细!$AH:$AH,MATCH(费用摘要!$B11,服务费明细!$B:$B,0)) -> 971055
B12: I006 | C12: =INDEX(服务费明细!$C:$C,MATCH(费用摘要!$B12,服务费明细!$B:$B,0)) -> 项目管理 | D12: =INDEX(服务费明细!$AF:$AF,MATCH(费用摘要!$B12,服务费明细!$B:$B,0)) -> 782562.5 | E12: =IF(F12<>D12,1-ROUND(IFERROR(F12/D12,0),2),"NA") -> NA | F12: =INDEX(服务费明细!$AH:$AH,MATCH(费用摘要!$B12,服务费明细!$B:$B,0)) -> 782562.5
B13: I007 | C13: =INDEX(服务费明细!$C:$C,MATCH(费用摘要!$B13,服务费明细!$B:$B,0)) -> 医学监查 | D13: =INDEX(服务费明细!$AF:$AF,MATCH(费用摘要!$B13,服务费明细!$B:$B,0)) -> 285273 | E13: =IF(F13<>D13,1-ROUND(IFERROR(F13/D13,0),2),"NA") -> NA | F13: =INDEX(服务费明细!$AH:$AH,MATCH(费用摘要!$B13,服务费明细!$B:$B,0)) -> 285273
B14: I008 | C14: =INDEX(服务费明细!$C:$C,MATCH(费用摘要!$B14,服务费明细!$B:$B,0)) -> 数据管理 | D14: =INDEX(服务费明细!$AF:$AF,MATCH(费用摘要!$B14,服务费明细!$B:$B,0)) -> 204684 | E14: =IF(F14<>D14,1-ROUND(IFERROR(F14/D14,0),2),"NA") -> NA | F14: =INDEX(服务费明细!$AH:$AH,MATCH(费用摘要!$B14,服务费明细!$B:$B,0)) -> 204684
B15: I009 | C15: =INDEX(服务费明细!$C:$C,MATCH(费用摘要!$B15,服务费明细!$B:$B,0)) -> 生物统计及分析 | D15: =INDEX(服务费明细!$AF:$AF,MATCH(费用摘要!$B15,服务费明细!$B:$B,0)) -> 243762.5 | E15: =IF(F15<>D15,1-ROUND(IFERROR(F15/D15,0),2),"NA") -> NA | F15: =INDEX(服务费明细!$AH:$AH,MATCH(费用摘要!$B15,服务费明细!$B:$B,0)) -> 243762.5
B16: I010 | C16: =INDEX(服务费明细!$C:$C,MATCH(费用摘要!$B16,服务费明细!$B:$B,0)) -> 临床药理 | D16: =INDEX(服务费明细!$AF:$AF,MATCH(费用摘要!$B16,服务费明细!$B:$B,0)) -> 113740 | E16: =IF(F16<>D16,1-ROUND(IFERROR(F16/D16,0),2),"NA") -> NA | F16: =INDEX(服务费明细!$AH:$AH,MATCH(费用摘要!$B16,服务费明细!$B:$B,0)) -> 113740
B17: I011 | C17: =INDEX(服务费明细!$C:$C,MATCH(费用摘要!$B17,服务费明细!$B:$B,0)) -> 安全警戒 | D17: =INDEX(服务费明细!$AF:$AF,MATCH(费用摘要!$B17,服务费明细!$B:$B,0)) -> 171520 | E17: =IF(F17<>D17,1-ROUND(IFERROR(F17/D17,0),2),"NA") -> NA | F17: =INDEX(服务费明细!$AH:$AH,MATCH(费用摘要!$B17,服务费明细!$B:$B,0)) -> 171520
B18: I012 | C18: =INDEX(服务费明细!$C:$C,MATCH(费用摘要!$B18,服务费明细!$B:$B,0)) -> 医学撰写 | D18: =INDEX(服务费明细!$AF:$AF,MATCH(费用摘要!$B18,服务费明细!$B:$B,0)) -> 101640 | E18: =IF(F18<>D18,1-ROUND(IFERROR(F18/D18,0),2),"NA") -> NA | F18: =INDEX(服务费明细!$AH:$AH,MATCH(费用摘要!$B18,服务费明细!$B:$B,0)) -> 101640
... B20: I014 | C20: =INDEX(服务费明细!$C:$C,MATCH(费用摘要!$B20,服务费明细!$B:$B,0)) -> 质量保证 | D20: =INDEX(服务费明细!$AF:$AF,MATCH(费用摘要!$B20,服务费明细!$B:$B,0)) -> 0 | E20: =IF(F20<>D20,1-ROUND(IFERROR(F20/D20,0),2),"NA") -> NA | F20: =INDEX(服务费明细!$AH:$AH,MATCH(费用摘要!$B20,服务费明细!$B:$B,0)) -> 0
B21: I015 | C21: =INDEX(服务费明细!$C:$C,MATCH(费用摘要!$B21,服务费明细!$B:$B,0)) -> 国家局核查支持 | D21: =INDEX(服务费明细!$AF:$AF,MATCH(费用摘要!$B21,服务费明细!$B:$B,0)) -> 0 | E21: =IF(F21<>D21,1-ROUND(IFERROR(F21/D21,0),2),"NA") -> NA | F21: =INDEX(服务费明细!$AH:$AH,MATCH(费用摘要!$B21,服务费明细!$B:$B,0)) -> 0 | G21: 临床试验结束后, 据实结算。
B22: 税前 | C22: 服务费合计 | D22: =ROUND(SUM($D$7:$D$21,D5),2) -> 3348842 | F22: =ROUND(SUM(F$7:F$21,F5),2) -> 3348842
B23: 税率 | C23: =服务费明细!$C$252 -> 0.066 | D23: =D24-D22 -> 221023.57 | F23: =F24-F22 -> 221023.57 | H23: 不展示
B24: 税后 | C24: 服务费合计 | D24: =ROUND(D22*(1+$C$23),2) -> 3569865.6 | F24: =ROUND(F22*(1+$C$23),2) -> 3569865.6 | H24: 不展示
B25: 税前 | C25: 服务费折扣金额 | D25: =D22-F22 -> 0 | E25: 优惠率 | F25: =IFERROR(ROUND(($D$22-$F$22)/$D$22,2),0) -> 0 | G25: =IF($F$25>0,IF(LEN(1-$F$25)-LEN(INT(1-$F$25))-1=1,(1-$F$25)*10&"折",(1-$F$25)*100&"折"),) -> 0 | H25: 不展示
B26: 编码 | C26: 其他费用描述 | D26: 费用 (RMB) | E26: 优惠率 | F26: 折扣后费用 (RMB) | G26: 备注
B27: TM | C27: =INDEX(其他费用明细!$D:$D,MATCH(费用摘要!$B27,其他费用明细!$C:$C,0)) -> 有临系统 | D27: =INDEX(其他费用明细!$I:$I,MATCH(费用摘要!$B27,其他费用明细!$C:$C,0)) -> 0 | E27: 0 | F27: =IF(E27="",D27,D27*(1-E27)) -> 0 | G27: =IF($E$27>0,IF(LEN(1-$E$27)-LEN(INT(1-$E$27))-1=1,(1-$E$27)*10&"折",(1-$E$27)*100&"折"),) -> 0 | H27: TM折扣根据审批填写
B28: PTU | C28: =INDEX(其他费用明细!$D:$D,MATCH(费用摘要!$B28,其他费用明细!$C:$C,0)) -> CRO间接费用 | D28: =INDEX(其他费用明细!$I:$I,MATCH(费用摘要!$B28,其他费用明细!$C:$C,0)) -> 147550 | E28: NA | F28: =IF(E28="NA",D28,D28*(1-E28)) -> 147550
B29: PTM | C29: =INDEX(其他费用明细!$D:$D,MATCH(费用摘要!$B29,其他费用明细!$C:$C,0)) -> 会议相关费用 | D29: =INDEX(其他费用明细!$I:$I,MATCH(费用摘要!$B29,其他费用明细!$C:$C,0)) -> 0 | E29: NA | F29: =IF(E29="NA",D29,D29*(1-E29)) -> 0
B30: PTV | C30: =INDEX(其他费用明细!$D:$D,MATCH(费用摘要!$B30,其他费用明细!$C:$C,0)) -> 供应商费用 | D30: =INDEX(其他费用明细!$I:$I,MATCH(费用摘要!$B30,其他费用明细!$C:$C,0)) -> 0 | E30: NA | F30: =IF(E30="NA",D30,D30*(1-E30)) -> 0
B31: PTS | C31: =INDEX(其他费用明细!$D:$D,MATCH(费用摘要!$B31,其他费用明细!$C:$C,0)) -> 研究中心费用 | D31: =INDEX(其他费用明细!$I:$I,MATCH(费用摘要!$B31,其他费用明细!$C:$C,0)) -> 0 | E31: NA | F31: =IF(E31="NA",D31,D31*(1-E31)) -> 0
B32: 税前 | C32: 其他费用合计 | D32: =ROUND(SUM($D$27:$D$31),2) -> 147550 | F32: =ROUND(SUM($F$27:$F$31),2) -> 147550 | G32: 据实结算
B33: 税率 | C33: =其他费用明细!D73 -> 0.066 | D33: =D34-D32 -> 9738.3 | F33: =F34-F32 -> 9738.3 | H33: 不展示
B34: 税后 | C34: 其他费用合计 | D34: =ROUND(D32*(1+$C$33),2) -> 157288.3 | F34: =ROUND(F32*(1+$C$33),2) -> 157288.3 | H34: 不展示
B36: 税前 | C36: 总计 | D36: =D22+D32 -> 3496392 | F36: =F22+F32 -> 3496392
B37: 税率 | C37: =服务费明细!C252 -> 0.066 | D37: =D38-D36 -> 230761.87 | F37: =F38-F36 -> 230761.87
B38: 税后 | C38: 总计 | D38: =D24+D34 -> 3727153.9 | F38: =F24+F34 -> 3727153.9 | H38: =F38/入组试验参与者数 -> 124238.46
B40: 已优惠总金额 | D40: =D38-F38 -> 0 | H40: 不展示
B41: 说明： | H41: 说明视情况调整 | I41: 2. 在入组病例数和中心数未发生变化，且项目周期延后不超过3个月的前提下，非有临直接原因导致的以下变更，将按以下原则收费:
B42: ﹡客户需在临床研究开始前根据项目需求，将相关定稿的核心文件提供给有临。 | I42: 1) 试验设计未发生实质性变更的前提下，文件定稿前如需额外版本，则每版按此项原服务费的5%收取；
B43: ﹡ 本报价均根据目前的信息估算，在一些影响因素发生变化时，相关费用也会发生变化，例如服务范围，研究设计，样本量，研究中心，研究时间等。如果相关信息发生变化时，有临会及时重新调整报价，并和客户进行沟通。 | I43: 2) 试验设计未发生实质性变更的前提下，文件定稿后发生修订，则每增加一次定稿版的修订按此项原服务费的25%收取；
I44: 3) 伦理和遗传办在首次递交审批通过后发生的后续递交，则每次发生的后续递交按首次递交的50%收取；
I45: 3. 在入组病例数或和中心数发生变化，或和项目周期延后超过3个月，或和试验设计发生实质性变更时，双方将就变更部分重新协商并调整报价。
I46: 注：实质性变更定义源自国家药监局药审中心发布的2022年第34号文件《药物临床试验期间方案变更技术指导原则(试行)》

Sheet Ballpark报价单

Sheet 服务费明细
B1: 服务费明细 | AI1: 备注需要根据实际情况修订，修订后本提示语删除！！ | AJ1: 仅供内部参考，外发须申请。 | BI1: 仅供内部参考，外发须申请。 | BQ1: 折扣前内部参考，不可外发。
B2: 注：是否执行,"0"表述CRO不执行且报价不含此服务，"1"表示CRO执行并报价。 | G2: 每个Task总工时。默认不展示,展示需王总审批并提示语删除 | AC2: 默认不展示 | AG2: 默认不展示,展示则提示语删除 | AH2: 默认不展示,展示则提示语删除
A3: 筛选 | B3: 编码 | C3: 专业服务 | D3: 是否执行 | E3: 数量 | F3: 单位类型 | G3: CRA | H3: CTA | I3: PM | J3: PMD | K3: QCM | L3: MD | M3: MM | N3: PVS | O3: PVM | P3: PVP | Q3: DBP | R3: DM | S3: LDM | T3: SA | U3: SAM | V3: ST | W3: STM | X3: CPS | Y3: CPSS | Z3: QAD | AA3: QAM | AB3: QAS | AC3: 小计 (RMB,不含税) | AD3: 逻辑检查 | AE3: 单价 (RMB,不含税) | AF3: 小计 (RMB,不含税) | AG3: 折扣后单价 (RMB,不含税) | AH3: 折扣后小计 (RMB,不含税) | AI3: 备注 | AJ3: 单位小时数 | AK3: 小时数 | AL3: CRA | AM3: CTA | AN3: PM | AO3: PMD | AP3: QCM | AQ3: MD | AR3: MM | AS3: PVS | AT3: PVM | AU3: PVP | AV3: DBP | AW3: DM | AX3: LDM | AY3: SA | AZ3: SAM | BA3: ST | BB3: STM | BC3: CPS | BD3: CPSS | BE3: QAD | BF3: QAM | BG3: QAS | BI3: 医学 | BJ3: 临床运营 | BK3: 数据管理 | BL3: 生物统计及分析 | BM3: 药物警戒 | BN3: 临床药理 | BO3: 质量保证 | BQ3: 医学 | BR3: 临床运营 | BS3: 数据管理 | BT3: 生物统计及分析 | BU3: 药物警戒 | BV3: 临床药理 | BW3: 质量保证
C4: 人员单价 | G4: ='Rate Card'!K3 -> 340 | H4: ='Rate Card'!J4 -> 220 | I4: ='Rate Card'!J5 -> 650 | J4: ='Rate Card'!J6 -> 800 | K4: ='Rate Card'!J7 -> 600 | L4: ='Rate Card'!K10 -> 990 | M4: ='Rate Card'!K11 -> 650 | N4: ='Rate Card'!K14 -> 300 | O4: ='Rate Card'!K12 -> 500 | P4: ='Rate Card'!K13 -> 700 | Q4: ='Rate Card'!K15 -> 300 | R4: ='Rate Card'!K16 -> 200 | S4: ='Rate Card'!K17 -> 360 | T4: ='Rate Card'!K18 -> 225 | U4: ='Rate Card'!K19 -> 450 | V4: ='Rate Card'!K20 -> 400 | W4: ='Rate Card'!K21 -> 700 | X4: ='Rate Card'!K25 -> 580 | Y4: ='Rate Card'!K26 -> 700 | Z4: ='Rate Card'!K22 -> 1000 | AA4: ='Rate Card'!K23 -> 600 | AB4: ='Rate Card'!K24 -> 400
B5: I001 | C5: =INDEX(二三级标准!$Q:$Q,MATCH(服务费明细!$B5,二三级标准!$O:$O,0)) -> 研究文件撰写和审核 | D5: =IF(医学撰写YN=1,1,0) -> 1 | G5: =SUM(G6:G14) -> 0 | H5: =SUM(H6:H14) -> 0 | I5: =SUM(I6:I14) -> 16 | J5: =SUM(J6:J14) -> 0 | K5: =SUM(K6:K14) -> 0 | L5: =SUM(L6:L14) -> 41.5 | M5: =SUM(M6:M14) -> 149 | N5: =SUM(N6:N14) -> 0 | ... AB5: =SUM(AB6:AB14) -> 0 | AD5: =SUM(G5:AB5) -> 247.5 | AF5: =SUM(AF6:AF14) -> 163695 | AH5: =SUM(AH6:AH14) -> 163695 | AK5: =SUM(AK6:AK14) -> 247.5 | BI5: =SUM(BI6:BI14) -> 190.5 | BJ5: =SUM(BJ6:BJ14) -> 16 | BK5: =SUM(BK6:BK14) -> 25 | BL5: =SUM(BL6:BL14) -> 12 | BM5: =SUM(BM6:BM14) -> 0 | BN5: =SUM(BN6:BN14) -> 4 | BO5: =SUM(BO6:BO14) -> 0 | BQ5: =SUM(BQ6:BQ14) -> 137935 | BR5: =SUM(BR6:BR14) -> 10400 | BS5: =SUM(BS6:BS14) -> 5960 | BT5: =SUM(BT6:BT14) -> 6600 | BU5: =SUM(BU6:BU14) -> 0 | BV5: =SUM(BV6:BV14) -> 2800 | BW5: =SUM(BW6:BW14) -> 0
B6: A001 | C6: =INDEX(二三级标准!$C:$C,MATCH(服务费明细!$B6,二三级标准!$B:$B,0)) -> 方案撰写 | D6: =IF($D$5=1,1,0) -> 1 | E6: =IF($D6=1,1,0) -> 1 | F6: =INDEX(二三级标准!$G:$G,MATCH(服务费明细!$B6,二三级标准!$B:$B,0)) -> 份 | G6: =AL6 -> 0 | H6: =AM6 -> 0 | I6: =AN6 -> 0 | J6: =AO6 -> 0 | K6: =AP6 -> 0 | L6: =AQ6 -> 26 | M6: =AR6 -> 80 | N6: =AS6 -> 0 | ... AB6: =BG6 -> 0 | AC6: {=SUMPRODUCT(G6:AB6,$G$4:$AB$4)} -> 81940 | AD6: =IF(AF6=AC6,TRUE,FALSE) -> TRUE | AE6: =IFERROR(SUMIF(服务费底表!$K:$K,服务费明细!$B6,服务费底表!$AD:$AD)/E6,0) -> 81940 | AF6: =E6*AE6 -> 81940 | AG6: =IFERROR(SUMIF(服务费底表!$K:$K,服务费明细!$B6,服务费底表!$AG:$AG)/E6,0) -> 81940 | AH6: =AG6*E6 -> 81940 | AI6: 默认2份草稿，1份终稿。 | AJ6: =IF(D6=1,AK6/E6,0) -> 112 | AK6: =SUMIF(服务费底表!$K:$K,服务费明细!$B6,服务费底表!$AC:$AC) -> 112 | AL6: =SUMIFS(服务费底表!$AC:$AC,服务费底表!$K:$K,服务费明细!$B6,服务费底表!$T:$T,AL$3) -> 0 | AM6: =SUMIFS(服务费底表!$AC:$AC,服务费底表!$K:$K,服务费明细!$B6,服务费底表!$T:$T,AM$3) -> 0 | AN6: =SUMIFS(服务费底表!$AC:$AC,服务费底表!$K:$K,服务费明细!$B6,服务费底表!$T:$T,AN$3) -> 0 | AO6: =SUMIFS(服务费底表!$AC:$AC,服务费底表!$K:$K,服务费明细!$B6,服务费底表!$T:$T,AO$3) -> 0 | AP6: =SUMIFS(服务费底表!$AC:$AC,服务费底表!$K:$K,服务费明细!$B6,服务费底表!$T:$T,AP$3) -> 0 | AQ6: =SUMIFS(服务费底表!$AC:$AC,服务费底表!$K:$K,服务费明细!$B6,服务费底表!$T:$T,AQ$3) -> 26 | AR6: =SUMIFS(服务费底表!$AC:$AC,服务费底表!$K:$K,服务费明细!$B6,服务费底表!$T:$T,AR$3) -> 80 | AS6: =SUMIFS(服务费底表!$AC:$AC,服务费底表!$K:$K,服务费明细!$B6,服务费底表!$T:$T,AS$3) -> 0 | ... BG6: =SUMIFS(服务费底表!$AC:$AC,服务费底表!$K:$K,服务费明细!$B6,服务费底表!$T:$T,BG$3) -> 0 | BI6: =SUMIFS(服务费底表!$AC:$AC,服务费底表!$K:$K,服务费明细!$B6,服务费底表!$H:$H,服务费明细!BI$3) -> 106 | BJ6: =SUMIFS(服务费底表!$AC:$AC,服务费底表!$K:$K,服务费明细!$B6,服务费底表!$H:$H,服务费明细!BJ$3) -> 0 | BK6: =SUMIFS(服务费底表!$AC:$AC,服务费底表!$K:$K,服务费明细!$B6,服务费底表!$H:$H,服务费明细!BK$3) -> 0 | BL6: =SUMIFS(服务费底表!$AC:$AC,服务费底表!$K:$K,服务费明细!$B6,服务费底表!$H:$H,服务费明细!BL$3) -> 6 | BM6: =SUMIFS(服务费底表!$AC:$AC,服务费底表!$K:$K,服务费明细!$B6,服务费底表!$H:$H,服务费明细!BM$3) -> 0 | BN6: =SUMIFS(服务费底表!$AC:$AC,服务费底表!$K:$K,服务费明细!$B6,服务费底表!$H:$H,服务费明细!BN$3) -> 0 | BO6: =SUMIFS(服务费底表!$AC:$AC,服务费底表!$K:$K,服务费明细!$B6,服务费底表!$H:$H,服务费明细!BO$3) -> 0 | BQ6: =SUMIFS(服务费底表!$AD:$AD,服务费底表!$K:$K,服务费明细!$B6,服务费底表!$H:$H,服务费明细!BQ$3) -> 77740 | BR6: =SUMIFS(服务费底表!$AD:$AD,服务费底表!$K:$K,服务费明细!$B6,服务费底表!$H:$H,服务费明细!BR$3) -> 0 | BS6: =SUMIFS(服务费底表!$AD:$AD,服务费底表!$K:$K,服务费明细!$B6,服务费底表!$H:$H,服务费明细!BS$3) -> 0 | BT6: =SUMIFS(服务费底表!$AD:$AD,服务费底表!$K:$K,服务费明细!$B6,服务费底表!$H:$H,服务费明细!BT$3) -> 4200 | BU6: =SUMIFS(服务费底表!$AD:$AD,服务费底表!$K:$K,服务费明细!$B6,服务费底表!$H:$H,服务费明细!BU$3) -> 0 | BV6: =SUMIFS(服务费底表!$AD:$AD,服务费底表!$K:$K,服务费明细!$B6,服务费底表!$H:$H,服务费明细!BV$3) -> 0 | BW6: =SUMIFS(服务费底表!$AD:$AD,服务费底表!$K:$K,服务费明细!$B6,服务费底表!$H:$H,服务费明细!BW$3) -> 0
B7: A284 | C7: =INDEX(二三级标准!$C:$C,MATCH(服务费明细!$B7,二三级标准!$B:$B,0)) -> 熟悉与研究相关的资料及文献检索 | D7: 0 | E7: =IF($D7=1,1,0) -> 0 | F7: =INDEX(二三级标准!$G:$G,MATCH(服务费明细!$B7,二三级标准!$B:$B,0)) -> 项目 | AE7: =IFERROR(SUMIF(服务费底表!$K:$K,服务费明细!$B7,服务费底表!$AD:$AD)/E7,0) -> 0 | AF7: =E7*AE7 -> 0 | AG7: =IFERROR(SUMIF(服务费底表!$K:$K,服务费明细!$B7,服务费底表!$AG:$AG)/E7,0) -> 0 | AH7: =AG7*E7 -> 0 | AJ7: =IF(D7=1,AK7/E7,0) -> 0 | AK7: =SUMIF(服务费底表!$K:$K,服务费明细!$B7,服务费底表!$AC:$AC) -> 0 | AL7: =SUMIFS(服务费底表!$AC:$AC,服务费底表!$K:$K,服务费明细!$B7,服务费底表!$T:$T,AL$3) -> 0 | AM7: =SUMIFS(服务费底表!$AC:$AC,服务费底表!$K:$K,服务费明细!$B7,服务费底表!$T:$T,AM$3) -> 0 | AN7: =SUMIFS(服务费底表!$AC:$AC,服务费底表!$K:$K,服务费明细!$B7,服务费底表!$T:$T,AN$3) -> 0 | AO7: =SUMIFS(服务费底表!$AC:$AC,服务费底表!$K:$K,服务费明细!$B7,服务费底表!$T:$T,AO$3) -> 0 | AP7: =SUMIFS(服务费底表!$AC:$AC,服务费底表!$K:$K,服务费明细!$B7,服务费底表!$T:$T,AP$3) -> 0 | AQ7: =SUMIFS(服务费底表!$AC:$AC,服务费底表!$K:$K,服务费明细!$B7,服务费底表!$T:$T,AQ$3) -> 0 | AR7: =SUMIFS(服务费底表!$AC:$AC,服务费底表!$K:$K,服务费明细!$B7,服务费底表!$T:$T,AR$3) -> 0 | AS7: =SUMIFS(服务费底表!$AC:$AC,服务费底表!$K:$K,服务费明细!$B7,服务费底表!$T:$T,AS$3) -> 0 | ... BG7: =SUMIFS(服务费底表!$AC:$AC,服务费底表!$K:$K,服务费明细!$B7,服务费底表!$T:$T,BG$3) -> 0
B8: A001a | C8: =INDEX(二三级标准!$C:$C,MATCH(服务费明细!$B8,二三级标准!$B:$B,0)) -> 方案（中译英） | D8: 0 | E8: =IF($D8=1,1,0) -> 0 | F8: =INDEX(二三级标准!$G:$G,MATCH(服务费明细!$B8,二三级标准!$B:$B,0)) -> 份 | G8: =AL8 -> 0 | H8: =AM8 -> 0 | I8: =AN8 -> 0 | J8: =AO8 -> 0 | K8: =AP8 -> 0 | L8: =AQ8 -> 0 | M8: =AR8 -> 0 | N8: =AS8 -> 0 | ... AB8: =BG8 -> 0 | AC8: {=SUMPRODUCT(G8:AB8,$G$4:$AB$4)} -> 0 | AD8: =IF(AF8=AC8,TRUE,FALSE) -> TRUE | AE8: =IFERROR(SUMIF(服务费底表!$K:$K,服务费明细!$B8,服务费底表!$AD:$AD)/E8,0) -> 0 | AF8: =E8*AE8 -> 0 | AG8: =IFERROR(SUMIF(服务费底表!$K:$K,服务费明细!$B8,服务费底表!$AG:$AG)/E8,0) -> 0 | AH8: =AG8*E8 -> 0 | AI8: 医学审阅 | AJ8: =IF(D8=1,AK8/E8,0) -> 0 | AK8: =SUMIF(服务费底表!$K:$K,服务费明细!$B8,服务费底表!$AC:$AC) -> 0 | AL8: =SUMIFS(服务费底表!$AC:$AC,服务费底表!$K:$K,服务费明细!$B8,服务费底表!$T:$T,AL$3) -> 0 | AM8: =SUMIFS(服务费底表!$AC:$AC,服务费底表!$K:$K,服务费明细!$B8,服务费底表!$T:$T,AM$3) -> 0 | AN8: =SUMIFS(服务费底表!$AC:$AC,服务费底表!$K:$K,服务费明细!$B8,服务费底表!$T:$T,AN$3) -> 0 | AO8: =SUMIFS(服务费底表!$AC:$AC,服务费底表!$K:$K,服务费明细!$B8,服务费底表!$T:$T,AO$3) -> 0 | AP8: =SUMIFS(服务费底表!$AC:$AC,服务费底表!$K:$K,服务费明细!$B8,服务费底表!$T:$T,AP$3) -> 0 | AQ8: =SUMIFS(服务费底表!$AC:$AC,服务费底表!$K:$K,服务费明细!$B8,服务费底表!$T:$T,AQ$3) -> 0 | AR8: =SUMIFS(服务费底表!$AC:$AC,服务费底表!$K:$K,服务费明细!$B8,服务费底表!$T:$T,AR$3) -> 0 | AS8: =SUMIFS(服务费底表!$AC:$AC,服务费底表!$K:$K,服务费明细!$B8,服务费底表!$T:$T,AS$3) -> 0 | ... BG8: =SUMIFS(服务费底表!$AC:$AC,服务费底表!$K:$K,服务费明细!$B8,服务费底表!$T:$T,BG$3) -> 0 | BI8: =SUMIFS(服务费底表!$AC:$AC,服务费底表!$K:$K,服务费明细!$B8,服务费底表!$H:$H,服务费明细!BI$3) -> 0 | BJ8: =SUMIFS(服务费底表!$AC:$AC,服务费底表!$K:$K,服务费明细!$B8,服务费底表!$H:$H,服务费明细!BJ$3) -> 0 | BK8: =SUMIFS(服务费底表!$AC:$AC,服务费底表!$K:$K,服务费明细!$B8,服务费底表!$H:$H,服务费明细!BK$3) -> 0 | BL8: =SUMIFS(服务费底表!$AC:$AC,服务费底表!$K:$K,服务费明细!$B8,服务费底表!$H:$H,服务费明细!BL$3) -> 0 | BM8: =SUMIFS(服务费底表!$AC:$AC,服务费底表!$K:$K,服务费明细!$B8,服务费底表!$H:$H,服务费明细!BM$3) -> 0 | BN8: =SUMIFS(服务费底表!$AC:$AC,服务费底表!$K:$K,服务费明细!$B8,服务费底表!$H:$H,服务费明细!BN$3) -> 0 | BO8: =SUMIFS(服务费底表!$AC:$AC,服务费底表!$K:$K,服务费明细!$B8,服务费底表!$H:$H,服务费明细!BO$3) -> 0 | BQ8: =SUMIFS(服务费底表!$AD:$AD,服务费底表!$K:$K,服务费明细!$B8,服务费底表!$H:$H,服务费明细!BQ$3) -> 0 | BR8: =SUMIFS(服务费底表!$AD:$AD,服务费底表!$K:$K,服务费明细!$B8,服务费底表!$H:$H,服务费明细!BR$3) -> 0 | BS8: =SUMIFS(服务费底表!$AD:$AD,服务费底表!$K:$K,服务费明细!$B8,服务费底表!$H:$H,服务费明细!BS$3) -> 0 | BT8: =SUMIFS(服务费底表!$AD:$AD,服务费底表!$K:$K,服务费明细!$B8,服务费底表!$H:$H,服务费明细!BT$3) -> 0 | BU8: =SUMIFS(服务费底表!$AD:$AD,服务费底表!$K:$K,服务费明细!$B8,服务费底表!$H:$H,服务费明细!BU$3) -> 0 | BV8: =SUMIFS(服务费底表!$AD:$AD,服务费底表!$K:$K,服务费明细!$B8,服务费底表!$H:$H,服务费明细!BV$3) -> 0 | BW8: =SUMIFS(服务费底表!$AD:$AD,服务费底表!$K:$K,服务费明细!$B8,服务费底表!$H:$H,服务费明细!BW$3) -> 0
B9: A002 | C9: =INDEX(二三级标准!$C:$C,MATCH(服务费明细!$B9,二三级标准!$B:$B,0)) -> 撰写CRF | D9: =IF($D$5=1,1,0) -> 1 | E9: =IF($D9=1,1,0) -> 1 | F9: =INDEX(二三级标准!$G:$G,MATCH(服务费明细!$B9,二三级标准!$B:$B,0)) -> 份 | G9: =AL9 -> 0 | H9: =AM9 -> 0 | I9: =AN9 -> 2 | J9: =AO9 -> 0 | K9: =AP9 -> 0 | L9: =AQ9 -> 0 | M9: =AR9 -> 8 | N9: =AS9 -> 0 | ... AB9: =BG9 -> 0 | AC9: {=SUMPRODUCT(G9:AB9,$G$4:$AB$4)} -> 13260 | AD9: =IF(AF9=AC9,TRUE,FALSE) -> TRUE | AE9: =IFERROR(SUMIF(服务费底表!$K:$K,服务费明细!$B9,服务费底表!$AD:$AD)/E9,0) -> 13260 | AF9: =E9*AE9 -> 13260 | AG9: =IFERROR(SUMIF(服务费底表!$K:$K,服务费明细!$B9,服务费底表!$AG:$AG)/E9,0) -> 13260 | AH9: =AG9*E9 -> 13260 | AI9: CRF页面设计。基于定稿的方案，提供1份定稿版本。 | AJ9: =IF(D9=1,AK9/E9,0) -> 37 | AK9: =SUMIF(服务费底表!$K:$K,服务费明细!$B9,服务费底表!$AC:$AC) -> 37 | AL9: =SUMIFS(服务费底表!$AC:$AC,服务费底表!$K:$K,服务费明细!$B9,服务费底表!$T:$T,AL$3) -> 0 | AM9: =SUMIFS(服务费底表!$AC:$AC,服务费底表!$K:$K,服务费明细!$B9,服务费底表!$T:$T,AM$3) -> 0 | AN9: =SUMIFS(服务费底表!$AC:$AC,服务费底表!$K:$K,服务费明细!$B9,服务费底表!$T:$T,AN$3) -> 2 | AO9: =SUMIFS(服务费底表!$AC:$AC,服务费底表!$K:$K,服务费明细!$B9,服务费底表!$T:$T,AO$3) -> 0 | AP9: =SUMIFS(服务费底表!$AC:$AC,服务费底表!$K:$K,服务费明细!$B9,服务费底表!$T:$T,AP$3) -> 0 | AQ9: =SUMIFS(服务费底表!$AC:$AC,服务费底表!$K:$K,服务费明细!$B9,服务费底表!$T:$T,AQ$3) -> 0 | AR9: =SUMIFS(服务费底表!$AC:$AC,服务费底表!$K:$K,服务费明细!$B9,服务费底表!$T:$T,AR$3) -> 8 | AS9: =SUMIFS(服务费底表!$AC:$AC,服务费底表!$K:$K,服务费明细!$B9,服务费底表!$T:$T,AS$3) -> 0 | ... BG9: =SUMIFS(服务费底表!$AC:$AC,服务费底表!$K:$K,服务费明细!$B9,服务费底表!$T:$T,BG$3) -> 0 | BI9: =SUMIFS(服务费底表!$AC:$AC,服务费底表!$K:$K,服务费明细!$B9,服务费底表!$H:$H,服务费明细!BI$3) -> 8 | BJ9: =SUMIFS(服务费底表!$AC:$AC,服务费底表!$K:$K,服务费明细!$B9,服务费底表!$H:$H,服务费明细!BJ$3) -> 2 | BK9: =SUMIFS(服务费底表!$AC:$AC,服务费底表!$K:$K,服务费明细!$B9,服务费底表!$H:$H,服务费明细!BK$3) -> 25 | BL9: =SUMIFS(服务费底表!$AC:$AC,服务费底表!$K:$K,服务费明细!$B9,服务费底表!$H:$H,服务费明细!BL$3) -> 2 | BM9: =SUMIFS(服务费底表!$AC:$AC,服务费底表!$K:$K,服务费明细!$B9,服务费底表!$H:$H,服务费明细!BM$3) -> 0 | BN9: =SUMIFS(服务费底表!$AC:$AC,服务费底表!$K:$K,服务费明细!$B9,服务费底表!$H:$H,服务费明细!BN$3) -> 0 | BO9: =SUMIFS(服务费底表!$AC:$AC,服务费底表!$K:$K,服务费明细!$B9,服务费底表!$H:$H,服务费明细!BO$3) -> 0 | BQ9: =SUMIFS(服务费底表!$AD:$AD,服务费底表!$K:$K,服务费明细!$B9,服务费底表!$H:$H,服务费明细!BQ$3) -> 5200 | BR9: =SUMIFS(服务费底表!$AD:$AD,服务费底表!$K:$K,服务费明细!$B9,服务费底表!$H:$H,服务费明细!BR$3) -> 1300 | BS9: =SUMIFS(服务费底表!$AD:$AD,服务费底表!$K:$K,服务费明细!$B9,服务费底表!$H:$H,服务费明细!BS$3) -> 5960 | BT9: =SUMIFS(服务费底表!$AD:$AD,服务费底表!$K:$K,服务费明细!$B9,服务费底表!$H:$H,服务费明细!BT$3) -> 800 | BU9: =SUMIFS(服务费底表!$AD:$AD,服务费底表!$K:$K,服务费明细!$B9,服务费底表!$H:$H,服务费明细!BU$3) -> 0 | BV9: =SUMIFS(服务费底表!$AD:$AD,服务费底表!$K:$K,服务费明细!$B9,服务费底表!$H:$H,服务费明细!BV$3) -> 0 | BW9: =SUMIFS(服务费底表!$AD:$AD,服务费底表!$K:$K,服务费明细!$B9,服务费底表!$H:$H,服务费明细!BW$3) -> 0
B10: A003 | C10: =INDEX(二三级标准!$C:$C,MATCH(服务费明细!$B10,二三级标准!$B:$B,0)) -> 方案版本更新 | D10: =IF($D$5=1,1,0) -> 1 | E10: =IF($D10=1,1,0) -> 1 | F10: =INDEX(二三级标准!$G:$G,MATCH(服务费明细!$B10,二三级标准!$B:$B,0)) -> 次 | G10: =AL10 -> 0 | H10: =AM10 -> 0 | I10: =AN10 -> 0 | J10: =AO10 -> 0 | K10: =AP10 -> 0 | L10: =AQ10 -> 10 | M10: =AR10 -> 42 | N10: =AS10 -> 0 | ... AB10: =BG10 -> 0 | AC10: {=SUMPRODUCT(G10:AB10,$G$4:$AB$4)} -> 41600 | AD10: =IF(AF10=AC10,TRUE,FALSE) -> TRUE | AE10: =IFERROR(SUMIF(服务费底表!$K:$K,服务费明细!$B10,服务费底表!$AD:$AD)/E10,0) -> 41600 | AF10: =E10*AE10 -> 41600 | AG10: =IFERROR(SUMIF(服务费底表!$K:$K,服务费明细!$B10,服务费底表!$AG:$AG)/E10,0) -> 41600 | AH10: =AG10*E10 -> 41600 | AI10: 基于定稿的方案，提供1份更新的定稿版本。 | AJ10: =IF(D10=1,AK10/E10,0) -> 60 | AK10: =SUMIF(服务费底表!$K:$K,服务费明细!$B10,服务费底表!$AC:$AC) -> 60 | AL10: =SUMIFS(服务费底表!$AC:$AC,服务费底表!$K:$K,服务费明细!$B10,服务费底表!$T:$T,AL$3) -> 0 | AM10: =SUMIFS(服务费底表!$AC:$AC,服务费底表!$K:$K,服务费明细!$B10,服务费底表!$T:$T,AM$3) -> 0 | AN10: =SUMIFS(服务费底表!$AC:$AC,服务费底表!$K:$K,服务费明细!$B10,服务费底表!$T:$T,AN$3) -> 0 | AO10: =SUMIFS(服务费底表!$AC:$AC,服务费底表!$K:$K,服务费明细!$B10,服务费底表!$T:$T,AO$3) -> 0 | AP10: =SUMIFS(服务费底表!$AC:$AC,服务费底表!$K:$K,服务费明细!$B10,服务费底表!$T:$T,AP$3) -> 0 | AQ10: =SUMIFS(服务费底表!$AC:$AC,服务费底表!$K:$K,服务费明细!$B10,服务费底表!$T:$T,AQ$3) -> 10 | AR10: =SUMIFS(服务费底表!$AC:$AC,服务费底表!$K:$K,服务费明细!$B10,服务费底表!$T:$T,AR$3) -> 42 | AS10: =SUMIFS(服务费底表!$AC:$AC,服务费底表!$K:$K,服务费明细!$B10,服务费底表!$T:$T,AS$3) -> 0 | ... BG10: =SUMIFS(服务费底表!$AC:$AC,服务费底表!$K:$K,服务费明细!$B10,服务费底表!$T:$T,BG$3) -> 0 | BI10: =SUMIFS(服务费底表!$AC:$AC,服务费底表!$K:$K,服务费明细!$B10,服务费底表!$H:$H,服务费明细!BI$3) -> 52 | BJ10: =SUMIFS(服务费底表!$AC:$AC,服务费底表!$K:$K,服务费明细!$B10,服务费底表!$H:$H,服务费明细!BJ$3) -> 0 | BK10: =SUMIFS(服务费底表!$AC:$AC,服务费底表!$K:$K,服务费明细!$B10,服务费底表!$H:$H,服务费明细!BK$3) -> 0 | BL10: =SUMIFS(服务费底表!$AC:$AC,服务费底表!$K:$K,服务费明细!$B10,服务费底表!$H:$H,服务费明细!BL$3) -> 4 | BM10: =SUMIFS(服务费底表!$AC:$AC,服务费底表!$K:$K,服务费明细!$B10,服务费底表!$H:$H,服务费明细!BM$3) -> 0 | BN10: =SUMIFS(服务费底表!$AC:$AC,服务费底表!$K:$K,服务费明细!$B10,服务费底表!$H:$H,服务费明细!BN$3) -> 4 | BO10: =SUMIFS(服务费底表!$AC:$AC,服务费底表!$K:$K,服务费明细!$B10,服务费底表!$H:$H,服务费明细!BO$3) -> 0 | BQ10: =SUMIFS(服务费底表!$AD:$AD,服务费底表!$K:$K,服务费明细!$B10,服务费底表!$H:$H,服务费明细!BQ$3) -> 37200 | BR10: =SUMIFS(服务费底表!$AD:$AD,服务费底表!$K:$K,服务费明细!$B10,服务费底表!$H:$H,服务费明细!BR$3) -> 0 | BS10: =SUMIFS(服务费底表!$AD:$AD,服务费底表!$K:$K,服务费明细!$B10,服务费底表!$H:$H,服务费明细!BS$3) -> 0 | BT10: =SUMIFS(服务费底表!$AD:$AD,服务费底表!$K:$K,服务费明细!$B10,服务费底表!$H:$H,服务费明细!BT$3) -> 1600 | BU10: =SUMIFS(服务费底表!$AD:$AD,服务费底表!$K:$K,服务费明细!$B10,服务费底表!$H:$H,服务费明细!BU$3) -> 0 | BV10: =SUMIFS(服务费底表!$AD:$AD,服务费底表!$K:$K,服务费明细!$B10,服务费底表!$H:$H,服务费明细!BV$3) -> 2800 | BW10: =SUMIFS(服务费底表!$AD:$AD,服务费底表!$K:$K,服务费明细!$B10,服务费底表!$H:$H,服务费明细!BW$3) -> 0
B11: A004 | C11: =INDEX(二三级标准!$C:$C,MATCH(服务费明细!$B11,二三级标准!$B:$B,0)) -> 主知情同意撰写 | D11: =IF($D$5=1,1,0) -> 1 | E11: =IF($D11=1,1,0) -> 1 | F11: =INDEX(二三级标准!$G:$G,MATCH(服务费明细!$B11,二三级标准!$B:$B,0)) -> 次 | G11: =AL11 -> 0 | H11: =AM11 -> 0 | I11: =AN11 -> 2 | J11: =AO11 -> 0 | K11: =AP11 -> 0 | L11: =AQ11 -> 4 | M11: =AR11 -> 10 | N11: =AS11 -> 0 | ... AB11: =BG11 -> 0 | AC11: {=SUMPRODUCT(G11:AB11,$G$4:$AB$4)} -> 11760 | AD11: =IF(AF11=AC11,TRUE,FALSE) -> TRUE | AE11: =IFERROR(SUMIF(服务费底表!$K:$K,服务费明细!$B11,服务费底表!$AD:$AD)/E11,0) -> 11760 | AF11: =E11*AE11 -> 11760 | AG11: =IFERROR(SUMIF(服务费底表!$K:$K,服务费明细!$B11,服务费底表!$AG:$AG)/E11,0) -> 11760 | AH11: =AG11*E11 -> 11760 | AI11: 基于定稿的方案，提供1份定稿版本。 | AJ11: =IF(D11=1,AK11/E11,0) -> 16 | AK11: =SUMIF(服务费底表!$K:$K,服务费明细!$B11,服务费底表!$AC:$AC) -> 16 | AL11: =SUMIFS(服务费底表!$AC:$AC,服务费底表!$K:$K,服务费明细!$B11,服务费底表!$T:$T,AL$3) -> 0 | AM11: =SUMIFS(服务费底表!$AC:$AC,服务费底表!$K:$K,服务费明细!$B11,服务费底表!$T:$T,AM$3) -> 0 | AN11: =SUMIFS(服务费底表!$AC:$AC,服务费底表!$K:$K,服务费明细!$B11,服务费底表!$T:$T,AN$3) -> 2 | AO11: =SUMIFS(服务费底表!$AC:$AC,服务费底表!$K:$K,服务费明细!$B11,服务费底表!$T:$T,AO$3) -> 0 | AP11: =SUMIFS(服务费底表!$AC:$AC,服务费底表!$K:$K,服务费明细!$B11,服务费底表!$T:$T,AP$3) -> 0 | AQ11: =SUMIFS(服务费底表!$AC:$AC,服务费底表!$K:$K,服务费明细!$B11,服务费底表!$T:$T,AQ$3) -> 4 | AR11: =SUMIFS(服务费底表!$AC:$AC,服务费底表!$K:$K,服务费明细!$B11,服务费底表!$T:$T,AR$3) -> 10 | AS11: =SUMIFS(服务费底表!$AC:$AC,服务费底表!$K:$K,服务费明细!$B11,服务费底表!$T:$T,AS$3) -> 0 | ... BG11: =SUMIFS(服务费底表!$AC:$AC,服务费底表!$K:$K,服务费明细!$B11,服务费底表!$T:$T,BG$3) -> 0 | BI11: =SUMIFS(服务费底表!$AC:$AC,服务费底表!$K:$K,服务费明细!$B11,服务费底表!$H:$H,服务费明细!BI$3) -> 14 | BJ11: =SUMIFS(服务费底表!$AC:$AC,服务费底表!$K:$K,服务费明细!$B11,服务费底表!$H:$H,服务费明细!BJ$3) -> 2 | BK11: =SUMIFS(服务费底表!$AC:$AC,服务费底表!$K:$K,服务费明细!$B11,服务费底表!$H:$H,服务费明细!BK$3) -> 0 | BL11: =SUMIFS(服务费底表!$AC:$AC,服务费底表!$K:$K,服务费明细!$B11,服务费底表!$H:$H,服务费明细!BL$3) -> 0 | BM11: =SUMIFS(服务费底表!$AC:$AC,服务费底表!$K:$K,服务费明细!$B11,服务费底表!$H:$H,服务费明细!BM$3) -> 0 | BN11: =SUMIFS(服务费底表!$AC:$AC,服务费底表!$K:$K,服务费明细!$B11,服务费底表!$H:$H,服务费明细!BN$3) -> 0 | BO11: =SUMIFS(服务费底表!$AC:$AC,服务费底表!$K:$K,服务费明细!$B11,服务费底表!$H:$H,服务费明细!BO$3) -> 0 | BQ11: =SUMIFS(服务费底表!$AD:$AD,服务费底表!$K:$K,服务费明细!$B11,服务费底表!$H:$H,服务费明细!BQ$3) -> 10460 | BR11: =SUMIFS(服务费底表!$AD:$AD,服务费底表!$K:$K,服务费明细!$B11,服务费底表!$H:$H,服务费明细!BR$3) -> 1300 | BS11: =SUMIFS(服务费底表!$AD:$AD,服务费底表!$K:$K,服务费明细!$B11,服务费底表!$H:$H,服务费明细!BS$3) -> 0 | BT11: =SUMIFS(服务费底表!$AD:$AD,服务费底表!$K:$K,服务费明细!$B11,服务费底表!$H:$H,服务费明细!BT$3) -> 0 | BU11: =SUMIFS(服务费底表!$AD:$AD,服务费底表!$K:$K,服务费明细!$B11,服务费底表!$H:$H,服务费明细!BU$3) -> 0 | BV11: =SUMIFS(服务费底表!$AD:$AD,服务费底表!$K:$K,服务费明细!$B11,服务费底表!$H:$H,服务费明细!BV$3) -> 0 | BW11: =SUMIFS(服务费底表!$AD:$AD,服务费底表!$K:$K,服务费明细!$B11,服务费底表!$H:$H,服务费明细!BW$3) -> 0
B12: A005 | C12: =INDEX(二三级标准!$C:$C,MATCH(服务费明细!$B12,二三级标准!$B:$B,0)) -> 主知情同意版本更新 | D12: =IF($D$5=1,1,0) -> 1 | E12: =IF($D12=1,1,0) -> 1 | F12: =INDEX(二三级标准!$G:$G,MATCH(服务费明细!$B12,二三级标准!$B:$B,0)) -> 份 | G12: =AL12 -> 0 | H12: =AM12 -> 0 | I12: =AN12 -> 0 | J12: =AO12 -> 0 | K12: =AP12 -> 0 | L12: =AQ12 -> 1.5 | M12: =AR12 -> 6 | N12: =AS12 -> 0 | ... AB12: =BG12 -> 0 | AC12: {=SUMPRODUCT(G12:AB12,$G$4:$AB$4)} -> 5385 | AD12: =IF(AF12=AC12,TRUE,FALSE) -> TRUE | AE12: =IFERROR(SUMIF(服务费底表!$K:$K,服务费明细!$B12,服务费底表!$AD:$AD)/E12,0) -> 5385 | AF12: =E12*AE12 -> 5385 | AG12: =IFERROR(SUMIF(服务费底表!$K:$K,服务费明细!$B12,服务费底表!$AG:$AG)/E12,0) -> 5385 | AH12: =AG12*E12 -> 5385 | AI12: 基于定稿的主知情，提供1份更新的定稿版本。 | AJ12: =IF(D12=1,AK12/E12,0) -> 7.5 | AK12: =SUMIF(服务费底表!$K:$K,服务费明细!$B12,服务费底表!$AC:$AC) -> 7.5 | AL12: =SUMIFS(服务费底表!$AC:$AC,服务费底表!$K:$K,服务费明细!$B12,服务费底表!$T:$T,AL$3) -> 0 | AM12: =SUMIFS(服务费底表!$AC:$AC,服务费底表!$K:$K,服务费明细!$B12,服务费底表!$T:$T,AM$3) -> 0 | AN12: =SUMIFS(服务费底表!$AC:$AC,服务费底表!$K:$K,服务费明细!$B12,服务费底表!$T:$T,AN$3) -> 0 | AO12: =SUMIFS(服务费底表!$AC:$AC,服务费底表!$K:$K,服务费明细!$B12,服务费底表!$T:$T,AO$3) -> 0 | AP12: =SUMIFS(服务费底表!$AC:$AC,服务费底表!$K:$K,服务费明细!$B12,服务费底表!$T:$T,AP$3) -> 0 | AQ12: =SUMIFS(服务费底表!$AC:$AC,服务费底表!$K:$K,服务费明细!$B12,服务费底表!$T:$T,AQ$3) -> 1.5 | AR12: =SUMIFS(服务费底表!$AC:$AC,服务费底表!$K:$K,服务费明细!$B12,服务费底表!$T:$T,AR$3) -> 6 | AS12: =SUMIFS(服务费底表!$AC:$AC,服务费底表!$K:$K,服务费明细!$B12,服务费底表!$T:$T,AS$3) -> 0 | ... BG12: =SUMIFS(服务费底表!$AC:$AC,服务费底表!$K:$K,服务费明细!$B12,服务费底表!$T:$T,BG$3) -> 0 | BI12: =SUMIFS(服务费底表!$AC:$AC,服务费底表!$K:$K,服务费明细!$B12,服务费底表!$H:$H,服务费明细!BI$3) -> 7.5 | BJ12: =SUMIFS(服务费底表!$AC:$AC,服务费底表!$K:$K,服务费明细!$B12,服务费底表!$H:$H,服务费明细!BJ$3) -> 0 | BK12: =SUMIFS(服务费底表!$AC:$AC,服务费底表!$K:$K,服务费明细!$B12,服务费底表!$H:$H,服务费明细!BK$3) -> 0 | BL12: =SUMIFS(服务费底表!$AC:$AC,服务费底表!$K:$K,服务费明细!$B12,服务费底表!$H:$H,服务费明细!BL$3) -> 0 | BM12: =SUMIFS(服务费底表!$AC:$AC,服务费底表!$K:$K,服务费明细!$B12,服务费底表!$H:$H,服务费明细!BM$3) -> 0 | BN12: =SUMIFS(服务费底表!$AC:$AC,服务费底表!$K:$K,服务费明细!$B12,服务费底表!$H:$H,服务费明细!BN$3) -> 0 | BO12: =SUMIFS(服务费底表!$AC:$AC,服务费底表!$K:$K,服务费明细!$B12,服务费底表!$H:$H,服务费明细!BO$3) -> 0 | BQ12: =SUMIFS(服务费底表!$AD:$AD,服务费底表!$K:$K,服务费明细!$B12,服务费底表!$H:$H,服务费明细!BQ$3) -> 5385 | BR12: =SUMIFS(服务费底表!$AD:$AD,服务费底表!$K:$K,服务费明细!$B12,服务费底表!$H:$H,服务费明细!BR$3) -> 0 | BS12: =SUMIFS(服务费底表!$AD:$AD,服务费底表!$K:$K,服务费明细!$B12,服务费底表!$H:$H,服务费明细!BS$3) -> 0 | BT12: =SUMIFS(服务费底表!$AD:$AD,服务费底表!$K:$K,服务费明细!$B12,服务费底表!$H:$H,服务费明细!BT$3) -> 0 | BU12: =SUMIFS(服务费底表!$AD:$AD,服务费底表!$K:$K,服务费明细!$B12,服务费底表!$H:$H,服务费明细!BU$3) -> 0 | BV12: =SUMIFS(服务费底表!$AD:$AD,服务费底表!$K:$K,服务费明细!$B12,服务费底表!$H:$H,服务费明细!BV$3) -> 0 | BW12: =SUMIFS(服务费底表!$AD:$AD,服务费底表!$K:$K,服务费明细!$B12,服务费底表!$H:$H,服务费明细!BW$3) -> 0
B13: A006 | C13: =INDEX(二三级标准!$C:$C,MATCH(服务费明细!$B13,二三级标准!$B:$B,0)) -> 试验参与者日记卡撰写 | D13: {=IF(AND($D$5=1,试验参与者类型<>"健康人"),1,0)} -> 1 | E13: =IF($D13=1,1,0) -> 1 | F13: =INDEX(二三级标准!$G:$G,MATCH(服务费明细!$B13,二三级标准!$B:$B,0)) -> 次 | G13: =AL13 -> 0 | H13: =AM13 -> 0 | I13: =AN13 -> 6 | J13: =AO13 -> 0 | K13: =AP13 -> 0 | L13: =AQ13 -> 0 | M13: =AR13 -> 2 | N13: =AS13 -> 0 | ... AB13: =BG13 -> 0 | AC13: {=SUMPRODUCT(G13:AB13,$G$4:$AB$4)} -> 5200 | AD13: =IF(AF13=AC13,TRUE,FALSE) -> TRUE | AE13: =IFERROR(SUMIF(服务费底表!$K:$K,服务费明细!$B13,服务费底表!$AD:$AD)/E13,0) -> 5200 | AF13: =E13*AE13 -> 5200 | AG13: =IFERROR(SUMIF(服务费底表!$K:$K,服务费明细!$B13,服务费底表!$AG:$AG)/E13,0) -> 5200 | AH13: =AG13*E13 -> 5200 | AI13: 基于定稿的方案，提供1份定稿版本。 | AJ13: =IF(D13=1,AK13/E13,0) -> 8 | AK13: =SUMIF(服务费底表!$K:$K,服务费明细!$B13,服务费底表!$AC:$AC) -> 8 | AL13: =SUMIFS(服务费底表!$AC:$AC,服务费底表!$K:$K,服务费明细!$B13,服务费底表!$T:$T,AL$3) -> 0 | AM13: =SUMIFS(服务费底表!$AC:$AC,服务费底表!$K:$K,服务费明细!$B13,服务费底表!$T:$T,AM$3) -> 0 | AN13: =SUMIFS(服务费底表!$AC:$AC,服务费底表!$K:$K,服务费明细!$B13,服务费底表!$T:$T,AN$3) -> 6 | AO13: =SUMIFS(服务费底表!$AC:$AC,服务费底表!$K:$K,服务费明细!$B13,服务费底表!$T:$T,AO$3) -> 0 | AP13: =SUMIFS(服务费底表!$AC:$AC,服务费底表!$K:$K,服务费明细!$B13,服务费底表!$T:$T,AP$3) -> 0 | AQ13: =SUMIFS(服务费底表!$AC:$AC,服务费底表!$K:$K,服务费明细!$B13,服务费底表!$T:$T,AQ$3) -> 0 | AR13: =SUMIFS(服务费底表!$AC:$AC,服务费底表!$K:$K,服务费明细!$B13,服务费底表!$T:$T,AR$3) -> 2 | AS13: =SUMIFS(服务费底表!$AC:$AC,服务费底表!$K:$K,服务费明细!$B13,服务费底表!$T:$T,AS$3) -> 0 | ... BG13: =SUMIFS(服务费底表!$AC:$AC,服务费底表!$K:$K,服务费明细!$B13,服务费底表!$T:$T,BG$3) -> 0 | BI13: =SUMIFS(服务费底表!$AC:$AC,服务费底表!$K:$K,服务费明细!$B13,服务费底表!$H:$H,服务费明细!BI$3) -> 2 | BJ13: =SUMIFS(服务费底表!$AC:$AC,服务费底表!$K:$K,服务费明细!$B13,服务费底表!$H:$H,服务费明细!BJ$3) -> 6 | BK13: =SUMIFS(服务费底表!$AC:$AC,服务费底表!$K:$K,服务费明细!$B13,服务费底表!$H:$H,服务费明细!BK$3) -> 0 | BL13: =SUMIFS(服务费底表!$AC:$AC,服务费底表!$K:$K,服务费明细!$B13,服务费底表!$H:$H,服务费明细!BL$3) -> 0 | BM13: =SUMIFS(服务费底表!$AC:$AC,服务费底表!$K:$K,服务费明细!$B13,服务费底表!$H:$H,服务费明细!BM$3) -> 0 | BN13: =SUMIFS(服务费底表!$AC:$AC,服务费底表!$K:$K,服务费明细!$B13,服务费底表!$H:$H,服务费明细!BN$3) -> 0 | BO13: =SUMIFS(服务费底表!$AC:$AC,服务费底表!$K:$K,服务费明细!$B13,服务费底表!$H:$H,服务费明细!BO$3) -> 0 | BQ13: =SUMIFS(服务费底表!$AD:$AD,服务费底表!$K:$K,服务费明细!$B13,服务费底表!$H:$H,服务费明细!BQ$3) -> 1300 | BR13: =SUMIFS(服务费底表!$AD:$AD,服务费底表!$K:$K,服务费明细!$B13,服务费底表!$H:$H,服务费明细!BR$3) -> 3900 | BS13: =SUMIFS(服务费底表!$AD:$AD,服务费底表!$K:$K,服务费明细!$B13,服务费底表!$H:$H,服务费明细!BS$3) -> 0 | BT13: =SUMIFS(服务费底表!$AD:$AD,服务费底表!$K:$K,服务费明细!$B13,服务费底表!$H:$H,服务费明细!BT$3) -> 0 | BU13: =SUMIFS(服务费底表!$AD:$AD,服务费底表!$K:$K,服务费明细!$B13,服务费底表!$H:$H,服务费明细!BU$3) -> 0 | BV13: =SUMIFS(服务费底表!$AD:$AD,服务费底表!$K:$K,服务费明细!$B13,服务费底表!$H:$H,服务费明细!BV$3) -> 0 | BW13: =SUMIFS(服务费底表!$AD:$AD,服务费底表!$K:$K,服务费明细!$B13,服务费底表!$H:$H,服务费明细!BW$3) -> 0
B14: A007 | C14: =INDEX(二三级标准!$C:$C,MATCH(服务费明细!$B14,二三级标准!$B:$B,0)) -> 试验参与者招募广告撰写 | D14: =IF($D$5=1,1,0) -> 1 | E14: =IF($D14=1,1,0) -> 1 | F14: =INDEX(二三级标准!$G:$G,MATCH(服务费明细!$B14,二三级标准!$B:$B,0)) -> 份 | G14: =AL14 -> 0 | H14: =AM14 -> 0 | I14: =AN14 -> 6 | J14: =AO14 -> 0 | K14: =AP14 -> 0 | L14: =AQ14 -> 0 | M14: =AR14 -> 1 | N14: =AS14 -> 0 | ... AB14: =BG14 -> 0 | AC14: {=SUMPRODUCT(G14:AB14,$G$4:$AB$4)} -> 4550 | AD14: =IF(AF14=AC14,TRUE,FALSE) -> TRUE | AE14: =IFERROR(SUMIF(服务费底表!$K:$K,服务费明细!$B14,服务费底表!$AD:$AD)/E14,0) -> 4550 | AF14: =E14*AE14 -> 4550 | AG14: =IFERROR(SUMIF(服务费底表!$K:$K,服务费明细!$B14,服务费底表!$AG:$AG)/E14,0) -> 4550 | AH14: =AG14*E14 -> 4550 | AI14: 基于定稿的方案，提供1份定稿版本。 | AJ14: =IF(D14=1,AK14/E14,0) -> 7 | AK14: =SUMIF(服务费底表!$K:$K,服务费明细!$B14,服务费底表!$AC:$AC) -> 7 | AL14: =SUMIFS(服务费底表!$AC:$AC,服务费底表!$K:$K,服务费明细!$B14,服务费底表!$T:$T,AL$3) -> 0 | AM14: =SUMIFS(服务费底表!$AC:$AC,服务费底表!$K:$K,服务费明细!$B14,服务费底表!$T:$T,AM$3) -> 0 | AN14: =SUMIFS(服务费底表!$AC:$AC,服务费底表!$K:$K,服务费明细!$B14,服务费底表!$T:$T,AN$3) -> 6 | AO14: =SUMIFS(服务费底表!$AC:$AC,服务费底表!$K:$K,服务费明细!$B14,服务费底表!$T:$T,AO$3) -> 0 | AP14: =SUMIFS(服务费底表!$AC:$AC,服务费底表!$K:$K,服务费明细!$B14,服务费底表!$T:$T,AP$3) -> 0 | AQ14: =SUMIFS(服务费底表!$AC:$AC,服务费底表!$K:$K,服务费明细!$B14,服务费底表!$T:$T,AQ$3) -> 0 | AR14: =SUMIFS(服务费底表!$AC:$AC,服务费底表!$K:$K,服务费明细!$B14,服务费底表!$T:$T,AR$3) -> 1 | AS14: =SUMIFS(服务费底表!$AC:$AC,服务费底表!$K:$K,服务费明细!$B14,服务费底表!$T:$T,AS$3) -> 0 | ... BG14: =SUMIFS(服务费底表!$AC:$AC,服务费底表!$K:$K,服务费明细!$B14,服务费底表!$T:$T,BG$3) -> 0 | BI14: =SUMIFS(服务费底表!$AC:$AC,服务费底表!$K:$K,服务费明细!$B14,服务费底表!$H:$H,服务费明细!BI$3) -> 1 | BJ14: =SUMIFS(服务费底表!$AC:$AC,服务费底表!$K:$K,服务费明细!$B14,服务费底表!$H:$H,服务费明细!BJ$3) -> 6 | BK14: =SUMIFS(服务费底表!$AC:$AC,服务费底表!$K:$K,服务费明细!$B14,服务费底表!$H:$H,服务费明细!BK$3) -> 0 | BL14: =SUMIFS(服务费底表!$AC:$AC,服务费底表!$K:$K,服务费明细!$B14,服务费底表!$H:$H,服务费明细!BL$3) -> 0 | BM14: =SUMIFS(服务费底表!$AC:$AC,服务费底表!$K:$K,服务费明细!$B14,服务费底表!$H:$H,服务费明细!BM$3) -> 0 | BN14: =SUMIFS(服务费底表!$AC:$AC,服务费底表!$K:$K,服务费明细!$B14,服务费底表!$H:$H,服务费明细!BN$3) -> 0 | BO14: =SUMIFS(服务费底表!$AC:$AC,服务费底表!$K:$K,服务费明细!$B14,服务费底表!$H:$H,服务费明细!BO$3) -> 0 | BQ14: =SUMIFS(服务费底表!$AD:$AD,服务费底表!$K:$K,服务费明细!$B14,服务费底表!$H:$H,服务费明细!BQ$3) -> 650 | BR14: =SUMIFS(服务费底表!$AD:$AD,服务费底表!$K:$K,服务费明细!$B14,服务费底表!$H:$H,服务费明细!BR$3) -> 3900 | BS14: =SUMIFS(服务费底表!$AD:$AD,服务费底表!$K:$K,服务费明细!$B14,服务费底表!$H:$H,服务费明细!BS$3) -> 0 | BT14: =SUMIFS(服务费底表!$AD:$AD,服务费底表!$K:$K,服务费明细!$B14,服务费底表!$H:$H,服务费明细!BT$3) -> 0 | BU14: =SUMIFS(服务费底表!$AD:$AD,服务费底表!$K:$K,服务费明细!$B14,服务费底表!$H:$H,服务费明细!BU$3) -> 0 | BV14: =SUMIFS(服务费底表!$AD:$AD,服务费底表!$K:$K,服务费明细!$B14,服务费底表!$H:$H,服务费明细!BV$3) -> 0 | BW14: =SUMIFS(服务费底表!$AD:$AD,服务费底表!$K:$K,服务费明细!$B14,服务费底表!$H:$H,服务费明细!BW$3) -> 0
B15: I002 | C15: =INDEX(二三级标准!$Q:$Q,MATCH(服务费明细!$B15,二三级标准!$O:$O,0)) -> 试验准备 | D15: =IF(临床监查YN=1,1,0) -> 1 | G15: =SUM(G17:G33) -> 295 | H15: =SUM(H17:H33) -> 43 | I15: =SUM(I17:I33) -> 64 | J15: =SUM(J17:J33) -> 2 | K15: =SUM(K17:K33) -> 0 | L15: =SUM(L17:L33) -> 1 | M15: =SUM(M17:M33) -> 61 | N15: =SUM(N17:N33) -> 0 | ... AB15: =SUM(AB17:AB33) -> 0 | AD15: =SUM(G15:AB15) -> 478 | AF15: =SUM(AF16:AF33) -> 204560 | AH15: =SUM(AH16:AH33) -> 204560 | AK15: =SUM(AK16:AK33) -> 486 | BI15: =SUM(BI17:BI33) -> 62 | BJ15: =SUM(BJ17:BJ33) -> 404 | BK15: =SUM(BK17:BK33) -> 3 | BL15: =SUM(BL17:BL33) -> 3 | BM15: =SUM(BM17:BM33) -> 3 | BN15: =SUM(BN17:BN33) -> 3 | BO15: =SUM(BO17:BO33) -> 0 | BQ15: =SUM(BQ17:BQ33) -> 40640 | BR15: =SUM(BR17:BR33) -> 152960 | BS15: =SUM(BS17:BS33) -> 1080 | BT15: =SUM(BT17:BT33) -> 1200 | BU15: =SUM(BU17:BU33) -> 1500 | BV15: =SUM(BV17:BV33) -> 1980 | BW15: =SUM(BW17:BW33) -> 0
B16: A286 | C16: =INDEX(二三级标准!$C:$C,MATCH(服务费明细!$B16,二三级标准!$B:$B,0)) -> 研究中心启动会/立项会资料支持 | D16: =IF($D$15=1,1,0) -> 1 | E16: =IF($D16=1,启动中心数,0) -> 4 | F16: =INDEX(二三级标准!$G:$G,MATCH(服务费明细!$B16,二三级标准!$B:$B,0)) -> 中心 | G16: =AL16 -> 0 | H16: =AM16 -> 0 | I16: =AN16 -> 0 | J16: =AO16 -> 0 | K16: =AP16 -> 0 | L16: =AQ16 -> 0 | M16: =AR16 -> 8 | N16: =AS16 -> 0 | ... AB16: =BG16 -> 0 | AC16: {=SUMPRODUCT(G16:AB16,$G$4:$AB$4)} -> 5200 | AD16: =IF(AF16=AC16,TRUE,FALSE) -> TRUE | AE16: =IFERROR(SUMIF(服务费底表!$K:$K,服务费明细!$B16,服务费底表!$AD:$AD)/E16,0) -> 1300 | AF16: =E16*AE16 -> 5200 | AG16: =IFERROR(SUMIF(服务费底表!$K:$K,服务费明细!$B16,服务费底表!$AG:$AG)/E16,0) -> 1300 | AH16: =AG16*E16 -> 5200 | AJ16: =IF(D16=1,AK16/E16,0) -> 2 | AK16: =SUMIF(服务费底表!$K:$K,服务费明细!$B16,服务费底表!$AC:$AC) -> 8 | AL16: =SUMIFS(服务费底表!$AC:$AC,服务费底表!$K:$K,服务费明细!$B16,服务费底表!$T:$T,AL$3) -> 0 | AM16: =SUMIFS(服务费底表!$AC:$AC,服务费底表!$K:$K,服务费明细!$B16,服务费底表!$T:$T,AM$3) -> 0 | AN16: =SUMIFS(服务费底表!$AC:$AC,服务费底表!$K:$K,服务费明细!$B16,服务费底表!$T:$T,AN$3) -> 0 | AO16: =SUMIFS(服务费底表!$AC:$AC,服务费底表!$K:$K,服务费明细!$B16,服务费底表!$T:$T,AO$3) -> 0 | AP16: =SUMIFS(服务费底表!$AC:$AC,服务费底表!$K:$K,服务费明细!$B16,服务费底表!$T:$T,AP$3) -> 0 | AQ16: =SUMIFS(服务费底表!$AC:$AC,服务费底表!$K:$K,服务费明细!$B16,服务费底表!$T:$T,AQ$3) -> 0 | AR16: =SUMIFS(服务费底表!$AC:$AC,服务费底表!$K:$K,服务费明细!$B16,服务费底表!$T:$T,AR$3) -> 8 | AS16: =SUMIFS(服务费底表!$AC:$AC,服务费底表!$K:$K,服务费明细!$B16,服务费底表!$T:$T,AS$3) -> 0 | ... BG16: =SUMIFS(服务费底表!$AC:$AC,服务费底表!$K:$K,服务费明细!$B16,服务费底表!$T:$T,BG$3) -> 0 | BI16: =SUMIFS(服务费底表!$AC:$AC,服务费底表!$K:$K,服务费明细!$B16,服务费底表!$H:$H,服务费明细!BI$3) -> 8 | BJ16: =SUMIFS(服务费底表!$AC:$AC,服务费底表!$K:$K,服务费明细!$B16,服务费底表!$H:$H,服务费明细!BJ$3) -> 0 | BK16: =SUMIFS(服务费底表!$AC:$AC,服务费底表!$K:$K,服务费明细!$B16,服务费底表!$H:$H,服务费明细!BK$3) -> 0 | BL16: =SUMIFS(服务费底表!$AC:$AC,服务费底表!$K:$K,服务费明细!$B16,服务费底表!$H:$H,服务费明细!BL$3) -> 0 | BM16: =SUMIFS(服务费底表!$AC:$AC,服务费底表!$K:$K,服务费明细!$B16,服务费底表!$H:$H,服务费明细!BM$3) -> 0 | BN16: =SUMIFS(服务费底表!$AC:$AC,服务费底表!$K:$K,服务费明细!$B16,服务费底表!$H:$H,服务费明细!BN$3) -> 0 | BO16: =SUMIFS(服务费底表!$AC:$AC,服务费底表!$K:$K,服务费明细!$B16,服务费底表!$H:$H,服务费明细!BO$3) -> 0 | BQ16: =SUMIFS(服务费底表!$AD:$AD,服务费底表!$K:$K,服务费明细!$B16,服务费底表!$H:$H,服务费明细!BQ$3) -> 5200 | BR16: =SUMIFS(服务费底表!$AD:$AD,服务费底表!$K:$K,服务费明细!$B16,服务费底表!$H:$H,服务费明细!BR$3) -> 0 | BS16: =SUMIFS(服务费底表!$AD:$AD,服务费底表!$K:$K,服务费明细!$B16,服务费底表!$H:$H,服务费明细!BS$3) -> 0 | BT16: =SUMIFS(服务费底表!$AD:$AD,服务费底表!$K:$K,服务费明细!$B16,服务费底表!$H:$H,服务费明细!BT$3) -> 0 | BU16: =SUMIFS(服务费底表!$AD:$AD,服务费底表!$K:$K,服务费明细!$B16,服务费底表!$H:$H,服务费明细!BU$3) -> 0 | BV16: =SUMIFS(服务费底表!$AD:$AD,服务费底表!$K:$K,服务费明细!$B16,服务费底表!$H:$H,服务费明细!BV$3) -> 0 | BW16: =SUMIFS(服务费底表!$AD:$AD,服务费底表!$K:$K,服务费明细!$B16,服务费底表!$H:$H,服务费明细!BW$3) -> 0
B17: A008 | C17: =INDEX(二三级标准!$C:$C,MATCH(服务费明细!$B17,二三级标准!$B:$B,0)) -> 召开客户启动会 | D17: =IF($D$15=1,1,0) -> 1 | E17: =IF($D17=1,1,0) -> 1 | F17: =INDEX(二三级标准!$G:$G,MATCH(服务费明细!$B17,二三级标准!$B:$B,0)) -> 次 | G17: =AL17 -> 0 | H17: =AM17 -> 2 | I17: =AN17 -> 6 | J17: =AO17 -> 2 | K17: =AP17 -> 0 | L17: =AQ17 -> 0 | M17: =AR17 -> 2 | N17: =AS17 -> 0 | ... AB17: =BG17 -> 0 | AC17: {=SUMPRODUCT(G17:AB17,$G$4:$AB$4)} -> 11160 | AD17: =IF(AF17=AC17,TRUE,FALSE) -> TRUE | AE17: =IFERROR(SUMIF(服务费底表!$K:$K,服务费明细!$B17,服务费底表!$AD:$AD)/E17,0) -> 11160 | AF17: =E17*AE17 -> 11160 | AG17: =IFERROR(SUMIF(服务费底表!$K:$K,服务费明细!$B17,服务费底表!$AG:$AG)/E17,0) -> 11160 | AH17: =AG17*E17 -> 11160 | AJ17: =IF(D17=1,AK17/E17,0) -> 20 | AK17: =SUMIF(服务费底表!$K:$K,服务费明细!$B17,服务费底表!$AC:$AC) -> 20 | AL17: =SUMIFS(服务费底表!$AC:$AC,服务费底表!$K:$K,服务费明细!$B17,服务费底表!$T:$T,AL$3) -> 0 | AM17: =SUMIFS(服务费底表!$AC:$AC,服务费底表!$K:$K,服务费明细!$B17,服务费底表!$T:$T,AM$3) -> 2 | AN17: =SUMIFS(服务费底表!$AC:$AC,服务费底表!$K:$K,服务费明细!$B17,服务费底表!$T:$T,AN$3) -> 6 | AO17: =SUMIFS(服务费底表!$AC:$AC,服务费底表!$K:$K,服务费明细!$B17,服务费底表!$T:$T,AO$3) -> 2 | AP17: =SUMIFS(服务费底表!$AC:$AC,服务费底表!$K:$K,服务费明细!$B17,服务费底表!$T:$T,AP$3) -> 0 | AQ17: =SUMIFS(服务费底表!$AC:$AC,服务费底表!$K:$K,服务费明细!$B17,服务费底表!$T:$T,AQ$3) -> 0 | AR17: =SUMIFS(服务费底表!$AC:$AC,服务费底表!$K:$K,服务费明细!$B17,服务费底表!$T:$T,AR$3) -> 2 | AS17: =SUMIFS(服务费底表!$AC:$AC,服务费底表!$K:$K,服务费明细!$B17,服务费底表!$T:$T,AS$3) -> 0 | ... BG17: =SUMIFS(服务费底表!$AC:$AC,服务费底表!$K:$K,服务费明细!$B17,服务费底表!$T:$T,BG$3) -> 0 | BI17: =SUMIFS(服务费底表!$AC:$AC,服务费底表!$K:$K,服务费明细!$B17,服务费底表!$H:$H,服务费明细!BI$3) -> 2 | BJ17: =SUMIFS(服务费底表!$AC:$AC,服务费底表!$K:$K,服务费明细!$B17,服务费底表!$H:$H,服务费明细!BJ$3) -> 10 | BK17: =SUMIFS(服务费底表!$AC:$AC,服务费底表!$K:$K,服务费明细!$B17,服务费底表!$H:$H,服务费明细!BK$3) -> 2 | BL17: =SUMIFS(服务费底表!$AC:$AC,服务费底表!$K:$K,服务费明细!$B17,服务费底表!$H:$H,服务费明细!BL$3) -> 2 | BM17: =SUMIFS(服务费底表!$AC:$AC,服务费底表!$K:$K,服务费明细!$B17,服务费底表!$H:$H,服务费明细!BM$3) -> 2 | BN17: =SUMIFS(服务费底表!$AC:$AC,服务费底表!$K:$K,服务费明细!$B17,服务费底表!$H:$H,服务费明细!BN$3) -> 2 | BO17: =SUMIFS(服务费底表!$AC:$AC,服务费底表!$K:$K,服务费明细!$B17,服务费底表!$H:$H,服务费明细!BO$3) -> 0 | BQ17: =SUMIFS(服务费底表!$AD:$AD,服务费底表!$K:$K,服务费明细!$B17,服务费底表!$H:$H,服务费明细!BQ$3) -> 1300 | BR17: =SUMIFS(服务费底表!$AD:$AD,服务费底表!$K:$K,服务费明细!$B17,服务费底表!$H:$H,服务费明细!BR$3) -> 5940 | BS17: =SUMIFS(服务费底表!$AD:$AD,服务费底表!$K:$K,服务费明细!$B17,服务费底表!$H:$H,服务费明细!BS$3) -> 720 | BT17: =SUMIFS(服务费底表!$AD:$AD,服务费底表!$K:$K,服务费明细!$B17,服务费底表!$H:$H,服务费明细!BT$3) -> 800 | BU17: =SUMIFS(服务费底表!$AD:$AD,服务费底表!$K:$K,服务费明细!$B17,服务费底表!$H:$H,服务费明细!BU$3) -> 1000 | BV17: =SUMIFS(服务费底表!$AD:$AD,服务费底表!$K:$K,服务费明细!$B17,服务费底表!$H:$H,服务费明细!BV$3) -> 1400 | BW17: =SUMIFS(服务费底表!$AD:$AD,服务费底表!$K:$K,服务费明细!$B17,服务费底表!$H:$H,服务费明细!BW$3) -> 0
B18: A285 | C18: =INDEX(二三级标准!$C:$C,MATCH(服务费明细!$B18,二三级标准!$B:$B,0)) -> 协同拜访PI | D18: =IF($D$15=1,1,0) -> 1 | E18: =IF($D18=1,1,0) -> 1 | F18: =INDEX(二三级标准!$G:$G,MATCH(服务费明细!$B18,二三级标准!$B:$B,0)) -> 次 | G18: =AL18 -> 0 | H18: =AM18 -> 0 | I18: =AN18 -> 0 | J18: =AO18 -> 0 | K18: =AP18 -> 0 | L18: =AQ18 -> 0 | M18: =AR18 -> 16 | N18: =AS18 -> 0 | ... AB18: =BG18 -> 0 | AC18: {=SUMPRODUCT(G18:AB18,$G$4:$AB$4)} -> 10400 | AD18: =IF(AF18=AC18,TRUE,FALSE) -> TRUE | AE18: =IFERROR(SUMIF(服务费底表!$K:$K,服务费明细!$B18,服务费底表!$AD:$AD)/E18,0) -> 10400 | AF18: =E18*AE18 -> 10400 | AG18: =IFERROR(SUMIF(服务费底表!$K:$K,服务费明细!$B18,服务费底表!$AG:$AG)/E18,0) -> 10400 | AH18: =AG18*E18 -> 10400 | AI18: 有临医学协同拜访及拜访准备，差旅据实结算 | AJ18: =IF(D18=1,AK18/E18,0) -> 16 | AK18: =SUMIF(服务费底表!$K:$K,服务费明细!$B18,服务费底表!$AC:$AC) -> 16 | AL18: =SUMIFS(服务费底表!$AC:$AC,服务费底表!$K:$K,服务费明细!$B18,服务费底表!$T:$T,AL$3) -> 0 | AM18: =SUMIFS(服务费底表!$AC:$AC,服务费底表!$K:$K,服务费明细!$B18,服务费底表!$T:$T,AM$3) -> 0 | AN18: =SUMIFS(服务费底表!$AC:$AC,服务费底表!$K:$K,服务费明细!$B18,服务费底表!$T:$T,AN$3) -> 0 | AO18: =SUMIFS(服务费底表!$AC:$AC,服务费底表!$K:$K,服务费明细!$B18,服务费底表!$T:$T,AO$3) -> 0 | AP18: =SUMIFS(服务费底表!$AC:$AC,服务费底表!$K:$K,服务费明细!$B18,服务费底表!$T:$T,AP$3) -> 0 | AQ18: =SUMIFS(服务费底表!$AC:$AC,服务费底表!$K:$K,服务费明细!$B18,服务费底表!$T:$T,AQ$3) -> 0 | AR18: =SUMIFS(服务费底表!$AC:$AC,服务费底表!$K:$K,服务费明细!$B18,服务费底表!$T:$T,AR$3) -> 16 | AS18: =SUMIFS(服务费底表!$AC:$AC,服务费底表!$K:$K,服务费明细!$B18,服务费底表!$T:$T,AS$3) -> 0 | ... BG18: =SUMIFS(服务费底表!$AC:$AC,服务费底表!$K:$K,服务费明细!$B18,服务费底表!$T:$T,BG$3) -> 0 | BI18: =SUMIFS(服务费底表!$AC:$AC,服务费底表!$K:$K,服务费明细!$B18,服务费底表!$H:$H,服务费明细!BI$3) -> 16 | BJ18: =SUMIFS(服务费底表!$AC:$AC,服务费底表!$K:$K,服务费明细!$B18,服务费底表!$H:$H,服务费明细!BJ$3) -> 0 | BK18: =SUMIFS(服务费底表!$AC:$AC,服务费底表!$K:$K,服务费明细!$B18,服务费底表!$H:$H,服务费明细!BK$3) -> 0 | BL18: =SUMIFS(服务费底表!$AC:$AC,服务费底表!$K:$K,服务费明细!$B18,服务费底表!$H:$H,服务费明细!BL$3) -> 0 | BM18: =SUMIFS(服务费底表!$AC:$AC,服务费底表!$K:$K,服务费明细!$B18,服务费底表!$H:$H,服务费明细!BM$3) -> 0 | BN18: =SUMIFS(服务费底表!$AC:$AC,服务费底表!$K:$K,服务费明细!$B18,服务费底表!$H:$H,服务费明细!BN$3) -> 0 | BO18: =SUMIFS(服务费底表!$AC:$AC,服务费底表!$K:$K,服务费明细!$B18,服务费底表!$H:$H,服务费明细!BO$3) -> 0 | BQ18: =SUMIFS(服务费底表!$AD:$AD,服务费底表!$K:$K,服务费明细!$B18,服务费底表!$H:$H,服务费明细!BQ$3) -> 10400 | BR18: =SUMIFS(服务费底表!$AD:$AD,服务费底表!$K:$K,服务费明细!$B18,服务费底表!$H:$H,服务费明细!BR$3) -> 0 | BS18: =SUMIFS(服务费底表!$AD:$AD,服务费底表!$K:$K,服务费明细!$B18,服务费底表!$H:$H,服务费明细!BS$3) -> 0 | BT18: =SUMIFS(服务费底表!$AD:$AD,服务费底表!$K:$K,服务费明细!$B18,服务费底表!$H:$H,服务费明细!BT$3) -> 0 | BU18: =SUMIFS(服务费底表!$AD:$AD,服务费底表!$K:$K,服务费明细!$B18,服务费底表!$H:$H,服务费明细!BU$3) -> 0 | BV18: =SUMIFS(服务费底表!$AD:$AD,服务费底表!$K:$K,服务费明细!$B18,服务费底表!$H:$H,服务费明细!BV$3) -> 0 | BW18: =SUMIFS(服务费底表!$AD:$AD,服务费底表!$K:$K,服务费明细!$B18,服务费底表!$H:$H,服务费明细!BW$3) -> 0
B19: A287 | C19: =INDEX(二三级标准!$C:$C,MATCH(服务费明细!$B19,二三级标准!$B:$B,0)) -> 研究中心伦理意见答复 | D19: =IF($D$15=1,1,0) -> 1 | E19: =IF($D19=1,启动中心数,0) -> 4 | F19: =INDEX(二三级标准!$G:$G,MATCH(服务费明细!$B19,二三级标准!$B:$B,0)) -> 中心 | G19: =AL19 -> 0 | H19: =AM19 -> 0 | I19: =AN19 -> 0 | J19: =AO19 -> 0 | K19: =AP19 -> 0 | L19: =AQ19 -> 0 | M19: =AR19 -> 4 | N19: =AS19 -> 0 | ... AB19: =BG19 -> 0 | AC19: {=SUMPRODUCT(G19:AB19,$G$4:$AB$4)} -> 2600 | AD19: =IF(AF19=AC19,TRUE,FALSE) -> TRUE | AE19: =IFERROR(SUMIF(服务费底表!$K:$K,服务费明细!$B19,服务费底表!$AD:$AD)/E19,0) -> 650 | AF19: =E19*AE19 -> 2600 | AG19: =IFERROR(SUMIF(服务费底表!$K:$K,服务费明细!$B19,服务费底表!$AG:$AG)/E19,0) -> 650 | AH19: =AG19*E19 -> 2600 | AJ19: =IF(D19=1,AK19/E19,0) -> 1 | AK19: =SUMIF(服务费底表!$K:$K,服务费明细!$B19,服务费底表!$AC:$AC) -> 4 | AL19: =SUMIFS(服务费底表!$AC:$AC,服务费底表!$K:$K,服务费明细!$B19,服务费底表!$T:$T,AL$3) -> 0 | AM19: =SUMIFS(服务费底表!$AC:$AC,服务费底表!$K:$K,服务费明细!$B19,服务费底表!$T:$T,AM$3) -> 0 | AN19: =SUMIFS(服务费底表!$AC:$AC,服务费底表!$K:$K,服务费明细!$B19,服务费底表!$T:$T,AN$3) -> 0 | AO19: =SUMIFS(服务费底表!$AC:$AC,服务费底表!$K:$K,服务费明细!$B19,服务费底表!$T:$T,AO$3) -> 0 | AP19: =SUMIFS(服务费底表!$AC:$AC,服务费底表!$K:$K,服务费明细!$B19,服务费底表!$T:$T,AP$3) -> 0 | AQ19: =SUMIFS(服务费底表!$AC:$AC,服务费底表!$K:$K,服务费明细!$B19,服务费底表!$T:$T,AQ$3) -> 0 | AR19: =SUMIFS(服务费底表!$AC:$AC,服务费底表!$K:$K,服务费明细!$B19,服务费底表!$T:$T,AR$3) -> 4 | AS19: =SUMIFS(服务费底表!$AC:$AC,服务费底表!$K:$K,服务费明细!$B19,服务费底表!$T:$T,AS$3) -> 0 | ... BG19: =SUMIFS(服务费底表!$AC:$AC,服务费底表!$K:$K,服务费明细!$B19,服务费底表!$T:$T,BG$3) -> 0 | BI19: =SUMIFS(服务费底表!$AC:$AC,服务费底表!$K:$K,服务费明细!$B19,服务费底表!$H:$H,服务费明细!BI$3) -> 4 | BJ19: =SUMIFS(服务费底表!$AC:$AC,服务费底表!$K:$K,服务费明细!$B19,服务费底表!$H:$H,服务费明细!BJ$3) -> 0 | BK19: =SUMIFS(服务费底表!$AC:$AC,服务费底表!$K:$K,服务费明细!$B19,服务费底表!$H:$H,服务费明细!BK$3) -> 0 | BL19: =SUMIFS(服务费底表!$AC:$AC,服务费底表!$K:$K,服务费明细!$B19,服务费底表!$H:$H,服务费明细!BL$3) -> 0 | BM19: =SUMIFS(服务费底表!$AC:$AC,服务费底表!$K:$K,服务费明细!$B19,服务费底表!$H:$H,服务费明细!BM$3) -> 0 | BN19: =SUMIFS(服务费底表!$AC:$AC,服务费底表!$K:$K,服务费明细!$B19,服务费底表!$H:$H,服务费明细!BN$3) -> 0 | BO19: =SUMIFS(服务费底表!$AC:$AC,服务费底表!$K:$K,服务费明细!$B19,服务费底表!$H:$H,服务费明细!BO$3) -> 0 | BQ19: =SUMIFS(服务费底表!$AD:$AD,服务费底表!$K:$K,服务费明细!$B19,服务费底表!$H:$H,服务费明细!BQ$3) -> 2600 | BR19: =SUMIFS(服务费底表!$AD:$AD,服务费底表!$K:$K,服务费明细!$B19,服务费底表!$H:$H,服务费明细!BR$3) -> 0 | BS19: =SUMIFS(服务费底表!$AD:$AD,服务费底表!$K:$K,服务费明细!$B19,服务费底表!$H:$H,服务费明细!BS$3) -> 0 | BT19: =SUMIFS(服务费底表!$AD:$AD,服务费底表!$K:$K,服务费明细!$B19,服务费底表!$H:$H,服务费明细!BT$3) -> 0 | BU19: =SUMIFS(服务费底表!$AD:$AD,服务费底表!$K:$K,服务费明细!$B19,服务费底表!$H:$H,服务费明细!BU$3) -> 0 | BV19: =SUMIFS(服务费底表!$AD:$AD,服务费底表!$K:$K,服务费明细!$B19,服务费底表!$H:$H,服务费明细!BV$3) -> 0 | BW19: =SUMIFS(服务费底表!$AD:$AD,服务费底表!$K:$K,服务费明细!$B19,服务费底表!$H:$H,服务费明细!BW$3) -> 0
B20: A009 | C20: =INDEX(二三级标准!$C:$C,MATCH(服务费明细!$B20,二三级标准!$B:$B,0)) -> 方案培训 | D20: =IF($D$15=1,1,0) -> 1 | E20: =IF($D20=1,1,0) -> 1 | F20: =INDEX(二三级标准!$G:$G,MATCH(服务费明细!$B20,二三级标准!$B:$B,0)) -> 次 | G20: =AL20 -> 2 | H20: =AM20 -> 1 | I20: =AN20 -> 1 | J20: =AO20 -> 0 | K20: =AP20 -> 0 | L20: =AQ20 -> 1 | M20: =AR20 -> 7 | N20: =AS20 -> 0 | ... AB20: =BG20 -> 0 | AC20: {=SUMPRODUCT(G20:AB20,$G$4:$AB$4)} -> 8930 | AD20: =IF(AF20=AC20,TRUE,FALSE) -> TRUE | AE20: =IFERROR(SUMIF(服务费底表!$K:$K,服务费明细!$B20,服务费底表!$AD:$AD)/E20,0) -> 8930 | AF20: =E20*AE20 -> 8930 | AG20: =IFERROR(SUMIF(服务费底表!$K:$K,服务费明细!$B20,服务费底表!$AG:$AG)/E20,0) -> 8930 | AH20: =AG20*E20 -> 8930 | AI20: =IF(医学监查YN=1,"有临医学组织项目组的方案培训。","项目组按照客户安排参加方案培训或自行组织学习方案。") -> 有临医学组织项目组的方案培训。 | AJ20: =IF(D20=1,AK20/E20,0) -> 16 | AK20: =SUMIF(服务费底表!$K:$K,服务费明细!$B20,服务费底表!$AC:$AC) -> 16 | AL20: =SUMIFS(服务费底表!$AC:$AC,服务费底表!$K:$K,服务费明细!$B20,服务费底表!$T:$T,AL$3) -> 2 | AM20: =SUMIFS(服务费底表!$AC:$AC,服务费底表!$K:$K,服务费明细!$B20,服务费底表!$T:$T,AM$3) -> 1 | AN20: =SUMIFS(服务费底表!$AC:$AC,服务费底表!$K:$K,服务费明细!$B20,服务费底表!$T:$T,AN$3) -> 1 | AO20: =SUMIFS(服务费底表!$AC:$AC,服务费底表!$K:$K,服务费明细!$B20,服务费底表!$T:$T,AO$3) -> 0 | AP20: =SUMIFS(服务费底表!$AC:$AC,服务费底表!$K:$K,服务费明细!$B20,服务费底表!$T:$T,AP$3) -> 0 | AQ20: =SUMIFS(服务费底表!$AC:$AC,服务费底表!$K:$K,服务费明细!$B20,服务费底表!$T:$T,AQ$3) -> 1 | AR20: =SUMIFS(服务费底表!$AC:$AC,服务费底表!$K:$K,服务费明细!$B20,服务费底表!$T:$T,AR$3) -> 7 | AS20: =SUMIFS(服务费底表!$AC:$AC,服务费底表!$K:$K,服务费明细!$B20,服务费底表!$T:$T,AS$3) -> 0 | ... BG20: =SUMIFS(服务费底表!$AC:$AC,服务费底表!$K:$K,服务费明细!$B20,服务费底表!$T:$T,BG$3) -> 0 | BI20: =SUMIFS(服务费底表!$AC:$AC,服务费底表!$K:$K,服务费明细!$B20,服务费底表!$H:$H,服务费明细!BI$3) -> 8 | BJ20: =SUMIFS(服务费底表!$AC:$AC,服务费底表!$K:$K,服务费明细!$B20,服务费底表!$H:$H,服务费明细!BJ$3) -> 4 | BK20: =SUMIFS(服务费底表!$AC:$AC,服务费底表!$K:$K,服务费明细!$B20,服务费底表!$H:$H,服务费明细!BK$3) -> 1 | BL20: =SUMIFS(服务费底表!$AC:$AC,服务费底表!$K:$K,服务费明细!$B20,服务费底表!$H:$H,服务费明细!BL$3) -> 1 | BM20: =SUMIFS(服务费底表!$AC:$AC,服务费底表!$K:$K,服务费明细!$B20,服务费底表!$H:$H,服务费明细!BM$3) -> 1 | BN20: =SUMIFS(服务费底表!$AC:$AC,服务费底表!$K:$K,服务费明细!$B20,服务费底表!$H:$H,服务费明细!BN$3) -> 1 | BO20: =SUMIFS(服务费底表!$AC:$AC,服务费底表!$K:$K,服务费明细!$B20,服务费底表!$H:$H,服务费明细!BO$3) -> 0 | BQ20: =SUMIFS(服务费底表!$AD:$AD,服务费底表!$K:$K,服务费明细!$B20,服务费底表!$H:$H,服务费明细!BQ$3) -> 5540 | BR20: =SUMIFS(服务费底表!$AD:$AD,服务费底表!$K:$K,服务费明细!$B20,服务费底表!$H:$H,服务费明细!BR$3) -> 1550 | BS20: =SUMIFS(服务费底表!$AD:$AD,服务费底表!$K:$K,服务费明细!$B20,服务费底表!$H:$H,服务费明细!BS$3) -> 360 | BT20: =SUMIFS(服务费底表!$AD:$AD,服务费底表!$K:$K,服务费明细!$B20,服务费底表!$H:$H,服务费明细!BT$3) -> 400 | BU20: =SUMIFS(服务费底表!$AD:$AD,服务费底表!$K:$K,服务费明细!$B20,服务费底表!$H:$H,服务费明细!BU$3) -> 500 | BV20: =SUMIFS(服务费底表!$AD:$AD,服务费底表!$K:$K,服务费明细!$B20,服务费底表!$H:$H,服务费明细!BV$3) -> 580 | BW20: =SUMIFS(服务费底表!$AD:$AD,服务费底表!$K:$K,服务费明细!$B20,服务费底表!$H:$H,服务费明细!BW$3) -> 0
B21: A248 | C21: =INDEX(二三级标准!$C:$C,MATCH(服务费明细!$B21,二三级标准!$B:$B,0)) -> SSU阶段文件准备 | D21: =IF($D$15=1,1,0) -> 1 | E21: =IF($D21=1,1,0) -> 1 | F21: =INDEX(二三级标准!$G:$G,MATCH(服务费明细!$B21,二三级标准!$B:$B,0)) -> 份 | G21: =AL21 -> 0 | H21: =AM21 -> 0 | I21: =AN21 -> 24 | J21: =AO21 -> 0 | K21: =AP21 -> 0 | L21: =AQ21 -> 0 | M21: =AR21 -> 0 | N21: =AS21 -> 0 | ... AB21: =BG21 -> 0 | AC21: {=SUMPRODUCT(G21:AB21,$G$4:$AB$4)} -> 15600 | AD21: =IF(AF21=AC21,TRUE,FALSE) -> TRUE | AE21: =IFERROR(SUMIF(服务费底表!$K:$K,服务费明细!$B21,服务费底表!$AD:$AD)/E21,0) -> 15600 | AF21: =E21*AE21 -> 15600 | AG21: =IFERROR(SUMIF(服务费底表!$K:$K,服务费明细!$B21,服务费底表!$AG:$AG)/E21,0) -> 15600 | AH21: =AG21*E21 -> 15600 | AI21: 中心可行性调研问卷、立项伦理资料模版、合同模版等项目运营执行层面会使用到的表格模板、文件模板撰写。 | AJ21: =IF(D21=1,AK21/E21,0) -> 24 | AK21: =SUMIF(服务费底表!$K:$K,服务费明细!$B21,服务费底表!$AC:$AC) -> 24 | AL21: =SUMIFS(服务费底表!$AC:$AC,服务费底表!$K:$K,服务费明细!$B21,服务费底表!$T:$T,AL$3) -> 0 | AM21: =SUMIFS(服务费底表!$AC:$AC,服务费底表!$K:$K,服务费明细!$B21,服务费底表!$T:$T,AM$3) -> 0 | AN21: =SUMIFS(服务费底表!$AC:$AC,服务费底表!$K:$K,服务费明细!$B21,服务费底表!$T:$T,AN$3) -> 24 | AO21: =SUMIFS(服务费底表!$AC:$AC,服务费底表!$K:$K,服务费明细!$B21,服务费底表!$T:$T,AO$3) -> 0 | AP21: =SUMIFS(服务费底表!$AC:$AC,服务费底表!$K:$K,服务费明细!$B21,服务费底表!$T:$T,AP$3) -> 0 | AQ21: =SUMIFS(服务费底表!$AC:$AC,服务费底表!$K:$K,服务费明细!$B21,服务费底表!$T:$T,AQ$3) -> 0 | AR21: =SUMIFS(服务费底表!$AC:$AC,服务费底表!$K:$K,服务费明细!$B21,服务费底表!$T:$T,AR$3) -> 0 | AS21: =SUMIFS(服务费底表!$AC:$AC,服务费底表!$K:$K,服务费明细!$B21,服务费底表!$T:$T,AS$3) -> 0 | ... BG21: =SUMIFS(服务费底表!$AC:$AC,服务费底表!$K:$K,服务费明细!$B21,服务费底表!$T:$T,BG$3) -> 0 | BI21: =SUMIFS(服务费底表!$AC:$AC,服务费底表!$K:$K,服务费明细!$B21,服务费底表!$H:$H,服务费明细!BI$3) -> 0 | BJ21: =SUMIFS(服务费底表!$AC:$AC,服务费底表!$K:$K,服务费明细!$B21,服务费底表!$H:$H,服务费明细!BJ$3) -> 24 | BK21: =SUMIFS(服务费底表!$AC:$AC,服务费底表!$K:$K,服务费明细!$B21,服务费底表!$H:$H,服务费明细!BK$3) -> 0 | BL21: =SUMIFS(服务费底表!$AC:$AC,服务费底表!$K:$K,服务费明细!$B21,服务费底表!$H:$H,服务费明细!BL$3) -> 0 | BM21: =SUMIFS(服务费底表!$AC:$AC,服务费底表!$K:$K,服务费明细!$B21,服务费底表!$H:$H,服务费明细!BM$3) -> 0 | BN21: =SUMIFS(服务费底表!$AC:$AC,服务费底表!$K:$K,服务费明细!$B21,服务费底表!$H:$H,服务费明细!BN$3) -> 0 | BO21: =SUMIFS(服务费底表!$AC:$AC,服务费底表!$K:$K,服务费明细!$B21,服务费底表!$H:$H,服务费明细!BO$3) -> 0 | BQ21: =SUMIFS(服务费底表!$AD:$AD,服务费底表!$K:$K,服务费明细!$B21,服务费底表!$H:$H,服务费明细!BQ$3) -> 0 | BR21: =SUMIFS(服务费底表!$AD:$AD,服务费底表!$K:$K,服务费明细!$B21,服务费底表!$H:$H,服务费明细!BR$3) -> 15600 | BS21: =SUMIFS(服务费底表!$AD:$AD,服务费底表!$K:$K,服务费明细!$B21,服务费底表!$H:$H,服务费明细!BS$3) -> 0 | BT21: =SUMIFS(服务费底表!$AD:$AD,服务费底表!$K:$K,服务费明细!$B21,服务费底表!$H:$H,服务费明细!BT$3) -> 0 | BU21: =SUMIFS(服务费底表!$AD:$AD,服务费底表!$K:$K,服务费明细!$B21,服务费底表!$H:$H,服务费明细!BU$3) -> 0 | BV21: =SUMIFS(服务费底表!$AD:$AD,服务费底表!$K:$K,服务费明细!$B21,服务费底表!$H:$H,服务费明细!BV$3) -> 0 | BW21: =SUMIFS(服务费底表!$AD:$AD,服务费底表!$K:$K,服务费明细!$B21,服务费底表!$H:$H,服务费明细!BW$3) -> 0
B22: A010 | C22: =INDEX(二三级标准!$C:$C,MATCH(服务费明细!$B22,二三级标准!$B:$B,0)) -> 中心可行性调研 | D22: =IF($D$15=1,1,0) -> 1 | E22: =IF($D22=1,调研中心数,0) -> 8 | F22: =INDEX(二三级标准!$G:$G,MATCH(服务费明细!$B22,二三级标准!$B:$B,0)) -> 次 | G22: =AL22 -> 24 | H22: =AM22 -> 0 | I22: =AN22 -> 0 | J22: =AO22 -> 0 | K22: =AP22 -> 0 | L22: =AQ22 -> 0 | M22: =AR22 -> 0 | N22: =AS22 -> 0 | ... AB22: =BG22 -> 0 | AC22: {=SUMPRODUCT(G22:AB22,$G$4:$AB$4)} -> 8160 | AD22: =IF(AF22=AC22,TRUE,FALSE) -> TRUE | AE22: =IFERROR(SUMIF(服务费底表!$K:$K,服务费明细!$B22,服务费底表!$AD:$AD)/E22,0) -> 1020 | AF22: =E22*AE22 -> 8160 | AG22: =IFERROR(SUMIF(服务费底表!$K:$K,服务费明细!$B22,服务费底表!$AG:$AG)/E22,0) -> 1020 | AH22: =AG22*E22 -> 8160 | AI22: ="有临撰写各研究中心可行性调研问卷，并将与潜在的"&E22&"家中心确认是否有兴趣接收项目相关信息和保密协议。保密协议签署后，项目信息将发给中心。有临对所有联络的中心进行分发、跟踪、收集和审核问卷。" -> 有临撰写各研究中心可行性调研问卷，并将与潜在的8家中心确认是否有兴趣接收项目相关信息和保密协议。保密协议签署后，项目信息将发给中心。有临对所有联络的中心进行分发、跟踪、收集和审核问卷。 | AJ22: =IF(D22=1,AK22/E22,0) -> 3 | AK22: =SUMIF(服务费底表!$K:$K,服务费明细!$B22,服务费底表!$AC:$AC) -> 24 | AL22: =SUMIFS(服务费底表!$AC:$AC,服务费底表!$K:$K,服务费明细!$B22,服务费底表!$T:$T,AL$3) -> 24 | AM22: =SUMIFS(服务费底表!$AC:$AC,服务费底表!$K:$K,服务费明细!$B22,服务费底表!$T:$T,AM$3) -> 0 | AN22: =SUMIFS(服务费底表!$AC:$AC,服务费底表!$K:$K,服务费明细!$B22,服务费底表!$T:$T,AN$3) -> 0 | AO22: =SUMIFS(服务费底表!$AC:$AC,服务费底表!$K:$K,服务费明细!$B22,服务费底表!$T:$T,AO$3) -> 0 | AP22: =SUMIFS(服务费底表!$AC:$AC,服务费底表!$K:$K,服务费明细!$B22,服务费底表!$T:$T,AP$3) -> 0 | AQ22: =SUMIFS(服务费底表!$AC:$AC,服务费底表!$K:$K,服务费明细!$B22,服务费底表!$T:$T,AQ$3) -> 0 | AR22: =SUMIFS(服务费底表!$AC:$AC,服务费底表!$K:$K,服务费明细!$B22,服务费底表!$T:$T,AR$3) -> 0 | AS22: =SUMIFS(服务费底表!$AC:$AC,服务费底表!$K:$K,服务费明细!$B22,服务费底表!$T:$T,AS$3) -> 0 | ... BG22: =SUMIFS(服务费底表!$AC:$AC,服务费底表!$K:$K,服务费明细!$B22,服务费底表!$T:$T,BG$3) -> 0 | BI22: =SUMIFS(服务费底表!$AC:$AC,服务费底表!$K:$K,服务费明细!$B22,服务费底表!$H:$H,服务费明细!BI$3) -> 0 | BJ22: =SUMIFS(服务费底表!$AC:$AC,服务费底表!$K:$K,服务费明细!$B22,服务费底表!$H:$H,服务费明细!BJ$3) -> 24 | BK22: =SUMIFS(服务费底表!$AC:$AC,服务费底表!$K:$K,服务费明细!$B22,服务费底表!$H:$H,服务费明细!BK$3) -> 0 | BL22: =SUMIFS(服务费底表!$AC:$AC,服务费底表!$K:$K,服务费明细!$B22,服务费底表!$H:$H,服务费明细!BL$3) -> 0 | BM22: =SUMIFS(服务费底表!$AC:$AC,服务费底表!$K:$K,服务费明细!$B22,服务费底表!$H:$H,服务费明细!BM$3) -> 0 | BN22: =SUMIFS(服务费底表!$AC:$AC,服务费底表!$K:$K,服务费明细!$B22,服务费底表!$H:$H,服务费明细!BN$3) -> 0 | BO22: =SUMIFS(服务费底表!$AC:$AC,服务费底表!$K:$K,服务费明细!$B22,服务费底表!$H:$H,服务费明细!BO$3) -> 0 | BQ22: =SUMIFS(服务费底表!$AD:$AD,服务费底表!$K:$K,服务费明细!$B22,服务费底表!$H:$H,服务费明细!BQ$3) -> 0 | BR22: =SUMIFS(服务费底表!$AD:$AD,服务费底表!$K:$K,服务费明细!$B22,服务费底表!$H:$H,服务费明细!BR$3) -> 8160 | BS22: =SUMIFS(服务费底表!$AD:$AD,服务费底表!$K:$K,服务费明细!$B22,服务费底表!$H:$H,服务费明细!BS$3) -> 0 | BT22: =SUMIFS(服务费底表!$AD:$AD,服务费底表!$K:$K,服务费明细!$B22,服务费底表!$H:$H,服务费明细!BT$3) -> 0 | BU22: =SUMIFS(服务费底表!$AD:$AD,服务费底表!$K:$K,服务费明细!$B22,服务费底表!$H:$H,服务费明细!BU$3) -> 0 | BV22: =SUMIFS(服务费底表!$AD:$AD,服务费底表!$K:$K,服务费明细!$B22,服务费底表!$H:$H,服务费明细!BV$3) -> 0 | BW22: =SUMIFS(服务费底表!$AD:$AD,服务费底表!$K:$K,服务费明细!$B22,服务费底表!$H:$H,服务费明细!BW$3) -> 0
B23: A011 | C23: =INDEX(二三级标准!$C:$C,MATCH(服务费明细!$B23,二三级标准!$B:$B,0)) -> 筛选访视 | D23: =IF($D$15=1,1,0) -> 1 | E23: =IF($D23=1,筛选中心数,0) -> 6 | F23: =INDEX(二三级标准!$G:$G,MATCH(服务费明细!$B23,二三级标准!$B:$B,0)) -> 次 | G23: =AL23 -> 90 | H23: =AM23 -> 0 | I23: =AN23 -> 12 | J23: =AO23 -> 0 | K23: =AP23 -> 0 | L23: =AQ23 -> 0 | M23: =AR23 -> 0 | N23: =AS23 -> 0 | ... AB23: =BG23 -> 0 | AC23: {=SUMPRODUCT(G23:AB23,$G$4:$AB$4)} -> 38400 | AD23: =IF(AF23=AC23,TRUE,FALSE) -> TRUE | AE23: =IFERROR(SUMIF(服务费底表!$K:$K,服务费明细!$B23,服务费底表!$AD:$AD)/E23,0) -> 6400 | AF23: =E23*AE23 -> 38400 | AG23: =IFERROR(SUMIF(服务费底表!$K:$K,服务费明细!$B23,服务费底表!$AG:$AG)/E23,0) -> 6400 | AH23: =AG23*E23 -> 38400 | AI23: ="从"&E23&"次筛选访视中筛选"&启动中心数&"家中心" -> 从6次筛选访视中筛选4家中心 | AJ23: =IF(D23=1,AK23/E23,0) -> 17 | AK23: =SUMIF(服务费底表!$K:$K,服务费明细!$B23,服务费底表!$AC:$AC) -> 102 | AL23: =SUMIFS(服务费底表!$AC:$AC,服务费底表!$K:$K,服务费明细!$B23,服务费底表!$T:$T,AL$3) -> 90 | AM23: =SUMIFS(服务费底表!$AC:$AC,服务费底表!$K:$K,服务费明细!$B23,服务费底表!$T:$T,AM$3) -> 0 | AN23: =SUMIFS(服务费底表!$AC:$AC,服务费底表!$K:$K,服务费明细!$B23,服务费底表!$T:$T,AN$3) -> 12 | AO23: =SUMIFS(服务费底表!$AC:$AC,服务费底表!$K:$K,服务费明细!$B23,服务费底表!$T:$T,AO$3) -> 0 | AP23: =SUMIFS(服务费底表!$AC:$AC,服务费底表!$K:$K,服务费明细!$B23,服务费底表!$T:$T,AP$3) -> 0 | AQ23: =SUMIFS(服务费底表!$AC:$AC,服务费底表!$K:$K,服务费明细!$B23,服务费底表!$T:$T,AQ$3) -> 0 | AR23: =SUMIFS(服务费底表!$AC:$AC,服务费底表!$K:$K,服务费明细!$B23,服务费底表!$T:$T,AR$3) -> 0 | AS23: =SUMIFS(服务费底表!$AC:$AC,服务费底表!$K:$K,服务费明细!$B23,服务费底表!$T:$T,AS$3) -> 0 | ... BG23: =SUMIFS(服务费底表!$AC:$AC,服务费底表!$K:$K,服务费明细!$B23,服务费底表!$T:$T,BG$3) -> 0 | BI23: =SUMIFS(服务费底表!$AC:$AC,服务费底表!$K:$K,服务费明细!$B23,服务费底表!$H:$H,服务费明细!BI$3) -> 0 | BJ23: =SUMIFS(服务费底表!$AC:$AC,服务费底表!$K:$K,服务费明细!$B23,服务费底表!$H:$H,服务费明细!BJ$3) -> 102 | BK23: =SUMIFS(服务费底表!$AC:$AC,服务费底表!$K:$K,服务费明细!$B23,服务费底表!$H:$H,服务费明细!BK$3) -> 0 | BL23: =SUMIFS(服务费底表!$AC:$AC,服务费底表!$K:$K,服务费明细!$B23,服务费底表!$H:$H,服务费明细!BL$3) -> 0 | BM23: =SUMIFS(服务费底表!$AC:$AC,服务费底表!$K:$K,服务费明细!$B23,服务费底表!$H:$H,服务费明细!BM$3) -> 0 | BN23: =SUMIFS(服务费底表!$AC:$AC,服务费底表!$K:$K,服务费明细!$B23,服务费底表!$H:$H,服务费明细!BN$3) -> 0 | BO23: =SUMIFS(服务费底表!$AC:$AC,服务费底表!$K:$K,服务费明细!$B23,服务费底表!$H:$H,服务费明细!BO$3) -> 0 | BQ23: =SUMIFS(服务费底表!$AD:$AD,服务费底表!$K:$K,服务费明细!$B23,服务费底表!$H:$H,服务费明细!BQ$3) -> 0 | BR23: =SUMIFS(服务费底表!$AD:$AD,服务费底表!$K:$K,服务费明细!$B23,服务费底表!$H:$H,服务费明细!BR$3) -> 38400 | BS23: =SUMIFS(服务费底表!$AD:$AD,服务费底表!$K:$K,服务费明细!$B23,服务费底表!$H:$H,服务费明细!BS$3) -> 0 | BT23: =SUMIFS(服务费底表!$AD:$AD,服务费底表!$K:$K,服务费明细!$B23,服务费底表!$H:$H,服务费明细!BT$3) -> 0 | BU23: =SUMIFS(服务费底表!$AD:$AD,服务费底表!$K:$K,服务费明细!$B23,服务费底表!$H:$H,服务费明细!BU$3) -> 0 | BV23: =SUMIFS(服务费底表!$AD:$AD,服务费底表!$K:$K,服务费明细!$B23,服务费底表!$H:$H,服务费明细!BV$3) -> 0 | BW23: =SUMIFS(服务费底表!$AD:$AD,服务费底表!$K:$K,服务费明细!$B23,服务费底表!$H:$H,服务费明细!BW$3) -> 0
B24: A012 | C24: =INDEX(二三级标准!$C:$C,MATCH(服务费明细!$B24,二三级标准!$B:$B,0)) -> 机构立项 | D24: =IF($D$15=1,1,0) -> 1 | E24: =IF($D24=1,启动中心数,0) -> 4 | F24: =INDEX(二三级标准!$G:$G,MATCH(服务费明细!$B24,二三级标准!$B:$B,0)) -> 次 | G24: =AL24 -> 64 | H24: =AM24 -> 12 | I24: =AN24 -> 8 | J24: =AO24 -> 0 | K24: =AP24 -> 0 | L24: =AQ24 -> 0 | M24: =AR24 -> 0 | N24: =AS24 -> 0 | ... AB24: =BG24 -> 0 | AC24: {=SUMPRODUCT(G24:AB24,$G$4:$AB$4)} -> 29600 | AD24: =IF(AF24=AC24,TRUE,FALSE) -> TRUE | AE24: =IFERROR(SUMIF(服务费底表!$K:$K,服务费明细!$B24,服务费底表!$AD:$AD)/E24,0) -> 7400 | AF24: =E24*AE24 -> 29600 | AG24: =IFERROR(SUMIF(服务费底表!$K:$K,服务费明细!$B24,服务费底表!$AG:$AG)/E24,0) -> 7400 | AH24: =AG24*E24 -> 29600 | AI24: 机构首次立项的准备、提交和跟踪。 | AJ24: =IF(D24=1,AK24/E24,0) -> 21 | AK24: =SUMIF(服务费底表!$K:$K,服务费明细!$B24,服务费底表!$AC:$AC) -> 84 | AL24: =SUMIFS(服务费底表!$AC:$AC,服务费底表!$K:$K,服务费明细!$B24,服务费底表!$T:$T,AL$3) -> 64 | AM24: =SUMIFS(服务费底表!$AC:$AC,服务费底表!$K:$K,服务费明细!$B24,服务费底表!$T:$T,AM$3) -> 12 | AN24: =SUMIFS(服务费底表!$AC:$AC,服务费底表!$K:$K,服务费明细!$B24,服务费底表!$T:$T,AN$3) -> 8 | AO24: =SUMIFS(服务费底表!$AC:$AC,服务费底表!$K:$K,服务费明细!$B24,服务费底表!$T:$T,AO$3) -> 0 | AP24: =SUMIFS(服务费底表!$AC:$AC,服务费底表!$K:$K,服务费明细!$B24,服务费底表!$T:$T,AP$3) -> 0 | AQ24: =SUMIFS(服务费底表!$AC:$AC,服务费底表!$K:$K,服务费明细!$B24,服务费底表!$T:$T,AQ$3) -> 0 | AR24: =SUMIFS(服务费底表!$AC:$AC,服务费底表!$K:$K,服务费明细!$B24,服务费底表!$T:$T,AR$3) -> 0 | AS24: =SUMIFS(服务费底表!$AC:$AC,服务费底表!$K:$K,服务费明细!$B24,服务费底表!$T:$T,AS$3) -> 0 | ... BG24: =SUMIFS(服务费底表!$AC:$AC,服务费底表!$K:$K,服务费明细!$B24,服务费底表!$T:$T,BG$3) -> 0 | BI24: =SUMIFS(服务费底表!$AC:$AC,服务费底表!$K:$K,服务费明细!$B24,服务费底表!$H:$H,服务费明细!BI$3) -> 0 | BJ24: =SUMIFS(服务费底表!$AC:$AC,服务费底表!$K:$K,服务费明细!$B24,服务费底表!$H:$H,服务费明细!BJ$3) -> 84 | BK24: =SUMIFS(服务费底表!$AC:$AC,服务费底表!$K:$K,服务费明细!$B24,服务费底表!$H:$H,服务费明细!BK$3) -> 0 | BL24: =SUMIFS(服务费底表!$AC:$AC,服务费底表!$K:$K,服务费明细!$B24,服务费底表!$H:$H,服务费明细!BL$3) -> 0 | BM24: =SUMIFS(服务费底表!$AC:$AC,服务费底表!$K:$K,服务费明细!$B24,服务费底表!$H:$H,服务费明细!BM$3) -> 0 | BN24: =SUMIFS(服务费底表!$AC:$AC,服务费底表!$K:$K,服务费明细!$B24,服务费底表!$H:$H,服务费明细!BN$3) -> 0 | BO24: =SUMIFS(服务费底表!$AC:$AC,服务费底表!$K:$K,服务费明细!$B24,服务费底表!$H:$H,服务费明细!BO$3) -> 0 | BQ24: =SUMIFS(服务费底表!$AD:$AD,服务费底表!$K:$K,服务费明细!$B24,服务费底表!$H:$H,服务费明细!BQ$3) -> 0 | BR24: =SUMIFS(服务费底表!$AD:$AD,服务费底表!$K:$K,服务费明细!$B24,服务费底表!$H:$H,服务费明细!BR$3) -> 29600 | BS24: =SUMIFS(服务费底表!$AD:$AD,服务费底表!$K:$K,服务费明细!$B24,服务费底表!$H:$H,服务费明细!BS$3) -> 0 | BT24: =SUMIFS(服务费底表!$AD:$AD,服务费底表!$K:$K,服务费明细!$B24,服务费底表!$H:$H,服务费明细!BT$3) -> 0 | BU24: =SUMIFS(服务费底表!$AD:$AD,服务费底表!$K:$K,服务费明细!$B24,服务费底表!$H:$H,服务费明细!BU$3) -> 0 | BV24: =SUMIFS(服务费底表!$AD:$AD,服务费底表!$K:$K,服务费明细!$B24,服务费底表!$H:$H,服务费明细!BV$3) -> 0 | BW24: =SUMIFS(服务费底表!$AD:$AD,服务费底表!$K:$K,服务费明细!$B24,服务费底表!$H:$H,服务费明细!BW$3) -> 0
B25: A013 | C25: =INDEX(二三级标准!$C:$C,MATCH(服务费明细!$B25,二三级标准!$B:$B,0)) -> 首次伦理文件准备和递交 | D25: =IF($D$15=1,1,0) -> 1 | E25: =IF($D25=1,启动中心数,0) -> 4 | F25: =INDEX(二三级标准!$G:$G,MATCH(服务费明细!$B25,二三级标准!$B:$B,0)) -> 次 | G25: =AL25 -> 96 | H25: =AM25 -> 12 | I25: =AN25 -> 8 | J25: =AO25 -> 0 | K25: =AP25 -> 0 | L25: =AQ25 -> 0 | M25: =AR25 -> 0 | N25: =AS25 -> 0 | ... AB25: =BG25 -> 0 | AC25: {=SUMPRODUCT(G25:AB25,$G$4:$AB$4)} -> 40480 | AD25: =IF(AF25=AC25,TRUE,FALSE) -> TRUE | AE25: =IFERROR(SUMIF(服务费底表!$K:$K,服务费明细!$B25,服务费底表!$AD:$AD)/E25,0) -> 10120 | AF25: =E25*AE25 -> 40480 | AG25: =IFERROR(SUMIF(服务费底表!$K:$K,服务费明细!$B25,服务费底表!$AG:$AG)/E25,0) -> 10120 | AH25: =AG25*E25 -> 40480 | AI25: 包括首次伦理文件准备、递交和跟踪伦理递交申请及文件修订(加入中心信息和根据伦理要求修改)。 | AJ25: =IF(D25=1,AK25/E25,0) -> 29 | AK25: =SUMIF(服务费底表!$K:$K,服务费明细!$B25,服务费底表!$AC:$AC) -> 116 | AL25: =SUMIFS(服务费底表!$AC:$AC,服务费底表!$K:$K,服务费明细!$B25,服务费底表!$T:$T,AL$3) -> 96 | AM25: =SUMIFS(服务费底表!$AC:$AC,服务费底表!$K:$K,服务费明细!$B25,服务费底表!$T:$T,AM$3) -> 12 | AN25: =SUMIFS(服务费底表!$AC:$AC,服务费底表!$K:$K,服务费明细!$B25,服务费底表!$T:$T,AN$3) -> 8 | AO25: =SUMIFS(服务费底表!$AC:$AC,服务费底表!$K:$K,服务费明细!$B25,服务费底表!$T:$T,AO$3) -> 0 | AP25: =SUMIFS(服务费底表!$AC:$AC,服务费底表!$K:$K,服务费明细!$B25,服务费底表!$T:$T,AP$3) -> 0 | AQ25: =SUMIFS(服务费底表!$AC:$AC,服务费底表!$K:$K,服务费明细!$B25,服务费底表!$T:$T,AQ$3) -> 0 | AR25: =SUMIFS(服务费底表!$AC:$AC,服务费底表!$K:$K,服务费明细!$B25,服务费底表!$T:$T,AR$3) -> 0 | AS25: =SUMIFS(服务费底表!$AC:$AC,服务费底表!$K:$K,服务费明细!$B25,服务费底表!$T:$T,AS$3) -> 0 | ... BG25: =SUMIFS(服务费底表!$AC:$AC,服务费底表!$K:$K,服务费明细!$B25,服务费底表!$T:$T,BG$3) -> 0 | BI25: =SUMIFS(服务费底表!$AC:$AC,服务费底表!$K:$K,服务费明细!$B25,服务费底表!$H:$H,服务费明细!BI$3) -> 0 | BJ25: =SUMIFS(服务费底表!$AC:$AC,服务费底表!$K:$K,服务费明细!$B25,服务费底表!$H:$H,服务费明细!BJ$3) -> 116 | BK25: =SUMIFS(服务费底表!$AC:$AC,服务费底表!$K:$K,服务费明细!$B25,服务费底表!$H:$H,服务费明细!BK$3) -> 0 | BL25: =SUMIFS(服务费底表!$AC:$AC,服务费底表!$K:$K,服务费明细!$B25,服务费底表!$H:$H,服务费明细!BL$3) -> 0 | BM25: =SUMIFS(服务费底表!$AC:$AC,服务费底表!$K:$K,服务费明细!$B25,服务费底表!$H:$H,服务费明细!BM$3) -> 0 | BN25: =SUMIFS(服务费底表!$AC:$AC,服务费底表!$K:$K,服务费明细!$B25,服务费底表!$H:$H,服务费明细!BN$3) -> 0 | BO25: =SUMIFS(服务费底表!$AC:$AC,服务费底表!$K:$K,服务费明细!$B25,服务费底表!$H:$H,服务费明细!BO$3) -> 0 | BQ25: =SUMIFS(服务费底表!$AD:$AD,服务费底表!$K:$K,服务费明细!$B25,服务费底表!$H:$H,服务费明细!BQ$3) -> 0 | BR25: =SUMIFS(服务费底表!$AD:$AD,服务费底表!$K:$K,服务费明细!$B25,服务费底表!$H:$H,服务费明细!BR$3) -> 40480 | BS25: =SUMIFS(服务费底表!$AD:$AD,服务费底表!$K:$K,服务费明细!$B25,服务费底表!$H:$H,服务费明细!BS$3) -> 0 | BT25: =SUMIFS(服务费底表!$AD:$AD,服务费底表!$K:$K,服务费明细!$B25,服务费底表!$H:$H,服务费明细!BT$3) -> 0 | BU25: =SUMIFS(服务费底表!$AD:$AD,服务费底表!$K:$K,服务费明细!$B25,服务费底表!$H:$H,服务费明细!BU$3) -> 0 | BV25: =SUMIFS(服务费底表!$AD:$AD,服务费底表!$K:$K,服务费明细!$B25,服务费底表!$H:$H,服务费明细!BV$3) -> 0 | BW25: =SUMIFS(服务费底表!$AD:$AD,服务费底表!$K:$K,服务费明细!$B25,服务费底表!$H:$H,服务费明细!BW$3) -> 0
B26: A288 | C26: =INDEX(二三级标准!$C:$C,MATCH(服务费明细!$B26,二三级标准!$B:$B,0)) -> 研究方案Q&A回复 | D26: =IF($D$15=1,1,0) -> 1 | E26: =IF($D26=1,ROUND(SUM(首家伦理月+首家合同月+遗传办月+入组月+治疗月+随访月+长随访月),0),0) -> 16 | F26: =INDEX(二三级标准!$G:$G,MATCH(服务费明细!$B26,二三级标准!$B:$B,0)) -> 月 | G26: =AL26 -> 0 | H26: =AM26 -> 0 | I26: =AN26 -> 0 | J26: =AO26 -> 0 | K26: =AP26 -> 0 | L26: =AQ26 -> 0 | M26: =AR26 -> 32 | N26: =AS26 -> 0 | ... AB26: =BG26 -> 0 | AC26: {=SUMPRODUCT(G26:AB26,$G$4:$AB$4)} -> 20800 | AD26: =IF(AF26=AC26,TRUE,FALSE) -> TRUE | AE26: =IFERROR(SUMIF(服务费底表!$K:$K,服务费明细!$B26,服务费底表!$AD:$AD)/E26,0) -> 1300 | AF26: =E26*AE26 -> 20800 | AG26: =IFERROR(SUMIF(服务费底表!$K:$K,服务费明细!$B26,服务费底表!$AG:$AG)/E26,0) -> 1300 | AH26: =AG26*E26 -> 20800 | AJ26: =IF(D26=1,AK26/E26,0) -> 2 | AK26: =SUMIF(服务费底表!$K:$K,服务费明细!$B26,服务费底表!$AC:$AC) -> 32 | AL26: =SUMIFS(服务费底表!$AC:$AC,服务费底表!$K:$K,服务费明细!$B26,服务费底表!$T:$T,AL$3) -> 0 | AM26: =SUMIFS(服务费底表!$AC:$AC,服务费底表!$K:$K,服务费明细!$B26,服务费底表!$T:$T,AM$3) -> 0 | AN26: =SUMIFS(服务费底表!$AC:$AC,服务费底表!$K:$K,服务费明细!$B26,服务费底表!$T:$T,AN$3) -> 0 | AO26: =SUMIFS(服务费底表!$AC:$AC,服务费底表!$K:$K,服务费明细!$B26,服务费底表!$T:$T,AO$3) -> 0 | AP26: =SUMIFS(服务费底表!$AC:$AC,服务费底表!$K:$K,服务费明细!$B26,服务费底表!$T:$T,AP$3) -> 0 | AQ26: =SUMIFS(服务费底表!$AC:$AC,服务费底表!$K:$K,服务费明细!$B26,服务费底表!$T:$T,AQ$3) -> 0 | AR26: =SUMIFS(服务费底表!$AC:$AC,服务费底表!$K:$K,服务费明细!$B26,服务费底表!$T:$T,AR$3) -> 32 | AS26: =SUMIFS(服务费底表!$AC:$AC,服务费底表!$K:$K,服务费明细!$B26,服务费底表!$T:$T,AS$3) -> 0 | ... BG26: =SUMIFS(服务费底表!$AC:$AC,服务费底表!$K:$K,服务费明细!$B26,服务费底表!$T:$T,BG$3) -> 0 | BI26: =SUMIFS(服务费底表!$AC:$AC,服务费底表!$K:$K,服务费明细!$B26,服务费底表!$H:$H,服务费明细!BI$3) -> 32 | BJ26: =SUMIFS(服务费底表!$AC:$AC,服务费底表!$K:$K,服务费明细!$B26,服务费底表!$H:$H,服务费明细!BJ$3) -> 0 | BK26: =SUMIFS(服务费底表!$AC:$AC,服务费底表!$K:$K,服务费明细!$B26,服务费底表!$H:$H,服务费明细!BK$3) -> 0 | BL26: =SUMIFS(服务费底表!$AC:$AC,服务费底表!$K:$K,服务费明细!$B26,服务费底表!$H:$H,服务费明细!BL$3) -> 0 | BM26: =SUMIFS(服务费底表!$AC:$AC,服务费底表!$K:$K,服务费明细!$B26,服务费底表!$H:$H,服务费明细!BM$3) -> 0 | BN26: =SUMIFS(服务费底表!$AC:$AC,服务费底表!$K:$K,服务费明细!$B26,服务费底表!$H:$H,服务费明细!BN$3) -> 0 | BO26: =SUMIFS(服务费底表!$AC:$AC,服务费底表!$K:$K,服务费明细!$B26,服务费底表!$H:$H,服务费明细!BO$3) -> 0 | BQ26: =SUMIFS(服务费底表!$AD:$AD,服务费底表!$K:$K,服务费明细!$B26,服务费底表!$H:$H,服务费明细!BQ$3) -> 20800 | BR26: =SUMIFS(服务费底表!$AD:$AD,服务费底表!$K:$K,服务费明细!$B26,服务费底表!$H:$H,服务费明细!BR$3) -> 0 | BS26: =SUMIFS(服务费底表!$AD:$AD,服务费底表!$K:$K,服务费明细!$B26,服务费底表!$H:$H,服务费明细!BS$3) -> 0 | BT26: =SUMIFS(服务费底表!$AD:$AD,服务费底表!$K:$K,服务费明细!$B26,服务费底表!$H:$H,服务费明细!BT$3) -> 0 | BU26: =SUMIFS(服务费底表!$AD:$AD,服务费底表!$K:$K,服务费明细!$B26,服务费底表!$H:$H,服务费明细!BU$3) -> 0 | BV26: =SUMIFS(服务费底表!$AD:$AD,服务费底表!$K:$K,服务费明细!$B26,服务费底表!$H:$H,服务费明细!BV$3) -> 0 | BW26: =SUMIFS(服务费底表!$AD:$AD,服务费底表!$K:$K,服务费明细!$B26,服务费底表!$H:$H,服务费明细!BW$3) -> 0
B27: A014 | C27: =INDEX(二三级标准!$C:$C,MATCH(服务费明细!$B27,二三级标准!$B:$B,0)) -> 中心知情同意书撰写 | D27: =IF($D$15=1,1,0) -> 1 | E27: =IF($D27=1,ROUND(启动中心数*100%-1,0),0) -> 3 | F27: =INDEX(二三级标准!$G:$G,MATCH(服务费明细!$B27,二三级标准!$B:$B,0)) -> 份 | G27: =AL27 -> 3 | H27: =AM27 -> 0 | I27: =AN27 -> 3 | J27: =AO27 -> 0 | K27: =AP27 -> 0 | L27: =AQ27 -> 0 | M27: =AR27 -> 0 | N27: =AS27 -> 0 | ... AB27: =BG27 -> 0 | AC27: {=SUMPRODUCT(G27:AB27,$G$4:$AB$4)} -> 2970 | AD27: =IF(AF27=AC27,TRUE,FALSE) -> TRUE | AE27: =IFERROR(SUMIF(服务费底表!$K:$K,服务费明细!$B27,服务费底表!$AD:$AD)/E27,0) -> 990 | AF27: =E27*AE27 -> 2970 | AG27: =IFERROR(SUMIF(服务费底表!$K:$K,服务费明细!$B27,服务费底表!$AG:$AG)/E27,0) -> 990 | AH27: =AG27*E27 -> 2970 | AI27: ="有临负责"&E27&"份中心知情同意书的撰写。" -> 有临负责3份中心知情同意书的撰写。 | AJ27: =IF(D27=1,AK27/E27,0) -> 2 | AK27: =SUMIF(服务费底表!$K:$K,服务费明细!$B27,服务费底表!$AC:$AC) -> 6 | AL27: =SUMIFS(服务费底表!$AC:$AC,服务费底表!$K:$K,服务费明细!$B27,服务费底表!$T:$T,AL$3) -> 3 | AM27: =SUMIFS(服务费底表!$AC:$AC,服务费底表!$K:$K,服务费明细!$B27,服务费底表!$T:$T,AM$3) -> 0 | AN27: =SUMIFS(服务费底表!$AC:$AC,服务费底表!$K:$K,服务费明细!$B27,服务费底表!$T:$T,AN$3) -> 3 | AO27: =SUMIFS(服务费底表!$AC:$AC,服务费底表!$K:$K,服务费明细!$B27,服务费底表!$T:$T,AO$3) -> 0 | AP27: =SUMIFS(服务费底表!$AC:$AC,服务费底表!$K:$K,服务费明细!$B27,服务费底表!$T:$T,AP$3) -> 0 | AQ27: =SUMIFS(服务费底表!$AC:$AC,服务费底表!$K:$K,服务费明细!$B27,服务费底表!$T:$T,AQ$3) -> 0 | AR27: =SUMIFS(服务费底表!$AC:$AC,服务费底表!$K:$K,服务费明细!$B27,服务费底表!$T:$T,AR$3) -> 0 | AS27: =SUMIFS(服务费底表!$AC:$AC,服务费底表!$K:$K,服务费明细!$B27,服务费底表!$T:$T,AS$3) -> 0 | ... BG27: =SUMIFS(服务费底表!$AC:$AC,服务费底表!$K:$K,服务费明细!$B27,服务费底表!$T:$T,BG$3) -> 0 | BI27: =SUMIFS(服务费底表!$AC:$AC,服务费底表!$K:$K,服务费明细!$B27,服务费底表!$H:$H,服务费明细!BI$3) -> 0 | BJ27: =SUMIFS(服务费底表!$AC:$AC,服务费底表!$K:$K,服务费明细!$B27,服务费底表!$H:$H,服务费明细!BJ$3) -> 6 | BK27: =SUMIFS(服务费底表!$AC:$AC,服务费底表!$K:$K,服务费明细!$B27,服务费底表!$H:$H,服务费明细!BK$3) -> 0 | BL27: =SUMIFS(服务费底表!$AC:$AC,服务费底表!$K:$K,服务费明细!$B27,服务费底表!$H:$H,服务费明细!BL$3) -> 0 | BM27: =SUMIFS(服务费底表!$AC:$AC,服务费底表!$K:$K,服务费明细!$B27,服务费底表!$H:$H,服务费明细!BM$3) -> 0 | BN27: =SUMIFS(服务费底表!$AC:$AC,服务费底表!$K:$K,服务费明细!$B27,服务费底表!$H:$H,服务费明细!BN$3) -> 0 | BO27: =SUMIFS(服务费底表!$AC:$AC,服务费底表!$K:$K,服务费明细!$B27,服务费底表!$H:$H,服务费明细!BO$3) -> 0 | BQ27: =SUMIFS(服务费底表!$AD:$AD,服务费底表!$K:$K,服务费明细!$B27,服务费底表!$H:$H,服务费明细!BQ$3) -> 0 | BR27: =SUMIFS(服务费底表!$AD:$AD,服务费底表!$K:$K,服务费明细!$B27,服务费底表!$H:$H,服务费明细!BR$3) -> 2970 | BS27: =SUMIFS(服务费底表!$AD:$AD,服务费底表!$K:$K,服务费明细!$B27,服务费底表!$H:$H,服务费明细!BS$3) -> 0 | BT27: =SUMIFS(服务费底表!$AD:$AD,服务费底表!$K:$K,服务费明细!$B27,服务费底表!$H:$H,服务费明细!BT$3) -> 0 | BU27: =SUMIFS(服务费底表!$AD:$AD,服务费底表!$K:$K,服务费明细!$B27,服务费底表!$H:$H,服务费明细!BU$3) -> 0 | BV27: =SUMIFS(服务费底表!$AD:$AD,服务费底表!$K:$K,服务费明细!$B27,服务费底表!$H:$H,服务费明细!BV$3) -> 0 | BW27: =SUMIFS(服务费底表!$AD:$AD,服务费底表!$K:$K,服务费明细!$B27,服务费底表!$H:$H,服务费明细!BW$3) -> 0
B28: A015 | C28: =INDEX(二三级标准!$C:$C,MATCH(服务费明细!$B28,二三级标准!$B:$B,0)) -> EDC上线前测试 | D28: =IF($D$15=1,1,0) -> 1 | E28: =IF($D28=1,1,0) -> 1 | F28: =INDEX(二三级标准!$G:$G,MATCH(服务费明细!$B28,二三级标准!$B:$B,0)) -> 次 | G28: =AL28 -> 0 | H28: =AM28 -> 0 | I28: =AN28 -> 2 | J28: =AO28 -> 0 | K28: =AP28 -> 0 | L28: =AQ28 -> 0 | M28: =AR28 -> 0 | N28: =AS28 -> 0 | ... AB28: =BG28 -> 0 | AC28: {=SUMPRODUCT(G28:AB28,$G$4:$AB$4)} -> 1300 | AD28: =IF(AF28=AC28,TRUE,FALSE) -> TRUE | AE28: =IFERROR(SUMIF(服务费底表!$K:$K,服务费明细!$B28,服务费底表!$AD:$AD)/E28,0) -> 1300 | AF28: =E28*AE28 -> 1300 | AG28: =IFERROR(SUMIF(服务费底表!$K:$K,服务费明细!$B28,服务费底表!$AG:$AG)/E28,0) -> 1300 | AH28: =AG28*E28 -> 1300 | AJ28: =IF(D28=1,AK28/E28,0) -> 2 | AK28: =SUMIF(服务费底表!$K:$K,服务费明细!$B28,服务费底表!$AC:$AC) -> 2 | AL28: =SUMIFS(服务费底表!$AC:$AC,服务费底表!$K:$K,服务费明细!$B28,服务费底表!$T:$T,AL$3) -> 0 | AM28: =SUMIFS(服务费底表!$AC:$AC,服务费底表!$K:$K,服务费明细!$B28,服务费底表!$T:$T,AM$3) -> 0 | AN28: =SUMIFS(服务费底表!$AC:$AC,服务费底表!$K:$K,服务费明细!$B28,服务费底表!$T:$T,AN$3) -> 2 | AO28: =SUMIFS(服务费底表!$AC:$AC,服务费底表!$K:$K,服务费明细!$B28,服务费底表!$T:$T,AO$3) -> 0 | AP28: =SUMIFS(服务费底表!$AC:$AC,服务费底表!$K:$K,服务费明细!$B28,服务费底表!$T:$T,AP$3) -> 0 | AQ28: =SUMIFS(服务费底表!$AC:$AC,服务费底表!$K:$K,服务费明细!$B28,服务费底表!$T:$T,AQ$3) -> 0 | AR28: =SUMIFS(服务费底表!$AC:$AC,服务费底表!$K:$K,服务费明细!$B28,服务费底表!$T:$T,AR$3) -> 0 | AS28: =SUMIFS(服务费底表!$AC:$AC,服务费底表!$K:$K,服务费明细!$B28,服务费底表!$T:$T,AS$3) -> 0 | ... BG28: =SUMIFS(服务费底表!$AC:$AC,服务费底表!$K:$K,服务费明细!$B28,服务费底表!$T:$T,BG$3) -> 0 | BI28: =SUMIFS(服务费底表!$AC:$AC,服务费底表!$K:$K,服务费明细!$B28,服务费底表!$H:$H,服务费明细!BI$3) -> 0 | BJ28: =SUMIFS(服务费底表!$AC:$AC,服务费底表!$K:$K,服务费明细!$B28,服务费底表!$H:$H,服务费明细!BJ$3) -> 2 | BK28: =SUMIFS(服务费底表!$AC:$AC,服务费底表!$K:$K,服务费明细!$B28,服务费底表!$H:$H,服务费明细!BK$3) -> 0 | BL28: =SUMIFS(服务费底表!$AC:$AC,服务费底表!$K:$K,服务费明细!$B28,服务费底表!$H:$H,服务费明细!BL$3) -> 0 | BM28: =SUMIFS(服务费底表!$AC:$AC,服务费底表!$K:$K,服务费明细!$B28,服务费底表!$H:$H,服务费明细!BM$3) -> 0 | BN28: =SUMIFS(服务费底表!$AC:$AC,服务费底表!$K:$K,服务费明细!$B28,服务费底表!$H:$H,服务费明细!BN$3) -> 0 | BO28: =SUMIFS(服务费底表!$AC:$AC,服务费底表!$K:$K,服务费明细!$B28,服务费底表!$H:$H,服务费明细!BO$3) -> 0 | BQ28: =SUMIFS(服务费底表!$AD:$AD,服务费底表!$K:$K,服务费明细!$B28,服务费底表!$H:$H,服务费明细!BQ$3) -> 0 | BR28: =SUMIFS(服务费底表!$AD:$AD,服务费底表!$K:$K,服务费明细!$B28,服务费底表!$H:$H,服务费明细!BR$3) -> 1300 | BS28: =SUMIFS(服务费底表!$AD:$AD,服务费底表!$K:$K,服务费明细!$B28,服务费底表!$H:$H,服务费明细!BS$3) -> 0 | BT28: =SUMIFS(服务费底表!$AD:$AD,服务费底表!$K:$K,服务费明细!$B28,服务费底表!$H:$H,服务费明细!BT$3) -> 0 | BU28: =SUMIFS(服务费底表!$AD:$AD,服务费底表!$K:$K,服务费明细!$B28,服务费底表!$H:$H,服务费明细!BU$3) -> 0 | BV28: =SUMIFS(服务费底表!$AD:$AD,服务费底表!$K:$K,服务费明细!$B28,服务费底表!$H:$H,服务费明细!BV$3) -> 0 | BW28: =SUMIFS(服务费底表!$AD:$AD,服务费底表!$K:$K,服务费明细!$B28,服务费底表!$H:$H,服务费明细!BW$3) -> 0
B29: A016 | C29: =INDEX(二三级标准!$C:$C,MATCH(服务费明细!$B29,二三级标准!$B:$B,0)) -> 研究中心启动文件准备和快递 | D29: =IF($D$15=1,1,0) -> 1 | E29: =IF($D29=1,启动中心数,0) -> 4 | F29: =INDEX(二三级标准!$G:$G,MATCH(服务费明细!$B29,二三级标准!$B:$B,0)) -> 次 | G29: =AL29 -> 16 | H29: =AM29 -> 16 | I29: =AN29 -> 0 | J29: =AO29 -> 0 | K29: =AP29 -> 0 | L29: =AQ29 -> 0 | M29: =AR29 -> 0 | N29: =AS29 -> 0 | ... AB29: =BG29 -> 0 | AC29: {=SUMPRODUCT(G29:AB29,$G$4:$AB$4)} -> 8960 | AD29: =IF(AF29=AC29,TRUE,FALSE) -> TRUE | AE29: =IFERROR(SUMIF(服务费底表!$K:$K,服务费明细!$B29,服务费底表!$AD:$AD)/E29,0) -> 2240 | AF29: =E29*AE29 -> 8960 | AG29: =IFERROR(SUMIF(服务费底表!$K:$K,服务费明细!$B29,服务费底表!$AG:$AG)/E29,0) -> 2240 | AH29: =AG29*E29 -> 8960 | AI29: 包含下述： -中心启动文档和材料准备(包括ISF Binder、知情同意书、入排卡等) -后续更新版文件的递交 -中心文档质检、上传 | AJ29: =IF(D29=1,AK29/E29,0) -> 8 | AK29: =SUMIF(服务费底表!$K:$K,服务费明细!$B29,服务费底表!$AC:$AC) -> 32 | AL29: =SUMIFS(服务费底表!$AC:$AC,服务费底表!$K:$K,服务费明细!$B29,服务费底表!$T:$T,AL$3) -> 16 | AM29: =SUMIFS(服务费底表!$AC:$AC,服务费底表!$K:$K,服务费明细!$B29,服务费底表!$T:$T,AM$3) -> 16 | AN29: =SUMIFS(服务费底表!$AC:$AC,服务费底表!$K:$K,服务费明细!$B29,服务费底表!$T:$T,AN$3) -> 0 | AO29: =SUMIFS(服务费底表!$AC:$AC,服务费底表!$K:$K,服务费明细!$B29,服务费底表!$T:$T,AO$3) -> 0 | AP29: =SUMIFS(服务费底表!$AC:$AC,服务费底表!$K:$K,服务费明细!$B29,服务费底表!$T:$T,AP$3) -> 0 | AQ29: =SUMIFS(服务费底表!$AC:$AC,服务费底表!$K:$K,服务费明细!$B29,服务费底表!$T:$T,AQ$3) -> 0 | AR29: =SUMIFS(服务费底表!$AC:$AC,服务费底表!$K:$K,服务费明细!$B29,服务费底表!$T:$T,AR$3) -> 0 | AS29: =SUMIFS(服务费底表!$AC:$AC,服务费底表!$K:$K,服务费明细!$B29,服务费底表!$T:$T,AS$3) -> 0 | ... BG29: =SUMIFS(服务费底表!$AC:$AC,服务费底表!$K:$K,服务费明细!$B29,服务费底表!$T:$T,BG$3) -> 0 | BI29: =SUMIFS(服务费底表!$AC:$AC,服务费底表!$K:$K,服务费明细!$B29,服务费底表!$H:$H,服务费明细!BI$3) -> 0 | BJ29: =SUMIFS(服务费底表!$AC:$AC,服务费底表!$K:$K,服务费明细!$B29,服务费底表!$H:$H,服务费明细!BJ$3) -> 32 | BK29: =SUMIFS(服务费底表!$AC:$AC,服务费底表!$K:$K,服务费明细!$B29,服务费底表!$H:$H,服务费明细!BK$3) -> 0 | BL29: =SUMIFS(服务费底表!$AC:$AC,服务费底表!$K:$K,服务费明细!$B29,服务费底表!$H:$H,服务费明细!BL$3) -> 0 | BM29: =SUMIFS(服务费底表!$AC:$AC,服务费底表!$K:$K,服务费明细!$B29,服务费底表!$H:$H,服务费明细!BM$3) -> 0 | BN29: =SUMIFS(服务费底表!$AC:$AC,服务费底表!$K:$K,服务费明细!$B29,服务费底表!$H:$H,服务费明细!BN$3) -> 0 | BO29: =SUMIFS(服务费底表!$AC:$AC,服务费底表!$K:$K,服务费明细!$B29,服务费底表!$H:$H,服务费明细!BO$3) -> 0 | BQ29: =SUMIFS(服务费底表!$AD:$AD,服务费底表!$K:$K,服务费明细!$B29,服务费底表!$H:$H,服务费明细!BQ$3) -> 0 | BR29: =SUMIFS(服务费底表!$AD:$AD,服务费底表!$K:$K,服务费明细!$B29,服务费底表!$H:$H,服务费明细!BR$3) -> 8960 | BS29: =SUMIFS(服务费底表!$AD:$AD,服务费底表!$K:$K,服务费明细!$B29,服务费底表!$H:$H,服务费明细!BS$3) -> 0 | BT29: =SUMIFS(服务费底表!$AD:$AD,服务费底表!$K:$K,服务费明细!$B29,服务费底表!$H:$H,服务费明细!BT$3) -> 0 | BU29: =SUMIFS(服务费底表!$AD:$AD,服务费底表!$K:$K,服务费明细!$B29,服务费底表!$H:$H,服务费明细!BU$3) -> 0 | BV29: =SUMIFS(服务费底表!$AD:$AD,服务费底表!$K:$K,服务费明细!$B29,服务费底表!$H:$H,服务费明细!BV$3) -> 0 | BW29: =SUMIFS(服务费底表!$AD:$AD,服务费底表!$K:$K,服务费明细!$B29,服务费底表!$H:$H,服务费明细!BW$3) -> 0
B30: A017 | C30: =INDEX(二三级标准!$C:$C,MATCH(服务费明细!$B30,二三级标准!$B:$B,0)) -> 临床试验国家局备案 | D30: 0 | E30: =IF($D30=1,1,0) -> 0 | F30: =INDEX(二三级标准!$G:$G,MATCH(服务费明细!$B30,二三级标准!$B:$B,0)) -> 次 | G30: =AL30 -> 0 | H30: =AM30 -> 0 | I30: =AN30 -> 0 | J30: =AO30 -> 0 | K30: =AP30 -> 0 | L30: =AQ30 -> 0 | M30: =AR30 -> 0 | N30: =AS30 -> 0 | ... AB30: =BG30 -> 0 | AC30: {=SUMPRODUCT(G30:AB30,$G$4:$AB$4)} -> 0 | AD30: =IF(AF30=AC30,TRUE,FALSE) -> TRUE | AE30: =IFERROR(SUMIF(服务费底表!$K:$K,服务费明细!$B30,服务费底表!$AD:$AD)/E30,0) -> 0 | AF30: =E30*AE30 -> 0 | AG30: =IFERROR(SUMIF(服务费底表!$K:$K,服务费明细!$B30,服务费底表!$AG:$AG)/E30,0) -> 0 | AH30: =AG30*E30 -> 0 | AJ30: =IF(D30=1,AK30/E30,0) -> 0 | AK30: =SUMIF(服务费底表!$K:$K,服务费明细!$B30,服务费底表!$AC:$AC) -> 0 | AL30: =SUMIFS(服务费底表!$AC:$AC,服务费底表!$K:$K,服务费明细!$B30,服务费底表!$T:$T,AL$3) -> 0 | AM30: =SUMIFS(服务费底表!$AC:$AC,服务费底表!$K:$K,服务费明细!$B30,服务费底表!$T:$T,AM$3) -> 0 | AN30: =SUMIFS(服务费底表!$AC:$AC,服务费底表!$K:$K,服务费明细!$B30,服务费底表!$T:$T,AN$3) -> 0 | AO30: =SUMIFS(服务费底表!$AC:$AC,服务费底表!$K:$K,服务费明细!$B30,服务费底表!$T:$T,AO$3) -> 0 | AP30: =SUMIFS(服务费底表!$AC:$AC,服务费底表!$K:$K,服务费明细!$B30,服务费底表!$T:$T,AP$3) -> 0 | AQ30: =SUMIFS(服务费底表!$AC:$AC,服务费底表!$K:$K,服务费明细!$B30,服务费底表!$T:$T,AQ$3) -> 0 | AR30: =SUMIFS(服务费底表!$AC:$AC,服务费底表!$K:$K,服务费明细!$B30,服务费底表!$T:$T,AR$3) -> 0 | AS30: =SUMIFS(服务费底表!$AC:$AC,服务费底表!$K:$K,服务费明细!$B30,服务费底表!$T:$T,AS$3) -> 0 | ... BG30: =SUMIFS(服务费底表!$AC:$AC,服务费底表!$K:$K,服务费明细!$B30,服务费底表!$T:$T,BG$3) -> 0 | BI30: =SUMIFS(服务费底表!$AC:$AC,服务费底表!$K:$K,服务费明细!$B30,服务费底表!$H:$H,服务费明细!BI$3) -> 0 | BJ30: =SUMIFS(服务费底表!$AC:$AC,服务费底表!$K:$K,服务费明细!$B30,服务费底表!$H:$H,服务费明细!BJ$3) -> 0 | BK30: =SUMIFS(服务费底表!$AC:$AC,服务费底表!$K:$K,服务费明细!$B30,服务费底表!$H:$H,服务费明细!BK$3) -> 0 | BL30: =SUMIFS(服务费底表!$AC:$AC,服务费底表!$K:$K,服务费明细!$B30,服务费底表!$H:$H,服务费明细!BL$3) -> 0 | BM30: =SUMIFS(服务费底表!$AC:$AC,服务费底表!$K:$K,服务费明细!$B30,服务费底表!$H:$H,服务费明细!BM$3) -> 0 | BN30: =SUMIFS(服务费底表!$AC:$AC,服务费底表!$K:$K,服务费明细!$B30,服务费底表!$H:$H,服务费明细!BN$3) -> 0 | BO30: =SUMIFS(服务费底表!$AC:$AC,服务费底表!$K:$K,服务费明细!$B30,服务费底表!$H:$H,服务费明细!BO$3) -> 0 | BQ30: =SUMIFS(服务费底表!$AD:$AD,服务费底表!$K:$K,服务费明细!$B30,服务费底表!$H:$H,服务费明细!BQ$3) -> 0 | BR30: =SUMIFS(服务费底表!$AD:$AD,服务费底表!$K:$K,服务费明细!$B30,服务费底表!$H:$H,服务费明细!BR$3) -> 0 | BS30: =SUMIFS(服务费底表!$AD:$AD,服务费底表!$K:$K,服务费明细!$B30,服务费底表!$H:$H,服务费明细!BS$3) -> 0 | BT30: =SUMIFS(服务费底表!$AD:$AD,服务费底表!$K:$K,服务费明细!$B30,服务费底表!$H:$H,服务费明细!BT$3) -> 0 | BU30: =SUMIFS(服务费底表!$AD:$AD,服务费底表!$K:$K,服务费明细!$B30,服务费底表!$H:$H,服务费明细!BU$3) -> 0 | BV30: =SUMIFS(服务费底表!$AD:$AD,服务费底表!$K:$K,服务费明细!$B30,服务费底表!$H:$H,服务费明细!BV$3) -> 0 | BW30: =SUMIFS(服务费底表!$AD:$AD,服务费底表!$K:$K,服务费明细!$B30,服务费底表!$H:$H,服务费明细!BW$3) -> 0
B31: A018 | C31: =INDEX(二三级标准!$C:$C,MATCH(服务费明细!$B31,二三级标准!$B:$B,0)) -> 临床试验省局备案 | D31: 0 | E31: =IF($D31=1,ROUNDUP(启动中心数*30%,0),0) -> 0 | F31: =INDEX(二三级标准!$G:$G,MATCH(服务费明细!$B31,二三级标准!$B:$B,0)) -> 次 | G31: =AL31 -> 0 | H31: =AM31 -> 0 | I31: =AN31 -> 0 | J31: =AO31 -> 0 | K31: =AP31 -> 0 | L31: =AQ31 -> 0 | M31: =AR31 -> 0 | N31: =AS31 -> 0 | ... AB31: =BG31 -> 0 | AC31: {=SUMPRODUCT(G31:AB31,$G$4:$AB$4)} -> 0 | AD31: =IF(AF31=AC31,TRUE,FALSE) -> TRUE | AE31: =IFERROR(SUMIF(服务费底表!$K:$K,服务费明细!$B31,服务费底表!$AD:$AD)/E31,0) -> 0 | AF31: =E31*AE31 -> 0 | AG31: =IFERROR(SUMIF(服务费底表!$K:$K,服务费明细!$B31,服务费底表!$AG:$AG)/E31,0) -> 0 | AH31: =AG31*E31 -> 0 | AJ31: =IF(D31=1,AK31/E31,0) -> 0 | AK31: =SUMIF(服务费底表!$K:$K,服务费明细!$B31,服务费底表!$AC:$AC) -> 0 | AL31: =SUMIFS(服务费底表!$AC:$AC,服务费底表!$K:$K,服务费明细!$B31,服务费底表!$T:$T,AL$3) -> 0 | AM31: =SUMIFS(服务费底表!$AC:$AC,服务费底表!$K:$K,服务费明细!$B31,服务费底表!$T:$T,AM$3) -> 0 | AN31: =SUMIFS(服务费底表!$AC:$AC,服务费底表!$K:$K,服务费明细!$B31,服务费底表!$T:$T,AN$3) -> 0 | AO31: =SUMIFS(服务费底表!$AC:$AC,服务费底表!$K:$K,服务费明细!$B31,服务费底表!$T:$T,AO$3) -> 0 | AP31: =SUMIFS(服务费底表!$AC:$AC,服务费底表!$K:$K,服务费明细!$B31,服务费底表!$T:$T,AP$3) -> 0 | AQ31: =SUMIFS(服务费底表!$AC:$AC,服务费底表!$K:$K,服务费明细!$B31,服务费底表!$T:$T,AQ$3) -> 0 | AR31: =SUMIFS(服务费底表!$AC:$AC,服务费底表!$K:$K,服务费明细!$B31,服务费底表!$T:$T,AR$3) -> 0 | AS31: =SUMIFS(服务费底表!$AC:$AC,服务费底表!$K:$K,服务费明细!$B31,服务费底表!$T:$T,AS$3) -> 0 | ... BG31: =SUMIFS(服务费底表!$AC:$AC,服务费底表!$K:$K,服务费明细!$B31,服务费底表!$T:$T,BG$3) -> 0 | BI31: =SUMIFS(服务费底表!$AC:$AC,服务费底表!$K:$K,服务费明细!$B31,服务费底表!$H:$H,服务费明细!BI$3) -> 0 | BJ31: =SUMIFS(服务费底表!$AC:$AC,服务费底表!$K:$K,服务费明细!$B31,服务费底表!$H:$H,服务费明细!BJ$3) -> 0 | BK31: =SUMIFS(服务费底表!$AC:$AC,服务费底表!$K:$K,服务费明细!$B31,服务费底表!$H:$H,服务费明细!BK$3) -> 0 | BL31: =SUMIFS(服务费底表!$AC:$AC,服务费底表!$K:$K,服务费明细!$B31,服务费底表!$H:$H,服务费明细!BL$3) -> 0 | BM31: =SUMIFS(服务费底表!$AC:$AC,服务费底表!$K:$K,服务费明细!$B31,服务费底表!$H:$H,服务费明细!BM$3) -> 0 | BN31: =SUMIFS(服务费底表!$AC:$AC,服务费底表!$K:$K,服务费明细!$B31,服务费底表!$H:$H,服务费明细!BN$3) -> 0 | BO31: =SUMIFS(服务费底表!$AC:$AC,服务费底表!$K:$K,服务费明细!$B31,服务费底表!$H:$H,服务费明细!BO$3) -> 0 | BQ31: =SUMIFS(服务费底表!$AD:$AD,服务费底表!$K:$K,服务费明细!$B31,服务费底表!$H:$H,服务费明细!BQ$3) -> 0 | BR31: =SUMIFS(服务费底表!$AD:$AD,服务费底表!$K:$K,服务费明细!$B31,服务费底表!$H:$H,服务费明细!BR$3) -> 0 | BS31: =SUMIFS(服务费底表!$AD:$AD,服务费底表!$K:$K,服务费明细!$B31,服务费底表!$H:$H,服务费明细!BS$3) -> 0 | BT31: =SUMIFS(服务费底表!$AD:$AD,服务费底表!$K:$K,服务费明细!$B31,服务费底表!$H:$H,服务费明细!BT$3) -> 0 | BU31: =SUMIFS(服务费底表!$AD:$AD,服务费底表!$K:$K,服务费明细!$B31,服务费底表!$H:$H,服务费明细!BU$3) -> 0 | BV31: =SUMIFS(服务费底表!$AD:$AD,服务费底表!$K:$K,服务费明细!$B31,服务费底表!$H:$H,服务费明细!BV$3) -> 0 | BW31: =SUMIFS(服务费底表!$AD:$AD,服务费底表!$K:$K,服务费明细!$B31,服务费底表!$H:$H,服务费明细!BW$3) -> 0
B32: A019 | C32: =INDEX(二三级标准!$C:$C,MATCH(服务费明细!$B32,二三级标准!$B:$B,0)) -> ClinicalTrials翻译 | D32: 0 | E32: =IF($D32=1,1,0) -> 0 | F32: =INDEX(二三级标准!$G:$G,MATCH(服务费明细!$B32,二三级标准!$B:$B,0)) -> 次 | G32: =AL32 -> 0 | H32: =AM32 -> 0 | I32: =AN32 -> 0 | J32: =AO32 -> 0 | K32: =AP32 -> 0 | L32: =AQ32 -> 0 | M32: =AR32 -> 0 | N32: =AS32 -> 0 | ... AB32: =BG32 -> 0 | AC32: {=SUMPRODUCT(G32:AB32,$G$4:$AB$4)} -> 0 | AD32: =IF(AF32=AC32,TRUE,FALSE) -> TRUE | AE32: =IFERROR(SUMIF(服务费底表!$K:$K,服务费明细!$B32,服务费底表!$AD:$AD)/E32,0) -> 0 | AF32: =E32*AE32 -> 0 | AG32: =IFERROR(SUMIF(服务费底表!$K:$K,服务费明细!$B32,服务费底表!$AG:$AG)/E32,0) -> 0 | AH32: =AG32*E32 -> 0 | AJ32: =IF(D32=1,AK32/E32,0) -> 0 | AK32: =SUMIF(服务费底表!$K:$K,服务费明细!$B32,服务费底表!$AC:$AC) -> 0 | AL32: =SUMIFS(服务费底表!$AC:$AC,服务费底表!$K:$K,服务费明细!$B32,服务费底表!$T:$T,AL$3) -> 0 | AM32: =SUMIFS(服务费底表!$AC:$AC,服务费底表!$K:$K,服务费明细!$B32,服务费底表!$T:$T,AM$3) -> 0 | AN32: =SUMIFS(服务费底表!$AC:$AC,服务费底表!$K:$K,服务费明细!$B32,服务费底表!$T:$T,AN$3) -> 0 | AO32: =SUMIFS(服务费底表!$AC:$AC,服务费底表!$K:$K,服务费明细!$B32,服务费底表!$T:$T,AO$3) -> 0 | AP32: =SUMIFS(服务费底表!$AC:$AC,服务费底表!$K:$K,服务费明细!$B32,服务费底表!$T:$T,AP$3) -> 0 | AQ32: =SUMIFS(服务费底表!$AC:$AC,服务费底表!$K:$K,服务费明细!$B32,服务费底表!$T:$T,AQ$3) -> 0 | AR32: =SUMIFS(服务费底表!$AC:$AC,服务费底表!$K:$K,服务费明细!$B32,服务费底表!$T:$T,AR$3) -> 0 | AS32: =SUMIFS(服务费底表!$AC:$AC,服务费底表!$K:$K,服务费明细!$B32,服务费底表!$T:$T,AS$3) -> 0 | ... BG32: =SUMIFS(服务费底表!$AC:$AC,服务费底表!$K:$K,服务费明细!$B32,服务费底表!$T:$T,BG$3) -> 0 | BI32: =SUMIFS(服务费底表!$AC:$AC,服务费底表!$K:$K,服务费明细!$B32,服务费底表!$H:$H,服务费明细!BI$3) -> 0 | BJ32: =SUMIFS(服务费底表!$AC:$AC,服务费底表!$K:$K,服务费明细!$B32,服务费底表!$H:$H,服务费明细!BJ$3) -> 0 | BK32: =SUMIFS(服务费底表!$AC:$AC,服务费底表!$K:$K,服务费明细!$B32,服务费底表!$H:$H,服务费明细!BK$3) -> 0 | BL32: =SUMIFS(服务费底表!$AC:$AC,服务费底表!$K:$K,服务费明细!$B32,服务费底表!$H:$H,服务费明细!BL$3) -> 0 | BM32: =SUMIFS(服务费底表!$AC:$AC,服务费底表!$K:$K,服务费明细!$B32,服务费底表!$H:$H,服务费明细!BM$3) -> 0 | BN32: =SUMIFS(服务费底表!$AC:$AC,服务费底表!$K:$K,服务费明细!$B32,服务费底表!$H:$H,服务费明细!BN$3) -> 0 | BO32: =SUMIFS(服务费底表!$AC:$AC,服务费底表!$K:$K,服务费明细!$B32,服务费底表!$H:$H,服务费明细!BO$3) -> 0 | BQ32: =SUMIFS(服务费底表!$AD:$AD,服务费底表!$K:$K,服务费明细!$B32,服务费底表!$H:$H,服务费明细!BQ$3) -> 0 | BR32: =SUMIFS(服务费底表!$AD:$AD,服务费底表!$K:$K,服务费明细!$B32,服务费底表!$H:$H,服务费明细!BR$3) -> 0 | BS32: =SUMIFS(服务费底表!$AD:$AD,服务费底表!$K:$K,服务费明细!$B32,服务费底表!$H:$H,服务费明细!BS$3) -> 0 | BT32: =SUMIFS(服务费底表!$AD:$AD,服务费底表!$K:$K,服务费明细!$B32,服务费底表!$H:$H,服务费明细!BT$3) -> 0 | BU32: =SUMIFS(服务费底表!$AD:$AD,服务费底表!$K:$K,服务费明细!$B32,服务费底表!$H:$H,服务费明细!BU$3) -> 0 | BV32: =SUMIFS(服务费底表!$AD:$AD,服务费底表!$K:$K,服务费明细!$B32,服务费底表!$H:$H,服务费明细!BV$3) -> 0 | BW32: =SUMIFS(服务费底表!$AD:$AD,服务费底表!$K:$K,服务费明细!$B32,服务费底表!$H:$H,服务费明细!BW$3) -> 0
B33: A209 | C33: =INDEX(二三级标准!$C:$C,MATCH(服务费明细!$B33,二三级标准!$B:$B,0)) -> 卫健委备案 | D33: =IF(报价场景="非注册",1,0) -> 0 | E33: =IF($D33=1,1,0) -> 0 | F33: =INDEX(二三级标准!$G:$G,MATCH(服务费明细!$B33,二三级标准!$B:$B,0)) -> 次 | G33: =AL33 -> 0 | H33: =AM33 -> 0 | I33: =AN33 -> 0 | J33: =AO33 -> 0 | K33: =AP33 -> 0 | L33: =AQ33 -> 0 | M33: =AR33 -> 0 | N33: =AS33 -> 0 | ... AB33: =BG33 -> 0 | AC33: {=SUMPRODUCT(G33:AB33,$G$4:$AB$4)} -> 0 | AD33: =IF(AF33=AC33,TRUE,FALSE) -> TRUE | AE33: =IFERROR(SUMIF(服务费底表!$K:$K,服务费明细!$B33,服务费底表!$AD:$AD)/E33,0) -> 0 | AF33: =E33*AE33 -> 0 | AG33: =IFERROR(SUMIF(服务费底表!$K:$K,服务费明细!$B33,服务费底表!$AG:$AG)/E33,0) -> 0 | AH33: =AG33*E33 -> 0 | AJ33: =IF(D33=1,AK33/E33,0) -> 0 | AK33: =SUMIF(服务费底表!$K:$K,服务费明细!$B33,服务费底表!$AC:$AC) -> 0 | AL33: =SUMIFS(服务费底表!$AC:$AC,服务费底表!$K:$K,服务费明细!$B33,服务费底表!$T:$T,AL$3) -> 0 | AM33: =SUMIFS(服务费底表!$AC:$AC,服务费底表!$K:$K,服务费明细!$B33,服务费底表!$T:$T,AM$3) -> 0 | AN33: =SUMIFS(服务费底表!$AC:$AC,服务费底表!$K:$K,服务费明细!$B33,服务费底表!$T:$T,AN$3) -> 0 | AO33: =SUMIFS(服务费底表!$AC:$AC,服务费底表!$K:$K,服务费明细!$B33,服务费底表!$T:$T,AO$3) -> 0 | AP33: =SUMIFS(服务费底表!$AC:$AC,服务费底表!$K:$K,服务费明细!$B33,服务费底表!$T:$T,AP$3) -> 0 | AQ33: =SUMIFS(服务费底表!$AC:$AC,服务费底表!$K:$K,服务费明细!$B33,服务费底表!$T:$T,AQ$3) -> 0 | AR33: =SUMIFS(服务费底表!$AC:$AC,服务费底表!$K:$K,服务费明细!$B33,服务费底表!$T:$T,AR$3) -> 0 | AS33: =SUMIFS(服务费底表!$AC:$AC,服务费底表!$K:$K,服务费明细!$B33,服务费底表!$T:$T,AS$3) -> 0 | ... BG33: =SUMIFS(服务费底表!$AC:$AC,服务费底表!$K:$K,服务费明细!$B33,服务费底表!$T:$T,BG$3) -> 0 | BI33: =SUMIFS(服务费底表!$AC:$AC,服务费底表!$K:$K,服务费明细!$B33,服务费底表!$H:$H,服务费明细!BI$3) -> 0 | BJ33: =SUMIFS(服务费底表!$AC:$AC,服务费底表!$K:$K,服务费明细!$B33,服务费底表!$H:$H,服务费明细!BJ$3) -> 0 | BK33: =SUMIFS(服务费底表!$AC:$AC,服务费底表!$K:$K,服务费明细!$B33,服务费底表!$H:$H,服务费明细!BK$3) -> 0 | BL33: =SUMIFS(服务费底表!$AC:$AC,服务费底表!$K:$K,服务费明细!$B33,服务费底表!$H:$H,服务费明细!BL$3) -> 0 | BM33: =SUMIFS(服务费底表!$AC:$AC,服务费底表!$K:$K,服务费明细!$B33,服务费底表!$H:$H,服务费明细!BM$3) -> 0 | BN33: =SUMIFS(服务费底表!$AC:$AC,服务费底表!$K:$K,服务费明细!$B33,服务费底表!$H:$H,服务费明细!BN$3) -> 0 | BO33: =SUMIFS(服务费底表!$AC:$AC,服务费底表!$K:$K,服务费明细!$B33,服务费底表!$H:$H,服务费明细!BO$3) -> 0 | BQ33: =SUMIFS(服务费底表!$AD:$AD,服务费底表!$K:$K,服务费明细!$B33,服务费底表!$H:$H,服务费明细!BQ$3) -> 0 | BR33: =SUMIFS(服务费底表!$AD:$AD,服务费底表!$K:$K,服务费明细!$B33,服务费底表!$H:$H,服务费明细!BR$3) -> 0 | BS33: =SUMIFS(服务费底表!$AD:$AD,服务费底表!$K:$K,服务费明细!$B33,服务费底表!$H:$H,服务费明细!BS$3) -> 0 | BT33: =SUMIFS(服务费底表!$AD:$AD,服务费底表!$K:$K,服务费明细!$B33,服务费底表!$H:$H,服务费明细!BT$3) -> 0 | BU33: =SUMIFS(服务费底表!$AD:$AD,服务费底表!$K:$K,服务费明细!$B33,服务费底表!$H:$H,服务费明细!BU$3) -> 0 | BV33: =SUMIFS(服务费底表!$AD:$AD,服务费底表!$K:$K,服务费明细!$B33,服务费底表!$H:$H,服务费明细!BV$3) -> 0 | BW33: =SUMIFS(服务费底表!$AD:$AD,服务费底表!$K:$K,服务费明细!$B33,服务费底表!$H:$H,服务费明细!BW$3) -> 0
B34: I003 | C34: =INDEX(二三级标准!$Q:$Q,MATCH(服务费明细!$B34,二三级标准!$O:$O,0)) -> 遗传办递交和跟进 | D34: =IF(AND(临床监查YN=1,遗传办递交和跟进<>"不适用"),1,0) -> 1 | G34: =SUM(G35:G38) -> 48 | H34: =SUM(H35:H38) -> 5 | I34: =SUM(I35:I38) -> 24 | J34: =SUM(J35:J38) -> 0 | K34: =SUM(K35:K38) -> 0 | L34: =SUM(L35:L38) -> 0 | M34: =SUM(M35:M38) -> 0 | N34: =SUM(N35:N38) -> 0 | ... AB34: =SUM(AB35:AB38) -> 0 | AD34: =SUM(G34:AC34) -> 77 | AF34: =SUM(AF35:AF38) -> 33020 | AH34: =SUM(AH35:AH38) -> 33020 | AK34: =SUM(AK35:AK38) -> 77 | BI34: =SUM(BI35:BI38) -> 0 | BJ34: =SUM(BJ35:BJ38) -> 77 | BK34: =SUM(BK35:BK38) -> 0 | BL34: =SUM(BL35:BL38) -> 0 | BM34: =SUM(BM35:BM38) -> 0 | BN34: =SUM(BN35:BN38) -> 0 | BO34: =SUM(BO35:BO38) -> 0 | BQ34: =SUM(BQ35:BQ38) -> 0 | BR34: =SUM(BR35:BR38) -> 33020 | BS34: =SUM(BS35:BS38) -> 0 | BT34: =SUM(BT35:BT38) -> 0 | BU34: =SUM(BU35:BU38) -> 0 | BV34: =SUM(BV35:BV38) -> 0 | BW34: =SUM(BW35:BW38) -> 0
B35: A276 | C35: =INDEX(二三级标准!$C:$C,MATCH(服务费明细!$B35,二三级标准!$B:$B,0)) -> 遗传办首次申报 | D35: =IF($D$34=1,1,0) -> 1 | E35: =IF($D35=1,1,0) -> 1 | F35: =INDEX(二三级标准!$G:$G,MATCH(服务费明细!$B35,二三级标准!$B:$B,0)) -> 次 | G35: =AL35 -> 0 | H35: =AM35 -> 3 | I35: =AN35 -> 15 | J35: =AO35 -> 0 | K35: =AP35 -> 0 | L35: =AQ35 -> 0 | M35: =AR35 -> 0 | N35: =AS35 -> 0 | ... AB35: =BG35 -> 0 | AC35: {=SUMPRODUCT(G35:AB35,$G$4:$AB$4)} -> 10410 | AD35: =IF(AF35=AC35,TRUE,FALSE) -> TRUE | AE35: =IFERROR(SUMIF(服务费底表!$K:$K,服务费明细!$B35,服务费底表!$AD:$AD)/E35,0) -> 10410 | AF35: =E35*AE35 -> 10410 | AG35: =IFERROR(SUMIF(服务费底表!$K:$K,服务费明细!$B35,服务费底表!$AG:$AG)/E35,0) -> 10410 | AH35: =AG35*E35 -> 10410 | AJ35: =IF(D35=1,AK35/E35,0) -> 18 | AK35: =SUMIF(服务费底表!$K:$K,服务费明细!$B35,服务费底表!$AC:$AC) -> 18 | AL35: =SUMIFS(服务费底表!$AC:$AC,服务费底表!$K:$K,服务费明细!$B35,服务费底表!$T:$T,AL$3) -> 0 | AM35: =SUMIFS(服务费底表!$AC:$AC,服务费底表!$K:$K,服务费明细!$B35,服务费底表!$T:$T,AM$3) -> 3 | AN35: =SUMIFS(服务费底表!$AC:$AC,服务费底表!$K:$K,服务费明细!$B35,服务费底表!$T:$T,AN$3) -> 15 | AO35: =SUMIFS(服务费底表!$AC:$AC,服务费底表!$K:$K,服务费明细!$B35,服务费底表!$T:$T,AO$3) -> 0 | AP35: =SUMIFS(服务费底表!$AC:$AC,服务费底表!$K:$K,服务费明细!$B35,服务费底表!$T:$T,AP$3) -> 0 | AQ35: =SUMIFS(服务费底表!$AC:$AC,服务费底表!$K:$K,服务费明细!$B35,服务费底表!$T:$T,AQ$3) -> 0 | AR35: =SUMIFS(服务费底表!$AC:$AC,服务费底表!$K:$K,服务费明细!$B35,服务费底表!$T:$T,AR$3) -> 0 | AS35: =SUMIFS(服务费底表!$AC:$AC,服务费底表!$K:$K,服务费明细!$B35,服务费底表!$T:$T,AS$3) -> 0 | ... BG35: =SUMIFS(服务费底表!$AC:$AC,服务费底表!$K:$K,服务费明细!$B35,服务费底表!$T:$T,BG$3) -> 0 | BI35: =SUMIFS(服务费底表!$AC:$AC,服务费底表!$K:$K,服务费明细!$B35,服务费底表!$H:$H,服务费明细!BI$3) -> 0 | BJ35: =SUMIFS(服务费底表!$AC:$AC,服务费底表!$K:$K,服务费明细!$B35,服务费底表!$H:$H,服务费明细!BJ$3) -> 18 | BK35: =SUMIFS(服务费底表!$AC:$AC,服务费底表!$K:$K,服务费明细!$B35,服务费底表!$H:$H,服务费明细!BK$3) -> 0 | BL35: =SUMIFS(服务费底表!$AC:$AC,服务费底表!$K:$K,服务费明细!$B35,服务费底表!$H:$H,服务费明细!BL$3) -> 0 | BM35: =SUMIFS(服务费底表!$AC:$AC,服务费底表!$K:$K,服务费明细!$B35,服务费底表!$H:$H,服务费明细!BM$3) -> 0 | BN35: =SUMIFS(服务费底表!$AC:$AC,服务费底表!$K:$K,服务费明细!$B35,服务费底表!$H:$H,服务费明细!BN$3) -> 0 | BO35: =SUMIFS(服务费底表!$AC:$AC,服务费底表!$K:$K,服务费明细!$B35,服务费底表!$H:$H,服务费明细!BO$3) -> 0 | BQ35: =SUMIFS(服务费底表!$AD:$AD,服务费底表!$K:$K,服务费明细!$B35,服务费底表!$H:$H,服务费明细!BQ$3) -> 0 | BR35: =SUMIFS(服务费底表!$AD:$AD,服务费底表!$K:$K,服务费明细!$B35,服务费底表!$H:$H,服务费明细!BR$3) -> 10410 | BS35: =SUMIFS(服务费底表!$AD:$AD,服务费底表!$K:$K,服务费明细!$B35,服务费底表!$H:$H,服务费明细!BS$3) -> 0 | BT35: =SUMIFS(服务费底表!$AD:$AD,服务费底表!$K:$K,服务费明细!$B35,服务费底表!$H:$H,服务费明细!BT$3) -> 0 | BU35: =SUMIFS(服务费底表!$AD:$AD,服务费底表!$K:$K,服务费明细!$B35,服务费底表!$H:$H,服务费明细!BU$3) -> 0 | BV35: =SUMIFS(服务费底表!$AD:$AD,服务费底表!$K:$K,服务费明细!$B35,服务费底表!$H:$H,服务费明细!BV$3) -> 0 | BW35: =SUMIFS(服务费底表!$AD:$AD,服务费底表!$K:$K,服务费明细!$B35,服务费底表!$H:$H,服务费明细!BW$3) -> 0
B36: A277 | C36: =INDEX(二三级标准!$C:$C,MATCH(服务费明细!$B36,二三级标准!$B:$B,0)) -> 遗传办合作签章和承诺书的获取 | D36: =IF($D$34=1,1,0) -> 1 | E36: =IF($D36=1,启动中心数,0) -> 4 | F36: =INDEX(二三级标准!$G:$G,MATCH(服务费明细!$B36,二三级标准!$B:$B,0)) -> 中心 | G36: =AL36 -> 48 | H36: =AM36 -> 0 | I36: =AN36 -> 0 | J36: =AO36 -> 0 | K36: =AP36 -> 0 | L36: =AQ36 -> 0 | M36: =AR36 -> 0 | N36: =AS36 -> 0 | ... AB36: =BG36 -> 0 | AC36: {=SUMPRODUCT(G36:AB36,$G$4:$AB$4)} -> 16320 | AD36: =IF(AF36=AC36,TRUE,FALSE) -> TRUE | AE36: =IFERROR(SUMIF(服务费底表!$K:$K,服务费明细!$B36,服务费底表!$AD:$AD)/E36,0) -> 4080 | AF36: =E36*AE36 -> 16320 | AG36: =IFERROR(SUMIF(服务费底表!$K:$K,服务费明细!$B36,服务费底表!$AG:$AG)/E36,0) -> 4080 | AH36: =AG36*E36 -> 16320 | AJ36: =IF(D36=1,AK36/E36,0) -> 12 | AK36: =SUMIF(服务费底表!$K:$K,服务费明细!$B36,服务费底表!$AC:$AC) -> 48 | AL36: =SUMIFS(服务费底表!$AC:$AC,服务费底表!$K:$K,服务费明细!$B36,服务费底表!$T:$T,AL$3) -> 48 | AM36: =SUMIFS(服务费底表!$AC:$AC,服务费底表!$K:$K,服务费明细!$B36,服务费底表!$T:$T,AM$3) -> 0 | AN36: =SUMIFS(服务费底表!$AC:$AC,服务费底表!$K:$K,服务费明细!$B36,服务费底表!$T:$T,AN$3) -> 0 | AO36: =SUMIFS(服务费底表!$AC:$AC,服务费底表!$K:$K,服务费明细!$B36,服务费底表!$T:$T,AO$3) -> 0 | AP36: =SUMIFS(服务费底表!$AC:$AC,服务费底表!$K:$K,服务费明细!$B36,服务费底表!$T:$T,AP$3) -> 0 | AQ36: =SUMIFS(服务费底表!$AC:$AC,服务费底表!$K:$K,服务费明细!$B36,服务费底表!$T:$T,AQ$3) -> 0 | AR36: =SUMIFS(服务费底表!$AC:$AC,服务费底表!$K:$K,服务费明细!$B36,服务费底表!$T:$T,AR$3) -> 0 | AS36: =SUMIFS(服务费底表!$AC:$AC,服务费底表!$K:$K,服务费明细!$B36,服务费底表!$T:$T,AS$3) -> 0 | ... BG36: =SUMIFS(服务费底表!$AC:$AC,服务费底表!$K:$K,服务费明细!$B36,服务费底表!$T:$T,BG$3) -> 0 | BI36: =SUMIFS(服务费底表!$AC:$AC,服务费底表!$K:$K,服务费明细!$B36,服务费底表!$H:$H,服务费明细!BI$3) -> 0 | BJ36: =SUMIFS(服务费底表!$AC:$AC,服务费底表!$K:$K,服务费明细!$B36,服务费底表!$H:$H,服务费明细!BJ$3) -> 48 | BK36: =SUMIFS(服务费底表!$AC:$AC,服务费底表!$K:$K,服务费明细!$B36,服务费底表!$H:$H,服务费明细!BK$3) -> 0 | BL36: =SUMIFS(服务费底表!$AC:$AC,服务费底表!$K:$K,服务费明细!$B36,服务费底表!$H:$H,服务费明细!BL$3) -> 0 | BM36: =SUMIFS(服务费底表!$AC:$AC,服务费底表!$K:$K,服务费明细!$B36,服务费底表!$H:$H,服务费明细!BM$3) -> 0 | BN36: =SUMIFS(服务费底表!$AC:$AC,服务费底表!$K:$K,服务费明细!$B36,服务费底表!$H:$H,服务费明细!BN$3) -> 0 | BO36: =SUMIFS(服务费底表!$AC:$AC,服务费底表!$K:$K,服务费明细!$B36,服务费底表!$H:$H,服务费明细!BO$3) -> 0 | BQ36: =SUMIFS(服务费底表!$AD:$AD,服务费底表!$K:$K,服务费明细!$B36,服务费底表!$H:$H,服务费明细!BQ$3) -> 0 | BR36: =SUMIFS(服务费底表!$AD:$AD,服务费底表!$K:$K,服务费明细!$B36,服务费底表!$H:$H,服务费明细!BR$3) -> 16320 | BS36: =SUMIFS(服务费底表!$AD:$AD,服务费底表!$K:$K,服务费明细!$B36,服务费底表!$H:$H,服务费明细!BS$3) -> 0 | BT36: =SUMIFS(服务费底表!$AD:$AD,服务费底表!$K:$K,服务费明细!$B36,服务费底表!$H:$H,服务费明细!BT$3) -> 0 | BU36: =SUMIFS(服务费底表!$AD:$AD,服务费底表!$K:$K,服务费明细!$B36,服务费底表!$H:$H,服务费明细!BU$3) -> 0 | BV36: =SUMIFS(服务费底表!$AD:$AD,服务费底表!$K:$K,服务费明细!$B36,服务费底表!$H:$H,服务费明细!BV$3) -> 0 | BW36: =SUMIFS(服务费底表!$AD:$AD,服务费底表!$K:$K,服务费明细!$B36,服务费底表!$H:$H,服务费明细!BW$3) -> 0
B37: A278 | C37: =INDEX(二三级标准!$C:$C,MATCH(服务费明细!$B37,二三级标准!$B:$B,0)) -> 遗传办变更 | D37: 0 | E37: =IF($D37=1,项目参数!C57,0) -> 0 | F37: =INDEX(二三级标准!$G:$G,MATCH(服务费明细!$B37,二三级标准!$B:$B,0)) -> 次 | G37: =AL37 -> 0 | H37: =AM37 -> 0 | I37: =AN37 -> 0 | J37: =AO37 -> 0 | K37: =AP37 -> 0 | L37: =AQ37 -> 0 | M37: =AR37 -> 0 | N37: =AS37 -> 0 | ... AB37: =BG37 -> 0 | AC37: {=SUMPRODUCT(G37:AB37,$G$4:$AB$4)} -> 0 | AD37: =IF(AF37=AC37,TRUE,FALSE) -> TRUE | AE37: =IFERROR(SUMIF(服务费底表!$K:$K,服务费明细!$B37,服务费底表!$AD:$AD)/E37,0) -> 0 | AF37: =E37*AE37 -> 0 | AG37: =IFERROR(SUMIF(服务费底表!$K:$K,服务费明细!$B37,服务费底表!$AG:$AG)/E37,0) -> 0 | AH37: =AG37*E37 -> 0 | AJ37: =IF(D37=1,AK37/E37,0) -> 0 | AK37: =SUMIF(服务费底表!$K:$K,服务费明细!$B37,服务费底表!$AC:$AC) -> 0 | AL37: =SUMIFS(服务费底表!$AC:$AC,服务费底表!$K:$K,服务费明细!$B37,服务费底表!$T:$T,AL$3) -> 0 | AM37: =SUMIFS(服务费底表!$AC:$AC,服务费底表!$K:$K,服务费明细!$B37,服务费底表!$T:$T,AM$3) -> 0 | AN37: =SUMIFS(服务费底表!$AC:$AC,服务费底表!$K:$K,服务费明细!$B37,服务费底表!$T:$T,AN$3) -> 0 | AO37: =SUMIFS(服务费底表!$AC:$AC,服务费底表!$K:$K,服务费明细!$B37,服务费底表!$T:$T,AO$3) -> 0 | AP37: =SUMIFS(服务费底表!$AC:$AC,服务费底表!$K:$K,服务费明细!$B37,服务费底表!$T:$T,AP$3) -> 0 | AQ37: =SUMIFS(服务费底表!$AC:$AC,服务费底表!$K:$K,服务费明细!$B37,服务费底表!$T:$T,AQ$3) -> 0 | AR37: =SUMIFS(服务费底表!$AC:$AC,服务费底表!$K:$K,服务费明细!$B37,服务费底表!$T:$T,AR$3) -> 0 | AS37: =SUMIFS(服务费底表!$AC:$AC,服务费底表!$K:$K,服务费明细!$B37,服务费底表!$T:$T,AS$3) -> 0 | ... BG37: =SUMIFS(服务费底表!$AC:$AC,服务费底表!$K:$K,服务费明细!$B37,服务费底表!$T:$T,BG$3) -> 0 | BI37: =SUMIFS(服务费底表!$AC:$AC,服务费底表!$K:$K,服务费明细!$B37,服务费底表!$H:$H,服务费明细!BI$3) -> 0 | BJ37: =SUMIFS(服务费底表!$AC:$AC,服务费底表!$K:$K,服务费明细!$B37,服务费底表!$H:$H,服务费明细!BJ$3) -> 0 | BK37: =SUMIFS(服务费底表!$AC:$AC,服务费底表!$K:$K,服务费明细!$B37,服务费底表!$H:$H,服务费明细!BK$3) -> 0 | BL37: =SUMIFS(服务费底表!$AC:$AC,服务费底表!$K:$K,服务费明细!$B37,服务费底表!$H:$H,服务费明细!BL$3) -> 0 | BM37: =SUMIFS(服务费底表!$AC:$AC,服务费底表!$K:$K,服务费明细!$B37,服务费底表!$H:$H,服务费明细!BM$3) -> 0 | BN37: =SUMIFS(服务费底表!$AC:$AC,服务费底表!$K:$K,服务费明细!$B37,服务费底表!$H:$H,服务费明细!BN$3) -> 0 | BO37: =SUMIFS(服务费底表!$AC:$AC,服务费底表!$K:$K,服务费明细!$B37,服务费底表!$H:$H,服务费明细!BO$3) -> 0 | BQ37: =SUMIFS(服务费底表!$AD:$AD,服务费底表!$K:$K,服务费明细!$B37,服务费底表!$H:$H,服务费明细!BQ$3) -> 0 | BR37: =SUMIFS(服务费底表!$AD:$AD,服务费底表!$K:$K,服务费明细!$B37,服务费底表!$H:$H,服务费明细!BR$3) -> 0 | BS37: =SUMIFS(服务费底表!$AD:$AD,服务费底表!$K:$K,服务费明细!$B37,服务费底表!$H:$H,服务费明细!BS$3) -> 0 | BT37: =SUMIFS(服务费底表!$AD:$AD,服务费底表!$K:$K,服务费明细!$B37,服务费底表!$H:$H,服务费明细!BT$3) -> 0 | BU37: =SUMIFS(服务费底表!$AD:$AD,服务费底表!$K:$K,服务费明细!$B37,服务费底表!$H:$H,服务费明细!BU$3) -> 0 | BV37: =SUMIFS(服务费底表!$AD:$AD,服务费底表!$K:$K,服务费明细!$B37,服务费底表!$H:$H,服务费明细!BV$3) -> 0 | BW37: =SUMIFS(服务费底表!$AD:$AD,服务费底表!$K:$K,服务费明细!$B37,服务费底表!$H:$H,服务费明细!BW$3) -> 0
B38: A279 | C38: =INDEX(二三级标准!$C:$C,MATCH(服务费明细!$B38,二三级标准!$B:$B,0)) -> 遗传办总结填报和跟踪 | D38: =IF($D$34=1,1,0) -> 1 | E38: =IF($D38=1,1,0) -> 1 | F38: =INDEX(二三级标准!$G:$G,MATCH(服务费明细!$B38,二三级标准!$B:$B,0)) -> 次 | G38: =AL38 -> 0 | H38: =AM38 -> 2 | I38: =AN38 -> 9 | J38: =AO38 -> 0 | K38: =AP38 -> 0 | L38: =AQ38 -> 0 | M38: =AR38 -> 0 | N38: =AS38 -> 0 | ... AB38: =BG38 -> 0 | AC38: {=SUMPRODUCT(G38:AB38,$G$4:$AB$4)} -> 6290 | AD38: =IF(AF38=AC38,TRUE,FALSE) -> TRUE | AE38: =IFERROR(SUMIF(服务费底表!$K:$K,服务费明细!$B38,服务费底表!$AD:$AD)/E38,0) -> 6290 | AF38: =E38*AE38 -> 6290 | AG38: =IFERROR(SUMIF(服务费底表!$K:$K,服务费明细!$B38,服务费底表!$AG:$AG)/E38,0) -> 6290 | AH38: =AG38*E38 -> 6290 | AJ38: =IF(D38=1,AK38/E38,0) -> 11 | AK38: =SUMIF(服务费底表!$K:$K,服务费明细!$B38,服务费底表!$AC:$AC) -> 11 | AL38: =SUMIFS(服务费底表!$AC:$AC,服务费底表!$K:$K,服务费明细!$B38,服务费底表!$T:$T,AL$3) -> 0 | AM38: =SUMIFS(服务费底表!$AC:$AC,服务费底表!$K:$K,服务费明细!$B38,服务费底表!$T:$T,AM$3) -> 2 | AN38: =SUMIFS(服务费底表!$AC:$AC,服务费底表!$K:$K,服务费明细!$B38,服务费底表!$T:$T,AN$3) -> 9 | AO38: =SUMIFS(服务费底表!$AC:$AC,服务费底表!$K:$K,服务费明细!$B38,服务费底表!$T:$T,AO$3) -> 0 | AP38: =SUMIFS(服务费底表!$AC:$AC,服务费底表!$K:$K,服务费明细!$B38,服务费底表!$T:$T,AP$3) -> 0 | AQ38: =SUMIFS(服务费底表!$AC:$AC,服务费底表!$K:$K,服务费明细!$B38,服务费底表!$T:$T,AQ$3) -> 0 | AR38: =SUMIFS(服务费底表!$AC:$AC,服务费底表!$K:$K,服务费明细!$B38,服务费底表!$T:$T,AR$3) -> 0 | AS38: =SUMIFS(服务费底表!$AC:$AC,服务费底表!$K:$K,服务费明细!$B38,服务费底表!$T:$T,AS$3) -> 0 | ... BG38: =SUMIFS(服务费底表!$AC:$AC,服务费底表!$K:$K,服务费明细!$B38,服务费底表!$T:$T,BG$3) -> 0 | BI38: =SUMIFS(服务费底表!$AC:$AC,服务费底表!$K:$K,服务费明细!$B38,服务费底表!$H:$H,服务费明细!BI$3) -> 0 | BJ38: =SUMIFS(服务费底表!$AC:$AC,服务费底表!$K:$K,服务费明细!$B38,服务费底表!$H:$H,服务费明细!BJ$3) -> 11 | BK38: =SUMIFS(服务费底表!$AC:$AC,服务费底表!$K:$K,服务费明细!$B38,服务费底表!$H:$H,服务费明细!BK$3) -> 0 | BL38: =SUMIFS(服务费底表!$AC:$AC,服务费底表!$K:$K,服务费明细!$B38,服务费底表!$H:$H,服务费明细!BL$3) -> 0 | BM38: =SUMIFS(服务费底表!$AC:$AC,服务费底表!$K:$K,服务费明细!$B38,服务费底表!$H:$H,服务费明细!BM$3) -> 0 | BN38: =SUMIFS(服务费底表!$AC:$AC,服务费底表!$K:$K,服务费明细!$B38,服务费底表!$H:$H,服务费明细!BN$3) -> 0 | BO38: =SUMIFS(服务费底表!$AC:$AC,服务费底表!$K:$K,服务费明细!$B38,服务费底表!$H:$H,服务费明细!BO$3) -> 0 | BQ38: =SUMIFS(服务费底表!$AD:$AD,服务费底表!$K:$K,服务费明细!$B38,服务费底表!$H:$H,服务费明细!BQ$3) -> 0 | BR38: =SUMIFS(服务费底表!$AD:$AD,服务费底表!$K:$K,服务费明细!$B38,服务费底表!$H:$H,服务费明细!BR$3) -> 6290 | BS38: =SUMIFS(服务费底表!$AD:$AD,服务费底表!$K:$K,服务费明细!$B38,服务费底表!$H:$H,服务费明细!BS$3) -> 0 | BT38: =SUMIFS(服务费底表!$AD:$AD,服务费底表!$K:$K,服务费明细!$B38,服务费底表!$H:$H,服务费明细!BT$3) -> 0 | BU38: =SUMIFS(服务费底表!$AD:$AD,服务费底表!$K:$K,服务费明细!$B38,服务费底表!$H:$H,服务费明细!BU$3) -> 0 | BV38: =SUMIFS(服务费底表!$AD:$AD,服务费底表!$K:$K,服务费明细!$B38,服务费底表!$H:$H,服务费明细!BV$3) -> 0 | BW38: =SUMIFS(服务费底表!$AD:$AD,服务费底表!$K:$K,服务费明细!$B38,服务费底表!$H:$H,服务费明细!BW$3) -> 0
B39: I004 | C39: =INDEX(二三级标准!$Q:$Q,MATCH(服务费明细!$B39,二三级标准!$O:$O,0)) -> 召开研究者会议 | D39: =IF(临床监查YN=1,1,0) -> 1 | G39: =SUM(G40:G45) -> 4 | H39: =SUM(H40:H45) -> 3 | I39: =SUM(I40:I45) -> 10 | J39: =SUM(J40:J45) -> 0 | K39: =SUM(K40:K45) -> 0 | L39: =SUM(L40:L45) -> 5 | M39: =SUM(M40:M45) -> 68 | N39: =SUM(N40:N45) -> 0 | ... AB39: =SUM(AB40:AB45) -> 0 | AD39: =SUM(G39:AB39) -> 123 | AF39: =SUM(AF40:AF45) -> 73330 | AH39: =SUM(AH40:AH45) -> 73330 | AK39: =SUM(AK40:AK45) -> 123 | AL39: =SUMIFS(服务费底表!$AC:$AC,服务费底表!$K:$K,服务费明细!$B39,服务费底表!$T:$T,AL$3) -> 0 | AM39: =SUMIFS(服务费底表!$AC:$AC,服务费底表!$K:$K,服务费明细!$B39,服务费底表!$T:$T,AM$3) -> 0 | AN39: =SUMIFS(服务费底表!$AC:$AC,服务费底表!$K:$K,服务费明细!$B39,服务费底表!$T:$T,AN$3) -> 0 | AO39: =SUMIFS(服务费底表!$AC:$AC,服务费底表!$K:$K,服务费明细!$B39,服务费底表!$T:$T,AO$3) -> 0 | AP39: =SUMIFS(服务费底表!$AC:$AC,服务费底表!$K:$K,服务费明细!$B39,服务费底表!$T:$T,AP$3) -> 0 | AQ39: =SUMIFS(服务费底表!$AC:$AC,服务费底表!$K:$K,服务费明细!$B39,服务费底表!$T:$T,AQ$3) -> 0 | AR39: =SUMIFS(服务费底表!$AC:$AC,服务费底表!$K:$K,服务费明细!$B39,服务费底表!$T:$T,AR$3) -> 0 | AS39: =SUMIFS(服务费底表!$AC:$AC,服务费底表!$K:$K,服务费明细!$B39,服务费底表!$T:$T,AS$3) -> 0 | ... BG39: =SUMIFS(服务费底表!$AC:$AC,服务费底表!$K:$K,服务费明细!$B39,服务费底表!$T:$T,BG$3) -> 0 | BI39: =SUM(BI40:BI45) -> 73 | BJ39: =SUM(BJ40:BJ45) -> 17 | BK39: =SUM(BK40:BK45) -> 12 | BL39: =SUM(BL40:BL45) -> 2 | BM39: =SUM(BM40:BM45) -> 0 | BN39: =SUM(BN40:BN45) -> 19 | BO39: =SUM(BO40:BO45) -> 0 | BQ39: =SUM(BQ40:BQ45) -> 49150 | BR39: =SUM(BR40:BR45) -> 8520 | BS39: =SUM(BS40:BS45) -> 2400 | BT39: =SUM(BT40:BT45) -> 800 | BU39: =SUM(BU40:BU45) -> 0 | BV39: =SUM(BV40:BV45) -> 12460 | BW39: =SUM(BW40:BW45) -> 0
B40: A025 | C40: =INDEX(二三级标准!$C:$C,MATCH(服务费明细!$B40,二三级标准!$B:$B,0)) -> 召开方案讨论会 | D40: =IF($D$39=1,1,0) -> 1 | E40: =IF($D40=1,1,0) -> 1 | F40: =INDEX(二三级标准!$G:$G,MATCH(服务费明细!$B40,二三级标准!$B:$B,0)) -> 次 | G40: =AL40 -> 0 | H40: =AM40 -> 0 | I40: =AN40 -> 1 | J40: =AO40 -> 0 | K40: =AP40 -> 0 | L40: =AQ40 -> 2 | M40: =AR40 -> 13 | N40: =AS40 -> 0 | ... AB40: =BG40 -> 0 | AC40: {=SUMPRODUCT(G40:AB40,$G$4:$AB$4)} -> 12060 | AD40: =IF(AF40=AC40,TRUE,FALSE) -> TRUE | AE40: =IFERROR(SUMIF(服务费底表!$K:$K,服务费明细!$B40,服务费底表!$AD:$AD)/E40,0) -> 12060 | AF40: =E40*AE40 -> 12060 | AG40: =IFERROR(SUMIF(服务费底表!$K:$K,服务费明细!$B40,服务费底表!$AG:$AG)/E40,0) -> 12060 | AH40: =AG40*E40 -> 12060 | AI40: 线上 | AJ40: =IF(D40=1,AK40/E40,0) -> 18 | AK40: =SUMIF(服务费底表!$K:$K,服务费明细!$B40,服务费底表!$AC:$AC) -> 18 | AL40: =SUMIFS(服务费底表!$AC:$AC,服务费底表!$K:$K,服务费明细!$B40,服务费底表!$T:$T,AL$3) -> 0 | AM40: =SUMIFS(服务费底表!$AC:$AC,服务费底表!$K:$K,服务费明细!$B40,服务费底表!$T:$T,AM$3) -> 0 | AN40: =SUMIFS(服务费底表!$AC:$AC,服务费底表!$K:$K,服务费明细!$B40,服务费底表!$T:$T,AN$3) -> 1 | AO40: =SUMIFS(服务费底表!$AC:$AC,服务费底表!$K:$K,服务费明细!$B40,服务费底表!$T:$T,AO$3) -> 0 | AP40: =SUMIFS(服务费底表!$AC:$AC,服务费底表!$K:$K,服务费明细!$B40,服务费底表!$T:$T,AP$3) -> 0 | AQ40: =SUMIFS(服务费底表!$AC:$AC,服务费底表!$K:$K,服务费明细!$B40,服务费底表!$T:$T,AQ$3) -> 2 | AR40: =SUMIFS(服务费底表!$AC:$AC,服务费底表!$K:$K,服务费明细!$B40,服务费底表!$T:$T,AR$3) -> 13 | AS40: =SUMIFS(服务费底表!$AC:$AC,服务费底表!$K:$K,服务费明细!$B40,服务费底表!$T:$T,AS$3) -> 0 | ... BG40: =SUMIFS(服务费底表!$AC:$AC,服务费底表!$K:$K,服务费明细!$B40,服务费底表!$T:$T,BG$3) -> 0 | BI40: =SUMIFS(服务费底表!$AC:$AC,服务费底表!$K:$K,服务费明细!$B40,服务费底表!$H:$H,服务费明细!BI$3) -> 15 | BJ40: =SUMIFS(服务费底表!$AC:$AC,服务费底表!$K:$K,服务费明细!$B40,服务费底表!$H:$H,服务费明细!BJ$3) -> 1 | BK40: =SUMIFS(服务费底表!$AC:$AC,服务费底表!$K:$K,服务费明细!$B40,服务费底表!$H:$H,服务费明细!BK$3) -> 0 | BL40: =SUMIFS(服务费底表!$AC:$AC,服务费底表!$K:$K,服务费明细!$B40,服务费底表!$H:$H,服务费明细!BL$3) -> 1 | BM40: =SUMIFS(服务费底表!$AC:$AC,服务费底表!$K:$K,服务费明细!$B40,服务费底表!$H:$H,服务费明细!BM$3) -> 0 | BN40: =SUMIFS(服务费底表!$AC:$AC,服务费底表!$K:$K,服务费明细!$B40,服务费底表!$H:$H,服务费明细!BN$3) -> 1 | BO40: =SUMIFS(服务费底表!$AC:$AC,服务费底表!$K:$K,服务费明细!$B40,服务费底表!$H:$H,服务费明细!BO$3) -> 0 | BQ40: =SUMIFS(服务费底表!$AD:$AD,服务费底表!$K:$K,服务费明细!$B40,服务费底表!$H:$H,服务费明细!BQ$3) -> 10430 | BR40: =SUMIFS(服务费底表!$AD:$AD,服务费底表!$K:$K,服务费明细!$B40,服务费底表!$H:$H,服务费明细!BR$3) -> 650 | BS40: =SUMIFS(服务费底表!$AD:$AD,服务费底表!$K:$K,服务费明细!$B40,服务费底表!$H:$H,服务费明细!BS$3) -> 0 | BT40: =SUMIFS(服务费底表!$AD:$AD,服务费底表!$K:$K,服务费明细!$B40,服务费底表!$H:$H,服务费明细!BT$3) -> 400 | BU40: =SUMIFS(服务费底表!$AD:$AD,服务费底表!$K:$K,服务费明细!$B40,服务费底表!$H:$H,服务费明细!BU$3) -> 0 | BV40: =SUMIFS(服务费底表!$AD:$AD,服务费底表!$K:$K,服务费明细!$B40,服务费底表!$H:$H,服务费明细!BV$3) -> 580 | BW40: =SUMIFS(服务费底表!$AD:$AD,服务费底表!$K:$K,服务费明细!$B40,服务费底表!$H:$H,服务费明细!BW$3) -> 0
B41: A026 | C41: =INDEX(二三级标准!$C:$C,MATCH(服务费明细!$B41,二三级标准!$B:$B,0)) -> 召开首次研究者会 | D41: =IF($D$39=1,1,0) -> 1 | E41: =IF($D41=1,1,0) -> 1 | F41: =INDEX(二三级标准!$G:$G,MATCH(服务费明细!$B41,二三级标准!$B:$B,0)) -> 次 | G41: =AL41 -> 4 | H41: =AM41 -> 3 | I41: =AN41 -> 3 | J41: =AO41 -> 0 | K41: =AP41 -> 0 | L41: =AQ41 -> 1 | M41: =AR41 -> 5 | N41: =AS41 -> 0 | ... AB41: =BG41 -> 0 | AC41: {=SUMPRODUCT(G41:AB41,$G$4:$AB$4)} -> 8610 | AD41: =IF(AF41=AC41,TRUE,FALSE) -> TRUE | AE41: =IFERROR(SUMIF(服务费底表!$K:$K,服务费明细!$B41,服务费底表!$AD:$AD)/E41,0) -> 8610 | AF41: =E41*AE41 -> 8610 | AG41: =IFERROR(SUMIF(服务费底表!$K:$K,服务费明细!$B41,服务费底表!$AG:$AG)/E41,0) -> 8610 | AH41: =AG41*E41 -> 8610 | AI41: 线上 | AJ41: =IF(D41=1,AK41/E41,0) -> 17 | AK41: =SUMIF(服务费底表!$K:$K,服务费明细!$B41,服务费底表!$AC:$AC) -> 17 | AL41: =SUMIFS(服务费底表!$AC:$AC,服务费底表!$K:$K,服务费明细!$B41,服务费底表!$T:$T,AL$3) -> 4 | AM41: =SUMIFS(服务费底表!$AC:$AC,服务费底表!$K:$K,服务费明细!$B41,服务费底表!$T:$T,AM$3) -> 3 | AN41: =SUMIFS(服务费底表!$AC:$AC,服务费底表!$K:$K,服务费明细!$B41,服务费底表!$T:$T,AN$3) -> 3 | AO41: =SUMIFS(服务费底表!$AC:$AC,服务费底表!$K:$K,服务费明细!$B41,服务费底表!$T:$T,AO$3) -> 0 | AP41: =SUMIFS(服务费底表!$AC:$AC,服务费底表!$K:$K,服务费明细!$B41,服务费底表!$T:$T,AP$3) -> 0 | AQ41: =SUMIFS(服务费底表!$AC:$AC,服务费底表!$K:$K,服务费明细!$B41,服务费底表!$T:$T,AQ$3) -> 1 | AR41: =SUMIFS(服务费底表!$AC:$AC,服务费底表!$K:$K,服务费明细!$B41,服务费底表!$T:$T,AR$3) -> 5 | AS41: =SUMIFS(服务费底表!$AC:$AC,服务费底表!$K:$K,服务费明细!$B41,服务费底表!$T:$T,AS$3) -> 0 | ... BG41: =SUMIFS(服务费底表!$AC:$AC,服务费底表!$K:$K,服务费明细!$B41,服务费底表!$T:$T,BG$3) -> 0 | BI41: =SUMIFS(服务费底表!$AC:$AC,服务费底表!$K:$K,服务费明细!$B41,服务费底表!$H:$H,服务费明细!BI$3) -> 6 | BJ41: =SUMIFS(服务费底表!$AC:$AC,服务费底表!$K:$K,服务费明细!$B41,服务费底表!$H:$H,服务费明细!BJ$3) -> 10 | BK41: =SUMIFS(服务费底表!$AC:$AC,服务费底表!$K:$K,服务费明细!$B41,服务费底表!$H:$H,服务费明细!BK$3) -> 0 | BL41: =SUMIFS(服务费底表!$AC:$AC,服务费底表!$K:$K,服务费明细!$B41,服务费底表!$H:$H,服务费明细!BL$3) -> 1 | BM41: =SUMIFS(服务费底表!$AC:$AC,服务费底表!$K:$K,服务费明细!$B41,服务费底表!$H:$H,服务费明细!BM$3) -> 0 | BN41: =SUMIFS(服务费底表!$AC:$AC,服务费底表!$K:$K,服务费明细!$B41,服务费底表!$H:$H,服务费明细!BN$3) -> 0 | BO41: =SUMIFS(服务费底表!$AC:$AC,服务费底表!$K:$K,服务费明细!$B41,服务费底表!$H:$H,服务费明细!BO$3) -> 0 | BQ41: =SUMIFS(服务费底表!$AD:$AD,服务费底表!$K:$K,服务费明细!$B41,服务费底表!$H:$H,服务费明细!BQ$3) -> 4240 | BR41: =SUMIFS(服务费底表!$AD:$AD,服务费底表!$K:$K,服务费明细!$B41,服务费底表!$H:$H,服务费明细!BR$3) -> 3970 | BS41: =SUMIFS(服务费底表!$AD:$AD,服务费底表!$K:$K,服务费明细!$B41,服务费底表!$H:$H,服务费明细!BS$3) -> 0 | BT41: =SUMIFS(服务费底表!$AD:$AD,服务费底表!$K:$K,服务费明细!$B41,服务费底表!$H:$H,服务费明细!BT$3) -> 400 | BU41: =SUMIFS(服务费底表!$AD:$AD,服务费底表!$K:$K,服务费明细!$B41,服务费底表!$H:$H,服务费明细!BU$3) -> 0 | BV41: =SUMIFS(服务费底表!$AD:$AD,服务费底表!$K:$K,服务费明细!$B41,服务费底表!$H:$H,服务费明细!BV$3) -> 0 | BW41: =SUMIFS(服务费底表!$AD:$AD,服务费底表!$K:$K,服务费明细!$B41,服务费底表!$H:$H,服务费明细!BW$3) -> 0
B42: A027 | C42: =INDEX(二三级标准!$C:$C,MATCH(服务费明细!$B42,二三级标准!$B:$B,0)) -> SRC/SMC章程撰写 | D42: {=IF(AND($D$39=1,SRC会议次数>0,试验参与者类型<>"健康人"),1,0)} -> 1 | E42: =IF($D42=1,1,0) -> 1 | F42: =INDEX(二三级标准!$G:$G,MATCH(服务费明细!$B42,二三级标准!$B:$B,0)) -> 次 | G42: =AL42 -> 0 | H42: =AM42 -> 0 | I42: =AN42 -> 0 | J42: =AO42 -> 0 | K42: =AP42 -> 0 | L42: =AQ42 -> 2 | M42: =AR42 -> 8 | N42: =AS42 -> 0 | ... AB42: =BG42 -> 0 | AC42: {=SUMPRODUCT(G42:AB42,$G$4:$AB$4)} -> 7180 | AD42: =IF(AF42=AC42,TRUE,FALSE) -> TRUE | AE42: =IFERROR(SUMIF(服务费底表!$K:$K,服务费明细!$B42,服务费底表!$AD:$AD)/E42,0) -> 7180 | AF42: =E42*AE42 -> 7180 | AG42: =IFERROR(SUMIF(服务费底表!$K:$K,服务费明细!$B42,服务费底表!$AG:$AG)/E42,0) -> 7180 | AH42: =AG42*E42 -> 7180 | AI42: SRC章程撰写 | AJ42: =IF(D42=1,AK42/E42,0) -> 10 | AK42: =SUMIF(服务费底表!$K:$K,服务费明细!$B42,服务费底表!$AC:$AC) -> 10 | AL42: =SUMIFS(服务费底表!$AC:$AC,服务费底表!$K:$K,服务费明细!$B42,服务费底表!$T:$T,AL$3) -> 0 | AM42: =SUMIFS(服务费底表!$AC:$AC,服务费底表!$K:$K,服务费明细!$B42,服务费底表!$T:$T,AM$3) -> 0 | AN42: =SUMIFS(服务费底表!$AC:$AC,服务费底表!$K:$K,服务费明细!$B42,服务费底表!$T:$T,AN$3) -> 0 | AO42: =SUMIFS(服务费底表!$AC:$AC,服务费底表!$K:$K,服务费明细!$B42,服务费底表!$T:$T,AO$3) -> 0 | AP42: =SUMIFS(服务费底表!$AC:$AC,服务费底表!$K:$K,服务费明细!$B42,服务费底表!$T:$T,AP$3) -> 0 | AQ42: =SUMIFS(服务费底表!$AC:$AC,服务费底表!$K:$K,服务费明细!$B42,服务费底表!$T:$T,AQ$3) -> 2 | AR42: =SUMIFS(服务费底表!$AC:$AC,服务费底表!$K:$K,服务费明细!$B42,服务费底表!$T:$T,AR$3) -> 8 | AS42: =SUMIFS(服务费底表!$AC:$AC,服务费底表!$K:$K,服务费明细!$B42,服务费底表!$T:$T,AS$3) -> 0 | ... BG42: =SUMIFS(服务费底表!$AC:$AC,服务费底表!$K:$K,服务费明细!$B42,服务费底表!$T:$T,BG$3) -> 0 | BI42: =SUMIFS(服务费底表!$AC:$AC,服务费底表!$K:$K,服务费明细!$B42,服务费底表!$H:$H,服务费明细!BI$3) -> 10 | BJ42: =SUMIFS(服务费底表!$AC:$AC,服务费底表!$K:$K,服务费明细!$B42,服务费底表!$H:$H,服务费明细!BJ$3) -> 0 | BK42: =SUMIFS(服务费底表!$AC:$AC,服务费底表!$K:$K,服务费明细!$B42,服务费底表!$H:$H,服务费明细!BK$3) -> 0 | BL42: =SUMIFS(服务费底表!$AC:$AC,服务费底表!$K:$K,服务费明细!$B42,服务费底表!$H:$H,服务费明细!BL$3) -> 0 | BM42: =SUMIFS(服务费底表!$AC:$AC,服务费底表!$K:$K,服务费明细!$B42,服务费底表!$H:$H,服务费明细!BM$3) -> 0 | BN42: =SUMIFS(服务费底表!$AC:$AC,服务费底表!$K:$K,服务费明细!$B42,服务费底表!$H:$H,服务费明细!BN$3) -> 0 | BO42: =SUMIFS(服务费底表!$AC:$AC,服务费底表!$K:$K,服务费明细!$B42,服务费底表!$H:$H,服务费明细!BO$3) -> 0 | BQ42: =SUMIFS(服务费底表!$AD:$AD,服务费底表!$K:$K,服务费明细!$B42,服务费底表!$H:$H,服务费明细!BQ$3) -> 7180 | BR42: =SUMIFS(服务费底表!$AD:$AD,服务费底表!$K:$K,服务费明细!$B42,服务费底表!$H:$H,服务费明细!BR$3) -> 0 | BS42: =SUMIFS(服务费底表!$AD:$AD,服务费底表!$K:$K,服务费明细!$B42,服务费底表!$H:$H,服务费明细!BS$3) -> 0 | BT42: =SUMIFS(服务费底表!$AD:$AD,服务费底表!$K:$K,服务费明细!$B42,服务费底表!$H:$H,服务费明细!BT$3) -> 0 | BU42: =SUMIFS(服务费底表!$AD:$AD,服务费底表!$K:$K,服务费明细!$B42,服务费底表!$H:$H,服务费明细!BU$3) -> 0 | BV42: =SUMIFS(服务费底表!$AD:$AD,服务费底表!$K:$K,服务费明细!$B42,服务费底表!$H:$H,服务费明细!BV$3) -> 0 | BW42: =SUMIFS(服务费底表!$AD:$AD,服务费底表!$K:$K,服务费明细!$B42,服务费底表!$H:$H,服务费明细!BW$3) -> 0
B43: A028 | C43: =INDEX(二三级标准!$C:$C,MATCH(服务费明细!$B43,二三级标准!$B:$B,0)) -> 召开SRC/SMC会 | D43: =IF(AND($D$39=1,SRC会议次数>0),1,0) -> 1 | E43: =IF($D43=1,SRC会议次数,0) -> 6 | F43: =INDEX(二三级标准!$G:$G,MATCH(服务费明细!$B43,二三级标准!$B:$B,0)) -> 次 | G43: =AL43 -> 0 | H43: =AM43 -> 0 | I43: =AN43 -> 6 | J43: =AO43 -> 0 | K43: =AP43 -> 0 | L43: =AQ43 -> 0 | M43: =AR43 -> 42 | N43: =AS43 -> 0 | ... AB43: =BG43 -> 0 | AC43: {=SUMPRODUCT(G43:AB43,$G$4:$AB$4)} -> 45480 | AD43: =IF(AF43=AC43,TRUE,FALSE) -> TRUE | AE43: =IFERROR(SUMIF(服务费底表!$K:$K,服务费明细!$B43,服务费底表!$AD:$AD)/E43,0) -> 7580 | AF43: =E43*AE43 -> 45480 | AG43: =IFERROR(SUMIF(服务费底表!$K:$K,服务费明细!$B43,服务费底表!$AG:$AG)/E43,0) -> 7580 | AH43: =AG43*E43 -> 45480 | AI43: 线上 | AJ43: =IF(D43=1,AK43/E43,0) -> 13 | AK43: =SUMIF(服务费底表!$K:$K,服务费明细!$B43,服务费底表!$AC:$AC) -> 78 | AL43: =SUMIFS(服务费底表!$AC:$AC,服务费底表!$K:$K,服务费明细!$B43,服务费底表!$T:$T,AL$3) -> 0 | AM43: =SUMIFS(服务费底表!$AC:$AC,服务费底表!$K:$K,服务费明细!$B43,服务费底表!$T:$T,AM$3) -> 0 | AN43: =SUMIFS(服务费底表!$AC:$AC,服务费底表!$K:$K,服务费明细!$B43,服务费底表!$T:$T,AN$3) -> 6 | AO43: =SUMIFS(服务费底表!$AC:$AC,服务费底表!$K:$K,服务费明细!$B43,服务费底表!$T:$T,AO$3) -> 0 | AP43: =SUMIFS(服务费底表!$AC:$AC,服务费底表!$K:$K,服务费明细!$B43,服务费底表!$T:$T,AP$3) -> 0 | AQ43: =SUMIFS(服务费底表!$AC:$AC,服务费底表!$K:$K,服务费明细!$B43,服务费底表!$T:$T,AQ$3) -> 0 | AR43: =SUMIFS(服务费底表!$AC:$AC,服务费底表!$K:$K,服务费明细!$B43,服务费底表!$T:$T,AR$3) -> 42 | AS43: =SUMIFS(服务费底表!$AC:$AC,服务费底表!$K:$K,服务费明细!$B43,服务费底表!$T:$T,AS$3) -> 0 | ... BG43: =SUMIFS(服务费底表!$AC:$AC,服务费底表!$K:$K,服务费明细!$B43,服务费底表!$T:$T,BG$3) -> 0 | BI43: =SUMIFS(服务费底表!$AC:$AC,服务费底表!$K:$K,服务费明细!$B43,服务费底表!$H:$H,服务费明细!BI$3) -> 42 | BJ43: =SUMIFS(服务费底表!$AC:$AC,服务费底表!$K:$K,服务费明细!$B43,服务费底表!$H:$H,服务费明细!BJ$3) -> 6 | BK43: =SUMIFS(服务费底表!$AC:$AC,服务费底表!$K:$K,服务费明细!$B43,服务费底表!$H:$H,服务费明细!BK$3) -> 12 | BL43: =SUMIFS(服务费底表!$AC:$AC,服务费底表!$K:$K,服务费明细!$B43,服务费底表!$H:$H,服务费明细!BL$3) -> 0 | BM43: =SUMIFS(服务费底表!$AC:$AC,服务费底表!$K:$K,服务费明细!$B43,服务费底表!$H:$H,服务费明细!BM$3) -> 0 | BN43: =SUMIFS(服务费底表!$AC:$AC,服务费底表!$K:$K,服务费明细!$B43,服务费底表!$H:$H,服务费明细!BN$3) -> 18 | BO43: =SUMIFS(服务费底表!$AC:$AC,服务费底表!$K:$K,服务费明细!$B43,服务费底表!$H:$H,服务费明细!BO$3) -> 0 | BQ43: =SUMIFS(服务费底表!$AD:$AD,服务费底表!$K:$K,服务费明细!$B43,服务费底表!$H:$H,服务费明细!BQ$3) -> 27300 | BR43: =SUMIFS(服务费底表!$AD:$AD,服务费底表!$K:$K,服务费明细!$B43,服务费底表!$H:$H,服务费明细!BR$3) -> 3900 | BS43: =SUMIFS(服务费底表!$AD:$AD,服务费底表!$K:$K,服务费明细!$B43,服务费底表!$H:$H,服务费明细!BS$3) -> 2400 | BT43: =SUMIFS(服务费底表!$AD:$AD,服务费底表!$K:$K,服务费明细!$B43,服务费底表!$H:$H,服务费明细!BT$3) -> 0 | BU43: =SUMIFS(服务费底表!$AD:$AD,服务费底表!$K:$K,服务费明细!$B43,服务费底表!$H:$H,服务费明细!BU$3) -> 0 | BV43: =SUMIFS(服务费底表!$AD:$AD,服务费底表!$K:$K,服务费明细!$B43,服务费底表!$H:$H,服务费明细!BV$3) -> 11880 | BW43: =SUMIFS(服务费底表!$AD:$AD,服务费底表!$K:$K,服务费明细!$B43,服务费底表!$H:$H,服务费明细!BW$3) -> 0
B44: A029 | C44: =INDEX(二三级标准!$C:$C,MATCH(服务费明细!$B44,二三级标准!$B:$B,0)) -> 召开中期研究者会 | D44: 0 | E44: =IF($D44=1,1,0) -> 0 | F44: =INDEX(二三级标准!$G:$G,MATCH(服务费明细!$B44,二三级标准!$B:$B,0)) -> 次 | G44: =AL44 -> 0 | H44: =AM44 -> 0 | I44: =AN44 -> 0 | J44: =AO44 -> 0 | K44: =AP44 -> 0 | L44: =AQ44 -> 0 | M44: =AR44 -> 0 | N44: =AS44 -> 0 | ... AB44: =BG44 -> 0 | AC44: {=SUMPRODUCT(G44:AB44,$G$4:$AB$4)} -> 0 | AD44: =IF(AF44=AC44,TRUE,FALSE) -> TRUE | AE44: =IFERROR(SUMIF(服务费底表!$K:$K,服务费明细!$B44,服务费底表!$AD:$AD)/E44,0) -> 0 | AF44: =E44*AE44 -> 0 | AG44: =IFERROR(SUMIF(服务费底表!$K:$K,服务费明细!$B44,服务费底表!$AG:$AG)/E44,0) -> 0 | AH44: =AG44*E44 -> 0 | AI44: 线下 | AJ44: =IF(D44=1,AK44/E44,0) -> 0 | AK44: =SUMIF(服务费底表!$K:$K,服务费明细!$B44,服务费底表!$AC:$AC) -> 0 | AL44: =SUMIFS(服务费底表!$AC:$AC,服务费底表!$K:$K,服务费明细!$B44,服务费底表!$T:$T,AL$3) -> 0 | AM44: =SUMIFS(服务费底表!$AC:$AC,服务费底表!$K:$K,服务费明细!$B44,服务费底表!$T:$T,AM$3) -> 0 | AN44: =SUMIFS(服务费底表!$AC:$AC,服务费底表!$K:$K,服务费明细!$B44,服务费底表!$T:$T,AN$3) -> 0 | AO44: =SUMIFS(服务费底表!$AC:$AC,服务费底表!$K:$K,服务费明细!$B44,服务费底表!$T:$T,AO$3) -> 0 | AP44: =SUMIFS(服务费底表!$AC:$AC,服务费底表!$K:$K,服务费明细!$B44,服务费底表!$T:$T,AP$3) -> 0 | AQ44: =SUMIFS(服务费底表!$AC:$AC,服务费底表!$K:$K,服务费明细!$B44,服务费底表!$T:$T,AQ$3) -> 0 | AR44: =SUMIFS(服务费底表!$AC:$AC,服务费底表!$K:$K,服务费明细!$B44,服务费底表!$T:$T,AR$3) -> 0 | AS44: =SUMIFS(服务费底表!$AC:$AC,服务费底表!$K:$K,服务费明细!$B44,服务费底表!$T:$T,AS$3) -> 0 | ... BG44: =SUMIFS(服务费底表!$AC:$AC,服务费底表!$K:$K,服务费明细!$B44,服务费底表!$T:$T,BG$3) -> 0 | BI44: =SUMIFS(服务费底表!$AC:$AC,服务费底表!$K:$K,服务费明细!$B44,服务费底表!$H:$H,服务费明细!BI$3) -> 0 | BJ44: =SUMIFS(服务费底表!$AC:$AC,服务费底表!$K:$K,服务费明细!$B44,服务费底表!$H:$H,服务费明细!BJ$3) -> 0 | BK44: =SUMIFS(服务费底表!$AC:$AC,服务费底表!$K:$K,服务费明细!$B44,服务费底表!$H:$H,服务费明细!BK$3) -> 0 | BL44: =SUMIFS(服务费底表!$AC:$AC,服务费底表!$K:$K,服务费明细!$B44,服务费底表!$H:$H,服务费明细!BL$3) -> 0 | BM44: =SUMIFS(服务费底表!$AC:$AC,服务费底表!$K:$K,服务费明细!$B44,服务费底表!$H:$H,服务费明细!BM$3) -> 0 | BN44: =SUMIFS(服务费底表!$AC:$AC,服务费底表!$K:$K,服务费明细!$B44,服务费底表!$H:$H,服务费明细!BN$3) -> 0 | BO44: =SUMIFS(服务费底表!$AC:$AC,服务费底表!$K:$K,服务费明细!$B44,服务费底表!$H:$H,服务费明细!BO$3) -> 0 | BQ44: =SUMIFS(服务费底表!$AD:$AD,服务费底表!$K:$K,服务费明细!$B44,服务费底表!$H:$H,服务费明细!BQ$3) -> 0 | BR44: =SUMIFS(服务费底表!$AD:$AD,服务费底表!$K:$K,服务费明细!$B44,服务费底表!$H:$H,服务费明细!BR$3) -> 0 | BS44: =SUMIFS(服务费底表!$AD:$AD,服务费底表!$K:$K,服务费明细!$B44,服务费底表!$H:$H,服务费明细!BS$3) -> 0 | BT44: =SUMIFS(服务费底表!$AD:$AD,服务费底表!$K:$K,服务费明细!$B44,服务费底表!$H:$H,服务费明细!BT$3) -> 0 | BU44: =SUMIFS(服务费底表!$AD:$AD,服务费底表!$K:$K,服务费明细!$B44,服务费底表!$H:$H,服务费明细!BU$3) -> 0 | BV44: =SUMIFS(服务费底表!$AD:$AD,服务费底表!$K:$K,服务费明细!$B44,服务费底表!$H:$H,服务费明细!BV$3) -> 0 | BW44: =SUMIFS(服务费底表!$AD:$AD,服务费底表!$K:$K,服务费明细!$B44,服务费底表!$H:$H,服务费明细!BW$3) -> 0
B45: A030 | C45: =INDEX(二三级标准!$C:$C,MATCH(服务费明细!$B45,二三级标准!$B:$B,0)) -> 召开研究总结会 | D45: 0 | E45: =IF($D45=1,1,0) -> 0 | F45: =INDEX(二三级标准!$G:$G,MATCH(服务费明细!$B45,二三级标准!$B:$B,0)) -> 次 | G45: =AL45 -> 0 | H45: =AM45 -> 0 | I45: =AN45 -> 0 | J45: =AO45 -> 0 | K45: =AP45 -> 0 | L45: =AQ45 -> 0 | M45: =AR45 -> 0 | N45: =AS45 -> 0 | ... AB45: =BG45 -> 0 | AC45: {=SUMPRODUCT(G45:AB45,$G$4:$AB$4)} -> 0 | AD45: =IF(AF45=AC45,TRUE,FALSE) -> TRUE | AE45: =IFERROR(SUMIF(服务费底表!$K:$K,服务费明细!$B45,服务费底表!$AD:$AD)/E45,0) -> 0 | AF45: =E45*AE45 -> 0 | AG45: =IFERROR(SUMIF(服务费底表!$K:$K,服务费明细!$B45,服务费底表!$AG:$AG)/E45,0) -> 0 | AH45: =AG45*E45 -> 0 | AI45: 线下 | AJ45: =IF(D45=1,AK45/E45,0) -> 0 | AK45: =SUMIF(服务费底表!$K:$K,服务费明细!$B45,服务费底表!$AC:$AC) -> 0 | AL45: =SUMIFS(服务费底表!$AC:$AC,服务费底表!$K:$K,服务费明细!$B45,服务费底表!$T:$T,AL$3) -> 0 | AM45: =SUMIFS(服务费底表!$AC:$AC,服务费底表!$K:$K,服务费明细!$B45,服务费底表!$T:$T,AM$3) -> 0 | AN45: =SUMIFS(服务费底表!$AC:$AC,服务费底表!$K:$K,服务费明细!$B45,服务费底表!$T:$T,AN$3) -> 0 | AO45: =SUMIFS(服务费底表!$AC:$AC,服务费底表!$K:$K,服务费明细!$B45,服务费底表!$T:$T,AO$3) -> 0 | AP45: =SUMIFS(服务费底表!$AC:$AC,服务费底表!$K:$K,服务费明细!$B45,服务费底表!$T:$T,AP$3) -> 0 | AQ45: =SUMIFS(服务费底表!$AC:$AC,服务费底表!$K:$K,服务费明细!$B45,服务费底表!$T:$T,AQ$3) -> 0 | AR45: =SUMIFS(服务费底表!$AC:$AC,服务费底表!$K:$K,服务费明细!$B45,服务费底表!$T:$T,AR$3) -> 0 | AS45: =SUMIFS(服务费底表!$AC:$AC,服务费底表!$K:$K,服务费明细!$B45,服务费底表!$T:$T,AS$3) -> 0 | ... BG45: =SUMIFS(服务费底表!$AC:$AC,服务费底表!$K:$K,服务费明细!$B45,服务费底表!$T:$T,BG$3) -> 0 | BI45: =SUMIFS(服务费底表!$AC:$AC,服务费底表!$K:$K,服务费明细!$B45,服务费底表!$H:$H,服务费明细!BI$3) -> 0 | BJ45: =SUMIFS(服务费底表!$AC:$AC,服务费底表!$K:$K,服务费明细!$B45,服务费底表!$H:$H,服务费明细!BJ$3) -> 0 | BK45: =SUMIFS(服务费底表!$AC:$AC,服务费底表!$K:$K,服务费明细!$B45,服务费底表!$H:$H,服务费明细!BK$3) -> 0 | BL45: =SUMIFS(服务费底表!$AC:$AC,服务费底表!$K:$K,服务费明细!$B45,服务费底表!$H:$H,服务费明细!BL$3) -> 0 | BM45: =SUMIFS(服务费底表!$AC:$AC,服务费底表!$K:$K,服务费明细!$B45,服务费底表!$H:$H,服务费明细!BM$3) -> 0 | BN45: =SUMIFS(服务费底表!$AC:$AC,服务费底表!$K:$K,服务费明细!$B45,服务费底表!$H:$H,服务费明细!BN$3) -> 0 | BO45: =SUMIFS(服务费底表!$AC:$AC,服务费底表!$K:$K,服务费明细!$B45,服务费底表!$H:$H,服务费明细!BO$3) -> 0 | BQ45: =SUMIFS(服务费底表!$AD:$AD,服务费底表!$K:$K,服务费明细!$B45,服务费底表!$H:$H,服务费明细!BQ$3) -> 0 | BR45: =SUMIFS(服务费底表!$AD:$AD,服务费底表!$K:$K,服务费明细!$B45,服务费底表!$H:$H,服务费明细!BR$3) -> 0 | BS45: =SUMIFS(服务费底表!$AD:$AD,服务费底表!$K:$K,服务费明细!$B45,服务费底表!$H:$H,服务费明细!BS$3) -> 0 | BT45: =SUMIFS(服务费底表!$AD:$AD,服务费底表!$K:$K,服务费明细!$B45,服务费底表!$H:$H,服务费明细!BT$3) -> 0 | BU45: =SUMIFS(服务费底表!$AD:$AD,服务费底表!$K:$K,服务费明细!$B45,服务费底表!$H:$H,服务费明细!BU$3) -> 0 | BV45: =SUMIFS(服务费底表!$AD:$AD,服务费底表!$K:$K,服务费明细!$B45,服务费底表!$H:$H,服务费明细!BV$3) -> 0 | BW45: =SUMIFS(服务费底表!$AD:$AD,服务费底表!$K:$K,服务费明细!$B45,服务费底表!$H:$H,服务费明细!BW$3) -> 0
B46: I005 | C46: =INDEX(二三级标准!$Q:$Q,MATCH(服务费明细!$B46,二三级标准!$O:$O,0)) -> 临床监查和中心管理 | D46: =IF(临床监查YN=1,1,0) -> 1 | G46: =SUM(G47:G69) -> 2201 | H46: =SUM(H47:H69) -> 32 | I46: =SUM(I47:I69) -> 267.5 | J46: =SUM(J47:J69) -> 8 | K46: =SUM(K47:K69) -> 46 | L46: =SUM(L47:L69) -> 0 | M46: =SUM(M47:M69) -> 12 | N46: =SUM(N47:N69) -> 0 | ... AB46: =SUM(AB47:AB69) -> 0 | AD46: =SUM(G46:AB46) -> 2566.5 | AF46: =SUM(AF47:AF69) -> 971055 | AH46: =SUM(AH47:AH69) -> 971055 | AK46: =SUM(AK47:AK69) -> 2566.5 | BI46: =SUM(BI47:BI69) -> 12 | BJ46: =SUM(BJ47:BJ69) -> 2554.5 | BK46: =SUM(BK47:BK69) -> 0 | BL46: =SUM(BL47:BL69) -> 0 | BM46: =SUM(BM47:BM69) -> 0 | BN46: =SUM(BN47:BN69) -> 0 | BO46: =SUM(BO47:BO69) -> 0 | BQ46: =SUM(BQ47:BQ69) -> 7800 | BR46: =SUM(BR47:BR69) -> 963255 | BS46: =SUM(BS47:BS69) -> 0 | BT46: =SUM(BT47:BT69) -> 0 | BU46: =SUM(BU47:BU69) -> 0 | BV46: =SUM(BV47:BV69) -> 0 | BW46: =SUM(BW47:BW69) -> 0
B47: A031 | C47: =INDEX(二三级标准!$C:$C,MATCH(服务费明细!$B47,二三级标准!$B:$B,0)) -> 准备或签署研究中心合同 | D47: =IF($D$46=1,1,0) -> 1 | E47: =IF($D47=1,启动中心数,0) -> 4 | F47: =INDEX(二三级标准!$G:$G,MATCH(服务费明细!$B47,二三级标准!$B:$B,0)) -> 份 | G47: =AL47 -> 128 | H47: =AM47 -> 0 | I47: =AN47 -> 8 | J47: =AO47 -> 0 | K47: =AP47 -> 0 | L47: =AQ47 -> 0 | M47: =AR47 -> 0 | N47: =AS47 -> 0 | ... AB47: =BG47 -> 0 | AC47: {=SUMPRODUCT(G47:AB47,$G$4:$AB$4)} -> 48720 | AD47: =IF(AF47=AC47,TRUE,FALSE) -> TRUE | AE47: =IFERROR(SUMIF(服务费底表!$K:$K,服务费明细!$B47,服务费底表!$AD:$AD)/E47,0) -> 12180 | AF47: =E47*AE47 -> 48720 | AG47: =IFERROR(SUMIF(服务费底表!$K:$K,服务费明细!$B47,服务费底表!$AG:$AG)/E47,0) -> 12180 | AH47: =AG47*E47 -> 48720 | AI47: ="有临负责"&E47&"份中心合同的协商和签署。默认每中心一份。" -> 有临负责4份中心合同的协商和签署。默认每中心一份。 | AJ47: =IF(D47=1,AK47/E47,0) -> 34 | AK47: =SUMIF(服务费底表!$K:$K,服务费明细!$B47,服务费底表!$AC:$AC) -> 136 | AL47: =SUMIFS(服务费底表!$AC:$AC,服务费底表!$K:$K,服务费明细!$B47,服务费底表!$T:$T,AL$3) -> 128 | AM47: =SUMIFS(服务费底表!$AC:$AC,服务费底表!$K:$K,服务费明细!$B47,服务费底表!$T:$T,AM$3) -> 0 | AN47: =SUMIFS(服务费底表!$AC:$AC,服务费底表!$K:$K,服务费明细!$B47,服务费底表!$T:$T,AN$3) -> 8 | AO47: =SUMIFS(服务费底表!$AC:$AC,服务费底表!$K:$K,服务费明细!$B47,服务费底表!$T:$T,AO$3) -> 0 | AP47: =SUMIFS(服务费底表!$AC:$AC,服务费底表!$K:$K,服务费明细!$B47,服务费底表!$T:$T,AP$3) -> 0 | AQ47: =SUMIFS(服务费底表!$AC:$AC,服务费底表!$K:$K,服务费明细!$B47,服务费底表!$T:$T,AQ$3) -> 0 | AR47: =SUMIFS(服务费底表!$AC:$AC,服务费底表!$K:$K,服务费明细!$B47,服务费底表!$T:$T,AR$3) -> 0 | AS47: =SUMIFS(服务费底表!$AC:$AC,服务费底表!$K:$K,服务费明细!$B47,服务费底表!$T:$T,AS$3) -> 0 | ... BG47: =SUMIFS(服务费底表!$AC:$AC,服务费底表!$K:$K,服务费明细!$B47,服务费底表!$T:$T,BG$3) -> 0 | BI47: =SUMIFS(服务费底表!$AC:$AC,服务费底表!$K:$K,服务费明细!$B47,服务费底表!$H:$H,服务费明细!BI$3) -> 0 | BJ47: =SUMIFS(服务费底表!$AC:$AC,服务费底表!$K:$K,服务费明细!$B47,服务费底表!$H:$H,服务费明细!BJ$3) -> 136 | BK47: =SUMIFS(服务费底表!$AC:$AC,服务费底表!$K:$K,服务费明细!$B47,服务费底表!$H:$H,服务费明细!BK$3) -> 0 | BL47: =SUMIFS(服务费底表!$AC:$AC,服务费底表!$K:$K,服务费明细!$B47,服务费底表!$H:$H,服务费明细!BL$3) -> 0 | BM47: =SUMIFS(服务费底表!$AC:$AC,服务费底表!$K:$K,服务费明细!$B47,服务费底表!$H:$H,服务费明细!BM$3) -> 0 | BN47: =SUMIFS(服务费底表!$AC:$AC,服务费底表!$K:$K,服务费明细!$B47,服务费底表!$H:$H,服务费明细!BN$3) -> 0 | BO47: =SUMIFS(服务费底表!$AC:$AC,服务费底表!$K:$K,服务费明细!$B47,服务费底表!$H:$H,服务费明细!BO$3) -> 0 | BQ47: =SUMIFS(服务费底表!$AD:$AD,服务费底表!$K:$K,服务费明细!$B47,服务费底表!$H:$H,服务费明细!BQ$3) -> 0 | BR47: =SUMIFS(服务费底表!$AD:$AD,服务费底表!$K:$K,服务费明细!$B47,服务费底表!$H:$H,服务费明细!BR$3) -> 48720 | BS47: =SUMIFS(服务费底表!$AD:$AD,服务费底表!$K:$K,服务费明细!$B47,服务费底表!$H:$H,服务费明细!BS$3) -> 0 | BT47: =SUMIFS(服务费底表!$AD:$AD,服务费底表!$K:$K,服务费明细!$B47,服务费底表!$H:$H,服务费明细!BT$3) -> 0 | BU47: =SUMIFS(服务费底表!$AD:$AD,服务费底表!$K:$K,服务费明细!$B47,服务费底表!$H:$H,服务费明细!BU$3) -> 0 | BV47: =SUMIFS(服务费底表!$AD:$AD,服务费底表!$K:$K,服务费明细!$B47,服务费底表!$H:$H,服务费明细!BV$3) -> 0 | BW47: =SUMIFS(服务费底表!$AD:$AD,服务费底表!$K:$K,服务费明细!$B47,服务费底表!$H:$H,服务费明细!BW$3) -> 0
B48: A032 | C48: =INDEX(二三级标准!$C:$C,MATCH(服务费明细!$B48,二三级标准!$B:$B,0)) -> 启动访视 | D48: =IF($D$46=1,1,0) -> 1 | E48: =IF($D48=1,启动访视次数,0) -> 4 | F48: =INDEX(二三级标准!$G:$G,MATCH(服务费明细!$B48,二三级标准!$B:$B,0)) -> 次 | G48: =AL48 -> 68 | H48: =AM48 -> 0 | I48: =AN48 -> 8 | J48: =AO48 -> 0 | K48: =AP48 -> 0 | L48: =AQ48 -> 0 | M48: =AR48 -> 0 | N48: =AS48 -> 0 | ... AB48: =BG48 -> 0 | AC48: {=SUMPRODUCT(G48:AB48,$G$4:$AB$4)} -> 28320 | AD48: =IF(AF48=AC48,TRUE,FALSE) -> TRUE | AE48: =IFERROR(SUMIF(服务费底表!$K:$K,服务费明细!$B48,服务费底表!$AD:$AD)/E48,0) -> 7080 | AF48: =E48*AE48 -> 28320 | AG48: =IFERROR(SUMIF(服务费底表!$K:$K,服务费明细!$B48,服务费底表!$AG:$AG)/E48,0) -> 7080 | AH48: =AG48*E48 -> 28320 | AI48: 准备，差旅，现场访视，报告和跟进。 | AJ48: =IF(D48=1,AK48/E48,0) -> 19 | AK48: =SUMIF(服务费底表!$K:$K,服务费明细!$B48,服务费底表!$AC:$AC) -> 76 | AL48: =SUMIFS(服务费底表!$AC:$AC,服务费底表!$K:$K,服务费明细!$B48,服务费底表!$T:$T,AL$3) -> 68 | AM48: =SUMIFS(服务费底表!$AC:$AC,服务费底表!$K:$K,服务费明细!$B48,服务费底表!$T:$T,AM$3) -> 0 | AN48: =SUMIFS(服务费底表!$AC:$AC,服务费底表!$K:$K,服务费明细!$B48,服务费底表!$T:$T,AN$3) -> 8 | AO48: =SUMIFS(服务费底表!$AC:$AC,服务费底表!$K:$K,服务费明细!$B48,服务费底表!$T:$T,AO$3) -> 0 | AP48: =SUMIFS(服务费底表!$AC:$AC,服务费底表!$K:$K,服务费明细!$B48,服务费底表!$T:$T,AP$3) -> 0 | AQ48: =SUMIFS(服务费底表!$AC:$AC,服务费底表!$K:$K,服务费明细!$B48,服务费底表!$T:$T,AQ$3) -> 0 | AR48: =SUMIFS(服务费底表!$AC:$AC,服务费底表!$K:$K,服务费明细!$B48,服务费底表!$T:$T,AR$3) -> 0 | AS48: =SUMIFS(服务费底表!$AC:$AC,服务费底表!$K:$K,服务费明细!$B48,服务费底表!$T:$T,AS$3) -> 0 | ... BG48: =SUMIFS(服务费底表!$AC:$AC,服务费底表!$K:$K,服务费明细!$B48,服务费底表!$T:$T,BG$3) -> 0 | BI48: =SUMIFS(服务费底表!$AC:$AC,服务费底表!$K:$K,服务费明细!$B48,服务费底表!$H:$H,服务费明细!BI$3) -> 0 | BJ48: =SUMIFS(服务费底表!$AC:$AC,服务费底表!$K:$K,服务费明细!$B48,服务费底表!$H:$H,服务费明细!BJ$3) -> 76 | BK48: =SUMIFS(服务费底表!$AC:$AC,服务费底表!$K:$K,服务费明细!$B48,服务费底表!$H:$H,服务费明细!BK$3) -> 0 | BL48: =SUMIFS(服务费底表!$AC:$AC,服务费底表!$K:$K,服务费明细!$B48,服务费底表!$H:$H,服务费明细!BL$3) -> 0 | BM48: =SUMIFS(服务费底表!$AC:$AC,服务费底表!$K:$K,服务费明细!$B48,服务费底表!$H:$H,服务费明细!BM$3) -> 0 | BN48: =SUMIFS(服务费底表!$AC:$AC,服务费底表!$K:$K,服务费明细!$B48,服务费底表!$H:$H,服务费明细!BN$3) -> 0 | BO48: =SUMIFS(服务费底表!$AC:$AC,服务费底表!$K:$K,服务费明细!$B48,服务费底表!$H:$H,服务费明细!BO$3) -> 0 | BQ48: =SUMIFS(服务费底表!$AD:$AD,服务费底表!$K:$K,服务费明细!$B48,服务费底表!$H:$H,服务费明细!BQ$3) -> 0 | BR48: =SUMIFS(服务费底表!$AD:$AD,服务费底表!$K:$K,服务费明细!$B48,服务费底表!$H:$H,服务费明细!BR$3) -> 28320 | BS48: =SUMIFS(服务费底表!$AD:$AD,服务费底表!$K:$K,服务费明细!$B48,服务费底表!$H:$H,服务费明细!BS$3) -> 0 | BT48: =SUMIFS(服务费底表!$AD:$AD,服务费底表!$K:$K,服务费明细!$B48,服务费底表!$H:$H,服务费明细!BT$3) -> 0 | BU48: =SUMIFS(服务费底表!$AD:$AD,服务费底表!$K:$K,服务费明细!$B48,服务费底表!$H:$H,服务费明细!BU$3) -> 0 | BV48: =SUMIFS(服务费底表!$AD:$AD,服务费底表!$K:$K,服务费明细!$B48,服务费底表!$H:$H,服务费明细!BV$3) -> 0 | BW48: =SUMIFS(服务费底表!$AD:$AD,服务费底表!$K:$K,服务费明细!$B48,服务费底表!$H:$H,服务费明细!BW$3) -> 0
B49: A211 | C49: =INDEX(二三级标准!$C:$C,MATCH(服务费明细!$B49,二三级标准!$B:$B,0)) -> 启动拜访 | D49: 0 | E49: =IF($D49=1,_xlfn.IFS(AND(启动中心数>1,试验分期="Ia"),2,OR(试验分期="Ib",试验分期="I期",试验分期="II期",试验分期="III期"),ROUND(启动中心数*20%,0),启动中心数=0,0),0) -> 0 | F49: =INDEX(二三级标准!$G:$G,MATCH(服务费明细!$B49,二三级标准!$B:$B,0)) -> 次 | G49: =AL49 -> 0 | H49: =AM49 -> 0 | I49: =AN49 -> 0 | J49: =AO49 -> 0 | K49: =AP49 -> 0 | L49: =AQ49 -> 0 | M49: =AR49 -> 0 | N49: =AS49 -> 0 | ... AB49: =BG49 -> 0 | AC49: {=SUMPRODUCT(G49:AB49,$G$4:$AB$4)} -> 0 | AD49: =IF(AF49=AC49,TRUE,FALSE) -> TRUE | AE49: =IFERROR(SUMIF(服务费底表!$K:$K,服务费明细!$B49,服务费底表!$AD:$AD)/E49,0) -> 0 | AF49: =E49*AE49 -> 0 | AG49: =IFERROR(SUMIF(服务费底表!$K:$K,服务费明细!$B49,服务费底表!$AG:$AG)/E49,0) -> 0 | AH49: =AG49*E49 -> 0 | AI49: PM现场拜访、支持 | AJ49: =IF(D49=1,AK49/E49,0) -> 0 | AK49: =SUMIF(服务费底表!$K:$K,服务费明细!$B49,服务费底表!$AC:$AC) -> 0 | AL49: =SUMIFS(服务费底表!$AC:$AC,服务费底表!$K:$K,服务费明细!$B49,服务费底表!$T:$T,AL$3) -> 0 | AM49: =SUMIFS(服务费底表!$AC:$AC,服务费底表!$K:$K,服务费明细!$B49,服务费底表!$T:$T,AM$3) -> 0 | AN49: =SUMIFS(服务费底表!$AC:$AC,服务费底表!$K:$K,服务费明细!$B49,服务费底表!$T:$T,AN$3) -> 0 | AO49: =SUMIFS(服务费底表!$AC:$AC,服务费底表!$K:$K,服务费明细!$B49,服务费底表!$T:$T,AO$3) -> 0 | AP49: =SUMIFS(服务费底表!$AC:$AC,服务费底表!$K:$K,服务费明细!$B49,服务费底表!$T:$T,AP$3) -> 0 | AQ49: =SUMIFS(服务费底表!$AC:$AC,服务费底表!$K:$K,服务费明细!$B49,服务费底表!$T:$T,AQ$3) -> 0 | AR49: =SUMIFS(服务费底表!$AC:$AC,服务费底表!$K:$K,服务费明细!$B49,服务费底表!$T:$T,AR$3) -> 0 | AS49: =SUMIFS(服务费底表!$AC:$AC,服务费底表!$K:$K,服务费明细!$B49,服务费底表!$T:$T,AS$3) -> 0 | ... BG49: =SUMIFS(服务费底表!$AC:$AC,服务费底表!$K:$K,服务费明细!$B49,服务费底表!$T:$T,BG$3) -> 0 | BI49: =SUMIFS(服务费底表!$AC:$AC,服务费底表!$K:$K,服务费明细!$B49,服务费底表!$H:$H,服务费明细!BI$3) -> 0 | BJ49: =SUMIFS(服务费底表!$AC:$AC,服务费底表!$K:$K,服务费明细!$B49,服务费底表!$H:$H,服务费明细!BJ$3) -> 0 | BK49: =SUMIFS(服务费底表!$AC:$AC,服务费底表!$K:$K,服务费明细!$B49,服务费底表!$H:$H,服务费明细!BK$3) -> 0 | BL49: =SUMIFS(服务费底表!$AC:$AC,服务费底表!$K:$K,服务费明细!$B49,服务费底表!$H:$H,服务费明细!BL$3) -> 0 | BM49: =SUMIFS(服务费底表!$AC:$AC,服务费底表!$K:$K,服务费明细!$B49,服务费底表!$H:$H,服务费明细!BM$3) -> 0 | BN49: =SUMIFS(服务费底表!$AC:$AC,服务费底表!$K:$K,服务费明细!$B49,服务费底表!$H:$H,服务费明细!BN$3) -> 0 | BO49: =SUMIFS(服务费底表!$AC:$AC,服务费底表!$K:$K,服务费明细!$B49,服务费底表!$H:$H,服务费明细!BO$3) -> 0 | BQ49: =SUMIFS(服务费底表!$AD:$AD,服务费底表!$K:$K,服务费明细!$B49,服务费底表!$H:$H,服务费明细!BQ$3) -> 0 | BR49: =SUMIFS(服务费底表!$AD:$AD,服务费底表!$K:$K,服务费明细!$B49,服务费底表!$H:$H,服务费明细!BR$3) -> 0 | BS49: =SUMIFS(服务费底表!$AD:$AD,服务费底表!$K:$K,服务费明细!$B49,服务费底表!$H:$H,服务费明细!BS$3) -> 0 | BT49: =SUMIFS(服务费底表!$AD:$AD,服务费底表!$K:$K,服务费明细!$B49,服务费底表!$H:$H,服务费明细!BT$3) -> 0 | BU49: =SUMIFS(服务费底表!$AD:$AD,服务费底表!$K:$K,服务费明细!$B49,服务费底表!$H:$H,服务费明细!BU$3) -> 0 | BV49: =SUMIFS(服务费底表!$AD:$AD,服务费底表!$K:$K,服务费明细!$B49,服务费底表!$H:$H,服务费明细!BV$3) -> 0 | BW49: =SUMIFS(服务费底表!$AD:$AD,服务费底表!$K:$K,服务费明细!$B49,服务费底表!$H:$H,服务费明细!BW$3) -> 0
B50: A033 | C50: =INDEX(二三级标准!$C:$C,MATCH(服务费明细!$B50,二三级标准!$B:$B,0)) -> 启动访视_启动会的医学远程支持 | D50: =IF(AND($D$46=1,OR(医学撰写YN=1,医学监查YN=1)),1,0) -> 1 | E50: =IF($D50=1,启动中心数,0) -> 4 | F50: =INDEX(二三级标准!$G:$G,MATCH(服务费明细!$B50,二三级标准!$B:$B,0)) -> 次 | G50: =AL50 -> 0 | H50: =AM50 -> 0 | I50: =AN50 -> 0 | J50: =AO50 -> 0 | K50: =AP50 -> 0 | L50: =AQ50 -> 0 | M50: =AR50 -> 12 | N50: =AS50 -> 0 | ... AB50: =BG50 -> 0 | AC50: {=SUMPRODUCT(G50:AB50,$G$4:$AB$4)} -> 7800 | AD50: =IF(AF50=AC50,TRUE,FALSE) -> TRUE | AE50: =IFERROR(SUMIF(服务费底表!$K:$K,服务费明细!$B50,服务费底表!$AD:$AD)/E50,0) -> 1950 | AF50: =E50*AE50 -> 7800 | AG50: =IFERROR(SUMIF(服务费底表!$K:$K,服务费明细!$B50,服务费底表!$AG:$AG)/E50,0) -> 1950 | AH50: =AG50*E50 -> 7800 | AI50: 线上参会支持。 | AJ50: =IF(D50=1,AK50/E50,0) -> 3 | AK50: =SUMIF(服务费底表!$K:$K,服务费明细!$B50,服务费底表!$AC:$AC) -> 12 | AL50: =SUMIFS(服务费底表!$AC:$AC,服务费底表!$K:$K,服务费明细!$B50,服务费底表!$T:$T,AL$3) -> 0 | AM50: =SUMIFS(服务费底表!$AC:$AC,服务费底表!$K:$K,服务费明细!$B50,服务费底表!$T:$T,AM$3) -> 0 | AN50: =SUMIFS(服务费底表!$AC:$AC,服务费底表!$K:$K,服务费明细!$B50,服务费底表!$T:$T,AN$3) -> 0 | AO50: =SUMIFS(服务费底表!$AC:$AC,服务费底表!$K:$K,服务费明细!$B50,服务费底表!$T:$T,AO$3) -> 0 | AP50: =SUMIFS(服务费底表!$AC:$AC,服务费底表!$K:$K,服务费明细!$B50,服务费底表!$T:$T,AP$3) -> 0 | AQ50: =SUMIFS(服务费底表!$AC:$AC,服务费底表!$K:$K,服务费明细!$B50,服务费底表!$T:$T,AQ$3) -> 0 | AR50: =SUMIFS(服务费底表!$AC:$AC,服务费底表!$K:$K,服务费明细!$B50,服务费底表!$T:$T,AR$3) -> 12 | AS50: =SUMIFS(服务费底表!$AC:$AC,服务费底表!$K:$K,服务费明细!$B50,服务费底表!$T:$T,AS$3) -> 0 | ... BG50: =SUMIFS(服务费底表!$AC:$AC,服务费底表!$K:$K,服务费明细!$B50,服务费底表!$T:$T,BG$3) -> 0 | BI50: =SUMIFS(服务费底表!$AC:$AC,服务费底表!$K:$K,服务费明细!$B50,服务费底表!$H:$H,服务费明细!BI$3) -> 12 | BJ50: =SUMIFS(服务费底表!$AC:$AC,服务费底表!$K:$K,服务费明细!$B50,服务费底表!$H:$H,服务费明细!BJ$3) -> 0 | BK50: =SUMIFS(服务费底表!$AC:$AC,服务费底表!$K:$K,服务费明细!$B50,服务费底表!$H:$H,服务费明细!BK$3) -> 0 | BL50: =SUMIFS(服务费底表!$AC:$AC,服务费底表!$K:$K,服务费明细!$B50,服务费底表!$H:$H,服务费明细!BL$3) -> 0 | BM50: =SUMIFS(服务费底表!$AC:$AC,服务费底表!$K:$K,服务费明细!$B50,服务费底表!$H:$H,服务费明细!BM$3) -> 0 | BN50: =SUMIFS(服务费底表!$AC:$AC,服务费底表!$K:$K,服务费明细!$B50,服务费底表!$H:$H,服务费明细!BN$3) -> 0 | BO50: =SUMIFS(服务费底表!$AC:$AC,服务费底表!$K:$K,服务费明细!$B50,服务费底表!$H:$H,服务费明细!BO$3) -> 0 | BQ50: =SUMIFS(服务费底表!$AD:$AD,服务费底表!$K:$K,服务费明细!$B50,服务费底表!$H:$H,服务费明细!BQ$3) -> 7800 | BR50: =SUMIFS(服务费底表!$AD:$AD,服务费底表!$K:$K,服务费明细!$B50,服务费底表!$H:$H,服务费明细!BR$3) -> 0 | BS50: =SUMIFS(服务费底表!$AD:$AD,服务费底表!$K:$K,服务费明细!$B50,服务费底表!$H:$H,服务费明细!BS$3) -> 0 | BT50: =SUMIFS(服务费底表!$AD:$AD,服务费底表!$K:$K,服务费明细!$B50,服务费底表!$H:$H,服务费明细!BT$3) -> 0 | BU50: =SUMIFS(服务费底表!$AD:$AD,服务费底表!$K:$K,服务费明细!$B50,服务费底表!$H:$H,服务费明细!BU$3) -> 0 | BV50: =SUMIFS(服务费底表!$AD:$AD,服务费底表!$K:$K,服务费明细!$B50,服务费底表!$H:$H,服务费明细!BV$3) -> 0 | BW50: =SUMIFS(服务费底表!$AD:$AD,服务费底表!$K:$K,服务费明细!$B50,服务费底表!$H:$H,服务费明细!BW$3) -> 0
B51: A247 | C51: =INDEX(二三级标准!$C:$C,MATCH(服务费明细!$B51,二三级标准!$B:$B,0)) -> 协助试验参与者招募审核 | D51: 0 | E51: {=IF($D51=1,试验参与者预筛,0)} -> 0 | F51: =INDEX(二三级标准!$G:$G,MATCH(服务费明细!$B51,二三级标准!$B:$B,0)) -> 例 | G51: =AL51 -> 0 | H51: =AM51 -> 0 | I51: =AN51 -> 0 | J51: =AO51 -> 0 | K51: =AP51 -> 0 | L51: =AQ51 -> 0 | M51: =AR51 -> 0 | N51: =AS51 -> 0 | ... AB51: =BG51 -> 0 | AC51: {=SUMPRODUCT(G51:AB51,$G$4:$AB$4)} -> 0 | AD51: =IF(AF51=AC51,TRUE,FALSE) -> TRUE | AE51: =IFERROR(SUMIF(服务费底表!$K:$K,服务费明细!$B51,服务费底表!$AD:$AD)/E51,0) -> 0 | AF51: =E51*AE51 -> 0 | AG51: =IFERROR(SUMIF(服务费底表!$K:$K,服务费明细!$B51,服务费底表!$AG:$AG)/E51,0) -> 0 | AH51: =AG51*E51 -> 0 | AJ51: =IF(D51=1,AK51/E51,0) -> 0 | AK51: =SUMIF(服务费底表!$K:$K,服务费明细!$B51,服务费底表!$AC:$AC) -> 0 | AL51: =SUMIFS(服务费底表!$AC:$AC,服务费底表!$K:$K,服务费明细!$B51,服务费底表!$T:$T,AL$3) -> 0 | AM51: =SUMIFS(服务费底表!$AC:$AC,服务费底表!$K:$K,服务费明细!$B51,服务费底表!$T:$T,AM$3) -> 0 | AN51: =SUMIFS(服务费底表!$AC:$AC,服务费底表!$K:$K,服务费明细!$B51,服务费底表!$T:$T,AN$3) -> 0 | AO51: =SUMIFS(服务费底表!$AC:$AC,服务费底表!$K:$K,服务费明细!$B51,服务费底表!$T:$T,AO$3) -> 0 | AP51: =SUMIFS(服务费底表!$AC:$AC,服务费底表!$K:$K,服务费明细!$B51,服务费底表!$T:$T,AP$3) -> 0 | AQ51: =SUMIFS(服务费底表!$AC:$AC,服务费底表!$K:$K,服务费明细!$B51,服务费底表!$T:$T,AQ$3) -> 0 | AR51: =SUMIFS(服务费底表!$AC:$AC,服务费底表!$K:$K,服务费明细!$B51,服务费底表!$T:$T,AR$3) -> 0 | AS51: =SUMIFS(服务费底表!$AC:$AC,服务费底表!$K:$K,服务费明细!$B51,服务费底表!$T:$T,AS$3) -> 0 | ... BG51: =SUMIFS(服务费底表!$AC:$AC,服务费底表!$K:$K,服务费明细!$B51,服务费底表!$T:$T,BG$3) -> 0
B52: A034 | C52: =INDEX(二三级标准!$C:$C,MATCH(服务费明细!$B52,二三级标准!$B:$B,0)) -> 常规监查访视 | D52: =IF($D$46=1,1,0) -> 1 | E52: =IF($D52=1,入组期IMV次数+治疗期IMV次数+随访期IMV次数+长随访期IMV次数,0) -> 52 | F52: =INDEX(二三级标准!$G:$G,MATCH(服务费明细!$B52,二三级标准!$B:$B,0)) -> 次 | G52: =AL52 -> 988 | H52: =AM52 -> 0 | I52: =AN52 -> 104 | J52: =AO52 -> 0 | K52: =AP52 -> 0 | L52: =AQ52 -> 0 | M52: =AR52 -> 0 | N52: =AS52 -> 0 | ... AB52: =BG52 -> 0 | AC52: {=SUMPRODUCT(G52:AB52,$G$4:$AB$4)} -> 403520 | AD52: =IF(AF52=AC52,TRUE,FALSE) -> TRUE | AE52: =IFERROR(SUMIF(服务费底表!$K:$K,服务费明细!$B52,服务费底表!$AD:$AD)/E52,0) -> 7760 | AF52: =E52*AE52 -> 403520 | AG52: =IFERROR(SUMIF(服务费底表!$K:$K,服务费明细!$B52,服务费底表!$AG:$AG)/E52,0) -> 7760 | AH52: =AG52*E52 -> 403520 | AI52: 准备，差旅，现场访视，报告和跟进。 | AJ52: =IF(D52=1,AK52/E52,0) -> 21 | AK52: =SUMIF(服务费底表!$K:$K,服务费明细!$B52,服务费底表!$AC:$AC) -> 1092 | AL52: =SUMIFS(服务费底表!$AC:$AC,服务费底表!$K:$K,服务费明细!$B52,服务费底表!$T:$T,AL$3) -> 988 | AM52: =SUMIFS(服务费底表!$AC:$AC,服务费底表!$K:$K,服务费明细!$B52,服务费底表!$T:$T,AM$3) -> 0 | AN52: =SUMIFS(服务费底表!$AC:$AC,服务费底表!$K:$K,服务费明细!$B52,服务费底表!$T:$T,AN$3) -> 104 | AO52: =SUMIFS(服务费底表!$AC:$AC,服务费底表!$K:$K,服务费明细!$B52,服务费底表!$T:$T,AO$3) -> 0 | AP52: =SUMIFS(服务费底表!$AC:$AC,服务费底表!$K:$K,服务费明细!$B52,服务费底表!$T:$T,AP$3) -> 0 | AQ52: =SUMIFS(服务费底表!$AC:$AC,服务费底表!$K:$K,服务费明细!$B52,服务费底表!$T:$T,AQ$3) -> 0 | AR52: =SUMIFS(服务费底表!$AC:$AC,服务费底表!$K:$K,服务费明细!$B52,服务费底表!$T:$T,AR$3) -> 0 | AS52: =SUMIFS(服务费底表!$AC:$AC,服务费底表!$K:$K,服务费明细!$B52,服务费底表!$T:$T,AS$3) -> 0 | ... BG52: =SUMIFS(服务费底表!$AC:$AC,服务费底表!$K:$K,服务费明细!$B52,服务费底表!$T:$T,BG$3) -> 0 | BI52: =SUMIFS(服务费底表!$AC:$AC,服务费底表!$K:$K,服务费明细!$B52,服务费底表!$H:$H,服务费明细!BI$3) -> 0 | BJ52: =SUMIFS(服务费底表!$AC:$AC,服务费底表!$K:$K,服务费明细!$B52,服务费底表!$H:$H,服务费明细!BJ$3) -> 1092 | BK52: =SUMIFS(服务费底表!$AC:$AC,服务费底表!$K:$K,服务费明细!$B52,服务费底表!$H:$H,服务费明细!BK$3) -> 0 | BL52: =SUMIFS(服务费底表!$AC:$AC,服务费底表!$K:$K,服务费明细!$B52,服务费底表!$H:$H,服务费明细!BL$3) -> 0 | BM52: =SUMIFS(服务费底表!$AC:$AC,服务费底表!$K:$K,服务费明细!$B52,服务费底表!$H:$H,服务费明细!BM$3) -> 0 | BN52: =SUMIFS(服务费底表!$AC:$AC,服务费底表!$K:$K,服务费明细!$B52,服务费底表!$H:$H,服务费明细!BN$3) -> 0 | BO52: =SUMIFS(服务费底表!$AC:$AC,服务费底表!$K:$K,服务费明细!$B52,服务费底表!$H:$H,服务费明细!BO$3) -> 0 | BQ52: =SUMIFS(服务费底表!$AD:$AD,服务费底表!$K:$K,服务费明细!$B52,服务费底表!$H:$H,服务费明细!BQ$3) -> 0 | BR52: =SUMIFS(服务费底表!$AD:$AD,服务费底表!$K:$K,服务费明细!$B52,服务费底表!$H:$H,服务费明细!BR$3) -> 403520 | BS52: =SUMIFS(服务费底表!$AD:$AD,服务费底表!$K:$K,服务费明细!$B52,服务费底表!$H:$H,服务费明细!BS$3) -> 0 | BT52: =SUMIFS(服务费底表!$AD:$AD,服务费底表!$K:$K,服务费明细!$B52,服务费底表!$H:$H,服务费明细!BT$3) -> 0 | BU52: =SUMIFS(服务费底表!$AD:$AD,服务费底表!$K:$K,服务费明细!$B52,服务费底表!$H:$H,服务费明细!BU$3) -> 0 | BV52: =SUMIFS(服务费底表!$AD:$AD,服务费底表!$K:$K,服务费明细!$B52,服务费底表!$H:$H,服务费明细!BV$3) -> 0 | BW52: =SUMIFS(服务费底表!$AD:$AD,服务费底表!$K:$K,服务费明细!$B52,服务费底表!$H:$H,服务费明细!BW$3) -> 0
B53: A035 | C53: =INDEX(二三级标准!$C:$C,MATCH(服务费明细!$B53,二三级标准!$B:$B,0)) -> 计划外访视 | D53: =IF($D$46=1,1,0) -> 1 | E53: =IF($D53=1,计划外访视次数,0) -> 4 | F53: =INDEX(二三级标准!$G:$G,MATCH(服务费明细!$B53,二三级标准!$B:$B,0)) -> 次 | G53: =AL53 -> 60 | H53: =AM53 -> 0 | I53: =AN53 -> 8 | J53: =AO53 -> 0 | K53: =AP53 -> 0 | L53: =AQ53 -> 0 | M53: =AR53 -> 0 | N53: =AS53 -> 0 | ... AB53: =BG53 -> 0 | AC53: {=SUMPRODUCT(G53:AB53,$G$4:$AB$4)} -> 25600 | AD53: =IF(AF53=AC53,TRUE,FALSE) -> TRUE | AE53: =IFERROR(SUMIF(服务费底表!$K:$K,服务费明细!$B53,服务费底表!$AD:$AD)/E53,0) -> 6400 | AF53: =E53*AE53 -> 25600 | AG53: =IFERROR(SUMIF(服务费底表!$K:$K,服务费明细!$B53,服务费底表!$AG:$AG)/E53,0) -> 6400 | AH53: =AG53*E53 -> 25600 | AI53: 准备，差旅，现场访视，报告和跟进。 | AJ53: =IF(D53=1,AK53/E53,0) -> 17 | AK53: =SUMIF(服务费底表!$K:$K,服务费明细!$B53,服务费底表!$AC:$AC) -> 68 | AL53: =SUMIFS(服务费底表!$AC:$AC,服务费底表!$K:$K,服务费明细!$B53,服务费底表!$T:$T,AL$3) -> 60 | AM53: =SUMIFS(服务费底表!$AC:$AC,服务费底表!$K:$K,服务费明细!$B53,服务费底表!$T:$T,AM$3) -> 0 | AN53: =SUMIFS(服务费底表!$AC:$AC,服务费底表!$K:$K,服务费明细!$B53,服务费底表!$T:$T,AN$3) -> 8 | AO53: =SUMIFS(服务费底表!$AC:$AC,服务费底表!$K:$K,服务费明细!$B53,服务费底表!$T:$T,AO$3) -> 0 | AP53: =SUMIFS(服务费底表!$AC:$AC,服务费底表!$K:$K,服务费明细!$B53,服务费底表!$T:$T,AP$3) -> 0 | AQ53: =SUMIFS(服务费底表!$AC:$AC,服务费底表!$K:$K,服务费明细!$B53,服务费底表!$T:$T,AQ$3) -> 0 | AR53: =SUMIFS(服务费底表!$AC:$AC,服务费底表!$K:$K,服务费明细!$B53,服务费底表!$T:$T,AR$3) -> 0 | AS53: =SUMIFS(服务费底表!$AC:$AC,服务费底表!$K:$K,服务费明细!$B53,服务费底表!$T:$T,AS$3) -> 0 | ... BG53: =SUMIFS(服务费底表!$AC:$AC,服务费底表!$K:$K,服务费明细!$B53,服务费底表!$T:$T,BG$3) -> 0 | BI53: =SUMIFS(服务费底表!$AC:$AC,服务费底表!$K:$K,服务费明细!$B53,服务费底表!$H:$H,服务费明细!BI$3) -> 0 | BJ53: =SUMIFS(服务费底表!$AC:$AC,服务费底表!$K:$K,服务费明细!$B53,服务费底表!$H:$H,服务费明细!BJ$3) -> 68 | BK53: =SUMIFS(服务费底表!$AC:$AC,服务费底表!$K:$K,服务费明细!$B53,服务费底表!$H:$H,服务费明细!BK$3) -> 0 | BL53: =SUMIFS(服务费底表!$AC:$AC,服务费底表!$K:$K,服务费明细!$B53,服务费底表!$H:$H,服务费明细!BL$3) -> 0 | BM53: =SUMIFS(服务费底表!$AC:$AC,服务费底表!$K:$K,服务费明细!$B53,服务费底表!$H:$H,服务费明细!BM$3) -> 0 | BN53: =SUMIFS(服务费底表!$AC:$AC,服务费底表!$K:$K,服务费明细!$B53,服务费底表!$H:$H,服务费明细!BN$3) -> 0 | BO53: =SUMIFS(服务费底表!$AC:$AC,服务费底表!$K:$K,服务费明细!$B53,服务费底表!$H:$H,服务费明细!BO$3) -> 0 | BQ53: =SUMIFS(服务费底表!$AD:$AD,服务费底表!$K:$K,服务费明细!$B53,服务费底表!$H:$H,服务费明细!BQ$3) -> 0 | BR53: =SUMIFS(服务费底表!$AD:$AD,服务费底表!$K:$K,服务费明细!$B53,服务费底表!$H:$H,服务费明细!BR$3) -> 25600 | BS53: =SUMIFS(服务费底表!$AD:$AD,服务费底表!$K:$K,服务费明细!$B53,服务费底表!$H:$H,服务费明细!BS$3) -> 0 | BT53: =SUMIFS(服务费底表!$AD:$AD,服务费底表!$K:$K,服务费明细!$B53,服务费底表!$H:$H,服务费明细!BT$3) -> 0 | BU53: =SUMIFS(服务费底表!$AD:$AD,服务费底表!$K:$K,服务费明细!$B53,服务费底表!$H:$H,服务费明细!BU$3) -> 0 | BV53: =SUMIFS(服务费底表!$AD:$AD,服务费底表!$K:$K,服务费明细!$B53,服务费底表!$H:$H,服务费明细!BV$3) -> 0 | BW53: =SUMIFS(服务费底表!$AD:$AD,服务费底表!$K:$K,服务费明细!$B53,服务费底表!$H:$H,服务费明细!BW$3) -> 0
B54: A036 | C54: =INDEX(二三级标准!$C:$C,MATCH(服务费明细!$B54,二三级标准!$B:$B,0)) -> 协同访视 | D54: =IF($D$46=1,1,0) -> 1 | E54: =IF($D54=1,协同访视次数,0) -> 2 | F54: =INDEX(二三级标准!$G:$G,MATCH(服务费明细!$B54,二三级标准!$B:$B,0)) -> 次 | G54: =AL54 -> 0 | H54: =AM54 -> 0 | I54: =AN54 -> 30 | J54: =AO54 -> 4 | K54: =AP54 -> 0 | L54: =AQ54 -> 0 | M54: =AR54 -> 0 | N54: =AS54 -> 0 | ... AB54: =BG54 -> 0 | AC54: {=SUMPRODUCT(G54:AB54,$G$4:$AB$4)} -> 22700 | AD54: =IF(AF54=AC54,TRUE,FALSE) -> TRUE | AE54: =IFERROR(SUMIF(服务费底表!$K:$K,服务费明细!$B54,服务费底表!$AD:$AD)/E54,0) -> 11350 | AF54: =E54*AE54 -> 22700 | AG54: =IFERROR(SUMIF(服务费底表!$K:$K,服务费明细!$B54,服务费底表!$AG:$AG)/E54,0) -> 11350 | AH54: =AG54*E54 -> 22700 | AI54: 准备，差旅，现场访视，报告和跟进。 | AJ54: =IF(D54=1,AK54/E54,0) -> 17 | AK54: =SUMIF(服务费底表!$K:$K,服务费明细!$B54,服务费底表!$AC:$AC) -> 34 | AL54: =SUMIFS(服务费底表!$AC:$AC,服务费底表!$K:$K,服务费明细!$B54,服务费底表!$T:$T,AL$3) -> 0 | AM54: =SUMIFS(服务费底表!$AC:$AC,服务费底表!$K:$K,服务费明细!$B54,服务费底表!$T:$T,AM$3) -> 0 | AN54: =SUMIFS(服务费底表!$AC:$AC,服务费底表!$K:$K,服务费明细!$B54,服务费底表!$T:$T,AN$3) -> 30 | AO54: =SUMIFS(服务费底表!$AC:$AC,服务费底表!$K:$K,服务费明细!$B54,服务费底表!$T:$T,AO$3) -> 4 | AP54: =SUMIFS(服务费底表!$AC:$AC,服务费底表!$K:$K,服务费明细!$B54,服务费底表!$T:$T,AP$3) -> 0 | AQ54: =SUMIFS(服务费底表!$AC:$AC,服务费底表!$K:$K,服务费明细!$B54,服务费底表!$T:$T,AQ$3) -> 0 | AR54: =SUMIFS(服务费底表!$AC:$AC,服务费底表!$K:$K,服务费明细!$B54,服务费底表!$T:$T,AR$3) -> 0 | AS54: =SUMIFS(服务费底表!$AC:$AC,服务费底表!$K:$K,服务费明细!$B54,服务费底表!$T:$T,AS$3) -> 0 | ... BG54: =SUMIFS(服务费底表!$AC:$AC,服务费底表!$K:$K,服务费明细!$B54,服务费底表!$T:$T,BG$3) -> 0 | BI54: =SUMIFS(服务费底表!$AC:$AC,服务费底表!$K:$K,服务费明细!$B54,服务费底表!$H:$H,服务费明细!BI$3) -> 0 | BJ54: =SUMIFS(服务费底表!$AC:$AC,服务费底表!$K:$K,服务费明细!$B54,服务费底表!$H:$H,服务费明细!BJ$3) -> 34 | BK54: =SUMIFS(服务费底表!$AC:$AC,服务费底表!$K:$K,服务费明细!$B54,服务费底表!$H:$H,服务费明细!BK$3) -> 0 | BL54: =SUMIFS(服务费底表!$AC:$AC,服务费底表!$K:$K,服务费明细!$B54,服务费底表!$H:$H,服务费明细!BL$3) -> 0 | BM54: =SUMIFS(服务费底表!$AC:$AC,服务费底表!$K:$K,服务费明细!$B54,服务费底表!$H:$H,服务费明细!BM$3) -> 0 | BN54: =SUMIFS(服务费底表!$AC:$AC,服务费底表!$K:$K,服务费明细!$B54,服务费底表!$H:$H,服务费明细!BN$3) -> 0 | BO54: =SUMIFS(服务费底表!$AC:$AC,服务费底表!$K:$K,服务费明细!$B54,服务费底表!$H:$H,服务费明细!BO$3) -> 0 | BQ54: =SUMIFS(服务费底表!$AD:$AD,服务费底表!$K:$K,服务费明细!$B54,服务费底表!$H:$H,服务费明细!BQ$3) -> 0 | BR54: =SUMIFS(服务费底表!$AD:$AD,服务费底表!$K:$K,服务费明细!$B54,服务费底表!$H:$H,服务费明细!BR$3) -> 22700 | BS54: =SUMIFS(服务费底表!$AD:$AD,服务费底表!$K:$K,服务费明细!$B54,服务费底表!$H:$H,服务费明细!BS$3) -> 0 | BT54: =SUMIFS(服务费底表!$AD:$AD,服务费底表!$K:$K,服务费明细!$B54,服务费底表!$H:$H,服务费明细!BT$3) -> 0 | BU54: =SUMIFS(服务费底表!$AD:$AD,服务费底表!$K:$K,服务费明细!$B54,服务费底表!$H:$H,服务费明细!BU$3) -> 0 | BV54: =SUMIFS(服务费底表!$AD:$AD,服务费底表!$K:$K,服务费明细!$B54,服务费底表!$H:$H,服务费明细!BV$3) -> 0 | BW54: =SUMIFS(服务费底表!$AD:$AD,服务费底表!$K:$K,服务费明细!$B54,服务费底表!$H:$H,服务费明细!BW$3) -> 0
B55: A037 | C55: =INDEX(二三级标准!$C:$C,MATCH(服务费明细!$B55,二三级标准!$B:$B,0)) -> 远程访视/电话访视 | D55: 0 | E55: =IF($D55=1,电话访视次数,0) -> 0 | F55: =INDEX(二三级标准!$G:$G,MATCH(服务费明细!$B55,二三级标准!$B:$B,0)) -> 次 | G55: =AL55 -> 0 | H55: =AM55 -> 0 | I55: =AN55 -> 0 | J55: =AO55 -> 0 | K55: =AP55 -> 0 | L55: =AQ55 -> 0 | M55: =AR55 -> 0 | N55: =AS55 -> 0 | ... AB55: =BG55 -> 0 | AC55: {=SUMPRODUCT(G55:AB55,$G$4:$AB$4)} -> 0 | AD55: =IF(AF55=AC55,TRUE,FALSE) -> TRUE | AE55: =IFERROR(SUMIF(服务费底表!$K:$K,服务费明细!$B55,服务费底表!$AD:$AD)/E55,0) -> 0 | AF55: =E55*AE55 -> 0 | AG55: =IFERROR(SUMIF(服务费底表!$K:$K,服务费明细!$B55,服务费底表!$AG:$AG)/E55,0) -> 0 | AH55: =AG55*E55 -> 0 | AI55: 准备，远程监查，报告和跟进。 | AJ55: =IF(D55=1,AK55/E55,0) -> 0 | AK55: =SUMIF(服务费底表!$K:$K,服务费明细!$B55,服务费底表!$AC:$AC) -> 0 | AL55: =SUMIFS(服务费底表!$AC:$AC,服务费底表!$K:$K,服务费明细!$B55,服务费底表!$T:$T,AL$3) -> 0 | AM55: =SUMIFS(服务费底表!$AC:$AC,服务费底表!$K:$K,服务费明细!$B55,服务费底表!$T:$T,AM$3) -> 0 | AN55: =SUMIFS(服务费底表!$AC:$AC,服务费底表!$K:$K,服务费明细!$B55,服务费底表!$T:$T,AN$3) -> 0 | AO55: =SUMIFS(服务费底表!$AC:$AC,服务费底表!$K:$K,服务费明细!$B55,服务费底表!$T:$T,AO$3) -> 0 | AP55: =SUMIFS(服务费底表!$AC:$AC,服务费底表!$K:$K,服务费明细!$B55,服务费底表!$T:$T,AP$3) -> 0 | AQ55: =SUMIFS(服务费底表!$AC:$AC,服务费底表!$K:$K,服务费明细!$B55,服务费底表!$T:$T,AQ$3) -> 0 | AR55: =SUMIFS(服务费底表!$AC:$AC,服务费底表!$K:$K,服务费明细!$B55,服务费底表!$T:$T,AR$3) -> 0 | AS55: =SUMIFS(服务费底表!$AC:$AC,服务费底表!$K:$K,服务费明细!$B55,服务费底表!$T:$T,AS$3) -> 0 | ... BG55: =SUMIFS(服务费底表!$AC:$AC,服务费底表!$K:$K,服务费明细!$B55,服务费底表!$T:$T,BG$3) -> 0 | BI55: =SUMIFS(服务费底表!$AC:$AC,服务费底表!$K:$K,服务费明细!$B55,服务费底表!$H:$H,服务费明细!BI$3) -> 0 | BJ55: =SUMIFS(服务费底表!$AC:$AC,服务费底表!$K:$K,服务费明细!$B55,服务费底表!$H:$H,服务费明细!BJ$3) -> 0 | BK55: =SUMIFS(服务费底表!$AC:$AC,服务费底表!$K:$K,服务费明细!$B55,服务费底表!$H:$H,服务费明细!BK$3) -> 0 | BL55: =SUMIFS(服务费底表!$AC:$AC,服务费底表!$K:$K,服务费明细!$B55,服务费底表!$H:$H,服务费明细!BL$3) -> 0 | BM55: =SUMIFS(服务费底表!$AC:$AC,服务费底表!$K:$K,服务费明细!$B55,服务费底表!$H:$H,服务费明细!BM$3) -> 0 | BN55: =SUMIFS(服务费底表!$AC:$AC,服务费底表!$K:$K,服务费明细!$B55,服务费底表!$H:$H,服务费明细!BN$3) -> 0 | BO55: =SUMIFS(服务费底表!$AC:$AC,服务费底表!$K:$K,服务费明细!$B55,服务费底表!$H:$H,服务费明细!BO$3) -> 0 | BQ55: =SUMIFS(服务费底表!$AD:$AD,服务费底表!$K:$K,服务费明细!$B55,服务费底表!$H:$H,服务费明细!BQ$3) -> 0 | BR55: =SUMIFS(服务费底表!$AD:$AD,服务费底表!$K:$K,服务费明细!$B55,服务费底表!$H:$H,服务费明细!BR$3) -> 0 | BS55: =SUMIFS(服务费底表!$AD:$AD,服务费底表!$K:$K,服务费明细!$B55,服务费底表!$H:$H,服务费明细!BS$3) -> 0 | BT55: =SUMIFS(服务费底表!$AD:$AD,服务费底表!$K:$K,服务费明细!$B55,服务费底表!$H:$H,服务费明细!BT$3) -> 0 | BU55: =SUMIFS(服务费底表!$AD:$AD,服务费底表!$K:$K,服务费明细!$B55,服务费底表!$H:$H,服务费明细!BU$3) -> 0 | BV55: =SUMIFS(服务费底表!$AD:$AD,服务费底表!$K:$K,服务费明细!$B55,服务费底表!$H:$H,服务费明细!BV$3) -> 0 | BW55: =SUMIFS(服务费底表!$AD:$AD,服务费底表!$K:$K,服务费明细!$B55,服务费底表!$H:$H,服务费明细!BW$3) -> 0
B56: A038 | C56: =INDEX(二三级标准!$C:$C,MATCH(服务费明细!$B56,二三级标准!$B:$B,0)) -> 质控访视 | D56: =IF($D$46=1,1,0) -> 1 | E56: =IF($D56=1,质控访视次数,0) -> 2 | F56: =INDEX(二三级标准!$G:$G,MATCH(服务费明细!$B56,二三级标准!$B:$B,0)) -> 次 | G56: =AL56 -> 0 | H56: =AM56 -> 0 | I56: =AN56 -> 0 | J56: =AO56 -> 4 | K56: =AP56 -> 46 | L56: =AQ56 -> 0 | M56: =AR56 -> 0 | N56: =AS56 -> 0 | ... AB56: =BG56 -> 0 | AC56: {=SUMPRODUCT(G56:AB56,$G$4:$AB$4)} -> 30800 | AD56: =IF(AF56=AC56,TRUE,FALSE) -> TRUE | AE56: =IFERROR(SUMIF(服务费底表!$K:$K,服务费明细!$B56,服务费底表!$AD:$AD)/E56,0) -> 15400 | AF56: =E56*AE56 -> 30800 | AG56: =IFERROR(SUMIF(服务费底表!$K:$K,服务费明细!$B56,服务费底表!$AG:$AG)/E56,0) -> 15400 | AH56: =AG56*E56 -> 30800 | AI56: 准备，差旅，现场访视，报告和跟进。 | AJ56: =IF(D56=1,AK56/E56,0) -> 25 | AK56: =SUMIF(服务费底表!$K:$K,服务费明细!$B56,服务费底表!$AC:$AC) -> 50 | AL56: =SUMIFS(服务费底表!$AC:$AC,服务费底表!$K:$K,服务费明细!$B56,服务费底表!$T:$T,AL$3) -> 0 | AM56: =SUMIFS(服务费底表!$AC:$AC,服务费底表!$K:$K,服务费明细!$B56,服务费底表!$T:$T,AM$3) -> 0 | AN56: =SUMIFS(服务费底表!$AC:$AC,服务费底表!$K:$K,服务费明细!$B56,服务费底表!$T:$T,AN$3) -> 0 | AO56: =SUMIFS(服务费底表!$AC:$AC,服务费底表!$K:$K,服务费明细!$B56,服务费底表!$T:$T,AO$3) -> 4 | AP56: =SUMIFS(服务费底表!$AC:$AC,服务费底表!$K:$K,服务费明细!$B56,服务费底表!$T:$T,AP$3) -> 46 | AQ56: =SUMIFS(服务费底表!$AC:$AC,服务费底表!$K:$K,服务费明细!$B56,服务费底表!$T:$T,AQ$3) -> 0 | AR56: =SUMIFS(服务费底表!$AC:$AC,服务费底表!$K:$K,服务费明细!$B56,服务费底表!$T:$T,AR$3) -> 0 | AS56: =SUMIFS(服务费底表!$AC:$AC,服务费底表!$K:$K,服务费明细!$B56,服务费底表!$T:$T,AS$3) -> 0 | ... BG56: =SUMIFS(服务费底表!$AC:$AC,服务费底表!$K:$K,服务费明细!$B56,服务费底表!$T:$T,BG$3) -> 0 | BI56: =SUMIFS(服务费底表!$AC:$AC,服务费底表!$K:$K,服务费明细!$B56,服务费底表!$H:$H,服务费明细!BI$3) -> 0 | BJ56: =SUMIFS(服务费底表!$AC:$AC,服务费底表!$K:$K,服务费明细!$B56,服务费底表!$H:$H,服务费明细!BJ$3) -> 50 | BK56: =SUMIFS(服务费底表!$AC:$AC,服务费底表!$K:$K,服务费明细!$B56,服务费底表!$H:$H,服务费明细!BK$3) -> 0 | BL56: =SUMIFS(服务费底表!$AC:$AC,服务费底表!$K:$K,服务费明细!$B56,服务费底表!$H:$H,服务费明细!BL$3) -> 0 | BM56: =SUMIFS(服务费底表!$AC:$AC,服务费底表!$K:$K,服务费明细!$B56,服务费底表!$H:$H,服务费明细!BM$3) -> 0 | BN56: =SUMIFS(服务费底表!$AC:$AC,服务费底表!$K:$K,服务费明细!$B56,服务费底表!$H:$H,服务费明细!BN$3) -> 0 | BO56: =SUMIFS(服务费底表!$AC:$AC,服务费底表!$K:$K,服务费明细!$B56,服务费底表!$H:$H,服务费明细!BO$3) -> 0 | BQ56: =SUMIFS(服务费底表!$AD:$AD,服务费底表!$K:$K,服务费明细!$B56,服务费底表!$H:$H,服务费明细!BQ$3) -> 0 | BR56: =SUMIFS(服务费底表!$AD:$AD,服务费底表!$K:$K,服务费明细!$B56,服务费底表!$H:$H,服务费明细!BR$3) -> 30800 | BS56: =SUMIFS(服务费底表!$AD:$AD,服务费底表!$K:$K,服务费明细!$B56,服务费底表!$H:$H,服务费明细!BS$3) -> 0 | BT56: =SUMIFS(服务费底表!$AD:$AD,服务费底表!$K:$K,服务费明细!$B56,服务费底表!$H:$H,服务费明细!BT$3) -> 0 | BU56: =SUMIFS(服务费底表!$AD:$AD,服务费底表!$K:$K,服务费明细!$B56,服务费底表!$H:$H,服务费明细!BU$3) -> 0 | BV56: =SUMIFS(服务费底表!$AD:$AD,服务费底表!$K:$K,服务费明细!$B56,服务费底表!$H:$H,服务费明细!BV$3) -> 0 | BW56: =SUMIFS(服务费底表!$AD:$AD,服务费底表!$K:$K,服务费明细!$B56,服务费底表!$H:$H,服务费明细!BW$3) -> 0
B57: A039 | C57: =INDEX(二三级标准!$C:$C,MATCH(服务费明细!$B57,二三级标准!$B:$B,0)) -> 稽查陪同 | D57: 0 | E57: =IF($D57=1,ROUNDUP(启动中心数*20%,0),0) -> 0 | F57: =INDEX(二三级标准!$G:$G,MATCH(服务费明细!$B57,二三级标准!$B:$B,0)) -> 次 | G57: =AL57 -> 0 | H57: =AM57 -> 0 | I57: =AN57 -> 0 | J57: =AO57 -> 0 | K57: =AP57 -> 0 | L57: =AQ57 -> 0 | M57: =AR57 -> 0 | N57: =AS57 -> 0 | ... AB57: =BG57 -> 0 | AC57: {=SUMPRODUCT(G57:AB57,$G$4:$AB$4)} -> 0 | AD57: =IF(AF57=AC57,TRUE,FALSE) -> TRUE | AE57: =IFERROR(SUMIF(服务费底表!$K:$K,服务费明细!$B57,服务费底表!$AD:$AD)/E57,0) -> 0 | AF57: =E57*AE57 -> 0 | AG57: =IFERROR(SUMIF(服务费底表!$K:$K,服务费明细!$B57,服务费底表!$AG:$AG)/E57,0) -> 0 | AH57: =AG57*E57 -> 0 | AJ57: =IF(D57=1,AK57/E57,0) -> 0 | AK57: =SUMIF(服务费底表!$K:$K,服务费明细!$B57,服务费底表!$AC:$AC) -> 0 | AL57: =SUMIFS(服务费底表!$AC:$AC,服务费底表!$K:$K,服务费明细!$B57,服务费底表!$T:$T,AL$3) -> 0 | AM57: =SUMIFS(服务费底表!$AC:$AC,服务费底表!$K:$K,服务费明细!$B57,服务费底表!$T:$T,AM$3) -> 0 | AN57: =SUMIFS(服务费底表!$AC:$AC,服务费底表!$K:$K,服务费明细!$B57,服务费底表!$T:$T,AN$3) -> 0 | AO57: =SUMIFS(服务费底表!$AC:$AC,服务费底表!$K:$K,服务费明细!$B57,服务费底表!$T:$T,AO$3) -> 0 | AP57: =SUMIFS(服务费底表!$AC:$AC,服务费底表!$K:$K,服务费明细!$B57,服务费底表!$T:$T,AP$3) -> 0 | AQ57: =SUMIFS(服务费底表!$AC:$AC,服务费底表!$K:$K,服务费明细!$B57,服务费底表!$T:$T,AQ$3) -> 0 | AR57: =SUMIFS(服务费底表!$AC:$AC,服务费底表!$K:$K,服务费明细!$B57,服务费底表!$T:$T,AR$3) -> 0 | AS57: =SUMIFS(服务费底表!$AC:$AC,服务费底表!$K:$K,服务费明细!$B57,服务费底表!$T:$T,AS$3) -> 0 | ... BG57: =SUMIFS(服务费底表!$AC:$AC,服务费底表!$K:$K,服务费明细!$B57,服务费底表!$T:$T,BG$3) -> 0 | BI57: =SUMIFS(服务费底表!$AC:$AC,服务费底表!$K:$K,服务费明细!$B57,服务费底表!$H:$H,服务费明细!BI$3) -> 0 | BJ57: =SUMIFS(服务费底表!$AC:$AC,服务费底表!$K:$K,服务费明细!$B57,服务费底表!$H:$H,服务费明细!BJ$3) -> 0 | BK57: =SUMIFS(服务费底表!$AC:$AC,服务费底表!$K:$K,服务费明细!$B57,服务费底表!$H:$H,服务费明细!BK$3) -> 0 | BL57: =SUMIFS(服务费底表!$AC:$AC,服务费底表!$K:$K,服务费明细!$B57,服务费底表!$H:$H,服务费明细!BL$3) -> 0 | BM57: =SUMIFS(服务费底表!$AC:$AC,服务费底表!$K:$K,服务费明细!$B57,服务费底表!$H:$H,服务费明细!BM$3) -> 0 | BN57: =SUMIFS(服务费底表!$AC:$AC,服务费底表!$K:$K,服务费明细!$B57,服务费底表!$H:$H,服务费明细!BN$3) -> 0 | BO57: =SUMIFS(服务费底表!$AC:$AC,服务费底表!$K:$K,服务费明细!$B57,服务费底表!$H:$H,服务费明细!BO$3) -> 0 | BQ57: =SUMIFS(服务费底表!$AD:$AD,服务费底表!$K:$K,服务费明细!$B57,服务费底表!$H:$H,服务费明细!BQ$3) -> 0 | BR57: =SUMIFS(服务费底表!$AD:$AD,服务费底表!$K:$K,服务费明细!$B57,服务费底表!$H:$H,服务费明细!BR$3) -> 0 | BS57: =SUMIFS(服务费底表!$AD:$AD,服务费底表!$K:$K,服务费明细!$B57,服务费底表!$H:$H,服务费明细!BS$3) -> 0 | BT57: =SUMIFS(服务费底表!$AD:$AD,服务费底表!$K:$K,服务费明细!$B57,服务费底表!$H:$H,服务费明细!BT$3) -> 0 | BU57: =SUMIFS(服务费底表!$AD:$AD,服务费底表!$K:$K,服务费明细!$B57,服务费底表!$H:$H,服务费明细!BU$3) -> 0 | BV57: =SUMIFS(服务费底表!$AD:$AD,服务费底表!$K:$K,服务费明细!$B57,服务费底表!$H:$H,服务费明细!BV$3) -> 0 | BW57: =SUMIFS(服务费底表!$AD:$AD,服务费底表!$K:$K,服务费明细!$B57,服务费底表!$H:$H,服务费明细!BW$3) -> 0
B58: A040 | C58: =INDEX(二三级标准!$C:$C,MATCH(服务费明细!$B58,二三级标准!$B:$B,0)) -> 中心安全性报告管理 | D58: =IF($D$46=1,1,0) -> 1 | E58: =IF($D58=1,ROUNDUP(入组试验参与者数*SAE发生率,0),0) -> 9 | F58: =INDEX(二三级标准!$G:$G,MATCH(服务费明细!$B58,二三级标准!$B:$B,0)) -> 个 | G58: =AL58 -> 36 | H58: =AM58 -> 0 | I58: =AN58 -> 9 | J58: =AO58 -> 0 | K58: =AP58 -> 0 | L58: =AQ58 -> 0 | M58: =AR58 -> 0 | N58: =AS58 -> 0 | ... AB58: =BG58 -> 0 | AC58: {=SUMPRODUCT(G58:AB58,$G$4:$AB$4)} -> 18090 | AD58: =IF(AF58=AC58,TRUE,FALSE) -> TRUE | AE58: =IFERROR(SUMIF(服务费底表!$K:$K,服务费明细!$B58,服务费底表!$AD:$AD)/E58,0) -> 2010 | AF58: =E58*AE58 -> 18090 | AG58: =IFERROR(SUMIF(服务费底表!$K:$K,服务费明细!$B58,服务费底表!$AG:$AG)/E58,0) -> 2010 | AH58: =AG58*E58 -> 18090 | AI58: 研究中心的安全性事件报告和管理。 | AJ58: =IF(D58=1,AK58/E58,0) -> 5 | AK58: =SUMIF(服务费底表!$K:$K,服务费明细!$B58,服务费底表!$AC:$AC) -> 45 | AL58: =SUMIFS(服务费底表!$AC:$AC,服务费底表!$K:$K,服务费明细!$B58,服务费底表!$T:$T,AL$3) -> 36 | AM58: =SUMIFS(服务费底表!$AC:$AC,服务费底表!$K:$K,服务费明细!$B58,服务费底表!$T:$T,AM$3) -> 0 | AN58: =SUMIFS(服务费底表!$AC:$AC,服务费底表!$K:$K,服务费明细!$B58,服务费底表!$T:$T,AN$3) -> 9 | AO58: =SUMIFS(服务费底表!$AC:$AC,服务费底表!$K:$K,服务费明细!$B58,服务费底表!$T:$T,AO$3) -> 0 | AP58: =SUMIFS(服务费底表!$AC:$AC,服务费底表!$K:$K,服务费明细!$B58,服务费底表!$T:$T,AP$3) -> 0 | AQ58: =SUMIFS(服务费底表!$AC:$AC,服务费底表!$K:$K,服务费明细!$B58,服务费底表!$T:$T,AQ$3) -> 0 | AR58: =SUMIFS(服务费底表!$AC:$AC,服务费底表!$K:$K,服务费明细!$B58,服务费底表!$T:$T,AR$3) -> 0 | AS58: =SUMIFS(服务费底表!$AC:$AC,服务费底表!$K:$K,服务费明细!$B58,服务费底表!$T:$T,AS$3) -> 0 | ... BG58: =SUMIFS(服务费底表!$AC:$AC,服务费底表!$K:$K,服务费明细!$B58,服务费底表!$T:$T,BG$3) -> 0 | BI58: =SUMIFS(服务费底表!$AC:$AC,服务费底表!$K:$K,服务费明细!$B58,服务费底表!$H:$H,服务费明细!BI$3) -> 0 | BJ58: =SUMIFS(服务费底表!$AC:$AC,服务费底表!$K:$K,服务费明细!$B58,服务费底表!$H:$H,服务费明细!BJ$3) -> 45 | BK58: =SUMIFS(服务费底表!$AC:$AC,服务费底表!$K:$K,服务费明细!$B58,服务费底表!$H:$H,服务费明细!BK$3) -> 0 | BL58: =SUMIFS(服务费底表!$AC:$AC,服务费底表!$K:$K,服务费明细!$B58,服务费底表!$H:$H,服务费明细!BL$3) -> 0 | BM58: =SUMIFS(服务费底表!$AC:$AC,服务费底表!$K:$K,服务费明细!$B58,服务费底表!$H:$H,服务费明细!BM$3) -> 0 | BN58: =SUMIFS(服务费底表!$AC:$AC,服务费底表!$K:$K,服务费明细!$B58,服务费底表!$H:$H,服务费明细!BN$3) -> 0 | BO58: =SUMIFS(服务费底表!$AC:$AC,服务费底表!$K:$K,服务费明细!$B58,服务费底表!$H:$H,服务费明细!BO$3) -> 0 | BQ58: =SUMIFS(服务费底表!$AD:$AD,服务费底表!$K:$K,服务费明细!$B58,服务费底表!$H:$H,服务费明细!BQ$3) -> 0 | BR58: =SUMIFS(服务费底表!$AD:$AD,服务费底表!$K:$K,服务费明细!$B58,服务费底表!$H:$H,服务费明细!BR$3) -> 18090 | BS58: =SUMIFS(服务费底表!$AD:$AD,服务费底表!$K:$K,服务费明细!$B58,服务费底表!$H:$H,服务费明细!BS$3) -> 0 | BT58: =SUMIFS(服务费底表!$AD:$AD,服务费底表!$K:$K,服务费明细!$B58,服务费底表!$H:$H,服务费明细!BT$3) -> 0 | BU58: =SUMIFS(服务费底表!$AD:$AD,服务费底表!$K:$K,服务费明细!$B58,服务费底表!$H:$H,服务费明细!BU$3) -> 0 | BV58: =SUMIFS(服务费底表!$AD:$AD,服务费底表!$K:$K,服务费明细!$B58,服务费底表!$H:$H,服务费明细!BV$3) -> 0 | BW58: =SUMIFS(服务费底表!$AD:$AD,服务费底表!$K:$K,服务费明细!$B58,服务费底表!$H:$H,服务费明细!BW$3) -> 0
B59: A041 | C59: =INDEX(二三级标准!$C:$C,MATCH(服务费明细!$B59,二三级标准!$B:$B,0)) -> 中心费用支付支持 | D59: =IF($D$46=1,1,0) -> 1 | E59: {=IF($D59=1,IF(试验参与者类型="健康人",3,4)*启动中心数,0)} -> 16 | F59: =INDEX(二三级标准!$G:$G,MATCH(服务费明细!$B59,二三级标准!$B:$B,0)) -> 次 | G59: =AL59 -> 32 | H59: =AM59 -> 32 | I59: =AN59 -> 16 | J59: =AO59 -> 0 | K59: =AP59 -> 0 | L59: =AQ59 -> 0 | M59: =AR59 -> 0 | N59: =AS59 -> 0 | ... AB59: =BG59 -> 0 | AC59: {=SUMPRODUCT(G59:AB59,$G$4:$AB$4)} -> 28320 | AD59: =IF(AF59=AC59,TRUE,FALSE) -> TRUE | AE59: =IFERROR(SUMIF(服务费底表!$K:$K,服务费明细!$B59,服务费底表!$AD:$AD)/E59,0) -> 1770 | AF59: =E59*AE59 -> 28320 | AG59: =IFERROR(SUMIF(服务费底表!$K:$K,服务费明细!$B59,服务费底表!$AG:$AG)/E59,0) -> 1770 | AH59: =AG59*E59 -> 28320 | AI59: ="有临将根据签署的研究者合同，负责管理"&启动中心数&"家研究中心的费用。" -> 有临将根据签署的研究者合同，负责管理4家研究中心的费用。 | AJ59: =IF(D59=1,AK59/E59,0) -> 5 | AK59: =SUMIF(服务费底表!$K:$K,服务费明细!$B59,服务费底表!$AC:$AC) -> 80 | AL59: =SUMIFS(服务费底表!$AC:$AC,服务费底表!$K:$K,服务费明细!$B59,服务费底表!$T:$T,AL$3) -> 32 | AM59: =SUMIFS(服务费底表!$AC:$AC,服务费底表!$K:$K,服务费明细!$B59,服务费底表!$T:$T,AM$3) -> 32 | AN59: =SUMIFS(服务费底表!$AC:$AC,服务费底表!$K:$K,服务费明细!$B59,服务费底表!$T:$T,AN$3) -> 16 | AO59: =SUMIFS(服务费底表!$AC:$AC,服务费底表!$K:$K,服务费明细!$B59,服务费底表!$T:$T,AO$3) -> 0 | AP59: =SUMIFS(服务费底表!$AC:$AC,服务费底表!$K:$K,服务费明细!$B59,服务费底表!$T:$T,AP$3) -> 0 | AQ59: =SUMIFS(服务费底表!$AC:$AC,服务费底表!$K:$K,服务费明细!$B59,服务费底表!$T:$T,AQ$3) -> 0 | AR59: =SUMIFS(服务费底表!$AC:$AC,服务费底表!$K:$K,服务费明细!$B59,服务费底表!$T:$T,AR$3) -> 0 | AS59: =SUMIFS(服务费底表!$AC:$AC,服务费底表!$K:$K,服务费明细!$B59,服务费底表!$T:$T,AS$3) -> 0 | ... BG59: =SUMIFS(服务费底表!$AC:$AC,服务费底表!$K:$K,服务费明细!$B59,服务费底表!$T:$T,BG$3) -> 0 | BI59: =SUMIFS(服务费底表!$AC:$AC,服务费底表!$K:$K,服务费明细!$B59,服务费底表!$H:$H,服务费明细!BI$3) -> 0 | BJ59: =SUMIFS(服务费底表!$AC:$AC,服务费底表!$K:$K,服务费明细!$B59,服务费底表!$H:$H,服务费明细!BJ$3) -> 80 | BK59: =SUMIFS(服务费底表!$AC:$AC,服务费底表!$K:$K,服务费明细!$B59,服务费底表!$H:$H,服务费明细!BK$3) -> 0 | BL59: =SUMIFS(服务费底表!$AC:$AC,服务费底表!$K:$K,服务费明细!$B59,服务费底表!$H:$H,服务费明细!BL$3) -> 0 | BM59: =SUMIFS(服务费底表!$AC:$AC,服务费底表!$K:$K,服务费明细!$B59,服务费底表!$H:$H,服务费明细!BM$3) -> 0 | BN59: =SUMIFS(服务费底表!$AC:$AC,服务费底表!$K:$K,服务费明细!$B59,服务费底表!$H:$H,服务费明细!BN$3) -> 0 | BO59: =SUMIFS(服务费底表!$AC:$AC,服务费底表!$K:$K,服务费明细!$B59,服务费底表!$H:$H,服务费明细!BO$3) -> 0 | BQ59: =SUMIFS(服务费底表!$AD:$AD,服务费底表!$K:$K,服务费明细!$B59,服务费底表!$H:$H,服务费明细!BQ$3) -> 0 | BR59: =SUMIFS(服务费底表!$AD:$AD,服务费底表!$K:$K,服务费明细!$B59,服务费底表!$H:$H,服务费明细!BR$3) -> 28320 | BS59: =SUMIFS(服务费底表!$AD:$AD,服务费底表!$K:$K,服务费明细!$B59,服务费底表!$H:$H,服务费明细!BS$3) -> 0 | BT59: =SUMIFS(服务费底表!$AD:$AD,服务费底表!$K:$K,服务费明细!$B59,服务费底表!$H:$H,服务费明细!BT$3) -> 0 | BU59: =SUMIFS(服务费底表!$AD:$AD,服务费底表!$K:$K,服务费明细!$B59,服务费底表!$H:$H,服务费明细!BU$3) -> 0 | BV59: =SUMIFS(服务费底表!$AD:$AD,服务费底表!$K:$K,服务费明细!$B59,服务费底表!$H:$H,服务费明细!BV$3) -> 0 | BW59: =SUMIFS(服务费底表!$AD:$AD,服务费底表!$K:$K,服务费明细!$B59,服务费底表!$H:$H,服务费明细!BW$3) -> 0
B60: A042 | C60: =INDEX(二三级标准!$C:$C,MATCH(服务费明细!$B60,二三级标准!$B:$B,0)) -> 研究简报撰写 | D60: =IF(AND($D$46=1,启动中心数>1),1,0) -> 1 | E60: =IF($D60=1,ROUND(入组月+治疗月/2,0),0) -> 10 | F60: =INDEX(二三级标准!$G:$G,MATCH(服务费明细!$B60,二三级标准!$B:$B,0)) -> 份 | G60: =AL60 -> 20 | H60: =AM60 -> 0 | I60: =AN60 -> 40 | J60: =AO60 -> 0 | K60: =AP60 -> 0 | L60: =AQ60 -> 0 | M60: =AR60 -> 0 | N60: =AS60 -> 0 | ... AB60: =BG60 -> 0 | AC60: {=SUMPRODUCT(G60:AB60,$G$4:$AB$4)} -> 32800 | AD60: =IF(AF60=AC60,TRUE,FALSE) -> TRUE | AE60: =IFERROR(SUMIF(服务费底表!$K:$K,服务费明细!$B60,服务费底表!$AD:$AD)/E60,0) -> 3280 | AF60: =E60*AE60 -> 32800 | AG60: =IFERROR(SUMIF(服务费底表!$K:$K,服务费明细!$B60,服务费底表!$AG:$AG)/E60,0) -> 3280 | AH60: =AG60*E60 -> 32800 | AI60: 研究简报Newsletter的撰写和分发。 | AJ60: =IF(D60=1,AK60/E60,0) -> 6 | AK60: =SUMIF(服务费底表!$K:$K,服务费明细!$B60,服务费底表!$AC:$AC) -> 60 | AL60: =SUMIFS(服务费底表!$AC:$AC,服务费底表!$K:$K,服务费明细!$B60,服务费底表!$T:$T,AL$3) -> 20 | AM60: =SUMIFS(服务费底表!$AC:$AC,服务费底表!$K:$K,服务费明细!$B60,服务费底表!$T:$T,AM$3) -> 0 | AN60: =SUMIFS(服务费底表!$AC:$AC,服务费底表!$K:$K,服务费明细!$B60,服务费底表!$T:$T,AN$3) -> 40 | AO60: =SUMIFS(服务费底表!$AC:$AC,服务费底表!$K:$K,服务费明细!$B60,服务费底表!$T:$T,AO$3) -> 0 | AP60: =SUMIFS(服务费底表!$AC:$AC,服务费底表!$K:$K,服务费明细!$B60,服务费底表!$T:$T,AP$3) -> 0 | AQ60: =SUMIFS(服务费底表!$AC:$AC,服务费底表!$K:$K,服务费明细!$B60,服务费底表!$T:$T,AQ$3) -> 0 | AR60: =SUMIFS(服务费底表!$AC:$AC,服务费底表!$K:$K,服务费明细!$B60,服务费底表!$T:$T,AR$3) -> 0 | AS60: =SUMIFS(服务费底表!$AC:$AC,服务费底表!$K:$K,服务费明细!$B60,服务费底表!$T:$T,AS$3) -> 0 | ... BG60: =SUMIFS(服务费底表!$AC:$AC,服务费底表!$K:$K,服务费明细!$B60,服务费底表!$T:$T,BG$3) -> 0 | BI60: =SUMIFS(服务费底表!$AC:$AC,服务费底表!$K:$K,服务费明细!$B60,服务费底表!$H:$H,服务费明细!BI$3) -> 0 | BJ60: =SUMIFS(服务费底表!$AC:$AC,服务费底表!$K:$K,服务费明细!$B60,服务费底表!$H:$H,服务费明细!BJ$3) -> 60 | BK60: =SUMIFS(服务费底表!$AC:$AC,服务费底表!$K:$K,服务费明细!$B60,服务费底表!$H:$H,服务费明细!BK$3) -> 0 | BL60: =SUMIFS(服务费底表!$AC:$AC,服务费底表!$K:$K,服务费明细!$B60,服务费底表!$H:$H,服务费明细!BL$3) -> 0 | BM60: =SUMIFS(服务费底表!$AC:$AC,服务费底表!$K:$K,服务费明细!$B60,服务费底表!$H:$H,服务费明细!BM$3) -> 0 | BN60: =SUMIFS(服务费底表!$AC:$AC,服务费底表!$K:$K,服务费明细!$B60,服务费底表!$H:$H,服务费明细!BN$3) -> 0 | BO60: =SUMIFS(服务费底表!$AC:$AC,服务费底表!$K:$K,服务费明细!$B60,服务费底表!$H:$H,服务费明细!BO$3) -> 0 | BQ60: =SUMIFS(服务费底表!$AD:$AD,服务费底表!$K:$K,服务费明细!$B60,服务费底表!$H:$H,服务费明细!BQ$3) -> 0 | BR60: =SUMIFS(服务费底表!$AD:$AD,服务费底表!$K:$K,服务费明细!$B60,服务费底表!$H:$H,服务费明细!BR$3) -> 32800 | BS60: =SUMIFS(服务费底表!$AD:$AD,服务费底表!$K:$K,服务费明细!$B60,服务费底表!$H:$H,服务费明细!BS$3) -> 0 | BT60: =SUMIFS(服务费底表!$AD:$AD,服务费底表!$K:$K,服务费明细!$B60,服务费底表!$H:$H,服务费明细!BT$3) -> 0 | BU60: =SUMIFS(服务费底表!$AD:$AD,服务费底表!$K:$K,服务费明细!$B60,服务费底表!$H:$H,服务费明细!BU$3) -> 0 | BV60: =SUMIFS(服务费底表!$AD:$AD,服务费底表!$K:$K,服务费明细!$B60,服务费底表!$H:$H,服务费明细!BV$3) -> 0 | BW60: =SUMIFS(服务费底表!$AD:$AD,服务费底表!$K:$K,服务费明细!$B60,服务费底表!$H:$H,服务费明细!BW$3) -> 0
B61: A043 | C61: =INDEX(二三级标准!$C:$C,MATCH(服务费明细!$B61,二三级标准!$B:$B,0)) -> 研究药品申请管理 | D61: =IF($D$46=1,1,0) -> 1 | E61: =IF($D61=1,ROUND((中心激活月-(随访月+长随访月)*启动中心数)/2,0),0) -> 28 | F61: =INDEX(二三级标准!$G:$G,MATCH(服务费明细!$B61,二三级标准!$B:$B,0)) -> 次 | G61: =AL61 -> 28 | H61: =AM61 -> 0 | I61: =AN61 -> 14 | J61: =AO61 -> 0 | K61: =AP61 -> 0 | L61: =AQ61 -> 0 | M61: =AR61 -> 0 | N61: =AS61 -> 0 | ... AB61: =BG61 -> 0 | AC61: {=SUMPRODUCT(G61:AB61,$G$4:$AB$4)} -> 18620 | AD61: =IF(AF61=AC61,TRUE,FALSE) -> TRUE | AE61: =IFERROR(SUMIF(服务费底表!$K:$K,服务费明细!$B61,服务费底表!$AD:$AD)/E61,0) -> 665 | AF61: =E61*AE61 -> 18620 | AG61: =IFERROR(SUMIF(服务费底表!$K:$K,服务费明细!$B61,服务费底表!$AG:$AG)/E61,0) -> 665 | AH61: =AG61*E61 -> 18620 | AI61: 根据项目实际进度申请研究药品发放和状态更新管理。 | AJ61: =IF(D61=1,AK61/E61,0) -> 1.5 | AK61: =SUMIF(服务费底表!$K:$K,服务费明细!$B61,服务费底表!$AC:$AC) -> 42 | AL61: =SUMIFS(服务费底表!$AC:$AC,服务费底表!$K:$K,服务费明细!$B61,服务费底表!$T:$T,AL$3) -> 28 | AM61: =SUMIFS(服务费底表!$AC:$AC,服务费底表!$K:$K,服务费明细!$B61,服务费底表!$T:$T,AM$3) -> 0 | AN61: =SUMIFS(服务费底表!$AC:$AC,服务费底表!$K:$K,服务费明细!$B61,服务费底表!$T:$T,AN$3) -> 14 | AO61: =SUMIFS(服务费底表!$AC:$AC,服务费底表!$K:$K,服务费明细!$B61,服务费底表!$T:$T,AO$3) -> 0 | AP61: =SUMIFS(服务费底表!$AC:$AC,服务费底表!$K:$K,服务费明细!$B61,服务费底表!$T:$T,AP$3) -> 0 | AQ61: =SUMIFS(服务费底表!$AC:$AC,服务费底表!$K:$K,服务费明细!$B61,服务费底表!$T:$T,AQ$3) -> 0 | AR61: =SUMIFS(服务费底表!$AC:$AC,服务费底表!$K:$K,服务费明细!$B61,服务费底表!$T:$T,AR$3) -> 0 | AS61: =SUMIFS(服务费底表!$AC:$AC,服务费底表!$K:$K,服务费明细!$B61,服务费底表!$T:$T,AS$3) -> 0 | ... BG61: =SUMIFS(服务费底表!$AC:$AC,服务费底表!$K:$K,服务费明细!$B61,服务费底表!$T:$T,BG$3) -> 0 | BI61: =SUMIFS(服务费底表!$AC:$AC,服务费底表!$K:$K,服务费明细!$B61,服务费底表!$H:$H,服务费明细!BI$3) -> 0 | BJ61: =SUMIFS(服务费底表!$AC:$AC,服务费底表!$K:$K,服务费明细!$B61,服务费底表!$H:$H,服务费明细!BJ$3) -> 42 | BK61: =SUMIFS(服务费底表!$AC:$AC,服务费底表!$K:$K,服务费明细!$B61,服务费底表!$H:$H,服务费明细!BK$3) -> 0 | BL61: =SUMIFS(服务费底表!$AC:$AC,服务费底表!$K:$K,服务费明细!$B61,服务费底表!$H:$H,服务费明细!BL$3) -> 0 | BM61: =SUMIFS(服务费底表!$AC:$AC,服务费底表!$K:$K,服务费明细!$B61,服务费底表!$H:$H,服务费明细!BM$3) -> 0 | BN61: =SUMIFS(服务费底表!$AC:$AC,服务费底表!$K:$K,服务费明细!$B61,服务费底表!$H:$H,服务费明细!BN$3) -> 0 | BO61: =SUMIFS(服务费底表!$AC:$AC,服务费底表!$K:$K,服务费明细!$B61,服务费底表!$H:$H,服务费明细!BO$3) -> 0 | BQ61: =SUMIFS(服务费底表!$AD:$AD,服务费底表!$K:$K,服务费明细!$B61,服务费底表!$H:$H,服务费明细!BQ$3) -> 0 | BR61: =SUMIFS(服务费底表!$AD:$AD,服务费底表!$K:$K,服务费明细!$B61,服务费底表!$H:$H,服务费明细!BR$3) -> 18620 | BS61: =SUMIFS(服务费底表!$AD:$AD,服务费底表!$K:$K,服务费明细!$B61,服务费底表!$H:$H,服务费明细!BS$3) -> 0 | BT61: =SUMIFS(服务费底表!$AD:$AD,服务费底表!$K:$K,服务费明细!$B61,服务费底表!$H:$H,服务费明细!BT$3) -> 0 | BU61: =SUMIFS(服务费底表!$AD:$AD,服务费底表!$K:$K,服务费明细!$B61,服务费底表!$H:$H,服务费明细!BU$3) -> 0 | BV61: =SUMIFS(服务费底表!$AD:$AD,服务费底表!$K:$K,服务费明细!$B61,服务费底表!$H:$H,服务费明细!BV$3) -> 0 | BW61: =SUMIFS(服务费底表!$AD:$AD,服务费底表!$K:$K,服务费明细!$B61,服务费底表!$H:$H,服务费明细!BW$3) -> 0
B62: A044 | C62: =INDEX(二三级标准!$C:$C,MATCH(服务费明细!$B62,二三级标准!$B:$B,0)) -> 研究物资申请和采购管理 | D62: =IF($D$46=1,1,0) -> 1 | E62: =IF($D62=1,ROUND(中心激活月/6,0),0) -> 9 | F62: =INDEX(二三级标准!$G:$G,MATCH(服务费明细!$B62,二三级标准!$B:$B,0)) -> 次 | G62: =AL62 -> 9 | H62: =AM62 -> 0 | I62: =AN62 -> 4.5 | J62: =AO62 -> 0 | K62: =AP62 -> 0 | L62: =AQ62 -> 0 | M62: =AR62 -> 0 | N62: =AS62 -> 0 | ... AB62: =BG62 -> 0 | AC62: {=SUMPRODUCT(G62:AB62,$G$4:$AB$4)} -> 5985 | AD62: =IF(AF62=AC62,TRUE,FALSE) -> TRUE | AE62: =IFERROR(SUMIF(服务费底表!$K:$K,服务费明细!$B62,服务费底表!$AD:$AD)/E62,0) -> 665 | AF62: =E62*AE62 -> 5985 | AG62: =IFERROR(SUMIF(服务费底表!$K:$K,服务费明细!$B62,服务费底表!$AG:$AG)/E62,0) -> 665 | AH62: =AG62*E62 -> 5985 | AI62: 研究中心物资的询价、审批、采购、寄送。 | AJ62: =IF(D62=1,AK62/E62,0) -> 1.5 | AK62: =SUMIF(服务费底表!$K:$K,服务费明细!$B62,服务费底表!$AC:$AC) -> 13.5 | AL62: =SUMIFS(服务费底表!$AC:$AC,服务费底表!$K:$K,服务费明细!$B62,服务费底表!$T:$T,AL$3) -> 9 | AM62: =SUMIFS(服务费底表!$AC:$AC,服务费底表!$K:$K,服务费明细!$B62,服务费底表!$T:$T,AM$3) -> 0 | AN62: =SUMIFS(服务费底表!$AC:$AC,服务费底表!$K:$K,服务费明细!$B62,服务费底表!$T:$T,AN$3) -> 4.5 | AO62: =SUMIFS(服务费底表!$AC:$AC,服务费底表!$K:$K,服务费明细!$B62,服务费底表!$T:$T,AO$3) -> 0 | AP62: =SUMIFS(服务费底表!$AC:$AC,服务费底表!$K:$K,服务费明细!$B62,服务费底表!$T:$T,AP$3) -> 0 | AQ62: =SUMIFS(服务费底表!$AC:$AC,服务费底表!$K:$K,服务费明细!$B62,服务费底表!$T:$T,AQ$3) -> 0 | AR62: =SUMIFS(服务费底表!$AC:$AC,服务费底表!$K:$K,服务费明细!$B62,服务费底表!$T:$T,AR$3) -> 0 | AS62: =SUMIFS(服务费底表!$AC:$AC,服务费底表!$K:$K,服务费明细!$B62,服务费底表!$T:$T,AS$3) -> 0 | ... BG62: =SUMIFS(服务费底表!$AC:$AC,服务费底表!$K:$K,服务费明细!$B62,服务费底表!$T:$T,BG$3) -> 0 | BI62: =SUMIFS(服务费底表!$AC:$AC,服务费底表!$K:$K,服务费明细!$B62,服务费底表!$H:$H,服务费明细!BI$3) -> 0 | BJ62: =SUMIFS(服务费底表!$AC:$AC,服务费底表!$K:$K,服务费明细!$B62,服务费底表!$H:$H,服务费明细!BJ$3) -> 13.5 | BK62: =SUMIFS(服务费底表!$AC:$AC,服务费底表!$K:$K,服务费明细!$B62,服务费底表!$H:$H,服务费明细!BK$3) -> 0 | BL62: =SUMIFS(服务费底表!$AC:$AC,服务费底表!$K:$K,服务费明细!$B62,服务费底表!$H:$H,服务费明细!BL$3) -> 0 | BM62: =SUMIFS(服务费底表!$AC:$AC,服务费底表!$K:$K,服务费明细!$B62,服务费底表!$H:$H,服务费明细!BM$3) -> 0 | BN62: =SUMIFS(服务费底表!$AC:$AC,服务费底表!$K:$K,服务费明细!$B62,服务费底表!$H:$H,服务费明细!BN$3) -> 0 | BO62: =SUMIFS(服务费底表!$AC:$AC,服务费底表!$K:$K,服务费明细!$B62,服务费底表!$H:$H,服务费明细!BO$3) -> 0 | BQ62: =SUMIFS(服务费底表!$AD:$AD,服务费底表!$K:$K,服务费明细!$B62,服务费底表!$H:$H,服务费明细!BQ$3) -> 0 | BR62: =SUMIFS(服务费底表!$AD:$AD,服务费底表!$K:$K,服务费明细!$B62,服务费底表!$H:$H,服务费明细!BR$3) -> 5985 | BS62: =SUMIFS(服务费底表!$AD:$AD,服务费底表!$K:$K,服务费明细!$B62,服务费底表!$H:$H,服务费明细!BS$3) -> 0 | BT62: =SUMIFS(服务费底表!$AD:$AD,服务费底表!$K:$K,服务费明细!$B62,服务费底表!$H:$H,服务费明细!BT$3) -> 0 | BU62: =SUMIFS(服务费底表!$AD:$AD,服务费底表!$K:$K,服务费明细!$B62,服务费底表!$H:$H,服务费明细!BU$3) -> 0 | BV62: =SUMIFS(服务费底表!$AD:$AD,服务费底表!$K:$K,服务费明细!$B62,服务费底表!$H:$H,服务费明细!BV$3) -> 0 | BW62: =SUMIFS(服务费底表!$AD:$AD,服务费底表!$K:$K,服务费明细!$B62,服务费底表!$H:$H,服务费明细!BW$3) -> 0
B63: A045 | C63: =INDEX(二三级标准!$C:$C,MATCH(服务费明细!$B63,二三级标准!$B:$B,0)) -> 后续伦理文件准备和递交 | D63: 0 | E63: =IF($D63=1,1*启动中心数,0) -> 0 | F63: =INDEX(二三级标准!$G:$G,MATCH(服务费明细!$B63,二三级标准!$B:$B,0)) -> 次 | G63: =AL63 -> 0 | H63: =AM63 -> 0 | I63: =AN63 -> 0 | J63: =AO63 -> 0 | K63: =AP63 -> 0 | L63: =AQ63 -> 0 | M63: =AR63 -> 0 | N63: =AS63 -> 0 | ... AB63: =BG63 -> 0 | AC63: {=SUMPRODUCT(G63:AB63,$G$4:$AB$4)} -> 0 | AD63: =IF(AF63=AC63,TRUE,FALSE) -> TRUE | AE63: =IFERROR(SUMIF(服务费底表!$K:$K,服务费明细!$B63,服务费底表!$AD:$AD)/E63,0) -> 0 | AF63: =E63*AE63 -> 0 | AG63: =IFERROR(SUMIF(服务费底表!$K:$K,服务费明细!$B63,服务费底表!$AG:$AG)/E63,0) -> 0 | AH63: =AG63*E63 -> 0 | AJ63: =IF(D63=1,AK63/E63,0) -> 0 | AK63: =SUMIF(服务费底表!$K:$K,服务费明细!$B63,服务费底表!$AC:$AC) -> 0 | AL63: =SUMIFS(服务费底表!$AC:$AC,服务费底表!$K:$K,服务费明细!$B63,服务费底表!$T:$T,AL$3) -> 0 | AM63: =SUMIFS(服务费底表!$AC:$AC,服务费底表!$K:$K,服务费明细!$B63,服务费底表!$T:$T,AM$3) -> 0 | AN63: =SUMIFS(服务费底表!$AC:$AC,服务费底表!$K:$K,服务费明细!$B63,服务费底表!$T:$T,AN$3) -> 0 | AO63: =SUMIFS(服务费底表!$AC:$AC,服务费底表!$K:$K,服务费明细!$B63,服务费底表!$T:$T,AO$3) -> 0 | AP63: =SUMIFS(服务费底表!$AC:$AC,服务费底表!$K:$K,服务费明细!$B63,服务费底表!$T:$T,AP$3) -> 0 | AQ63: =SUMIFS(服务费底表!$AC:$AC,服务费底表!$K:$K,服务费明细!$B63,服务费底表!$T:$T,AQ$3) -> 0 | AR63: =SUMIFS(服务费底表!$AC:$AC,服务费底表!$K:$K,服务费明细!$B63,服务费底表!$T:$T,AR$3) -> 0 | AS63: =SUMIFS(服务费底表!$AC:$AC,服务费底表!$K:$K,服务费明细!$B63,服务费底表!$T:$T,AS$3) -> 0 | ... BG63: =SUMIFS(服务费底表!$AC:$AC,服务费底表!$K:$K,服务费明细!$B63,服务费底表!$T:$T,BG$3) -> 0 | BI63: =SUMIFS(服务费底表!$AC:$AC,服务费底表!$K:$K,服务费明细!$B63,服务费底表!$H:$H,服务费明细!BI$3) -> 0 | BJ63: =SUMIFS(服务费底表!$AC:$AC,服务费底表!$K:$K,服务费明细!$B63,服务费底表!$H:$H,服务费明细!BJ$3) -> 0 | BK63: =SUMIFS(服务费底表!$AC:$AC,服务费底表!$K:$K,服务费明细!$B63,服务费底表!$H:$H,服务费明细!BK$3) -> 0 | BL63: =SUMIFS(服务费底表!$AC:$AC,服务费底表!$K:$K,服务费明细!$B63,服务费底表!$H:$H,服务费明细!BL$3) -> 0 | BM63: =SUMIFS(服务费底表!$AC:$AC,服务费底表!$K:$K,服务费明细!$B63,服务费底表!$H:$H,服务费明细!BM$3) -> 0 | BN63: =SUMIFS(服务费底表!$AC:$AC,服务费底表!$K:$K,服务费明细!$B63,服务费底表!$H:$H,服务费明细!BN$3) -> 0 | BO63: =SUMIFS(服务费底表!$AC:$AC,服务费底表!$K:$K,服务费明细!$B63,服务费底表!$H:$H,服务费明细!BO$3) -> 0 | BQ63: =SUMIFS(服务费底表!$AD:$AD,服务费底表!$K:$K,服务费明细!$B63,服务费底表!$H:$H,服务费明细!BQ$3) -> 0 | BR63: =SUMIFS(服务费底表!$AD:$AD,服务费底表!$K:$K,服务费明细!$B63,服务费底表!$H:$H,服务费明细!BR$3) -> 0 | BS63: =SUMIFS(服务费底表!$AD:$AD,服务费底表!$K:$K,服务费明细!$B63,服务费底表!$H:$H,服务费明细!BS$3) -> 0 | BT63: =SUMIFS(服务费底表!$AD:$AD,服务费底表!$K:$K,服务费明细!$B63,服务费底表!$H:$H,服务费明细!BT$3) -> 0 | BU63: =SUMIFS(服务费底表!$AD:$AD,服务费底表!$K:$K,服务费明细!$B63,服务费底表!$H:$H,服务费明细!BU$3) -> 0 | BV63: =SUMIFS(服务费底表!$AD:$AD,服务费底表!$K:$K,服务费明细!$B63,服务费底表!$H:$H,服务费明细!BV$3) -> 0 | BW63: =SUMIFS(服务费底表!$AD:$AD,服务费底表!$K:$K,服务费明细!$B63,服务费底表!$H:$H,服务费明细!BW$3) -> 0
B64: A046 | C64: =INDEX(二三级标准!$C:$C,MATCH(服务费明细!$B64,二三级标准!$B:$B,0)) -> 伦理年度报告准备和递交 | D64: =IF($D$46=1,1,0) -> 1 | E64: =IF($D64=1,ROUND((筛选月+入组月+治疗月+随访月+长随访月)/12,0)*启动中心数,0) -> 4 | F64: =INDEX(二三级标准!$G:$G,MATCH(服务费明细!$B64,二三级标准!$B:$B,0)) -> 次 | G64: =AL64 -> 8 | H64: =AM64 -> 0 | I64: =AN64 -> 2 | J64: =AO64 -> 0 | K64: =AP64 -> 0 | L64: =AQ64 -> 0 | M64: =AR64 -> 0 | N64: =AS64 -> 0 | ... AB64: =BG64 -> 0 | AC64: {=SUMPRODUCT(G64:AB64,$G$4:$AB$4)} -> 4020 | AD64: =IF(AF64=AC64,TRUE,FALSE) -> TRUE | AE64: =IFERROR(SUMIF(服务费底表!$K:$K,服务费明细!$B64,服务费底表!$AD:$AD)/E64,0) -> 1005 | AF64: =E64*AE64 -> 4020 | AG64: =IFERROR(SUMIF(服务费底表!$K:$K,服务费明细!$B64,服务费底表!$AG:$AG)/E64,0) -> 1005 | AH64: =AG64*E64 -> 4020 | AJ64: =IF(D64=1,AK64/E64,0) -> 2.5 | AK64: =SUMIF(服务费底表!$K:$K,服务费明细!$B64,服务费底表!$AC:$AC) -> 10 | AL64: =SUMIFS(服务费底表!$AC:$AC,服务费底表!$K:$K,服务费明细!$B64,服务费底表!$T:$T,AL$3) -> 8 | AM64: =SUMIFS(服务费底表!$AC:$AC,服务费底表!$K:$K,服务费明细!$B64,服务费底表!$T:$T,AM$3) -> 0 | AN64: =SUMIFS(服务费底表!$AC:$AC,服务费底表!$K:$K,服务费明细!$B64,服务费底表!$T:$T,AN$3) -> 2 | AO64: =SUMIFS(服务费底表!$AC:$AC,服务费底表!$K:$K,服务费明细!$B64,服务费底表!$T:$T,AO$3) -> 0 | AP64: =SUMIFS(服务费底表!$AC:$AC,服务费底表!$K:$K,服务费明细!$B64,服务费底表!$T:$T,AP$3) -> 0 | AQ64: =SUMIFS(服务费底表!$AC:$AC,服务费底表!$K:$K,服务费明细!$B64,服务费底表!$T:$T,AQ$3) -> 0 | AR64: =SUMIFS(服务费底表!$AC:$AC,服务费底表!$K:$K,服务费明细!$B64,服务费底表!$T:$T,AR$3) -> 0 | AS64: =SUMIFS(服务费底表!$AC:$AC,服务费底表!$K:$K,服务费明细!$B64,服务费底表!$T:$T,AS$3) -> 0 | ... BG64: =SUMIFS(服务费底表!$AC:$AC,服务费底表!$K:$K,服务费明细!$B64,服务费底表!$T:$T,BG$3) -> 0 | BI64: =SUMIFS(服务费底表!$AC:$AC,服务费底表!$K:$K,服务费明细!$B64,服务费底表!$H:$H,服务费明细!BI$3) -> 0 | BJ64: =SUMIFS(服务费底表!$AC:$AC,服务费底表!$K:$K,服务费明细!$B64,服务费底表!$H:$H,服务费明细!BJ$3) -> 10 | BK64: =SUMIFS(服务费底表!$AC:$AC,服务费底表!$K:$K,服务费明细!$B64,服务费底表!$H:$H,服务费明细!BK$3) -> 0 | BL64: =SUMIFS(服务费底表!$AC:$AC,服务费底表!$K:$K,服务费明细!$B64,服务费底表!$H:$H,服务费明细!BL$3) -> 0 | BM64: =SUMIFS(服务费底表!$AC:$AC,服务费底表!$K:$K,服务费明细!$B64,服务费底表!$H:$H,服务费明细!BM$3) -> 0 | BN64: =SUMIFS(服务费底表!$AC:$AC,服务费底表!$K:$K,服务费明细!$B64,服务费底表!$H:$H,服务费明细!BN$3) -> 0 | BO64: =SUMIFS(服务费底表!$AC:$AC,服务费底表!$K:$K,服务费明细!$B64,服务费底表!$H:$H,服务费明细!BO$3) -> 0 | BQ64: =SUMIFS(服务费底表!$AD:$AD,服务费底表!$K:$K,服务费明细!$B64,服务费底表!$H:$H,服务费明细!BQ$3) -> 0 | BR64: =SUMIFS(服务费底表!$AD:$AD,服务费底表!$K:$K,服务费明细!$B64,服务费底表!$H:$H,服务费明细!BR$3) -> 4020 | BS64: =SUMIFS(服务费底表!$AD:$AD,服务费底表!$K:$K,服务费明细!$B64,服务费底表!$H:$H,服务费明细!BS$3) -> 0 | BT64: =SUMIFS(服务费底表!$AD:$AD,服务费底表!$K:$K,服务费明细!$B64,服务费底表!$H:$H,服务费明细!BT$3) -> 0 | BU64: =SUMIFS(服务费底表!$AD:$AD,服务费底表!$K:$K,服务费明细!$B64,服务费底表!$H:$H,服务费明细!BU$3) -> 0 | BV64: =SUMIFS(服务费底表!$AD:$AD,服务费底表!$K:$K,服务费明细!$B64,服务费底表!$H:$H,服务费明细!BV$3) -> 0 | BW64: =SUMIFS(服务费底表!$AD:$AD,服务费底表!$K:$K,服务费明细!$B64,服务费底表!$H:$H,服务费明细!BW$3) -> 0
B65: A047 | C65: =INDEX(二三级标准!$C:$C,MATCH(服务费明细!$B65,二三级标准!$B:$B,0)) -> 中心日常支持和管理 | D65: =IF($D$46=1,1,0) -> 1 | E65: =IF($D65=1,中心激活月,0) -> 56 | F65: =INDEX(二三级标准!$G:$G,MATCH(服务费明细!$B65,二三级标准!$B:$B,0)) -> 月*中心 | G65: =AL65 -> 504 | H65: =AM65 -> 0 | I65: =AN65 -> 0 | J65: =AO65 -> 0 | K65: =AP65 -> 0 | L65: =AQ65 -> 0 | M65: =AR65 -> 0 | N65: =AS65 -> 0 | ... AB65: =BG65 -> 0 | AC65: {=SUMPRODUCT(G65:AB65,$G$4:$AB$4)} -> 171360 | AD65: =IF(AF65=AC65,TRUE,FALSE) -> TRUE | AE65: =IFERROR(SUMIF(服务费底表!$K:$K,服务费明细!$B65,服务费底表!$AD:$AD)/E65,0) -> 3060 | AF65: =E65*AE65 -> 171360 | AG65: =IFERROR(SUMIF(服务费底表!$K:$K,服务费明细!$B65,服务费底表!$AG:$AG)/E65,0) -> 3060 | AH65: =AG65*E65 -> 171360 | AI65: 自首家研究中心启动到最后一家研究中心关闭。包括定期联络中心，进行综合检查管理中心进展情况，试验参与者情况，数据采集、清理进展及项目组内沟通等。 | AJ65: =IF(D65=1,AK65/E65,0) -> 9 | AK65: =SUMIF(服务费底表!$K:$K,服务费明细!$B65,服务费底表!$AC:$AC) -> 504 | AL65: =SUMIFS(服务费底表!$AC:$AC,服务费底表!$K:$K,服务费明细!$B65,服务费底表!$T:$T,AL$3) -> 504 | AM65: =SUMIFS(服务费底表!$AC:$AC,服务费底表!$K:$K,服务费明细!$B65,服务费底表!$T:$T,AM$3) -> 0 | AN65: =SUMIFS(服务费底表!$AC:$AC,服务费底表!$K:$K,服务费明细!$B65,服务费底表!$T:$T,AN$3) -> 0 | AO65: =SUMIFS(服务费底表!$AC:$AC,服务费底表!$K:$K,服务费明细!$B65,服务费底表!$T:$T,AO$3) -> 0 | AP65: =SUMIFS(服务费底表!$AC:$AC,服务费底表!$K:$K,服务费明细!$B65,服务费底表!$T:$T,AP$3) -> 0 | AQ65: =SUMIFS(服务费底表!$AC:$AC,服务费底表!$K:$K,服务费明细!$B65,服务费底表!$T:$T,AQ$3) -> 0 | AR65: =SUMIFS(服务费底表!$AC:$AC,服务费底表!$K:$K,服务费明细!$B65,服务费底表!$T:$T,AR$3) -> 0 | AS65: =SUMIFS(服务费底表!$AC:$AC,服务费底表!$K:$K,服务费明细!$B65,服务费底表!$T:$T,AS$3) -> 0 | ... BG65: =SUMIFS(服务费底表!$AC:$AC,服务费底表!$K:$K,服务费明细!$B65,服务费底表!$T:$T,BG$3) -> 0 | BI65: =SUMIFS(服务费底表!$AC:$AC,服务费底表!$K:$K,服务费明细!$B65,服务费底表!$H:$H,服务费明细!BI$3) -> 0 | BJ65: =SUMIFS(服务费底表!$AC:$AC,服务费底表!$K:$K,服务费明细!$B65,服务费底表!$H:$H,服务费明细!BJ$3) -> 504 | BK65: =SUMIFS(服务费底表!$AC:$AC,服务费底表!$K:$K,服务费明细!$B65,服务费底表!$H:$H,服务费明细!BK$3) -> 0 | BL65: =SUMIFS(服务费底表!$AC:$AC,服务费底表!$K:$K,服务费明细!$B65,服务费底表!$H:$H,服务费明细!BL$3) -> 0 | BM65: =SUMIFS(服务费底表!$AC:$AC,服务费底表!$K:$K,服务费明细!$B65,服务费底表!$H:$H,服务费明细!BM$3) -> 0 | BN65: =SUMIFS(服务费底表!$AC:$AC,服务费底表!$K:$K,服务费明细!$B65,服务费底表!$H:$H,服务费明细!BN$3) -> 0 | BO65: =SUMIFS(服务费底表!$AC:$AC,服务费底表!$K:$K,服务费明细!$B65,服务费底表!$H:$H,服务费明细!BO$3) -> 0 | BQ65: =SUMIFS(服务费底表!$AD:$AD,服务费底表!$K:$K,服务费明细!$B65,服务费底表!$H:$H,服务费明细!BQ$3) -> 0 | BR65: =SUMIFS(服务费底表!$AD:$AD,服务费底表!$K:$K,服务费明细!$B65,服务费底表!$H:$H,服务费明细!BR$3) -> 171360 | BS65: =SUMIFS(服务费底表!$AD:$AD,服务费底表!$K:$K,服务费明细!$B65,服务费底表!$H:$H,服务费明细!BS$3) -> 0 | BT65: =SUMIFS(服务费底表!$AD:$AD,服务费底表!$K:$K,服务费明细!$B65,服务费底表!$H:$H,服务费明细!BT$3) -> 0 | BU65: =SUMIFS(服务费底表!$AD:$AD,服务费底表!$K:$K,服务费明细!$B65,服务费底表!$H:$H,服务费明细!BU$3) -> 0 | BV65: =SUMIFS(服务费底表!$AD:$AD,服务费底表!$K:$K,服务费明细!$B65,服务费底表!$H:$H,服务费明细!BV$3) -> 0 | BW65: =SUMIFS(服务费底表!$AD:$AD,服务费底表!$K:$K,服务费明细!$B65,服务费底表!$H:$H,服务费明细!BW$3) -> 0
B66: A048 | C66: =INDEX(二三级标准!$C:$C,MATCH(服务费明细!$B66,二三级标准!$B:$B,0)) -> 自查访视 | D66: =IF($D$46=1,1,0) -> 1 | E66: =IF($D66=1,机构自查访视次数,0) -> 4 | F66: =INDEX(二三级标准!$G:$G,MATCH(服务费明细!$B66,二三级标准!$B:$B,0)) -> 次 | G66: =AL66 -> 92 | H66: =AM66 -> 0 | I66: =AN66 -> 8 | J66: =AO66 -> 0 | K66: =AP66 -> 0 | L66: =AQ66 -> 0 | M66: =AR66 -> 0 | N66: =AS66 -> 0 | ... AB66: =BG66 -> 0 | AC66: {=SUMPRODUCT(G66:AB66,$G$4:$AB$4)} -> 36480 | AD66: =IF(AF66=AC66,TRUE,FALSE) -> TRUE | AE66: =IFERROR(SUMIF(服务费底表!$K:$K,服务费明细!$B66,服务费底表!$AD:$AD)/E66,0) -> 9120 | AF66: =E66*AE66 -> 36480 | AG66: =IFERROR(SUMIF(服务费底表!$K:$K,服务费明细!$B66,服务费底表!$AG:$AG)/E66,0) -> 9120 | AH66: =AG66*E66 -> 36480 | AI66: 准备，差旅，现场访视，报告和跟进。 | AJ66: =IF(D66=1,AK66/E66,0) -> 25 | AK66: =SUMIF(服务费底表!$K:$K,服务费明细!$B66,服务费底表!$AC:$AC) -> 100 | AL66: =SUMIFS(服务费底表!$AC:$AC,服务费底表!$K:$K,服务费明细!$B66,服务费底表!$T:$T,AL$3) -> 92 | AM66: =SUMIFS(服务费底表!$AC:$AC,服务费底表!$K:$K,服务费明细!$B66,服务费底表!$T:$T,AM$3) -> 0 | AN66: =SUMIFS(服务费底表!$AC:$AC,服务费底表!$K:$K,服务费明细!$B66,服务费底表!$T:$T,AN$3) -> 8 | AO66: =SUMIFS(服务费底表!$AC:$AC,服务费底表!$K:$K,服务费明细!$B66,服务费底表!$T:$T,AO$3) -> 0 | AP66: =SUMIFS(服务费底表!$AC:$AC,服务费底表!$K:$K,服务费明细!$B66,服务费底表!$T:$T,AP$3) -> 0 | AQ66: =SUMIFS(服务费底表!$AC:$AC,服务费底表!$K:$K,服务费明细!$B66,服务费底表!$T:$T,AQ$3) -> 0 | AR66: =SUMIFS(服务费底表!$AC:$AC,服务费底表!$K:$K,服务费明细!$B66,服务费底表!$T:$T,AR$3) -> 0 | AS66: =SUMIFS(服务费底表!$AC:$AC,服务费底表!$K:$K,服务费明细!$B66,服务费底表!$T:$T,AS$3) -> 0 | ... BG66: =SUMIFS(服务费底表!$AC:$AC,服务费底表!$K:$K,服务费明细!$B66,服务费底表!$T:$T,BG$3) -> 0 | BI66: =SUMIFS(服务费底表!$AC:$AC,服务费底表!$K:$K,服务费明细!$B66,服务费底表!$H:$H,服务费明细!BI$3) -> 0 | BJ66: =SUMIFS(服务费底表!$AC:$AC,服务费底表!$K:$K,服务费明细!$B66,服务费底表!$H:$H,服务费明细!BJ$3) -> 100 | BK66: =SUMIFS(服务费底表!$AC:$AC,服务费底表!$K:$K,服务费明细!$B66,服务费底表!$H:$H,服务费明细!BK$3) -> 0 | BL66: =SUMIFS(服务费底表!$AC:$AC,服务费底表!$K:$K,服务费明细!$B66,服务费底表!$H:$H,服务费明细!BL$3) -> 0 | BM66: =SUMIFS(服务费底表!$AC:$AC,服务费底表!$K:$K,服务费明细!$B66,服务费底表!$H:$H,服务费明细!BM$3) -> 0 | BN66: =SUMIFS(服务费底表!$AC:$AC,服务费底表!$K:$K,服务费明细!$B66,服务费底表!$H:$H,服务费明细!BN$3) -> 0 | BO66: =SUMIFS(服务费底表!$AC:$AC,服务费底表!$K:$K,服务费明细!$B66,服务费底表!$H:$H,服务费明细!BO$3) -> 0 | BQ66: =SUMIFS(服务费底表!$AD:$AD,服务费底表!$K:$K,服务费明细!$B66,服务费底表!$H:$H,服务费明细!BQ$3) -> 0 | BR66: =SUMIFS(服务费底表!$AD:$AD,服务费底表!$K:$K,服务费明细!$B66,服务费底表!$H:$H,服务费明细!BR$3) -> 36480 | BS66: =SUMIFS(服务费底表!$AD:$AD,服务费底表!$K:$K,服务费明细!$B66,服务费底表!$H:$H,服务费明细!BS$3) -> 0 | BT66: =SUMIFS(服务费底表!$AD:$AD,服务费底表!$K:$K,服务费明细!$B66,服务费底表!$H:$H,服务费明细!BT$3) -> 0 | BU66: =SUMIFS(服务费底表!$AD:$AD,服务费底表!$K:$K,服务费明细!$B66,服务费底表!$H:$H,服务费明细!BU$3) -> 0 | BV66: =SUMIFS(服务费底表!$AD:$AD,服务费底表!$K:$K,服务费明细!$B66,服务费底表!$H:$H,服务费明细!BV$3) -> 0 | BW66: =SUMIFS(服务费底表!$AD:$AD,服务费底表!$K:$K,服务费明细!$B66,服务费底表!$H:$H,服务费明细!BW$3) -> 0
